{
 "type": "FeatureCollection",
 "features": [
  {
   "type": "Feature",
   "id": "node/26859285",
   "properties": {
    "addr:city": "Oostkapelle",
    "addr:housenumber": "2a",
    "addr:postcode": "4356RJ",
    "addr:street": "Aagtekerkseweg",
    "backcountry": "no",
    "dog": "no",
    "drinking_water": "yes",
    "fee": "yes",
    "internet_access": "wlan",
    "internet_access:fee": "no",
    "name": "Ons Buiten",
    "openfire": "no",
    "phone": "+31 118 581 813",
    "power_supply": "yes",
    "reservation": "recommended",
    "sanitary_dump_station": "yes",
    "shower": "yes",
    "toilets": "yes",
    "tourism": "camp_site",
    "website": "https://www.onsbuiten.nl",
    "wheelchair": "limited",
    "id": "node/26859285",
    "_lat": "51.5629432",
    "_lon": "3.5458107",
    "_layer": "drinking_water",
    "_surface": "0",
    "_surface:ha": "0",
    "_length": "0",
    "_length:km": "0.0",
    "_last_edit:contributor": "cEvLGWiQ",
    "_last_edit:contributor:uid": 5432507,
    "_last_edit:changeset": 136649375,
    "_last_edit:timestamp": "2023-05-28T09:37:13Z",
    "_version_number": 6,
    "_geometry:type": "Point",
    "_country": "nl",
    "_closest_other_drinking_water": "{\"id\":\"node/9954451096\",\"distance\":\"21.91212159020902\"}",
    "_closest_other_drinking_water_id": "node/9954451096",
    "_closest_other_drinking_water_distance": "21"
   },
   "geometry": {
    "type": "Point",
    "coordinates": [
     3.5458107,
     51.5629432
    ]
   },
   "_lon": 3.5458107,
   "_lat": 51.5629432,
   "_is_patched": true
  },
  {
   "type": "Feature",
   "id": "node/4301318256",
   "properties": {
    "addr:city": "Domburg",
    "addr:housenumber": "20",
    "addr:postcode": "4357NM",
    "addr:street": "Zuiverseweg",
    "drinking_water": "yes",
    "internet_access": "wlan",
    "name": "Ardoer Camping Westhove",
    "phone": "+31 118 581 809",
    "shower": "yes",
    "source": "website",
    "toilets": "yes",
    "tourism": "camp_site",
    "website": "https://westhove.ardoer.com/nl/",
    "id": "node/4301318256",
    "_lat": "51.5566886",
    "_lon": "3.516707",
    "_layer": "drinking_water",
    "_surface": "0",
    "_surface:ha": "0",
    "_length": "0",
    "_length:km": "0.0",
    "_last_edit:contributor": "SnowStormFog",
    "_last_edit:contributor:uid": 13504467,
    "_last_edit:changeset": 136944044,
    "_last_edit:timestamp": "2023-06-04T18:35:42Z",
    "_version_number": 15,
    "_geometry:type": "Point",
    "_country": "nl",
    "_closest_other_drinking_water": "{\"id\":\"way/401779368\",\"distance\":\"0.973896671593076\"}",
    "_closest_other_drinking_water_id": "way/401779368",
    "_closest_other_drinking_water_distance": "0"
   },
   "geometry": {
    "type": "Point",
    "coordinates": [
     3.516707,
     51.5566886
    ]
   },
   "_lon": 3.516707,
   "_lat": 51.5566886,
   "_is_patched": true
  }
 ]
}