{
 "type": "FeatureCollection",
 "features": [
  {
   "type": "Feature",
   "id": "node/1169747699",
   "properties": {
    "leisure": "bird_hide",
    "name": "Kampina - Kolkven - Vogelkijkpunten",
    "note": "Kampina - Kolkven - Vogelkijkpunten",
    "id": "node/1169747699",
    "_lat": "51.55462",
    "_lon": "5.20696",
    "_layer": "birdhide",
    "_length": "0",
    "_length:km": "0.0",
    "_last_edit:contributor": "joostdejong",
    "_last_edit:contributor:uid": 21555,
    "_last_edit:changeset": 7380118,
    "_last_edit:timestamp": "2011-02-24T10:23:59Z",
    "_version_number": 1
   },
   "geometry": {
    "type": "Point",
    "coordinates": [
     5.20696,
     51.55462
    ]
   },
   "_lon": 5.20696,
   "_lat": 51.55462
  },
  {
   "type": "Feature",
   "id": "node/2428389369",
   "properties": {
    "leisure": "bird_hide",
    "shelter": "no",
    "id": "node/2428389369",
    "_lat": "51.5169082",
    "_lon": "5.2591842",
    "_layer": "birdhide",
    "_length": "0",
    "_length:km": "0.0",
    "_last_edit:contributor": "Jarien",
    "_last_edit:contributor:uid": 395348,
    "_last_edit:changeset": 17459207,
    "_last_edit:timestamp": "2013-08-22T17:49:37Z",
    "_version_number": 1
   },
   "geometry": {
    "type": "Point",
    "coordinates": [
     5.2591842,
     51.5169082
    ]
   },
   "_lon": 5.2591842,
   "_lat": 51.5169082
  }
 ]
}