{
 "type": "FeatureCollection",
 "features": [
  {
   "type": "Feature",
   "id": "node/3831544327",
   "properties": {
    "man_made": "watermill",
    "name": "Moulin à eau",
    "id": "node/3831544327",
    "_lat": "50.5856204",
    "_lon": "3.8847859",
    "_layer": "watermill",
    "_length": "0",
    "_length:km": "0.0",
    "_last_edit:contributor": "Walter Schlögl",
    "_last_edit:contributor:uid": 78656,
    "_last_edit:changeset": 35303614,
    "_last_edit:timestamp": "2015-11-14T10:42:49Z",
    "_version_number": 2
   },
   "geometry": {
    "type": "Point",
    "coordinates": [
     3.8847859,
     50.5856204
    ]
   },
   "_lon": 3.8847859,
   "_lat": 50.5856204
  }
 ]
}