{
 "type": "FeatureCollection",
 "features": [
  {
   "type": "Feature",
   "id": "node/4679098715",
   "properties": {
    "information": "board",
    "tourism": "information",
    "id": "node/4679098715",
    "_lat": "51.4984743",
    "_lon": "4.3289127",
    "_layer": "information_board",
    "_length": "0",
    "_length:km": "0.0",
    "_last_edit:contributor": "Rcnoor",
    "_last_edit:contributor:uid": 2275742,
    "_last_edit:changeset": 45983728,
    "_last_edit:timestamp": "2017-02-10T20:40:19Z",
    "_version_number": 1,
    "_geometry:type": "Point"
   },
   "geometry": {
    "type": "Point",
    "coordinates": [
     4.3289127,
     51.4984743
    ]
   },
   "_lon": 4.3289127,
   "_lat": 51.4984743
  },
  {
   "type": "Feature",
   "id": "node/6141092012",
   "properties": {
    "bicycle": "yes",
    "highway": "trailhead",
    "hiking": "yes",
    "information": "board",
    "name": "Natuurpoort Stayokay - Bergen op Zoom",
    "source": "gpsfietsroutesnederland.nl",
    "survey:date": "2018-11",
    "tourism": "information",
    "url": "https://gpsfietsroutesnederland.nl/toeristische-overstappunten/",
    "website": "https://www.natuurpoorten.nl/",
    "wikipedia": "nl:Toeristisch Overstappunt",
    "id": "node/6141092012",
    "_lat": "51.4878143",
    "_lon": "4.32596",
    "_layer": "information_board",
    "_length": "0",
    "_length:km": "0.0",
    "_last_edit:contributor": "Peter Elderson",
    "_last_edit:contributor:uid": 7103674,
    "_last_edit:changeset": 65734658,
    "_last_edit:timestamp": "2018-12-24T09:25:39Z",
    "_version_number": 3,
    "_geometry:type": "Point"
   },
   "geometry": {
    "type": "Point",
    "coordinates": [
     4.32596,
     51.4878143
    ]
   },
   "_lon": 4.32596,
   "_lat": 51.4878143
  }
 ]
}