{
 "type": "FeatureCollection",
 "features": [
  {
   "type": "Feature",
   "id": "node/3789613131",
   "properties": {
    "board_type": "notice",
    "description": "Niersauenkonzept Renaturierungsplan",
    "information": "board",
    "name": "Niers Verband",
    "tourism": "information",
    "id": "node/3789613131",
    "_lat": "51.1267664",
    "_lon": "6.4134079",
    "_layer": "information_board",
    "_length": "0",
    "_length:km": "0.0",
    "_last_edit:contributor": "GB_Germany_Vie",
    "_last_edit:contributor:uid": 46828,
    "_last_edit:changeset": 34683663,
    "_last_edit:timestamp": "2015-10-16T20:47:06Z",
    "_version_number": 1
   },
   "geometry": {
    "type": "Point",
    "coordinates": [
     6.4134079,
     51.1267664
    ]
   },
   "_lon": 6.4134079,
   "_lat": 51.1267664
  }
 ]
}