{
 "type": "FeatureCollection",
 "features": [
  {
   "type": "Feature",
   "id": "node/5572525969",
   "properties": {
    "board_type": "notice",
    "information": "board",
    "tourism": "information",
    "id": "node/5572525969",
    "_lat": "51.392894",
    "_lon": "4.8272668",
    "_layer": "information_board",
    "_length": "0",
    "_length:km": "0.0",
    "_last_edit:contributor": "escada",
    "_last_edit:contributor:uid": 436365,
    "_last_edit:changeset": 58325582,
    "_last_edit:timestamp": "2018-04-23T03:45:18Z",
    "_version_number": 1,
    "_geometry:type": "Point",
    "_country": "be"
   },
   "geometry": {
    "type": "Point",
    "coordinates": [
     4.8272668,
     51.392894
    ]
   },
   "_lon": 4.8272668,
   "_lat": 51.392894
  },
  {
   "type": "Feature",
   "id": "node/5572527252",
   "properties": {
    "board_type": "history",
    "information": "board",
    "name": "In Vlaanderens velden bloeien de klaprozen",
    "tourism": "information",
    "id": "node/5572527252",
    "_lat": "51.3938605",
    "_lon": "4.8273312",
    "_layer": "information_board",
    "_length": "0",
    "_length:km": "0.0",
    "_last_edit:contributor": "escada",
    "_last_edit:contributor:uid": 436365,
    "_last_edit:changeset": 58325582,
    "_last_edit:timestamp": "2018-04-23T03:45:20Z",
    "_version_number": 1,
    "_geometry:type": "Point",
    "_country": "be"
   },
   "geometry": {
    "type": "Point",
    "coordinates": [
     4.8273312,
     51.3938605
    ]
   },
   "_lon": 4.8273312,
   "_lat": 51.3938605
  },
  {
   "type": "Feature",
   "id": "node/7619158849",
   "properties": {
    "board_type": "nature",
    "information": "board",
    "name": "Plantentuin 'De Kleine Boerderij' Merksplas",
    "tourism": "information",
    "id": "node/7619158849",
    "_lat": "51.3502823",
    "_lon": "4.8277313",
    "_layer": "information_board",
    "_length": "0",
    "_length:km": "0.0",
    "_last_edit:contributor": "staf",
    "_last_edit:contributor:uid": 377797,
    "_last_edit:changeset": 113065843,
    "_last_edit:timestamp": "2021-10-28T06:14:49Z",
    "_version_number": 3,
    "_geometry:type": "Point",
    "_country": "be"
   },
   "geometry": {
    "type": "Point",
    "coordinates": [
     4.8277313,
     51.3502823
    ]
   },
   "_lon": 4.8277313,
   "_lat": 51.3502823
  },
  {
   "type": "Feature",
   "id": "node/7820592180",
   "properties": {
    "board_type": "nature",
    "information": "board",
    "tourism": "information",
    "id": "node/7820592180",
    "_lat": "51.377804",
    "_lon": "4.796267",
    "_layer": "information_board",
    "_length": "0",
    "_length:km": "0.0",
    "_last_edit:contributor": "staf",
    "_last_edit:contributor:uid": 377797,
    "_last_edit:changeset": 96416736,
    "_last_edit:timestamp": "2020-12-25T10:34:31Z",
    "_version_number": 2,
    "_geometry:type": "Point",
    "_country": "be"
   },
   "geometry": {
    "type": "Point",
    "coordinates": [
     4.796267,
     51.377804
    ]
   },
   "_lon": 4.796267,
   "_lat": 51.377804
  },
  {
   "type": "Feature",
   "id": "node/8198728590",
   "properties": {
    "board_type": "nature",
    "information": "board",
    "name": "Stortplaats voor drinkwaterslib Pidpa",
    "tourism": "information",
    "id": "node/8198728590",
    "_lat": "51.3628387",
    "_lon": "4.827459",
    "_layer": "information_board",
    "_length": "0",
    "_length:km": "0.0",
    "_last_edit:contributor": "staf",
    "_last_edit:contributor:uid": 377797,
    "_last_edit:changeset": 95365792,
    "_last_edit:timestamp": "2020-12-06T13:29:00Z",
    "_version_number": 3,
    "_geometry:type": "Point",
    "_country": "be"
   },
   "geometry": {
    "type": "Point",
    "coordinates": [
     4.827459,
     51.3628387
    ]
   },
   "_lon": 4.827459,
   "_lat": 51.3628387
  },
  {
   "type": "Feature",
   "id": "node/8259309146",
   "properties": {
    "board_type": "nature",
    "information": "board",
    "name": "Welkom in de Bolkse Beek",
    "tourism": "information",
    "id": "node/8259309146",
    "_lat": "51.3782814",
    "_lon": "4.7911916",
    "_layer": "information_board",
    "_length": "0",
    "_length:km": "0.0",
    "_last_edit:contributor": "staf",
    "_last_edit:contributor:uid": 377797,
    "_last_edit:changeset": 103564430,
    "_last_edit:timestamp": "2021-04-25T08:47:30Z",
    "_version_number": 3,
    "_geometry:type": "Point",
    "_country": "be"
   },
   "geometry": {
    "type": "Point",
    "coordinates": [
     4.7911916,
     51.3782814
    ]
   },
   "_lon": 4.7911916,
   "_lat": 51.3782814
  }
 ]
}