{
 "type": "FeatureCollection",
 "features": [
  {
   "type": "Feature",
   "id": "node/4735913356",
   "properties": {
    "description": "Plan",
    "information": "board",
    "mapillary": "Wlcrn-B9YpR7Ays2JxDpsQ",
    "name": "Welkom in de Brede Zeyp",
    "tourism": "information",
    "id": "node/4735913356",
    "_lat": "51.0837258",
    "_lon": "4.5727978",
    "_layer": "information_board",
    "_length": "0",
    "_length:km": "0.0",
    "_last_edit:contributor": "Jakka",
    "_last_edit:contributor:uid": 2403313,
    "_last_edit:changeset": 46865032,
    "_last_edit:timestamp": "2017-03-15T10:41:34Z",
    "_version_number": 1,
    "_geometry:type": "Point"
   },
   "geometry": {
    "type": "Point",
    "coordinates": [
     4.5727978,
     51.0837258
    ]
   },
   "_lon": 4.5727978,
   "_lat": 51.0837258
  },
  {
   "type": "Feature",
   "id": "node/7873085142",
   "properties": {
    "information": "board",
    "tourism": "information",
    "id": "node/7873085142",
    "_lat": "51.1203097",
    "_lon": "4.5777459",
    "_layer": "information_board",
    "_length": "0",
    "_length:km": "0.0",
    "_last_edit:contributor": "Jakka",
    "_last_edit:contributor:uid": 2403313,
    "_last_edit:changeset": 90372130,
    "_last_edit:timestamp": "2020-09-03T16:23:07Z",
    "_version_number": 1,
    "_geometry:type": "Point"
   },
   "geometry": {
    "type": "Point",
    "coordinates": [
     4.5777459,
     51.1203097
    ]
   },
   "_lon": 4.5777459,
   "_lat": 51.1203097
  }
 ]
}