{
 "type": "FeatureCollection",
 "features": [
  {
   "type": "Feature",
   "id": "node/10072583982",
   "properties": {
    "board_type": "notice",
    "information": "board",
    "name": "Charbon et Or",
    "operator": "Rugby Club Frameries",
    "tourism": "information",
    "id": "node/10072583982",
    "_lat": "50.3991345",
    "_lon": "3.9007902",
    "_layer": "information_board",
    "_surface": "0",
    "_surface:ha": "0",
    "_length": "0",
    "_length:km": "0.0",
    "_last_edit:contributor": "HannibalKane",
    "_last_edit:contributor:uid": 12816423,
    "_last_edit:changeset": 126928354,
    "_last_edit:timestamp": "2022-10-03T10:17:52Z",
    "_version_number": 1,
    "_geometry:type": "Point",
    "_country": "be"
   },
   "geometry": {
    "type": "Point",
    "coordinates": [
     3.9007902,
     50.3991345
    ]
   },
   "_lon": 3.9007902,
   "_lat": 50.3991345
  }
 ]
}