{
 "type": "FeatureCollection",
 "features": [
  {
   "type": "Feature",
   "id": "node/1169748899",
   "properties": {
    "leisure": "bird_hide",
    "name": "Bleeke Heide - Vogelkijkscherm",
    "note": "Bleeke Heide - Vogelkijkscherm",
    "id": "node/1169748899",
    "_lat": "51.49328",
    "_lon": "4.84578",
    "_layer": "birdhide",
    "_length": "0",
    "_length:km": "0.0",
    "_last_edit:contributor": "joostdejong",
    "_last_edit:contributor:uid": 21555,
    "_last_edit:changeset": 7380118,
    "_last_edit:timestamp": "2011-02-24T10:25:02Z",
    "_version_number": 1,
    "_geometry:type": "Point",
    "_country": "nl"
   },
   "geometry": {
    "type": "Point",
    "coordinates": [
     4.84578,
     51.49328
    ]
   },
   "_lon": 4.84578,
   "_lat": 51.49328
  }
 ]
}