{
 "type": "FeatureCollection",
 "features": [
  {
   "type": "Feature",
   "id": "node/9811893000",
   "properties": {
    "board_type": "nature",
    "information": "board",
    "name": "Biodiversité de l'étang Leo Lagrange",
    "tourism": "information",
    "id": "node/9811893000",
    "_lat": "50.4973225",
    "_lon": "2.674876",
    "_layer": "information_board",
    "_surface": "0",
    "_surface:ha": "0",
    "_length": "0",
    "_length:km": "0.0",
    "_last_edit:contributor": "MaxR_6429",
    "_last_edit:contributor:uid": 11559723,
    "_last_edit:changeset": 122269146,
    "_last_edit:timestamp": "2022-06-12T07:50:20Z",
    "_version_number": 1,
    "_geometry:type": "Point",
    "_country": "fr"
   },
   "geometry": {
    "type": "Point",
    "coordinates": [
     2.674876,
     50.4973225
    ]
   },
   "_lon": 2.674876,
   "_lat": 50.4973225
  },
  {
   "type": "Feature",
   "id": "node/9811893001",
   "properties": {
    "board_type": "nature",
    "information": "board",
    "name": "Biodiversité de l'étang Leo Lagrange - faune et flore",
    "tourism": "information",
    "id": "node/9811893001",
    "_lat": "50.498196",
    "_lon": "2.6740612",
    "_layer": "information_board",
    "_surface": "0",
    "_surface:ha": "0",
    "_length": "0",
    "_length:km": "0.0",
    "_last_edit:contributor": "MaxR_6429",
    "_last_edit:contributor:uid": 11559723,
    "_last_edit:changeset": 122269146,
    "_last_edit:timestamp": "2022-06-12T07:50:20Z",
    "_version_number": 1,
    "_geometry:type": "Point",
    "_country": "fr"
   },
   "geometry": {
    "type": "Point",
    "coordinates": [
     2.6740612,
     50.498196
    ]
   },
   "_lon": 2.6740612,
   "_lat": 50.498196
  },
  {
   "type": "Feature",
   "id": "node/10160184984",
   "properties": {
    "board_type": "welcome_sign",
    "information": "board",
    "tourism": "information",
    "id": "node/10160184984",
    "_lat": "50.4880789",
    "_lon": "2.717829",
    "_layer": "information_board",
    "_surface": "0",
    "_surface:ha": "0",
    "_length": "0",
    "_length:km": "0.0",
    "_last_edit:contributor": "Max_dbv",
    "_last_edit:contributor:uid": 15265748,
    "_last_edit:changeset": 128537125,
    "_last_edit:timestamp": "2022-11-05T21:24:03Z",
    "_version_number": 1,
    "_geometry:type": "Point",
    "_country": "fr"
   },
   "geometry": {
    "type": "Point",
    "coordinates": [
     2.717829,
     50.4880789
    ]
   },
   "_lon": 2.717829,
   "_lat": 50.4880789
  }
 ]
}