{
 "type": "FeatureCollection",
 "features": [
  {
   "type": "Feature",
   "id": "node/923241063",
   "properties": {
    "information": "board",
    "tourism": "information",
    "id": "node/923241063",
    "_lat": "50.5104627",
    "_lon": "6.1622016",
    "_layer": "information_board",
    "_surface": "0",
    "_surface:ha": "0",
    "_length": "0",
    "_length:km": "0.0",
    "_last_edit:contributor": "unixasket",
    "_last_edit:contributor:uid": 661499,
    "_last_edit:changeset": 11862710,
    "_last_edit:timestamp": "2012-06-11T09:06:52Z",
    "_version_number": 2,
    "_geometry:type": "Point",
    "_country": "be"
   },
   "geometry": {
    "type": "Point",
    "coordinates": [
     6.1622016,
     50.5104627
    ]
   },
   "_lon": 6.1622016,
   "_lat": 50.5104627
  },
  {
   "type": "Feature",
   "id": "node/8228956278",
   "properties": {
    "board_type": "history",
    "direction": "120",
    "ele": "463",
    "image": "https://www.zvs.be/wp-content/uploads/2018/03/Tafel48-08a-PD25.pdf",
    "information": "board",
    "name": "Au poste PD25bis",
    "name:de": "Am Posten PD25bis",
    "operator": "Kgl. Geschichts- und Museumsverein \"Zwischen Venn und Schneifel\"",
    "tourism": "information",
    "id": "node/8228956278",
    "_lat": "50.4950551",
    "_lon": "6.1709078",
    "_layer": "information_board",
    "_surface": "0",
    "_surface:ha": "0",
    "_length": "0",
    "_length:km": "0.0",
    "_direction:numerical": 120,
    "_direction:leftright": "right",
    "_last_edit:contributor": "xorx",
    "_last_edit:contributor:uid": 669961,
    "_last_edit:changeset": 122570185,
    "_last_edit:timestamp": "2022-06-19T08:07:19Z",
    "_version_number": 2,
    "_geometry:type": "Point",
    "_country": "be"
   },
   "geometry": {
    "type": "Point",
    "coordinates": [
     6.1709078,
     50.4950551
    ]
   },
   "_lon": 6.1709078,
   "_lat": 50.4950551
  }
 ]
}