{
 "type": "FeatureCollection",
 "features": [
  {
   "type": "Feature",
   "id": "node/1225794585",
   "properties": {
    "man_made": "watermill",
    "name": "Gitstappermolen",
    "id": "node/1225794585",
    "_lat": "51.13755",
    "_lon": "6.1086953",
    "_layer": "watermill",
    "_surface": "0",
    "_surface:ha": "0",
    "_length": "0",
    "_length:km": "0.0",
    "_last_edit:contributor": "jeroenrozema74",
    "_last_edit:contributor:uid": 183483,
    "_last_edit:changeset": 123571884,
    "_last_edit:timestamp": "2022-07-13T16:02:39Z",
    "_version_number": 3,
    "_geometry:type": "Point",
    "_country": "de"
   },
   "geometry": {
    "type": "Point",
    "coordinates": [
     6.1086953,
     51.13755
    ]
   },
   "_lon": 6.1086953,
   "_lat": 51.13755
  }
 ]
}