{
 "type": "FeatureCollection",
 "features": [
  {
   "type": "Feature",
   "id": "node/2612769395",
   "properties": {
    "man_made": "watermill",
    "name": "Riddermolen",
    "id": "node/2612769395",
    "_lat": "50.9540636",
    "_lon": "3.9506207",
    "_layer": "watermill",
    "_length": "0",
    "_length:km": "0.0",
    "_last_edit:contributor": "wegspotter",
    "_last_edit:contributor:uid": 428001,
    "_last_edit:changeset": 44190768,
    "_last_edit:timestamp": "2016-12-05T19:36:20Z",
    "_version_number": 2,
    "_geometry:type": "Point",
    "_country": "be"
   },
   "geometry": {
    "type": "Point",
    "coordinates": [
     3.9506207,
     50.9540636
    ]
   },
   "_lon": 3.9506207,
   "_lat": 50.9540636
  }
 ]
}