{
 "type": "FeatureCollection",
 "features": [
  {
   "type": "Feature",
   "id": "node/6566441898",
   "properties": {
    "information": "board",
    "name": "Schelde-Rijnkanaal",
    "tourism": "information",
    "id": "node/6566441898",
    "_lat": "51.5617817",
    "_lon": "4.2333065",
    "_layer": "information_board",
    "_length": "0",
    "_length:km": "0.0",
    "_last_edit:contributor": "Sint E7",
    "_last_edit:contributor:uid": 146393,
    "_last_edit:changeset": 71539129,
    "_last_edit:timestamp": "2019-06-23T18:57:52Z",
    "_version_number": 1,
    "_geometry:type": "Point",
    "_country": "nl"
   },
   "geometry": {
    "type": "Point",
    "coordinates": [
     4.2333065,
     51.5617817
    ]
   },
   "_lon": 4.2333065,
   "_lat": 51.5617817
  },
  {
   "type": "Feature",
   "id": "node/7955864747",
   "properties": {
    "information": "board",
    "tourism": "information",
    "id": "node/7955864747",
    "_lat": "51.5289104",
    "_lon": "4.2999747",
    "_layer": "information_board",
    "_length": "0",
    "_length:km": "0.0",
    "_last_edit:contributor": "FrankOverman",
    "_last_edit:contributor:uid": 1987570,
    "_last_edit:changeset": 91722366,
    "_last_edit:timestamp": "2020-09-29T17:37:35Z",
    "_version_number": 1,
    "_geometry:type": "Point",
    "_country": "nl"
   },
   "geometry": {
    "type": "Point",
    "coordinates": [
     4.2999747,
     51.5289104
    ]
   },
   "_lon": 4.2999747,
   "_lat": 51.5289104
  },
  {
   "type": "Feature",
   "id": "node/7955864748",
   "properties": {
    "information": "board",
    "tourism": "information",
    "id": "node/7955864748",
    "_lat": "51.5288534",
    "_lon": "4.3000344",
    "_layer": "information_board",
    "_length": "0",
    "_length:km": "0.0",
    "_last_edit:contributor": "FrankOverman",
    "_last_edit:contributor:uid": 1987570,
    "_last_edit:changeset": 91722366,
    "_last_edit:timestamp": "2020-09-29T17:37:35Z",
    "_version_number": 1,
    "_geometry:type": "Point",
    "_country": "nl"
   },
   "geometry": {
    "type": "Point",
    "coordinates": [
     4.3000344,
     51.5288534
    ]
   },
   "_lon": 4.3000344,
   "_lat": 51.5288534
  },
  {
   "type": "Feature",
   "id": "node/7955864749",
   "properties": {
    "information": "board",
    "tourism": "information",
    "id": "node/7955864749",
    "_lat": "51.5293931",
    "_lon": "4.298052",
    "_layer": "information_board",
    "_length": "0",
    "_length:km": "0.0",
    "_last_edit:contributor": "FrankOverman",
    "_last_edit:contributor:uid": 1987570,
    "_last_edit:changeset": 91722366,
    "_last_edit:timestamp": "2020-09-29T17:37:35Z",
    "_version_number": 1,
    "_geometry:type": "Point",
    "_country": "nl"
   },
   "geometry": {
    "type": "Point",
    "coordinates": [
     4.298052,
     51.5293931
    ]
   },
   "_lon": 4.298052,
   "_lat": 51.5293931
  }
 ]
}