{
 "type": "FeatureCollection",
 "features": [
  {
   "type": "Feature",
   "id": "node/9672755524",
   "properties": {
    "board_type": "information",
    "direction": "75",
    "information": "board",
    "name": "Cité du Bosquet",
    "operator": "Maisons & Cités",
    "tourism": "information",
    "id": "node/9672755524",
    "_lat": "50.3849654",
    "_lon": "3.4292652",
    "_layer": "information_board",
    "_surface": "0",
    "_surface:ha": "0",
    "_length": "0",
    "_length:km": "0.0",
    "_direction:numerical": 75,
    "_direction:leftright": "right",
    "_last_edit:contributor": "Olivier Gueguen",
    "_last_edit:contributor:uid": 9443043,
    "_last_edit:changeset": 119829664,
    "_last_edit:timestamp": "2022-04-17T19:42:39Z",
    "_version_number": 1,
    "_geometry:type": "Point",
    "_country": "fr"
   },
   "geometry": {
    "type": "Point",
    "coordinates": [
     3.4292652,
     50.3849654
    ]
   },
   "_lon": 3.4292652,
   "_lat": 50.3849654
  }
 ]
}