{
 "type": "FeatureCollection",
 "features": [
  {
   "type": "Feature",
   "id": "node/10177887237",
   "properties": {
    "access": "yes",
    "amenity": "toilets",
    "capacity:seated": "3",
    "capacity:urinal": "2",
    "toilets:handwashing": "yes",
    "toilets:paper_supplied": "yes",
    "toilets:position": "seated;urinal",
    "id": "node/10177887237",
    "_lat": "51.1174448",
    "_lon": "5.2480316",
    "_layer": "toilet",
    "_surface": "0",
    "_surface:ha": "0",
    "_length": "0",
    "_length:km": "0.0",
    "_last_edit:contributor": "Eebie",
    "_last_edit:contributor:uid": 715684,
    "_last_edit:changeset": 128806126,
    "_last_edit:timestamp": "2022-11-12T10:01:34Z",
    "_version_number": 1,
    "_geometry:type": "Point",
    "_country": "be"
   },
   "geometry": {
    "type": "Point",
    "coordinates": [
     5.2480316,
     51.1174448
    ]
   },
   "_lon": 5.2480316,
   "_lat": 51.1174448
  },
  {
   "type": "Feature",
   "id": "node/10177908679",
   "properties": {
    "access": "yes",
    "amenity": "toilets",
    "toilets:handwashing": "yes",
    "toilets:paper_supplied": "yes",
    "toilets:position": "seated",
    "id": "node/10177908679",
    "_lat": "51.1194808",
    "_lon": "5.2638225",
    "_layer": "toilet",
    "_surface": "0",
    "_surface:ha": "0",
    "_length": "0",
    "_length:km": "0.0",
    "_last_edit:contributor": "Eebie",
    "_last_edit:contributor:uid": 715684,
    "_last_edit:changeset": 128807069,
    "_last_edit:timestamp": "2022-11-12T10:34:21Z",
    "_version_number": 1,
    "_geometry:type": "Point",
    "_country": "be"
   },
   "geometry": {
    "type": "Point",
    "coordinates": [
     5.2638225,
     51.1194808
    ]
   },
   "_lon": 5.2638225,
   "_lat": 51.1194808
  }
 ]
}