{
 "type": "FeatureCollection",
 "features": [
  {
   "type": "Feature",
   "id": "node/9922360482",
   "properties": {
    "amenity": "drinking_water",
    "name": "Drinking water",
    "id": "node/9922360482",
    "_lat": "51.2333463",
    "_lon": "5.4345523",
    "_layer": "drinking_water",
    "_surface": "0",
    "_surface:ha": "0",
    "_length": "0",
    "_length:km": "0.0",
    "_last_edit:contributor": "EA99",
    "_last_edit:contributor:uid": 16672708,
    "_last_edit:changeset": 124302801,
    "_last_edit:timestamp": "2022-07-31T13:06:41Z",
    "_version_number": 1,
    "_geometry:type": "Point",
    "_country": "be",
    "_closest_other_drinking_water": "{\"id\":\"node/5914396587\",\"distance\":\"197.54932526100157\"}",
    "_closest_other_drinking_water_id": "node/5914396587",
    "_closest_other_drinking_water_distance": "197"
   },
   "geometry": {
    "type": "Point",
    "coordinates": [
     5.4345523,
     51.2333463
    ]
   },
   "_lon": 5.4345523,
   "_lat": 51.2333463,
   "_is_patched": true
  }
 ]
}