{
 "type": "FeatureCollection",
 "features": [
  {
   "type": "Feature",
   "id": "node/26859285",
   "properties": {
    "addr:city": "Oostkapelle",
    "addr:housenumber": "2a",
    "addr:postcode": "4356RJ",
    "addr:street": "Aagtekerkseweg",
    "backcountry": "no",
    "dog": "no",
    "drinking_water": "yes",
    "fee": "yes",
    "internet_access": "wlan",
    "internet_access:fee": "no",
    "name": "Ons Buiten",
    "openfire": "no",
    "phone": "+31.118.581813",
    "power_supply": "yes",
    "reservation": "recommended",
    "sanitary_dump_station": "yes",
    "shower": "yes",
    "toilets": "yes",
    "tourism": "camp_site",
    "website": "http://www.onsbuiten.nl",
    "wheelchair": "limited",
    "id": "node/26859285",
    "_lat": "51.5629432",
    "_lon": "3.5458107",
    "_layer": "drinking_water",
    "_surface": "0",
    "_surface:ha": "0",
    "_length": "0",
    "_length:km": "0.0",
    "_last_edit:contributor": "Schramme",
    "_last_edit:contributor:uid": 13382,
    "_last_edit:changeset": 124902687,
    "_last_edit:timestamp": "2022-08-14T20:29:27Z",
    "_version_number": 4,
    "_geometry:type": "Point",
    "_country": "nl",
    "_closest_other_drinking_water": "{\"id\":\"node/9954451096\",\"distance\":\"21.91212159020902\"}",
    "_closest_other_drinking_water_id": "node/9954451096",
    "_closest_other_drinking_water_distance": "21"
   },
   "geometry": {
    "type": "Point",
    "coordinates": [
     3.5458107,
     51.5629432
    ]
   },
   "_lon": 3.5458107,
   "_lat": 51.5629432,
   "_is_patched": true
  }
 ]
}