{
 "type": "FeatureCollection",
 "features": [
  {
   "type": "Feature",
   "id": "node/8599634822",
   "properties": {
    "board_type": "history",
    "information": "board",
    "name": "Château Seigneurial",
    "tourism": "information",
    "id": "node/8599634822",
    "_lat": "50.4343805",
    "_lon": "3.2439766",
    "_layer": "information_board",
    "_surface": "0",
    "_surface:ha": "0",
    "_length": "0",
    "_length:km": "0.0",
    "_last_edit:contributor": "Rems",
    "_last_edit:contributor:uid": 221860,
    "_last_edit:changeset": 102417762,
    "_last_edit:timestamp": "2021-04-06T15:23:42Z",
    "_version_number": 1,
    "_geometry:type": "Point",
    "_country": "fr"
   },
   "geometry": {
    "type": "Point",
    "coordinates": [
     3.2439766,
     50.4343805
    ]
   },
   "_lon": 3.2439766,
   "_lat": 50.4343805
  }
 ]
}