{
 "type": "FeatureCollection",
 "features": [
  {
   "type": "Feature",
   "id": "node/2906077862",
   "properties": {
    "board_type": "notice",
    "description": "Bus lines",
    "information": "board",
    "name": "Information TEC",
    "tourism": "information",
    "id": "node/2906077862",
    "_lat": "50.7233905",
    "_lon": "4.8774221",
    "_layer": "information_board",
    "_surface": "0",
    "_surface:ha": "0",
    "_length": "0",
    "_length:km": "0.0",
    "_last_edit:contributor": "Polyglot",
    "_last_edit:contributor:uid": 15188,
    "_last_edit:changeset": 22814307,
    "_last_edit:timestamp": "2014-06-08T17:35:04Z",
    "_version_number": 1,
    "_geometry:type": "Point",
    "_country": "be"
   },
   "geometry": {
    "type": "Point",
    "coordinates": [
     4.8774221,
     50.7233905
    ]
   },
   "_lon": 4.8774221,
   "_lat": 50.7233905
  },
  {
   "type": "Feature",
   "id": "node/8759746471",
   "properties": {
    "information": "board",
    "name": "Ravel",
    "tourism": "information",
    "id": "node/8759746471",
    "_lat": "50.723828",
    "_lon": "4.8776159",
    "_layer": "information_board",
    "_surface": "0",
    "_surface:ha": "0",
    "_length": "0",
    "_length:km": "0.0",
    "_last_edit:contributor": "Mizuna",
    "_last_edit:contributor:uid": 12496737,
    "_last_edit:changeset": 105203395,
    "_last_edit:timestamp": "2021-05-24T07:22:30Z",
    "_version_number": 1,
    "_geometry:type": "Point",
    "_country": "be"
   },
   "geometry": {
    "type": "Point",
    "coordinates": [
     4.8776159,
     50.723828
    ]
   },
   "_lon": 4.8776159,
   "_lat": 50.723828
  }
 ]
}