{
 "type": "FeatureCollection",
 "features": [
  {
   "type": "Feature",
   "id": "node/2008841047",
   "properties": {
    "description": "De oude beekloop in ere hersteld",
    "information": "board",
    "tourism": "information",
    "id": "node/2008841047",
    "_lat": "51.5050673",
    "_lon": "4.7815807",
    "_layer": "information_board",
    "_surface": "0",
    "_surface:ha": "0",
    "_length": "0",
    "_length:km": "0.0",
    "_last_edit:contributor": "de vries",
    "_last_edit:contributor:uid": 1707814,
    "_last_edit:changeset": 47319869,
    "_last_edit:timestamp": "2017-03-31T09:57:45Z",
    "_version_number": 2,
    "_geometry:type": "Point",
    "_country": "nl"
   },
   "geometry": {
    "type": "Point",
    "coordinates": [
     4.7815807,
     51.5050673
    ]
   },
   "_lon": 4.7815807,
   "_lat": 51.5050673
  },
  {
   "type": "Feature",
   "id": "node/7562613286",
   "properties": {
    "board_type": "nature",
    "information": "board",
    "name": "Zwartgoor (Smokkelroute)",
    "tourism": "information",
    "id": "node/7562613286",
    "_lat": "51.5001283",
    "_lon": "4.8228494",
    "_layer": "information_board",
    "_surface": "0",
    "_surface:ha": "0",
    "_length": "0",
    "_length:km": "0.0",
    "_last_edit:contributor": "staf",
    "_last_edit:contributor:uid": 377797,
    "_last_edit:changeset": 111376485,
    "_last_edit:timestamp": "2021-09-18T13:49:21Z",
    "_version_number": 3,
    "_geometry:type": "Point",
    "_country": "nl"
   },
   "geometry": {
    "type": "Point",
    "coordinates": [
     4.8228494,
     51.5001283
    ]
   },
   "_lon": 4.8228494,
   "_lat": 51.5001283
  },
  {
   "type": "Feature",
   "id": "node/8572980806",
   "properties": {
    "information": "board",
    "tourism": "information",
    "id": "node/8572980806",
    "_lat": "51.4739983",
    "_lon": "4.805279",
    "_layer": "information_board",
    "_surface": "0",
    "_surface:ha": "0",
    "_length": "0",
    "_length:km": "0.0",
    "_last_edit:contributor": "Stinus_Clasius",
    "_last_edit:contributor:uid": 1086503,
    "_last_edit:changeset": 101941226,
    "_last_edit:timestamp": "2021-03-29T21:28:30Z",
    "_version_number": 1,
    "_geometry:type": "Point",
    "_country": "be"
   },
   "geometry": {
    "type": "Point",
    "coordinates": [
     4.805279,
     51.4739983
    ]
   },
   "_lon": 4.805279,
   "_lat": 51.4739983
  }
 ]
}