{
 "type": "FeatureCollection",
 "features": [
  {
   "type": "Feature",
   "id": "node/2294787090",
   "properties": {
    "description": "Natuurpunt Hobokense Polder",
    "leisure": "bird_hide",
    "name": "Vogelkijkwand",
    "operator": "Natuurpunt",
    "tourism": "viewpoint",
    "id": "node/2294787090",
    "_lat": "51.1886252",
    "_lon": "4.3430927",
    "_layer": "birdhide",
    "_surface": "0",
    "_surface:ha": "0",
    "_length": "0",
    "_length:km": "0.0",
    "_last_edit:contributor": "Pieter Vander Vennet",
    "_last_edit:contributor:uid": 3818858,
    "_last_edit:changeset": 82546047,
    "_last_edit:timestamp": "2020-03-24T02:11:52Z",
    "_version_number": 4,
    "_geometry:type": "Point"
   },
   "geometry": {
    "type": "Point",
    "coordinates": [
     4.3430927,
     51.1886252
    ]
   },
   "_lon": 4.3430927,
   "_lat": 51.1886252
  },
  {
   "type": "Feature",
   "id": "node/8825287348",
   "properties": {
    "leisure": "bird_hide",
    "name": "Vogelkijkwand De IJsvogel",
    "operator": "Natuurpunt",
    "shelter": "no",
    "id": "node/8825287348",
    "_lat": "51.1880354",
    "_lon": "4.3457975",
    "_layer": "birdhide",
    "_surface": "0",
    "_surface:ha": "0",
    "_length": "0",
    "_length:km": "0.0",
    "_last_edit:contributor": "JanFi",
    "_last_edit:contributor:uid": 672253,
    "_last_edit:changeset": 123141217,
    "_last_edit:timestamp": "2022-07-03T07:28:20Z",
    "_version_number": 3,
    "_geometry:type": "Point"
   },
   "geometry": {
    "type": "Point",
    "coordinates": [
     4.3457975,
     51.1880354
    ]
   },
   "_lon": 4.3457975,
   "_lat": 51.1880354
  }
 ]
}