{
 "type": "FeatureCollection",
 "features": [
  {
   "type": "Feature",
   "id": "node/1369285568",
   "properties": {
    "board_type": "history",
    "information": "board",
    "tourism": "information",
    "id": "node/1369285568",
    "_lat": "50.9579087",
    "_lon": "4.7209296",
    "_layer": "information_board",
    "_length": "0",
    "_length:km": "0.0",
    "_last_edit:contributor": "escada",
    "_last_edit:contributor:uid": 436365,
    "_last_edit:changeset": 8791343,
    "_last_edit:timestamp": "2011-07-21T18:46:42Z",
    "_version_number": 1,
    "_geometry:type": "Point"
   },
   "geometry": {
    "type": "Point",
    "coordinates": [
     4.7209296,
     50.9579087
    ]
   },
   "_lon": 4.7209296,
   "_lat": 50.9579087
  },
  {
   "type": "Feature",
   "id": "node/2319729104",
   "properties": {
    "board_type": "board",
    "information": "board",
    "name": "Onze Lieve Vrouw van Troost-kapel",
    "tourism": "information",
    "id": "node/2319729104",
    "_lat": "50.9437985",
    "_lon": "4.6635434",
    "_layer": "information_board",
    "_length": "0",
    "_length:km": "0.0",
    "_last_edit:contributor": "GuyVV",
    "_last_edit:contributor:uid": 579178,
    "_last_edit:changeset": 16281221,
    "_last_edit:timestamp": "2013-05-25T16:09:55Z",
    "_version_number": 1,
    "_geometry:type": "Point"
   },
   "geometry": {
    "type": "Point",
    "coordinates": [
     4.6635434,
     50.9437985
    ]
   },
   "_lon": 4.6635434,
   "_lat": 50.9437985
  },
  {
   "type": "Feature",
   "id": "node/6396963713",
   "properties": {
    "information": "board",
    "tourism": "information",
    "id": "node/6396963713",
    "_lat": "50.9033736",
    "_lon": "4.6748367",
    "_layer": "information_board",
    "_length": "0",
    "_length:km": "0.0",
    "_last_edit:contributor": "Jakka",
    "_last_edit:contributor:uid": 2403313,
    "_last_edit:changeset": 69092151,
    "_last_edit:timestamp": "2019-04-10T17:50:33Z",
    "_version_number": 1,
    "_geometry:type": "Point"
   },
   "geometry": {
    "type": "Point",
    "coordinates": [
     4.6748367,
     50.9033736
    ]
   },
   "_lon": 4.6748367,
   "_lat": 50.9033736
  },
  {
   "type": "Feature",
   "id": "node/8109843125",
   "properties": {
    "board_type": "nature",
    "information": "board",
    "name": "De Gevel",
    "operator": "Agentschap Natuur & Bos",
    "tourism": "information",
    "id": "node/8109843125",
    "_lat": "50.9428248",
    "_lon": "4.7078586",
    "_layer": "information_board",
    "_length": "0",
    "_length:km": "0.0",
    "_last_edit:contributor": "GR-menneke",
    "_last_edit:contributor:uid": 2353901,
    "_last_edit:changeset": 93956763,
    "_last_edit:timestamp": "2020-11-12T00:13:19Z",
    "_version_number": 1,
    "_geometry:type": "Point"
   },
   "geometry": {
    "type": "Point",
    "coordinates": [
     4.7078586,
     50.9428248
    ]
   },
   "_lon": 4.7078586,
   "_lat": 50.9428248
  }
 ]
}