{
 "type": "FeatureCollection",
 "features": [
  {
   "type": "Feature",
   "id": "node/6879899087",
   "properties": {
    "access": "yes",
    "amenity": "toilets",
    "capacity:seated": "1",
    "description": "Composttoilet",
    "fee": "no",
    "toilets:disposal": "dry_toilet",
    "toilets:handwashing": "yes",
    "toilets:paper_supplied": "yes",
    "toilets:position": "seated",
    "wheelchair": "no",
    "id": "node/6879899087",
    "_lat": "50.7915562",
    "_lon": "5.3544439",
    "_layer": "toilet",
    "_surface": "0",
    "_surface:ha": "0",
    "_length": "0",
    "_length:km": "0.0",
    "_last_edit:contributor": "Wolderik",
    "_last_edit:contributor:uid": 471204,
    "_last_edit:changeset": 119923925,
    "_last_edit:timestamp": "2022-04-19T20:09:11Z",
    "_version_number": 5,
    "_geometry:type": "Point",
    "_country": "be"
   },
   "geometry": {
    "type": "Point",
    "coordinates": [
     5.3544439,
     50.7915562
    ]
   },
   "_lon": 5.3544439,
   "_lat": 50.7915562
  }
 ]
}