{
 "type": "FeatureCollection",
 "features": [
  {
   "type": "Feature",
   "id": "node/2151873524",
   "properties": {
    "information": "board",
    "tourism": "information",
    "id": "node/2151873524",
    "_lat": "51.5264507",
    "_lon": "5.7971859",
    "_layer": "information_board",
    "_length": "0",
    "_length:km": "0.0",
    "_last_edit:contributor": "Kogacarlo",
    "_last_edit:contributor:uid": 324890,
    "_last_edit:changeset": 113259482,
    "_last_edit:timestamp": "2021-11-01T23:56:42Z",
    "_version_number": 2,
    "_country": "nl"
   },
   "geometry": {
    "type": "Point",
    "coordinates": [
     5.7971859,
     51.5264507
    ]
   },
   "_lon": 5.7971859,
   "_lat": 51.5264507
  },
  {
   "type": "Feature",
   "id": "node/5729554570",
   "properties": {
    "information": "board",
    "tourism": "information",
    "id": "node/5729554570",
    "_lat": "51.5416779",
    "_lon": "5.748075",
    "_layer": "information_board",
    "_length": "0",
    "_length:km": "0.0",
    "_last_edit:contributor": "byckel",
    "_last_edit:contributor:uid": 2195662,
    "_last_edit:changeset": 60294040,
    "_last_edit:timestamp": "2018-06-30T05:40:58Z",
    "_version_number": 1,
    "_country": "nl"
   },
   "geometry": {
    "type": "Point",
    "coordinates": [
     5.748075,
     51.5416779
    ]
   },
   "_lon": 5.748075,
   "_lat": 51.5416779
  },
  {
   "type": "Feature",
   "id": "node/6141092023",
   "properties": {
    "bicycle": "yes",
    "fixme": "Resurvey needed to establish exact location",
    "highway": "trailhead",
    "hiking": "yes",
    "information": "board",
    "name": "Natuurpoort Nederheide",
    "note": "Location is not confirmed by air view or field view",
    "source": "gpsfietsroutesnederland.nl",
    "tourism": "information",
    "url": "https://gpsfietsroutesnederland.nl/toeristische-overstappunten/",
    "website": "https://www.natuurpoorten.nl/",
    "wikipedia": "nl:Toeristisch Overstappunt",
    "id": "node/6141092023",
    "_lat": "51.5183631",
    "_lon": "5.7863017",
    "_layer": "information_board",
    "_length": "0",
    "_length:km": "0.0",
    "_last_edit:contributor": "Peter Elderson",
    "_last_edit:contributor:uid": 7103674,
    "_last_edit:changeset": 65531302,
    "_last_edit:timestamp": "2018-12-16T20:34:47Z",
    "_version_number": 1,
    "_country": "nl"
   },
   "geometry": {
    "type": "Point",
    "coordinates": [
     5.7863017,
     51.5183631
    ]
   },
   "_lon": 5.7863017,
   "_lat": 51.5183631
  },
  {
   "type": "Feature",
   "id": "node/6635496341",
   "properties": {
    "board_type": "history",
    "information": "board",
    "tourism": "information",
    "id": "node/6635496341",
    "_lat": "51.5570645",
    "_lon": "5.7855654",
    "_layer": "information_board",
    "_length": "0",
    "_length:km": "0.0",
    "_last_edit:contributor": "byckel",
    "_last_edit:contributor:uid": 2195662,
    "_last_edit:changeset": 72486070,
    "_last_edit:timestamp": "2019-07-21T16:03:38Z",
    "_version_number": 1,
    "_country": "nl"
   },
   "geometry": {
    "type": "Point",
    "coordinates": [
     5.7855654,
     51.5570645
    ]
   },
   "_lon": 5.7855654,
   "_lat": 51.5570645
  }
 ]
}