{
 "type": "FeatureCollection",
 "features": [
  {
   "type": "Feature",
   "id": "node/3257174741",
   "properties": {
    "board_type": "notice",
    "information": "board",
    "name": "Rendez-Vous avec le Nord",
    "tourism": "information",
    "id": "node/3257174741",
    "_lat": "50.8091495",
    "_lon": "2.5775314",
    "_layer": "information_board",
    "_length": "0",
    "_length:km": "0.0",
    "_last_edit:contributor": "Bernard59118",
    "_last_edit:contributor:uid": 136303,
    "_last_edit:changeset": 27761880,
    "_last_edit:timestamp": "2014-12-28T19:47:06Z",
    "_version_number": 1,
    "_geometry:type": "Point"
   },
   "geometry": {
    "type": "Point",
    "coordinates": [
     2.5775314,
     50.8091495
    ]
   },
   "_lon": 2.5775314,
   "_lat": 50.8091495
  }
 ]
}