{
 "type": "FeatureCollection",
 "features": [
  {
   "type": "Feature",
   "id": "node/1777173388",
   "properties": {
    "board_type": "nature",
    "information": "board",
    "name": "Point d'information",
    "tourism": "information",
    "id": "node/1777173388",
    "_lat": "51.0591468",
    "_lon": "2.4489473",
    "_layer": "information_board",
    "_surface": "0",
    "_surface:ha": "0",
    "_length": "0",
    "_length:km": "0.0",
    "_last_edit:contributor": "Alexb60",
    "_last_edit:contributor:uid": 7453584,
    "_last_edit:changeset": 131029735,
    "_last_edit:timestamp": "2023-01-08T20:26:15Z",
    "_version_number": 4,
    "_geometry:type": "Point"
   },
   "geometry": {
    "type": "Point",
    "coordinates": [
     2.4489473,
     51.0591468
    ]
   },
   "_lon": 2.4489473,
   "_lat": 51.0591468
  },
  {
   "type": "Feature",
   "id": "node/5821355902",
   "properties": {
    "board_type": "history",
    "information": "board",
    "tourism": "information",
    "id": "node/5821355902",
    "_lat": "51.0488913",
    "_lon": "2.3832254",
    "_layer": "information_board",
    "_surface": "0",
    "_surface:ha": "0",
    "_length": "0",
    "_length:km": "0.0",
    "_last_edit:contributor": "widowild",
    "_last_edit:contributor:uid": 1504287,
    "_last_edit:changeset": 90145847,
    "_last_edit:timestamp": "2020-08-30T13:41:19Z",
    "_version_number": 2,
    "_geometry:type": "Point"
   },
   "geometry": {
    "type": "Point",
    "coordinates": [
     2.3832254,
     51.0488913
    ]
   },
   "_lon": 2.3832254,
   "_lat": 51.0488913
  },
  {
   "type": "Feature",
   "id": "node/6774985169",
   "properties": {
    "information": "board",
    "tourism": "information",
    "id": "node/6774985169",
    "_lat": "51.0315428",
    "_lon": "2.4055275",
    "_layer": "information_board",
    "_surface": "0",
    "_surface:ha": "0",
    "_length": "0",
    "_length:km": "0.0",
    "_last_edit:contributor": "Alexb60",
    "_last_edit:contributor:uid": 7453584,
    "_last_edit:changeset": 74140589,
    "_last_edit:timestamp": "2019-09-05T15:17:35Z",
    "_version_number": 1,
    "_geometry:type": "Point"
   },
   "geometry": {
    "type": "Point",
    "coordinates": [
     2.4055275,
     51.0315428
    ]
   },
   "_lon": 2.4055275,
   "_lat": 51.0315428
  },
  {
   "type": "Feature",
   "id": "node/7858419340",
   "properties": {
    "information": "board",
    "name": "Le P’tit Monde du Parc de Malo",
    "tourism": "information",
    "id": "node/7858419340",
    "_lat": "51.0462795",
    "_lon": "2.3911853",
    "_layer": "information_board",
    "_surface": "0",
    "_surface:ha": "0",
    "_length": "0",
    "_length:km": "0.0",
    "_last_edit:contributor": "Alexb60",
    "_last_edit:contributor:uid": 7453584,
    "_last_edit:changeset": 128700623,
    "_last_edit:timestamp": "2022-11-09T19:07:08Z",
    "_version_number": 2,
    "_geometry:type": "Point"
   },
   "geometry": {
    "type": "Point",
    "coordinates": [
     2.3911853,
     51.0462795
    ]
   },
   "_lon": 2.3911853,
   "_lat": 51.0462795
  },
  {
   "type": "Feature",
   "id": "node/10293395709",
   "properties": {
    "board_type": "history",
    "information": "board",
    "name": "Histoire de la Cité - L'Hôtel de Chosal",
    "survey:date": "2022-12-24",
    "tourism": "information",
    "id": "node/10293395709",
    "_lat": "51.0373953",
    "_lon": "2.3754961",
    "_layer": "information_board",
    "_surface": "0",
    "_surface:ha": "0",
    "_length": "0",
    "_length:km": "0.0",
    "_last_edit:contributor": "Alexb60",
    "_last_edit:contributor:uid": 7453584,
    "_last_edit:changeset": 130732890,
    "_last_edit:timestamp": "2022-12-31T20:27:59Z",
    "_version_number": 2,
    "_geometry:type": "Point"
   },
   "geometry": {
    "type": "Point",
    "coordinates": [
     2.3754961,
     51.0373953
    ]
   },
   "_lon": 2.3754961,
   "_lat": 51.0373953
  }
 ]
}