{
 "type": "FeatureCollection",
 "features": [
  {
   "type": "Feature",
   "id": "node/5006009827",
   "properties": {
    "information": "board",
    "name": "Panneau d'information LIFE Elia-RTE",
    "operator": "LIFE Elia-RTE",
    "tourism": "information",
    "website": "http://www.life-elia.eu",
    "id": "node/5006009827",
    "_lat": "50.5790886",
    "_lon": "5.4245571",
    "_layer": "information_board",
    "_length": "0",
    "_length:km": "0.0",
    "_last_edit:contributor": "JFGodeau",
    "_last_edit:contributor:uid": 3700778,
    "_last_edit:changeset": 50734590,
    "_last_edit:timestamp": "2017-07-31T22:18:34Z",
    "_version_number": 1,
    "_geometry:type": "Point"
   },
   "geometry": {
    "type": "Point",
    "coordinates": [
     5.4245571,
     50.5790886
    ]
   },
   "_lon": 5.4245571,
   "_lat": 50.5790886
  },
  {
   "type": "Feature",
   "id": "node/6765221591",
   "properties": {
    "board_type": "geology",
    "information": "board",
    "name": "Tchafornis",
    "tourism": "information",
    "id": "node/6765221591",
    "_lat": "50.584236",
    "_lon": "5.4056249",
    "_layer": "information_board",
    "_length": "0",
    "_length:km": "0.0",
    "_last_edit:contributor": "Eebie",
    "_last_edit:contributor:uid": 715684,
    "_last_edit:changeset": 73983317,
    "_last_edit:timestamp": "2019-09-01T22:27:30Z",
    "_version_number": 1,
    "_geometry:type": "Point"
   },
   "geometry": {
    "type": "Point",
    "coordinates": [
     5.4056249,
     50.584236
    ]
   },
   "_lon": 5.4056249,
   "_lat": 50.584236
  },
  {
   "type": "Feature",
   "id": "node/6765221620",
   "properties": {
    "information": "board",
    "name": "Schmerling",
    "tourism": "information",
    "id": "node/6765221620",
    "_lat": "50.5837924",
    "_lon": "5.4035309",
    "_layer": "information_board",
    "_length": "0",
    "_length:km": "0.0",
    "_last_edit:contributor": "Eebie",
    "_last_edit:contributor:uid": 715684,
    "_last_edit:changeset": 73983317,
    "_last_edit:timestamp": "2019-09-01T22:27:30Z",
    "_version_number": 1,
    "_geometry:type": "Point"
   },
   "geometry": {
    "type": "Point",
    "coordinates": [
     5.4035309,
     50.5837924
    ]
   },
   "_lon": 5.4035309,
   "_lat": 50.5837924
  }
 ]
}