{
 "type": "FeatureCollection",
 "features": [
  {
   "type": "Feature",
   "id": "node/5274265055",
   "properties": {
    "information": "board",
    "tourism": "information",
    "id": "node/5274265055",
    "_lat": "50.6551042",
    "_lon": "3.3994788",
    "_layer": "information_board",
    "_surface": "0",
    "_surface:ha": "0",
    "_length": "0",
    "_length:km": "0.0",
    "_last_edit:contributor": "magiraud",
    "_last_edit:contributor:uid": 65155,
    "_last_edit:changeset": 54497173,
    "_last_edit:timestamp": "2017-12-09T21:42:31Z",
    "_version_number": 1,
    "_geometry:type": "Point",
    "_country": "be"
   },
   "geometry": {
    "type": "Point",
    "coordinates": [
     3.3994788,
     50.6551042
    ]
   },
   "_lon": 3.3994788,
   "_lat": 50.6551042
  },
  {
   "type": "Feature",
   "id": "node/8695288517",
   "properties": {
    "bicycle": "yes",
    "information": "board",
    "name": "Pecq",
    "tourism": "information",
    "id": "node/8695288517",
    "_lat": "50.6741747",
    "_lon": "3.3540155",
    "_layer": "information_board",
    "_surface": "0",
    "_surface:ha": "0",
    "_length": "0",
    "_length:km": "0.0",
    "_last_edit:contributor": "vjyblauw",
    "_last_edit:contributor:uid": 2844254,
    "_last_edit:changeset": 126959346,
    "_last_edit:timestamp": "2022-10-03T21:06:02Z",
    "_version_number": 2,
    "_geometry:type": "Point",
    "_country": "be"
   },
   "geometry": {
    "type": "Point",
    "coordinates": [
     3.3540155,
     50.6741747
    ]
   },
   "_lon": 3.3540155,
   "_lat": 50.6741747
  }
 ]
}