{
 "type": "FeatureCollection",
 "features": [
  {
   "type": "Feature",
   "id": "node/2375387592",
   "properties": {
    "hiking": "yes",
    "information": "board",
    "name": "Wandelnetwerk Venlo",
    "tourism": "information",
    "id": "node/2375387592",
    "_lat": "51.4095412",
    "_lon": "6.1174739",
    "_layer": "information_board",
    "_surface": "0",
    "_surface:ha": "0",
    "_length": "0",
    "_length:km": "0.0",
    "_last_edit:contributor": "JanWandelaar",
    "_last_edit:contributor:uid": 424172,
    "_last_edit:changeset": 18073381,
    "_last_edit:timestamp": "2013-09-28T08:52:30Z",
    "_version_number": 2,
    "_geometry:type": "Point"
   },
   "geometry": {
    "type": "Point",
    "coordinates": [
     6.1174739,
     51.4095412
    ]
   },
   "_lon": 6.1174739,
   "_lat": 51.4095412
  },
  {
   "type": "Feature",
   "id": "node/9633262406",
   "properties": {
    "board:title": "Het Gebroken Slot",
    "board_type": "history",
    "information": "board",
    "tourism": "information",
    "id": "node/9633262406",
    "_lat": "51.4103374",
    "_lon": "6.1461688",
    "_layer": "information_board",
    "_surface": "0",
    "_surface:ha": "0",
    "_length": "0",
    "_length:km": "0.0",
    "_last_edit:contributor": "byckel",
    "_last_edit:contributor:uid": 2195662,
    "_last_edit:changeset": 119262221,
    "_last_edit:timestamp": "2022-04-03T12:06:33Z",
    "_version_number": 1,
    "_geometry:type": "Point"
   },
   "geometry": {
    "type": "Point",
    "coordinates": [
     6.1461688,
     51.4103374
    ]
   },
   "_lon": 6.1461688,
   "_lat": 51.4103374
  }
 ]
}