{
 "type": "FeatureCollection",
 "features": [
  {
   "type": "Feature",
   "id": "node/10087873840",
   "properties": {
    "information": "board",
    "name": "Réserve naturelle communale",
    "tourism": "information",
    "id": "node/10087873840",
    "_lat": "50.6616691",
    "_lon": "5.4319819",
    "_layer": "information_board",
    "_surface": "0",
    "_surface:ha": "0",
    "_length": "0",
    "_length:km": "0.0",
    "_last_edit:contributor": "Eebie",
    "_last_edit:contributor:uid": 715684,
    "_last_edit:changeset": 127269107,
    "_last_edit:timestamp": "2022-10-09T21:23:16Z",
    "_version_number": 1,
    "_geometry:type": "Point"
   },
   "geometry": {
    "type": "Point",
    "coordinates": [
     5.4319819,
     50.6616691
    ]
   },
   "_lon": 5.4319819,
   "_lat": 50.6616691
  }
 ]
}