{
 "type": "FeatureCollection",
 "features": [
  {
   "type": "Feature",
   "id": "node/7510186498",
   "properties": {
    "information": "board",
    "tourism": "information",
    "id": "node/7510186498",
    "_lat": "51.3628657",
    "_lon": "5.0158308",
    "_layer": "information_board",
    "_length": "0",
    "_length:km": "0.0",
    "_last_edit:contributor": "StijnRR",
    "_last_edit:contributor:uid": 911613,
    "_last_edit:changeset": 115137471,
    "_last_edit:timestamp": "2021-12-19T19:36:07Z",
    "_version_number": 2,
    "_geometry:type": "Point"
   },
   "geometry": {
    "type": "Point",
    "coordinates": [
     5.0158308,
     51.3628657
    ]
   },
   "_lon": 5.0158308,
   "_lat": 51.3628657
  },
  {
   "type": "Feature",
   "id": "node/7510463402",
   "properties": {
    "information": "board",
    "name": "Welkom in Gewestbos Ravels",
    "tourism": "information",
    "id": "node/7510463402",
    "_lat": "51.3776154",
    "_lon": "5.0345693",
    "_layer": "information_board",
    "_length": "0",
    "_length:km": "0.0",
    "_last_edit:contributor": "StijnRR",
    "_last_edit:contributor:uid": 911613,
    "_last_edit:changeset": 115767616,
    "_last_edit:timestamp": "2022-01-04T19:03:35Z",
    "_version_number": 2,
    "_geometry:type": "Point"
   },
   "geometry": {
    "type": "Point",
    "coordinates": [
     5.0345693,
     51.3776154
    ]
   },
   "_lon": 5.0345693,
   "_lat": 51.3776154
  },
  {
   "type": "Feature",
   "id": "node/9392782391",
   "properties": {
    "information": "board",
    "tourism": "information",
    "id": "node/9392782391",
    "_lat": "51.3796699",
    "_lon": "5.0463194",
    "_layer": "information_board",
    "_length": "0",
    "_length:km": "0.0",
    "_last_edit:contributor": "StijnRR",
    "_last_edit:contributor:uid": 911613,
    "_last_edit:changeset": 115767616,
    "_last_edit:timestamp": "2022-01-04T19:03:35Z",
    "_version_number": 1,
    "_geometry:type": "Point"
   },
   "geometry": {
    "type": "Point",
    "coordinates": [
     5.0463194,
     51.3796699
    ]
   },
   "_lon": 5.0463194,
   "_lat": 51.3796699
  }
 ]
}