{
 "type": "FeatureCollection",
 "features": [
  {
   "type": "Feature",
   "id": "node/8482466576",
   "properties": {
    "board_type": "map",
    "information": "board",
    "tourism": "information",
    "id": "node/8482466576",
    "_lat": "50.6237114",
    "_lon": "4.8138846",
    "_layer": "information_board",
    "_surface": "0",
    "_surface:ha": "0",
    "_length": "0",
    "_length:km": "0.0",
    "_last_edit:contributor": "Jakka",
    "_last_edit:contributor:uid": 2403313,
    "_last_edit:changeset": 100342240,
    "_last_edit:timestamp": "2021-03-03T10:39:02Z",
    "_version_number": 1,
    "_geometry:type": "Point"
   },
   "geometry": {
    "type": "Point",
    "coordinates": [
     4.8138846,
     50.6237114
    ]
   },
   "_lon": 4.8138846,
   "_lat": 50.6237114
  },
  {
   "type": "Feature",
   "id": "node/8644088626",
   "properties": {
    "information": "board",
    "name": "Le gros chêne",
    "tourism": "information",
    "id": "node/8644088626",
    "_lat": "50.5841779",
    "_lon": "4.8279318",
    "_layer": "information_board",
    "_surface": "0",
    "_surface:ha": "0",
    "_length": "0",
    "_length:km": "0.0",
    "_last_edit:contributor": "Eebie",
    "_last_edit:contributor:uid": 715684,
    "_last_edit:changeset": 103206217,
    "_last_edit:timestamp": "2021-04-19T14:47:23Z",
    "_version_number": 1,
    "_geometry:type": "Point"
   },
   "geometry": {
    "type": "Point",
    "coordinates": [
     4.8279318,
     50.5841779
    ]
   },
   "_lon": 4.8279318,
   "_lat": 50.5841779
  }
 ]
}