{
 "type": "FeatureCollection",
 "features": [
  {
   "type": "Feature",
   "id": "node/2801439096",
   "properties": {
    "board_type": "history",
    "information": "board",
    "tourism": "information",
    "id": "node/2801439096",
    "_lat": "51.3944729",
    "_lon": "3.5616443",
    "_layer": "information_board",
    "_surface": "0",
    "_surface:ha": "0",
    "_length": "0",
    "_length:km": "0.0",
    "_last_edit:contributor": "peeweeke",
    "_last_edit:contributor:uid": 494726,
    "_last_edit:changeset": 21800507,
    "_last_edit:timestamp": "2014-04-19T16:16:29Z",
    "_version_number": 1,
    "_geometry:type": "Point",
    "_country": "nl"
   },
   "geometry": {
    "type": "Point",
    "coordinates": [
     3.5616443,
     51.3944729
    ]
   },
   "_lon": 3.5616443,
   "_lat": 51.3944729
  },
  {
   "type": "Feature",
   "id": "node/5775865636",
   "properties": {
    "board_type": "notice",
    "description": "rondvaart",
    "information": "board",
    "name": "Rederij de Festijn",
    "tourism": "information",
    "website": "https://defestijn.nl",
    "id": "node/5775865636",
    "_lat": "51.3961312",
    "_lon": "3.5626978",
    "_layer": "information_board",
    "_surface": "0",
    "_surface:ha": "0",
    "_length": "0",
    "_length:km": "0.0",
    "_last_edit:contributor": "AdVerburg",
    "_last_edit:contributor:uid": 2831457,
    "_last_edit:changeset": 74918419,
    "_last_edit:timestamp": "2019-09-25T16:04:48Z",
    "_version_number": 2,
    "_geometry:type": "Point",
    "_country": "nl"
   },
   "geometry": {
    "type": "Point",
    "coordinates": [
     3.5626978,
     51.3961312
    ]
   },
   "_lon": 3.5626978,
   "_lat": 51.3961312
  }
 ]
}