{
 "type": "FeatureCollection",
 "features": [
  {
   "type": "Feature",
   "id": "node/2855298861",
   "properties": {
    "board_type": "history",
    "description": "Le Patrimoine de Douai",
    "information": "board",
    "name": "La Scarpe Inférieure",
    "tourism": "information",
    "id": "node/2855298861",
    "_lat": "50.3910139",
    "_lon": "3.1013126",
    "_layer": "information_board",
    "_length": "0",
    "_length:km": "0.0",
    "_last_edit:contributor": "Bernard59118",
    "_last_edit:contributor:uid": 136303,
    "_last_edit:changeset": 22312300,
    "_last_edit:timestamp": "2014-05-13T12:41:56Z",
    "_version_number": 1,
    "_geometry:type": "Point",
    "_country": "fr"
   },
   "geometry": {
    "type": "Point",
    "coordinates": [
     3.1013126,
     50.3910139
    ]
   },
   "_lon": 3.1013126,
   "_lat": 50.3910139
  },
  {
   "type": "Feature",
   "id": "node/7981628173",
   "properties": {
    "information": "board",
    "tourism": "information",
    "id": "node/7981628173",
    "_lat": "50.3500442",
    "_lon": "3.0876048",
    "_layer": "information_board",
    "_length": "0",
    "_length:km": "0.0",
    "_last_edit:contributor": "widowild",
    "_last_edit:contributor:uid": 1504287,
    "_last_edit:changeset": 92057066,
    "_last_edit:timestamp": "2020-10-06T14:58:12Z",
    "_version_number": 1,
    "_geometry:type": "Point",
    "_country": "fr"
   },
   "geometry": {
    "type": "Point",
    "coordinates": [
     3.0876048,
     50.3500442
    ]
   },
   "_lon": 3.0876048,
   "_lat": 50.3500442
  }
 ]
}