{
 "type": "FeatureCollection",
 "features": [
  {
   "type": "Feature",
   "id": "node/6815197340",
   "properties": {
    "leisure": "picnic_table",
    "name": "Picknicken",
    "id": "node/6815197340",
    "_lat": "50.5874997",
    "_lon": "2.1162396",
    "_layer": "picnic_table",
    "_surface": "0",
    "_surface:ha": "0",
    "_length": "0",
    "_length:km": "0.0",
    "_last_edit:contributor": "Janiek",
    "_last_edit:contributor:uid": 1705002,
    "_last_edit:changeset": 74766157,
    "_last_edit:timestamp": "2019-09-22T08:18:20Z",
    "_version_number": 1,
    "_geometry:type": "Point"
   },
   "geometry": {
    "type": "Point",
    "coordinates": [
     2.1162396,
     50.5874997
    ]
   },
   "_lon": 2.1162396,
   "_lat": 50.5874997
  },
  {
   "type": "Feature",
   "id": "node/6815210770",
   "properties": {
    "leisure": "picnic_table",
    "name": "Picknicken",
    "id": "node/6815210770",
    "_lat": "50.5939949",
    "_lon": "2.1199399",
    "_layer": "picnic_table",
    "_surface": "0",
    "_surface:ha": "0",
    "_length": "0",
    "_length:km": "0.0",
    "_last_edit:contributor": "Janiek",
    "_last_edit:contributor:uid": 1705002,
    "_last_edit:changeset": 74766350,
    "_last_edit:timestamp": "2019-09-22T08:28:37Z",
    "_version_number": 1,
    "_geometry:type": "Point"
   },
   "geometry": {
    "type": "Point",
    "coordinates": [
     2.1199399,
     50.5939949
    ]
   },
   "_lon": 2.1199399,
   "_lat": 50.5939949
  }
 ]
}