{
 "type": "FeatureCollection",
 "features": [
  {
   "type": "Feature",
   "id": "node/3376996972",
   "properties": {
    "information": "board",
    "name": "Réserve Naturelle du Coteau de Mont",
    "tourism": "information",
    "id": "node/3376996972",
    "_lat": "50.5400436",
    "_lon": "5.8052239",
    "_layer": "information_board",
    "_surface": "0",
    "_surface:ha": "0",
    "_length": "0",
    "_length:km": "0.0",
    "_last_edit:contributor": "StijnRR",
    "_last_edit:contributor:uid": 911613,
    "_last_edit:changeset": 29164895,
    "_last_edit:timestamp": "2015-02-28T20:39:21Z",
    "_version_number": 1,
    "_geometry:type": "Point"
   },
   "geometry": {
    "type": "Point",
    "coordinates": [
     5.8052239,
     50.5400436
    ]
   },
   "_lon": 5.8052239,
   "_lat": 50.5400436
  },
  {
   "type": "Feature",
   "id": "node/5004631149",
   "properties": {
    "board_type": "hikingmap",
    "information": "board",
    "tourism": "information",
    "id": "node/5004631149",
    "_lat": "50.5687365",
    "_lon": "5.8567041",
    "_layer": "information_board",
    "_surface": "0",
    "_surface:ha": "0",
    "_length": "0",
    "_length:km": "0.0",
    "_last_edit:contributor": "The RedBurn",
    "_last_edit:contributor:uid": 23835,
    "_last_edit:changeset": 109483806,
    "_last_edit:timestamp": "2021-08-10T20:44:20Z",
    "_version_number": 3,
    "_geometry:type": "Point"
   },
   "geometry": {
    "type": "Point",
    "coordinates": [
     5.8567041,
     50.5687365
    ]
   },
   "_lon": 5.8567041,
   "_lat": 50.5687365
  },
  {
   "type": "Feature",
   "id": "node/8996837611",
   "properties": {
    "board_type": "nature",
    "information": "board",
    "tourism": "information",
    "id": "node/8996837611",
    "_lat": "50.5673449",
    "_lon": "5.8519775",
    "_layer": "information_board",
    "_surface": "0",
    "_surface:ha": "0",
    "_length": "0",
    "_length:km": "0.0",
    "_last_edit:contributor": "The RedBurn",
    "_last_edit:contributor:uid": 23835,
    "_last_edit:changeset": 109482048,
    "_last_edit:timestamp": "2021-08-10T19:50:46Z",
    "_version_number": 1,
    "_geometry:type": "Point"
   },
   "geometry": {
    "type": "Point",
    "coordinates": [
     5.8519775,
     50.5673449
    ]
   },
   "_lon": 5.8519775,
   "_lat": 50.5673449
  },
  {
   "type": "Feature",
   "id": "node/8996837612",
   "properties": {
    "board_type": "nature",
    "information": "board",
    "tourism": "information",
    "id": "node/8996837612",
    "_lat": "50.5676458",
    "_lon": "5.8519486",
    "_layer": "information_board",
    "_surface": "0",
    "_surface:ha": "0",
    "_length": "0",
    "_length:km": "0.0",
    "_last_edit:contributor": "The RedBurn",
    "_last_edit:contributor:uid": 23835,
    "_last_edit:changeset": 109482048,
    "_last_edit:timestamp": "2021-08-10T19:50:46Z",
    "_version_number": 1,
    "_geometry:type": "Point"
   },
   "geometry": {
    "type": "Point",
    "coordinates": [
     5.8519486,
     50.5676458
    ]
   },
   "_lon": 5.8519486,
   "_lat": 50.5676458
  }
 ]
}