{
 "type": "FeatureCollection",
 "features": [
  {
   "type": "Feature",
   "id": "node/4287480145",
   "properties": {
    "amenity": "shelter",
    "building": "shelter",
    "leisure": "bird_hide",
    "name": "Vogelkijkhut Damvalleimeer",
    "operator": "Natuurpunt",
    "tourism": "viewpoint",
    "id": "node/4287480145",
    "_lat": "51.0517052",
    "_lon": "3.8099111",
    "_layer": "birdhide",
    "_surface": "0",
    "_surface:ha": "0",
    "_length": "0",
    "_length:km": "0.0",
    "_last_edit:contributor": "Pieter Vander Vennet",
    "_last_edit:contributor:uid": 3818858,
    "_last_edit:changeset": 82544029,
    "_last_edit:timestamp": "2020-03-23T23:54:26Z",
    "_version_number": 3,
    "_geometry:type": "Point",
    "_country": "be"
   },
   "geometry": {
    "type": "Point",
    "coordinates": [
     3.8099111,
     51.0517052
    ]
   },
   "_lon": 3.8099111,
   "_lat": 51.0517052
  }
 ]
}