{
 "type": "FeatureCollection",
 "features": [
  {
   "type": "Feature",
   "id": "node/3639963004",
   "properties": {
    "board_type": "history",
    "information": "board",
    "name": "Landmark Slag van Lafelt",
    "tourism": "information",
    "id": "node/3639963004",
    "_lat": "50.8282375",
    "_lon": "5.6049694",
    "_layer": "information_board",
    "_surface": "0",
    "_surface:ha": "0",
    "_length": "0",
    "_length:km": "0.0",
    "_last_edit:contributor": "Eebie",
    "_last_edit:contributor:uid": 715684,
    "_last_edit:changeset": 32484750,
    "_last_edit:timestamp": "2015-07-07T22:17:53Z",
    "_version_number": 1,
    "_geometry:type": "Point"
   },
   "geometry": {
    "type": "Point",
    "coordinates": [
     5.6049694,
     50.8282375
    ]
   },
   "_lon": 5.6049694,
   "_lat": 50.8282375
  },
  {
   "type": "Feature",
   "id": "node/9997941234",
   "properties": {
    "board_type": "history",
    "description": "Tumulus uit de Romeinse tijd",
    "information": "board",
    "name": "Gentombe",
    "tourism": "information",
    "id": "node/9997941234",
    "_lat": "50.8060298",
    "_lon": "5.5681976",
    "_layer": "information_board",
    "_surface": "0",
    "_surface:ha": "0",
    "_length": "0",
    "_length:km": "0.0",
    "_last_edit:contributor": "Eebie",
    "_last_edit:contributor:uid": 715684,
    "_last_edit:changeset": 125744560,
    "_last_edit:timestamp": "2022-09-03T16:11:47Z",
    "_version_number": 1,
    "_geometry:type": "Point"
   },
   "geometry": {
    "type": "Point",
    "coordinates": [
     5.5681976,
     50.8060298
    ]
   },
   "_lon": 5.5681976,
   "_lat": 50.8060298
  }
 ]
}