{
 "type": "FeatureCollection",
 "features": [
  {
   "type": "Feature",
   "id": "node/3789613131",
   "properties": {
    "board_type": "notice",
    "description": "Niersauenkonzept Renaturierungsplan",
    "information": "board",
    "name": "Niers Verband",
    "tourism": "information",
    "id": "node/3789613131",
    "_lat": "51.1267664",
    "_lon": "6.4134079",
    "_layer": "information_board",
    "_surface": "0",
    "_surface:ha": "0",
    "_length": "0",
    "_length:km": "0.0",
    "_last_edit:contributor": "GB_Germany_Vie",
    "_last_edit:contributor:uid": 46828,
    "_last_edit:changeset": 34683663,
    "_last_edit:timestamp": "2015-10-16T20:47:06Z",
    "_version_number": 1,
    "_geometry:type": "Point"
   },
   "geometry": {
    "type": "Point",
    "coordinates": [
     6.4134079,
     51.1267664
    ]
   },
   "_lon": 6.4134079,
   "_lat": 51.1267664
  },
  {
   "type": "Feature",
   "id": "node/9482320965",
   "properties": {
    "board_type": "sight",
    "information": "board",
    "name": "Münster St.Vitus",
    "tourism": "information",
    "traffic_sign": "DE:386.3",
    "id": "node/9482320965",
    "_lat": "51.1793228",
    "_lon": "6.4003958",
    "_layer": "information_board",
    "_surface": "0",
    "_surface:ha": "0",
    "_length": "0",
    "_length:km": "0.0",
    "_last_edit:contributor": "GB_Germany_Vie",
    "_last_edit:contributor:uid": 46828,
    "_last_edit:changeset": 117063266,
    "_last_edit:timestamp": "2022-02-05T22:48:27Z",
    "_version_number": 1,
    "_geometry:type": "Point"
   },
   "geometry": {
    "type": "Point",
    "coordinates": [
     6.4003958,
     51.1793228
    ]
   },
   "_lon": 6.4003958,
   "_lat": 51.1793228
  }
 ]
}