{
 "type": "FeatureCollection",
 "features": [
  {
   "type": "Feature",
   "id": "node/2894960413",
   "properties": {
    "board_type": "nature",
    "information": "board",
    "name": "Natuurreservaat De Westhoek / Réserve naturelle de Westhoek",
    "tourism": "information",
    "id": "node/2894960413",
    "_lat": "51.0773898",
    "_lon": "2.5545736",
    "_layer": "information_board",
    "_length": "0",
    "_length:km": "0.0",
    "_last_edit:contributor": "Vico1406",
    "_last_edit:contributor:uid": 12243010,
    "_last_edit:changeset": 106217050,
    "_last_edit:timestamp": "2021-06-11T13:21:39Z",
    "_version_number": 2,
    "_geometry:type": "Point"
   },
   "geometry": {
    "type": "Point",
    "coordinates": [
     2.5545736,
     51.0773898
    ]
   },
   "_lon": 2.5545736,
   "_lat": 51.0773898
  },
  {
   "type": "Feature",
   "id": "node/2894960416",
   "properties": {
    "board_type": "nature",
    "description": "Vlaams Natuurreservaat \"De Duinen en Bossen van De Panne\"",
    "information": "board",
    "name": "deelgebied Zwarten Hoek",
    "tourism": "information",
    "id": "node/2894960416",
    "_lat": "51.0724011",
    "_lon": "2.5597326",
    "_layer": "information_board",
    "_length": "0",
    "_length:km": "0.0",
    "_last_edit:contributor": "peeweeke",
    "_last_edit:contributor:uid": 494726,
    "_last_edit:changeset": 22688128,
    "_last_edit:timestamp": "2014-06-02T07:43:40Z",
    "_version_number": 1,
    "_geometry:type": "Point"
   },
   "geometry": {
    "type": "Point",
    "coordinates": [
     2.5597326,
     51.0724011
    ]
   },
   "_lon": 2.5597326,
   "_lat": 51.0724011
  },
  {
   "type": "Feature",
   "id": "node/2894960417",
   "properties": {
    "board_type": "nature",
    "description": "Vlaams Natuurreservaat \"De Duinen en Bossen van De Panne\"",
    "information": "board",
    "name": "deelgebied Zwarten Hoek",
    "tourism": "information",
    "id": "node/2894960417",
    "_lat": "51.0762985",
    "_lon": "2.564639",
    "_layer": "information_board",
    "_length": "0",
    "_length:km": "0.0",
    "_last_edit:contributor": "peeweeke",
    "_last_edit:contributor:uid": 494726,
    "_last_edit:changeset": 22688128,
    "_last_edit:timestamp": "2014-06-02T07:43:40Z",
    "_version_number": 1,
    "_geometry:type": "Point"
   },
   "geometry": {
    "type": "Point",
    "coordinates": [
     2.564639,
     51.0762985
    ]
   },
   "_lon": 2.564639,
   "_lat": 51.0762985
  },
  {
   "type": "Feature",
   "id": "node/3051842917",
   "properties": {
    "denomination": "Schuilhavenlaan",
    "information": "board",
    "tourism": "information",
    "id": "node/3051842917",
    "_lat": "51.0947249",
    "_lon": "2.5658122",
    "_layer": "information_board",
    "_length": "0",
    "_length:km": "0.0",
    "_last_edit:contributor": "willisturm",
    "_last_edit:contributor:uid": 5589496,
    "_last_edit:changeset": 103683854,
    "_last_edit:timestamp": "2021-04-27T07:27:03Z",
    "_version_number": 2,
    "_geometry:type": "Point"
   },
   "geometry": {
    "type": "Point",
    "coordinates": [
     2.5658122,
     51.0947249
    ]
   },
   "_lon": 2.5658122,
   "_lat": 51.0947249
  },
  {
   "type": "Feature",
   "id": "node/4517767176",
   "properties": {
    "board_type": "nature",
    "check_date": "2021-11-25",
    "information": "board",
    "tourism": "information",
    "id": "node/4517767176",
    "_lat": "51.0897625",
    "_lon": "2.5774098",
    "_layer": "information_board",
    "_length": "0",
    "_length:km": "0.0",
    "_last_edit:contributor": "Sigmund Walterson",
    "_last_edit:contributor:uid": 14479447,
    "_last_edit:changeset": 114224360,
    "_last_edit:timestamp": "2021-11-25T13:48:03Z",
    "_version_number": 2,
    "_geometry:type": "Point"
   },
   "geometry": {
    "type": "Point",
    "coordinates": [
     2.5774098,
     51.0897625
    ]
   },
   "_lon": 2.5774098,
   "_lat": 51.0897625
  },
  {
   "type": "Feature",
   "id": "node/5486762705",
   "properties": {
    "information": "board",
    "tourism": "information",
    "id": "node/5486762705",
    "_lat": "51.0836647",
    "_lon": "2.5822008",
    "_layer": "information_board",
    "_length": "0",
    "_length:km": "0.0",
    "_last_edit:contributor": "vjyblauw",
    "_last_edit:contributor:uid": 2844254,
    "_last_edit:changeset": 57295419,
    "_last_edit:timestamp": "2018-03-18T16:44:10Z",
    "_version_number": 1,
    "_geometry:type": "Point"
   },
   "geometry": {
    "type": "Point",
    "coordinates": [
     2.5822008,
     51.0836647
    ]
   },
   "_lon": 2.5822008,
   "_lat": 51.0836647
  }
 ]
}