{
 "type": "FeatureCollection",
 "features": [
  {
   "type": "Feature",
   "id": "node/2846328872",
   "properties": {
    "addr:city": "Tilburg",
    "addr:housenumber": "475a",
    "addr:postcode": "5032VD",
    "addr:street": "Gilzerbaan",
    "amenity": "toilets",
    "source": "BAG",
    "source:date": "2014-05-01",
    "id": "node/2846328872",
    "_lat": "51.5572409",
    "_lon": "4.9963207",
    "_layer": "toilet",
    "_length": "0",
    "_length:km": "0.0",
    "_last_edit:contributor": "FrankOverman",
    "_last_edit:contributor:uid": 1987570,
    "_last_edit:changeset": 91944137,
    "_last_edit:timestamp": "2020-10-04T19:26:59Z",
    "_version_number": 3,
    "_geometry:type": "Point",
    "_country": "nl"
   },
   "geometry": {
    "type": "Point",
    "coordinates": [
     4.9963207,
     51.5572409
    ]
   },
   "_lon": 4.9963207,
   "_lat": 51.5572409
  }
 ]
}