{
 "type": "FeatureCollection",
 "features": [
  {
   "type": "Feature",
   "id": "node/4449266889",
   "properties": {
    "leisure": "bird_hide",
    "name": "Vogelkijkwand",
    "tourism": "viewpoint",
    "id": "node/4449266889",
    "_lat": "50.918277",
    "_lon": "3.1341819",
    "_layer": "birdhide",
    "_length": "0",
    "_length:km": "0.0",
    "_last_edit:contributor": "gptm",
    "_last_edit:contributor:uid": 2873411,
    "_last_edit:changeset": 111822153,
    "_last_edit:timestamp": "2021-09-28T14:30:48Z",
    "_version_number": 2
   },
   "geometry": {
    "type": "Point",
    "coordinates": [
     3.1341819,
     50.918277
    ]
   },
   "_lon": 3.1341819,
   "_lat": 50.918277
  }
 ]
}