{
 "type": "FeatureCollection",
 "features": [
  {
   "type": "Feature",
   "id": "node/9882717705",
   "properties": {
    "board:title": "Natuurvijver De Wetering",
    "board_type": "nature",
    "information": "board",
    "tourism": "information",
    "id": "node/9882717705",
    "_lat": "51.3474557",
    "_lon": "5.4926581",
    "_layer": "information_board",
    "_surface": "0",
    "_surface:ha": "0",
    "_length": "0",
    "_length:km": "0.0",
    "_last_edit:contributor": "byckel",
    "_last_edit:contributor:uid": 2195662,
    "_last_edit:changeset": 123507517,
    "_last_edit:timestamp": "2022-07-12T08:36:12Z",
    "_version_number": 1,
    "_geometry:type": "Point"
   },
   "geometry": {
    "type": "Point",
    "coordinates": [
     5.4926581,
     51.3474557
    ]
   },
   "_lon": 5.4926581,
   "_lat": 51.3474557
  }
 ]
}