{
 "type": "FeatureCollection",
 "features": [
  {
   "type": "Feature",
   "id": "node/6698916030",
   "properties": {
    "information": "board",
    "name": "Cheratte-Haut",
    "tourism": "information",
    "id": "node/6698916030",
    "_lat": "50.6807022",
    "_lon": "5.6727264",
    "_layer": "information_board",
    "_length": "0",
    "_length:km": "0.0",
    "_last_edit:contributor": "Eebie",
    "_last_edit:contributor:uid": 715684,
    "_last_edit:changeset": 73221225,
    "_last_edit:timestamp": "2019-08-10T13:27:17Z",
    "_version_number": 1,
    "_geometry:type": "Point"
   },
   "geometry": {
    "type": "Point",
    "coordinates": [
     5.6727264,
     50.6807022
    ]
   },
   "_lon": 5.6727264,
   "_lat": 50.6807022
  }
 ]
}