{
 "type": "FeatureCollection",
 "features": [
  {
   "type": "Feature",
   "id": "node/3267800241",
   "properties": {
    "board_type": "nature",
    "description": "La place de l'eau",
    "information": "board",
    "name": "La Scarpe Inférieure",
    "tourism": "information",
    "id": "node/3267800241",
    "_lat": "50.4129413",
    "_lon": "3.3512639",
    "_layer": "information_board",
    "_length": "0",
    "_length:km": "0.0",
    "_last_edit:contributor": "Bernard59118",
    "_last_edit:contributor:uid": 136303,
    "_last_edit:changeset": 27895446,
    "_last_edit:timestamp": "2015-01-03T20:19:59Z",
    "_version_number": 1,
    "_geometry:type": "Point"
   },
   "geometry": {
    "type": "Point",
    "coordinates": [
     3.3512639,
     50.4129413
    ]
   },
   "_lon": 3.3512639,
   "_lat": 50.4129413
  },
  {
   "type": "Feature",
   "id": "node/3267800242",
   "properties": {
    "board_type": "nature",
    "description": "Le patrimoine d'Hasnon et de Millonfosse",
    "information": "board",
    "name": "La Scarpe Inférieure",
    "tourism": "information",
    "id": "node/3267800242",
    "_lat": "50.4244293",
    "_lon": "3.3913196",
    "_layer": "information_board",
    "_length": "0",
    "_length:km": "0.0",
    "_last_edit:contributor": "bibi6",
    "_last_edit:contributor:uid": 635080,
    "_last_edit:changeset": 36903751,
    "_last_edit:timestamp": "2016-01-30T18:53:48Z",
    "_version_number": 2,
    "_geometry:type": "Point"
   },
   "geometry": {
    "type": "Point",
    "coordinates": [
     3.3913196,
     50.4244293
    ]
   },
   "_lon": 3.3913196,
   "_lat": 50.4244293
  },
  {
   "type": "Feature",
   "id": "node/3267800243",
   "properties": {
    "board_type": "nature",
    "description": "Les peupleraies",
    "information": "board",
    "name": "La Scarpe Inférieure",
    "tourism": "information",
    "id": "node/3267800243",
    "_lat": "50.4262017",
    "_lon": "3.3840307",
    "_layer": "information_board",
    "_length": "0",
    "_length:km": "0.0",
    "_last_edit:contributor": "Bernard59118",
    "_last_edit:contributor:uid": 136303,
    "_last_edit:changeset": 27895446,
    "_last_edit:timestamp": "2015-01-03T20:19:59Z",
    "_version_number": 1,
    "_geometry:type": "Point"
   },
   "geometry": {
    "type": "Point",
    "coordinates": [
     3.3840307,
     50.4262017
    ]
   },
   "_lon": 3.3840307,
   "_lat": 50.4262017
  },
  {
   "type": "Feature",
   "id": "node/3267800244",
   "properties": {
    "board_type": "nature",
    "description": "Les zones humides",
    "information": "board",
    "name": "La Scarpe Inférieure",
    "tourism": "information",
    "id": "node/3267800244",
    "_lat": "50.4283814",
    "_lon": "3.4097604",
    "_layer": "information_board",
    "_length": "0",
    "_length:km": "0.0",
    "_last_edit:contributor": "Bernard59118",
    "_last_edit:contributor:uid": 136303,
    "_last_edit:changeset": 27895446,
    "_last_edit:timestamp": "2015-01-03T20:19:59Z",
    "_version_number": 1,
    "_geometry:type": "Point"
   },
   "geometry": {
    "type": "Point",
    "coordinates": [
     3.4097604,
     50.4283814
    ]
   },
   "_lon": 3.4097604,
   "_lat": 50.4283814
  },
  {
   "type": "Feature",
   "id": "node/8972417405",
   "properties": {
    "board_type": "notice",
    "information": "board",
    "name": "Rosult Centre",
    "tourism": "information",
    "id": "node/8972417405",
    "_lat": "50.4515329",
    "_lon": "3.3654273",
    "_layer": "information_board",
    "_length": "0",
    "_length:km": "0.0",
    "_last_edit:contributor": "Rems",
    "_last_edit:contributor:uid": 221860,
    "_last_edit:changeset": 108980275,
    "_last_edit:timestamp": "2021-08-01T16:26:11Z",
    "_version_number": 1,
    "_geometry:type": "Point"
   },
   "geometry": {
    "type": "Point",
    "coordinates": [
     3.3654273,
     50.4515329
    ]
   },
   "_lon": 3.3654273,
   "_lat": 50.4515329
  }
 ]
}