{
 "type": "FeatureCollection",
 "features": [
  {
   "type": "Feature",
   "id": "node/4988433795",
   "properties": {
    "information": "board",
    "name": "Frontierenroute",
    "tourism": "information",
    "id": "node/4988433795",
    "_lat": "50.8597424",
    "_lon": "2.619752",
    "_layer": "information_board",
    "_surface": "0",
    "_surface:ha": "0",
    "_length": "0",
    "_length:km": "0.0",
    "_last_edit:contributor": "Jakka",
    "_last_edit:contributor:uid": 2403313,
    "_last_edit:changeset": 50506281,
    "_last_edit:timestamp": "2017-07-23T16:53:16Z",
    "_version_number": 1,
    "_geometry:type": "Point",
    "_country": "be"
   },
   "geometry": {
    "type": "Point",
    "coordinates": [
     2.619752,
     50.8597424
    ]
   },
   "_lon": 2.619752,
   "_lat": 50.8597424
  },
  {
   "type": "Feature",
   "id": "node/4988449301",
   "properties": {
    "information": "board",
    "tourism": "information",
    "id": "node/4988449301",
    "_lat": "50.8590647",
    "_lon": "2.6194786",
    "_layer": "information_board",
    "_surface": "0",
    "_surface:ha": "0",
    "_length": "0",
    "_length:km": "0.0",
    "_last_edit:contributor": "Jakka",
    "_last_edit:contributor:uid": 2403313,
    "_last_edit:changeset": 50506497,
    "_last_edit:timestamp": "2017-07-23T17:02:34Z",
    "_version_number": 1,
    "_geometry:type": "Point",
    "_country": "be"
   },
   "geometry": {
    "type": "Point",
    "coordinates": [
     2.6194786,
     50.8590647
    ]
   },
   "_lon": 2.6194786,
   "_lat": 50.8590647
  }
 ]
}