{
 "type": "FeatureCollection",
 "features": [
  {
   "type": "Feature",
   "id": "node/4499071105",
   "properties": {
    "board_type": "nature",
    "information": "board",
    "name": "Kastel, een dorp vol zwaluwen",
    "tourism": "information",
    "id": "node/4499071105",
    "_lat": "51.0483959",
    "_lon": "4.1675118",
    "_layer": "information_board",
    "_length": "0",
    "_length:km": "0.0",
    "_last_edit:contributor": "Spacejockey",
    "_last_edit:contributor:uid": 7140090,
    "_last_edit:changeset": 58099054,
    "_last_edit:timestamp": "2018-04-14T22:06:36Z",
    "_version_number": 2,
    "_geometry:type": "Point",
    "_country": "be"
   },
   "geometry": {
    "type": "Point",
    "coordinates": [
     4.1675118,
     51.0483959
    ]
   },
   "_lon": 4.1675118,
   "_lat": 51.0483959
  },
  {
   "type": "Feature",
   "id": "node/4500503282",
   "properties": {
    "board_type": "nature",
    "information": "board",
    "name": "Trage wegen in Moerzeke",
    "tourism": "information",
    "id": "node/4500503282",
    "_lat": "51.0593778",
    "_lon": "4.1647658",
    "_layer": "information_board",
    "_length": "0",
    "_length:km": "0.0",
    "_last_edit:contributor": "escada",
    "_last_edit:contributor:uid": 436365,
    "_last_edit:changeset": 43642159,
    "_last_edit:timestamp": "2016-11-14T15:11:54Z",
    "_version_number": 2,
    "_geometry:type": "Point",
    "_country": "be"
   },
   "geometry": {
    "type": "Point",
    "coordinates": [
     4.1647658,
     51.0593778
    ]
   },
   "_lon": 4.1647658,
   "_lat": 51.0593778
  },
  {
   "type": "Feature",
   "id": "node/7806206010",
   "properties": {
    "board_type": "information",
    "information": "board",
    "tourism": "information",
    "id": "node/7806206010",
    "_lat": "51.0673936",
    "_lon": "4.1831876",
    "_layer": "information_board",
    "_length": "0",
    "_length:km": "0.0",
    "_last_edit:contributor": "Lieven Borms",
    "_last_edit:contributor:uid": 1455029,
    "_last_edit:changeset": 89295678,
    "_last_edit:timestamp": "2020-08-12T09:54:20Z",
    "_version_number": 1,
    "_geometry:type": "Point",
    "_country": "be"
   },
   "geometry": {
    "type": "Point",
    "coordinates": [
     4.1831876,
     51.0673936
    ]
   },
   "_lon": 4.1831876,
   "_lat": 51.0673936
  },
  {
   "type": "Feature",
   "id": "node/7806206017",
   "properties": {
    "board_type": "information",
    "information": "board",
    "tourism": "information",
    "id": "node/7806206017",
    "_lat": "51.0675287",
    "_lon": "4.1816696",
    "_layer": "information_board",
    "_length": "0",
    "_length:km": "0.0",
    "_last_edit:contributor": "Lieven Borms",
    "_last_edit:contributor:uid": 1455029,
    "_last_edit:changeset": 89295678,
    "_last_edit:timestamp": "2020-08-12T09:54:20Z",
    "_version_number": 1,
    "_geometry:type": "Point",
    "_country": "be"
   },
   "geometry": {
    "type": "Point",
    "coordinates": [
     4.1816696,
     51.0675287
    ]
   },
   "_lon": 4.1816696,
   "_lat": 51.0675287
  },
  {
   "type": "Feature",
   "id": "node/9168329859",
   "properties": {
    "information": "board",
    "tourism": "information",
    "id": "node/9168329859",
    "_lat": "51.0595342",
    "_lon": "4.1850024",
    "_layer": "information_board",
    "_length": "0",
    "_length:km": "0.0",
    "_last_edit:contributor": "L'imaginaire",
    "_last_edit:contributor:uid": 654234,
    "_last_edit:changeset": 112435555,
    "_last_edit:timestamp": "2021-10-12T20:58:49Z",
    "_version_number": 1,
    "_geometry:type": "Point",
    "_country": "be"
   },
   "geometry": {
    "type": "Point",
    "coordinates": [
     4.1850024,
     51.0595342
    ]
   },
   "_lon": 4.1850024,
   "_lat": 51.0595342
  },
  {
   "type": "Feature",
   "id": "node/9170341650",
   "properties": {
    "information": "board",
    "tourism": "information",
    "id": "node/9170341650",
    "_lat": "51.0403183",
    "_lon": "4.1658749",
    "_layer": "information_board",
    "_length": "0",
    "_length:km": "0.0",
    "_last_edit:contributor": "L'imaginaire",
    "_last_edit:contributor:uid": 654234,
    "_last_edit:changeset": 112475550,
    "_last_edit:timestamp": "2021-10-13T19:15:25Z",
    "_version_number": 1,
    "_geometry:type": "Point",
    "_country": "be"
   },
   "geometry": {
    "type": "Point",
    "coordinates": [
     4.1658749,
     51.0403183
    ]
   },
   "_lon": 4.1658749,
   "_lat": 51.0403183
  }
 ]
}