{
 "type": "FeatureCollection",
 "features": [
  {
   "type": "Feature",
   "id": "node/1225794585",
   "properties": {
    "man_made": "watermill",
    "name": "Gitstappermolen",
    "id": "node/1225794585",
    "_lat": "51.1375479",
    "_lon": "6.1087141",
    "_layer": "watermill",
    "_length": "0",
    "_length:km": "0.0",
    "_last_edit:contributor": "Cartographer10",
    "_last_edit:contributor:uid": 10124496,
    "_last_edit:changeset": 71961676,
    "_last_edit:timestamp": "2019-07-06T15:10:18Z",
    "_version_number": 2,
    "_geometry:type": "Point",
    "_country": "de"
   },
   "geometry": {
    "type": "Point",
    "coordinates": [
     6.1087141,
     51.1375479
    ]
   },
   "_lon": 6.1087141,
   "_lat": 51.1375479
  }
 ]
}