{
 "type": "FeatureCollection",
 "features": [
  {
   "type": "Feature",
   "id": "node/2832677672",
   "properties": {
    "addr:city": "Veere",
    "addr:housenumber": "2",
    "addr:postcode": "4351AZ",
    "addr:street": "Oranjeplein",
    "amenity": "toilets",
    "source": "BAG",
    "source:date": "2014-03-24",
    "id": "node/2832677672",
    "_lat": "51.54941",
    "_lon": "3.6693718",
    "_layer": "toilet",
    "_surface": "0",
    "_surface:ha": "0",
    "_length": "0",
    "_length:km": "0.0",
    "_last_edit:contributor": "AdVerburg",
    "_last_edit:contributor:uid": 2831457,
    "_last_edit:changeset": 103328059,
    "_last_edit:timestamp": "2021-04-21T09:40:41Z",
    "_version_number": 2,
    "_geometry:type": "Point",
    "_country": "nl"
   },
   "geometry": {
    "type": "Point",
    "coordinates": [
     3.6693718,
     51.54941
    ]
   },
   "_lon": 3.6693718,
   "_lat": 51.54941
  },
  {
   "type": "Feature",
   "id": "node/3641300318",
   "properties": {
    "amenity": "toilets",
    "toilets:wheelchair": "yes",
    "wheelchair": "yes",
    "id": "node/3641300318",
    "_lat": "51.54594",
    "_lon": "3.6682413",
    "_layer": "toilet",
    "_surface": "0",
    "_surface:ha": "0",
    "_length": "0",
    "_length:km": "0.0",
    "_last_edit:contributor": "wheelmap_android",
    "_last_edit:contributor:uid": 524500,
    "_last_edit:changeset": 60074399,
    "_last_edit:timestamp": "2018-06-22T12:15:51Z",
    "_version_number": 3,
    "_geometry:type": "Point",
    "_country": "nl"
   },
   "geometry": {
    "type": "Point",
    "coordinates": [
     3.6682413,
     51.54594
    ]
   },
   "_lon": 3.6682413,
   "_lat": 51.54594
  },
  {
   "type": "Feature",
   "id": "node/5711531422",
   "properties": {
    "access": "yes",
    "amenity": "toilets",
    "changing_table": "no",
    "fee": "no",
    "image": "https://i.imgur.com/VaPTM7F.jpg",
    "image:0": "https://i.imgur.com/QQ8m623.jpg",
    "toilets:position": "seated",
    "wheelchair": "yes",
    "id": "node/5711531422",
    "_lat": "51.5491398",
    "_lon": "3.6672167",
    "_layer": "toilet",
    "_surface": "0",
    "_surface:ha": "0",
    "_length": "0",
    "_length:km": "0.0",
    "_last_edit:contributor": "Pieter Vander Vennet",
    "_last_edit:contributor:uid": 3818858,
    "_last_edit:changeset": 111734127,
    "_last_edit:timestamp": "2021-09-26T17:50:28Z",
    "_version_number": 8,
    "_geometry:type": "Point",
    "_country": "nl"
   },
   "geometry": {
    "type": "Point",
    "coordinates": [
     3.6672167,
     51.5491398
    ]
   },
   "_lon": 3.6672167,
   "_lat": 51.5491398
  }
 ]
}