{
 "type": "FeatureCollection",
 "features": [
  {
   "type": "Feature",
   "id": "node/3616293095",
   "properties": {
    "board_type": "history",
    "description": "résistante",
    "information": "board",
    "name": "Marie Gognau-Noirhomme",
    "tourism": "information",
    "id": "node/3616293095",
    "_lat": "50.4485314",
    "_lon": "2.7412891",
    "_layer": "information_board",
    "_surface": "0",
    "_surface:ha": "0",
    "_length": "0",
    "_length:km": "0.0",
    "_last_edit:contributor": "Max_Kritic",
    "_last_edit:contributor:uid": 414659,
    "_last_edit:changeset": 43336090,
    "_last_edit:timestamp": "2016-11-01T20:08:27Z",
    "_version_number": 2,
    "_geometry:type": "Point",
    "_country": "fr"
   },
   "geometry": {
    "type": "Point",
    "coordinates": [
     2.7412891,
     50.4485314
    ]
   },
   "_lon": 2.7412891,
   "_lat": 50.4485314
  },
  {
   "type": "Feature",
   "id": "node/3616293097",
   "properties": {
    "board_type": "history",
    "information": "board",
    "name": "Nelson Mandela",
    "tourism": "information",
    "id": "node/3616293097",
    "_lat": "50.4519171",
    "_lon": "2.7406872",
    "_layer": "information_board",
    "_surface": "0",
    "_surface:ha": "0",
    "_length": "0",
    "_length:km": "0.0",
    "_last_edit:contributor": "Bernard59118",
    "_last_edit:contributor:uid": 136303,
    "_last_edit:changeset": 32194488,
    "_last_edit:timestamp": "2015-06-24T22:50:42Z",
    "_version_number": 1,
    "_geometry:type": "Point",
    "_country": "fr"
   },
   "geometry": {
    "type": "Point",
    "coordinates": [
     2.7406872,
     50.4519171
    ]
   },
   "_lon": 2.7406872,
   "_lat": 50.4519171
  },
  {
   "type": "Feature",
   "id": "node/5034393574",
   "properties": {
    "information": "board",
    "tourism": "information",
    "id": "node/5034393574",
    "_lat": "50.4466795",
    "_lon": "2.7811363",
    "_layer": "information_board",
    "_surface": "0",
    "_surface:ha": "0",
    "_length": "0",
    "_length:km": "0.0",
    "_last_edit:contributor": "magiraud",
    "_last_edit:contributor:uid": 65155,
    "_last_edit:changeset": 118974541,
    "_last_edit:timestamp": "2022-03-27T09:56:10Z",
    "_version_number": 2,
    "_geometry:type": "Point",
    "_country": "fr"
   },
   "geometry": {
    "type": "Point",
    "coordinates": [
     2.7811363,
     50.4466795
    ]
   },
   "_lon": 2.7811363,
   "_lat": 50.4466795
  },
  {
   "type": "Feature",
   "id": "node/5034504611",
   "properties": {
    "board_type": "history",
    "information": "board",
    "tourism": "information",
    "id": "node/5034504611",
    "_lat": "50.442298",
    "_lon": "2.7867473",
    "_layer": "information_board",
    "_surface": "0",
    "_surface:ha": "0",
    "_length": "0",
    "_length:km": "0.0",
    "_last_edit:contributor": "F5ZV",
    "_last_edit:contributor:uid": 4189749,
    "_last_edit:changeset": 51109763,
    "_last_edit:timestamp": "2017-08-14T12:29:17Z",
    "_version_number": 1,
    "_geometry:type": "Point",
    "_country": "fr"
   },
   "geometry": {
    "type": "Point",
    "coordinates": [
     2.7867473,
     50.442298
    ]
   },
   "_lon": 2.7867473,
   "_lat": 50.442298
  },
  {
   "type": "Feature",
   "id": "node/9610534926",
   "properties": {
    "information": "board",
    "tourism": "information",
    "id": "node/9610534926",
    "_lat": "50.4455132",
    "_lon": "2.7751474",
    "_layer": "information_board",
    "_surface": "0",
    "_surface:ha": "0",
    "_length": "0",
    "_length:km": "0.0",
    "_last_edit:contributor": "magiraud",
    "_last_edit:contributor:uid": 65155,
    "_last_edit:changeset": 118974541,
    "_last_edit:timestamp": "2022-03-27T09:56:10Z",
    "_version_number": 1,
    "_geometry:type": "Point",
    "_country": "fr"
   },
   "geometry": {
    "type": "Point",
    "coordinates": [
     2.7751474,
     50.4455132
    ]
   },
   "_lon": 2.7751474,
   "_lat": 50.4455132
  },
  {
   "type": "Feature",
   "id": "node/9610535039",
   "properties": {
    "information": "board",
    "tourism": "information",
    "id": "node/9610535039",
    "_lat": "50.4439375",
    "_lon": "2.7777983",
    "_layer": "information_board",
    "_surface": "0",
    "_surface:ha": "0",
    "_length": "0",
    "_length:km": "0.0",
    "_last_edit:contributor": "magiraud",
    "_last_edit:contributor:uid": 65155,
    "_last_edit:changeset": 118974541,
    "_last_edit:timestamp": "2022-03-27T09:56:10Z",
    "_version_number": 1,
    "_geometry:type": "Point",
    "_country": "fr"
   },
   "geometry": {
    "type": "Point",
    "coordinates": [
     2.7777983,
     50.4439375
    ]
   },
   "_lon": 2.7777983,
   "_lat": 50.4439375
  }
 ]
}