{
 "type": "FeatureCollection",
 "features": [
  {
   "type": "Feature",
   "id": "node/2335453131",
   "properties": {
    "board_type": "board",
    "information": "board",
    "name": "Argendaal wandelpad",
    "tourism": "information",
    "id": "node/2335453131",
    "_lat": "50.7681324",
    "_lon": "3.309516",
    "_layer": "information_board",
    "_surface": "0",
    "_surface:ha": "0",
    "_length": "0",
    "_length:km": "0.0",
    "_last_edit:contributor": "TripleBee",
    "_last_edit:contributor:uid": 497177,
    "_last_edit:changeset": 20343047,
    "_last_edit:timestamp": "2014-02-02T21:36:53Z",
    "_version_number": 2,
    "_geometry:type": "Point",
    "_country": "be"
   },
   "geometry": {
    "type": "Point",
    "coordinates": [
     3.309516,
     50.7681324
    ]
   },
   "_lon": 3.309516,
   "_lat": 50.7681324
  },
  {
   "type": "Feature",
   "id": "node/6672510066",
   "properties": {
    "description": "Wandelnetwerk",
    "information": "board",
    "name": "Land van Mortagne",
    "tourism": "information",
    "id": "node/6672510066",
    "_lat": "50.7400674",
    "_lon": "3.3313023",
    "_layer": "information_board",
    "_surface": "0",
    "_surface:ha": "0",
    "_length": "0",
    "_length:km": "0.0",
    "_last_edit:contributor": "Jakka",
    "_last_edit:contributor:uid": 2403313,
    "_last_edit:changeset": 72914536,
    "_last_edit:timestamp": "2019-08-01T20:42:18Z",
    "_version_number": 2,
    "_geometry:type": "Point",
    "_country": "be"
   },
   "geometry": {
    "type": "Point",
    "coordinates": [
     3.3313023,
     50.7400674
    ]
   },
   "_lon": 3.3313023,
   "_lat": 50.7400674
  }
 ]
}