{
 "type": "FeatureCollection",
 "features": [
  {
   "type": "Feature",
   "id": "node/3017239978",
   "properties": {
    "board_type": "nature",
    "description": "hiking network",
    "information": "board",
    "name": "Kustwandelroute",
    "tourism": "information",
    "id": "node/3017239978",
    "_lat": "51.3420024",
    "_lon": "3.28463",
    "_layer": "information_board",
    "_surface": "0",
    "_surface:ha": "0",
    "_length": "0",
    "_length:km": "0.0",
    "_last_edit:contributor": "projecter63",
    "_last_edit:contributor:uid": 251726,
    "_last_edit:changeset": 24755934,
    "_last_edit:timestamp": "2014-08-14T22:02:46Z",
    "_version_number": 1,
    "_geometry:type": "Point"
   },
   "geometry": {
    "type": "Point",
    "coordinates": [
     3.28463,
     51.3420024
    ]
   },
   "_lon": 3.28463,
   "_lat": 51.3420024
  },
  {
   "type": "Feature",
   "id": "node/3017239979",
   "properties": {
    "board_type": "nature",
    "description": "hiking network",
    "information": "board",
    "name": "Zwin",
    "tourism": "information",
    "id": "node/3017239979",
    "_lat": "51.3419862",
    "_lon": "3.2846359",
    "_layer": "information_board",
    "_surface": "0",
    "_surface:ha": "0",
    "_length": "0",
    "_length:km": "0.0",
    "_last_edit:contributor": "projecter63",
    "_last_edit:contributor:uid": 251726,
    "_last_edit:changeset": 24755934,
    "_last_edit:timestamp": "2014-08-14T22:02:46Z",
    "_version_number": 1,
    "_geometry:type": "Point"
   },
   "geometry": {
    "type": "Point",
    "coordinates": [
     3.2846359,
     51.3419862
    ]
   },
   "_lon": 3.2846359,
   "_lat": 51.3419862
  }
 ]
}