{
 "type": "FeatureCollection",
 "features": [
  {
   "type": "Feature",
   "id": "node/2825870739",
   "properties": {
    "addr:city": "Oirschot",
    "addr:housenumber": "130",
    "addr:postcode": "5688KE",
    "addr:street": "Spoordonkseweg",
    "email": "info@spoordonksewatermolen.nl",
    "heritage": "2",
    "heritage:operator": "rce",
    "man_made": "watermill",
    "name": "Spoordonkse Watermolen",
    "opening_hours": "We-Su 10:00+",
    "phone": "+31 0499577186",
    "ref:rce": "31351",
    "source": "BAG",
    "source:date": "2014-03-24",
    "website": "http://www.spoordonksewatermolen.nl/",
    "wikidata": "Q2099514",
    "wikipedia": "nl:Spoordonkse Watermolen",
    "id": "node/2825870739",
    "_lat": "51.5203544",
    "_lon": "5.2661339",
    "_layer": "watermill",
    "_surface": "0",
    "_surface:ha": "0",
    "_length": "0",
    "_length:km": "0.0",
    "_last_edit:contributor": "lovelyfurball88",
    "_last_edit:contributor:uid": 12424494,
    "_last_edit:changeset": 116763724,
    "_last_edit:timestamp": "2022-01-30T00:22:55Z",
    "_version_number": 10,
    "_geometry:type": "Point",
    "_country": "nl"
   },
   "geometry": {
    "type": "Point",
    "coordinates": [
     5.2661339,
     51.5203544
    ]
   },
   "_lon": 5.2661339,
   "_lat": 51.5203544
  }
 ]
}