{
 "type": "FeatureCollection",
 "features": [
  {
   "type": "Feature",
   "id": "node/6407767864",
   "properties": {
    "board_type": "welcome_sign;map;safety",
    "information": "board",
    "name": "Beez Climbing Information",
    "operator": "Club Alpin Belge",
    "tourism": "information",
    "id": "node/6407767864",
    "_lat": "50.4801417",
    "_lon": "4.9409155",
    "_layer": "information_board",
    "_length": "0",
    "_length:km": "0.0",
    "_last_edit:contributor": "Pieter Vander Vennet",
    "_last_edit:contributor:uid": 3818858,
    "_last_edit:changeset": 69250808,
    "_last_edit:timestamp": "2019-04-15T22:09:24Z",
    "_version_number": 1,
    "_geometry:type": "Point",
    "_country": "be"
   },
   "geometry": {
    "type": "Point",
    "coordinates": [
     4.9409155,
     50.4801417
    ]
   },
   "_lon": 4.9409155,
   "_lat": 50.4801417
  },
  {
   "type": "Feature",
   "id": "node/8275203189",
   "properties": {
    "board_type": "notice",
    "information": "board",
    "tourism": "information",
    "id": "node/8275203189",
    "_lat": "50.4854339",
    "_lon": "4.9481191",
    "_layer": "information_board",
    "_length": "0",
    "_length:km": "0.0",
    "_last_edit:contributor": "Jean-Louis Stanus",
    "_last_edit:contributor:uid": 116840,
    "_last_edit:changeset": 96689935,
    "_last_edit:timestamp": "2020-12-30T20:40:43Z",
    "_version_number": 1,
    "_geometry:type": "Point",
    "_country": "be"
   },
   "geometry": {
    "type": "Point",
    "coordinates": [
     4.9481191,
     50.4854339
    ]
   },
   "_lon": 4.9481191,
   "_lat": 50.4854339
  },
  {
   "type": "Feature",
   "id": "node/8275203190",
   "properties": {
    "board_type": "plants",
    "information": "board",
    "tourism": "information",
    "id": "node/8275203190",
    "_lat": "50.4853063",
    "_lon": "4.9484517",
    "_layer": "information_board",
    "_length": "0",
    "_length:km": "0.0",
    "_last_edit:contributor": "Jean-Louis Stanus",
    "_last_edit:contributor:uid": 116840,
    "_last_edit:changeset": 96689935,
    "_last_edit:timestamp": "2020-12-30T20:40:43Z",
    "_version_number": 1,
    "_geometry:type": "Point",
    "_country": "be"
   },
   "geometry": {
    "type": "Point",
    "coordinates": [
     4.9484517,
     50.4853063
    ]
   },
   "_lon": 4.9484517,
   "_lat": 50.4853063
  },
  {
   "type": "Feature",
   "id": "node/9025022196",
   "properties": {
    "description": "Altitude: 180 m",
    "ele": "180",
    "information": "board",
    "name": "Ancien fort de Marchovelette",
    "tourism": "information",
    "id": "node/9025022196",
    "_lat": "50.5071665",
    "_lon": "4.9402009",
    "_layer": "information_board",
    "_length": "0",
    "_length:km": "0.0",
    "_last_edit:contributor": "Eebie",
    "_last_edit:contributor:uid": 715684,
    "_last_edit:changeset": 110032204,
    "_last_edit:timestamp": "2021-08-21T15:13:52Z",
    "_version_number": 1,
    "_geometry:type": "Point",
    "_country": "be"
   },
   "geometry": {
    "type": "Point",
    "coordinates": [
     4.9402009,
     50.5071665
    ]
   },
   "_lon": 4.9402009,
   "_lat": 50.5071665
  },
  {
   "type": "Feature",
   "id": "node/9281724823",
   "properties": {
    "board_type": "climbing and nature info",
    "information": "board",
    "name": "Rochers de Beez: escalade",
    "operator": "CAB asbl",
    "tourism": "information",
    "id": "node/9281724823",
    "_lat": "50.4792711",
    "_lon": "4.9389718",
    "_layer": "information_board",
    "_length": "0",
    "_length:km": "0.0",
    "_last_edit:contributor": "Eebie",
    "_last_edit:contributor:uid": 715684,
    "_last_edit:changeset": 114200228,
    "_last_edit:timestamp": "2021-11-24T23:11:12Z",
    "_version_number": 1,
    "_geometry:type": "Point",
    "_country": "be"
   },
   "geometry": {
    "type": "Point",
    "coordinates": [
     4.9389718,
     50.4792711
    ]
   },
   "_lon": 4.9389718,
   "_lat": 50.4792711
  },
  {
   "type": "Feature",
   "id": "node/9312633153",
   "properties": {
    "information": "board",
    "tourism": "information",
    "id": "node/9312633153",
    "_lat": "50.4685588",
    "_lon": "4.986917",
    "_layer": "information_board",
    "_length": "0",
    "_length:km": "0.0",
    "_last_edit:contributor": "Macumba Macaca",
    "_last_edit:contributor:uid": 2109841,
    "_last_edit:changeset": 114586330,
    "_last_edit:timestamp": "2021-12-05T15:39:54Z",
    "_version_number": 1,
    "_geometry:type": "Point",
    "_country": "be"
   },
   "geometry": {
    "type": "Point",
    "coordinates": [
     4.986917,
     50.4685588
    ]
   },
   "_lon": 4.986917,
   "_lat": 50.4685588
  }
 ]
}