{
 "type": "FeatureCollection",
 "features": [
  {
   "type": "Feature",
   "id": "node/2304929780",
   "properties": {
    "board_type": "nature",
    "description": "Wateringen",
    "information": "board",
    "tourism": "information",
    "id": "node/2304929780",
    "_lat": "51.2321617",
    "_lon": "5.1885651",
    "_layer": "information_board",
    "_surface": "0",
    "_surface:ha": "0",
    "_length": "0",
    "_length:km": "0.0",
    "_last_edit:contributor": "escada",
    "_last_edit:contributor:uid": 436365,
    "_last_edit:changeset": 16137085,
    "_last_edit:timestamp": "2013-05-15T10:38:05Z",
    "_version_number": 1,
    "_geometry:type": "Point",
    "_country": "be"
   },
   "geometry": {
    "type": "Point",
    "coordinates": [
     5.1885651,
     51.2321617
    ]
   },
   "_lon": 5.1885651,
   "_lat": 51.2321617
  },
  {
   "type": "Feature",
   "id": "node/7574799369",
   "properties": {
    "board_type": "wildlife",
    "information": "board",
    "name": "Drijvende eilanden trekken sternen aan",
    "tourism": "information",
    "id": "node/7574799369",
    "_lat": "51.2296955",
    "_lon": "5.1920889",
    "_layer": "information_board",
    "_surface": "0",
    "_surface:ha": "0",
    "_length": "0",
    "_length:km": "0.0",
    "_last_edit:contributor": "schnitzi99",
    "_last_edit:contributor:uid": 7342884,
    "_last_edit:changeset": 134682151,
    "_last_edit:timestamp": "2023-04-09T10:36:13Z",
    "_version_number": 3,
    "_geometry:type": "Point",
    "_country": "be"
   },
   "geometry": {
    "type": "Point",
    "coordinates": [
     5.1920889,
     51.2296955
    ]
   },
   "_lon": 5.1920889,
   "_lat": 51.2296955
  },
  {
   "type": "Feature",
   "id": "node/9920446365",
   "properties": {
    "image": "https://i.imgur.com/uSQqYQy.jpg",
    "information": "board",
    "name": "Most-Keiheuvel",
    "tourism": "information",
    "id": "node/9920446365",
    "_lat": "51.1818115",
    "_lon": "5.2124341",
    "_layer": "information_board",
    "_surface": "0",
    "_surface:ha": "0",
    "_length": "0",
    "_length:km": "0.0",
    "_last_edit:contributor": "dentonny",
    "_last_edit:contributor:uid": 4198737,
    "_last_edit:changeset": 124256546,
    "_last_edit:timestamp": "2022-07-30T07:05:22Z",
    "_version_number": 1,
    "_geometry:type": "Point",
    "_country": "be"
   },
   "geometry": {
    "type": "Point",
    "coordinates": [
     5.2124341,
     51.1818115
    ]
   },
   "_lon": 5.2124341,
   "_lat": 51.1818115
  }
 ]
}