{
 "type": "FeatureCollection",
 "features": [
  {
   "type": "Feature",
   "id": "node/1169747586",
   "properties": {
    "leisure": "bird_hide",
    "name": "Westerschelde - Nummer Een - Vogelkijkhut",
    "note": "Westerschelde - Nummer Een - Vogelkijkhut",
    "id": "node/1169747586",
    "_lat": "51.38116",
    "_lon": "3.61131",
    "_layer": "birdhide",
    "_length": "0",
    "_length:km": "0.0",
    "_last_edit:contributor": "joostdejong",
    "_last_edit:contributor:uid": 21555,
    "_last_edit:changeset": 7380118,
    "_last_edit:timestamp": "2011-02-24T10:23:48Z",
    "_version_number": 1,
    "_geometry:type": "Point",
    "_country": "nl"
   },
   "geometry": {
    "type": "Point",
    "coordinates": [
     3.61131,
     51.38116
    ]
   },
   "_lon": 3.61131,
   "_lat": 51.38116
  }
 ]
}