{
 "type": "FeatureCollection",
 "features": [
  {
   "type": "Feature",
   "id": "node/5398247734",
   "properties": {
    "board_type": "yes",
    "information": "board",
    "name": "Park regels Gemeentepark Geluwe",
    "operator": "Stad Wervik",
    "tourism": "information",
    "id": "node/5398247734",
    "_lat": "50.8107185",
    "_lon": "3.0761673",
    "_layer": "information_board",
    "_surface": "0",
    "_surface:ha": "0",
    "_length": "0",
    "_length:km": "0.0",
    "_last_edit:contributor": "Ysser",
    "_last_edit:contributor:uid": 7315314,
    "_last_edit:changeset": 56180967,
    "_last_edit:timestamp": "2018-02-08T12:17:10Z",
    "_version_number": 1,
    "_geometry:type": "Point",
    "_country": "be"
   },
   "geometry": {
    "type": "Point",
    "coordinates": [
     3.0761673,
     50.8107185
    ]
   },
   "_lon": 3.0761673,
   "_lat": 50.8107185
  },
  {
   "type": "Feature",
   "id": "node/5419807069",
   "properties": {
    "board_type": "history",
    "information": "board",
    "name": "Infobord heraanleg Gemeentepark",
    "operator": "Stad Wervik",
    "tourism": "information",
    "id": "node/5419807069",
    "_lat": "50.8107758",
    "_lon": "3.0760769",
    "_layer": "information_board",
    "_surface": "0",
    "_surface:ha": "0",
    "_length": "0",
    "_length:km": "0.0",
    "_last_edit:contributor": "Ysser",
    "_last_edit:contributor:uid": 7315314,
    "_last_edit:changeset": 56458428,
    "_last_edit:timestamp": "2018-02-18T09:59:08Z",
    "_version_number": 1,
    "_geometry:type": "Point",
    "_country": "be"
   },
   "geometry": {
    "type": "Point",
    "coordinates": [
     3.0760769,
     50.8107758
    ]
   },
   "_lon": 3.0760769,
   "_lat": 50.8107758
  },
  {
   "type": "Feature",
   "id": "node/5586121462",
   "properties": {
    "information": "board",
    "name": "Infobord Nijverheidslaan",
    "tourism": "information",
    "id": "node/5586121462",
    "_lat": "50.8131085",
    "_lon": "3.0689245",
    "_layer": "information_board",
    "_surface": "0",
    "_surface:ha": "0",
    "_length": "0",
    "_length:km": "0.0",
    "_last_edit:contributor": "Ysser",
    "_last_edit:contributor:uid": 7315314,
    "_last_edit:changeset": 58526888,
    "_last_edit:timestamp": "2018-04-29T13:11:16Z",
    "_version_number": 1,
    "_geometry:type": "Point",
    "_country": "be"
   },
   "geometry": {
    "type": "Point",
    "coordinates": [
     3.0689245,
     50.8131085
    ]
   },
   "_lon": 3.0689245,
   "_lat": 50.8131085
  },
  {
   "type": "Feature",
   "id": "node/8515162397",
   "properties": {
    "board_type": "history",
    "information": "board",
    "tourism": "information",
    "id": "node/8515162397",
    "_lat": "50.8399901",
    "_lon": "3.0550113",
    "_layer": "information_board",
    "_surface": "0",
    "_surface:ha": "0",
    "_length": "0",
    "_length:km": "0.0",
    "_last_edit:contributor": "Jakka",
    "_last_edit:contributor:uid": 2403313,
    "_last_edit:changeset": 100968863,
    "_last_edit:timestamp": "2021-03-13T20:44:25Z",
    "_version_number": 1,
    "_geometry:type": "Point",
    "_country": "be"
   },
   "geometry": {
    "type": "Point",
    "coordinates": [
     3.0550113,
     50.8399901
    ]
   },
   "_lon": 3.0550113,
   "_lat": 50.8399901
  },
  {
   "type": "Feature",
   "id": "node/8515187790",
   "properties": {
    "board_type": "history",
    "information": "board",
    "tourism": "information",
    "id": "node/8515187790",
    "_lat": "50.840831",
    "_lon": "3.0590279",
    "_layer": "information_board",
    "_surface": "0",
    "_surface:ha": "0",
    "_length": "0",
    "_length:km": "0.0",
    "_last_edit:contributor": "Jakka",
    "_last_edit:contributor:uid": 2403313,
    "_last_edit:changeset": 100968869,
    "_last_edit:timestamp": "2021-03-13T20:44:42Z",
    "_version_number": 1,
    "_geometry:type": "Point",
    "_country": "be"
   },
   "geometry": {
    "type": "Point",
    "coordinates": [
     3.0590279,
     50.840831
    ]
   },
   "_lon": 3.0590279,
   "_lat": 50.840831
  }
 ]
}