{
 "type": "FeatureCollection",
 "features": [
  {
   "type": "Feature",
   "id": "node/5006009829",
   "properties": {
    "information": "board",
    "name": "Panneau d'information LIFE Elia-RTE",
    "operator": "LIFE Elia-RTE",
    "tourism": "information",
    "website": "http://www.life-elia.eu",
    "id": "node/5006009829",
    "_lat": "50.3783832",
    "_lon": "5.7831366",
    "_layer": "information_board",
    "_surface": "0",
    "_surface:ha": "0",
    "_length": "0",
    "_length:km": "0.0",
    "_last_edit:contributor": "JFGodeau",
    "_last_edit:contributor:uid": 3700778,
    "_last_edit:changeset": 50734590,
    "_last_edit:timestamp": "2017-07-31T22:18:34Z",
    "_version_number": 1,
    "_geometry:type": "Point"
   },
   "geometry": {
    "type": "Point",
    "coordinates": [
     5.7831366,
     50.3783832
    ]
   },
   "_lon": 5.7831366,
   "_lat": 50.3783832
  },
  {
   "type": "Feature",
   "id": "node/7004104869",
   "properties": {
    "information": "board",
    "name": "Le Mierdeux - LIFE Ardenne liégeoise",
    "tourism": "information",
    "id": "node/7004104869",
    "_lat": "50.3612552",
    "_lon": "5.7769176",
    "_layer": "information_board",
    "_surface": "0",
    "_surface:ha": "0",
    "_length": "0",
    "_length:km": "0.0",
    "_last_edit:contributor": "Lucas Lambert",
    "_last_edit:contributor:uid": 7714751,
    "_last_edit:changeset": 77458814,
    "_last_edit:timestamp": "2019-11-23T13:15:53Z",
    "_version_number": 1,
    "_geometry:type": "Point"
   },
   "geometry": {
    "type": "Point",
    "coordinates": [
     5.7769176,
     50.3612552
    ]
   },
   "_lon": 5.7769176,
   "_lat": 50.3612552
  },
  {
   "type": "Feature",
   "id": "node/7705551946",
   "properties": {
    "information": "board",
    "tourism": "information",
    "id": "node/7705551946",
    "_lat": "50.381559",
    "_lon": "5.7140237",
    "_layer": "information_board",
    "_surface": "0",
    "_surface:ha": "0",
    "_length": "0",
    "_length:km": "0.0",
    "_last_edit:contributor": "StijnRR",
    "_last_edit:contributor:uid": 911613,
    "_last_edit:changeset": 87861028,
    "_last_edit:timestamp": "2020-07-11T18:38:09Z",
    "_version_number": 1,
    "_geometry:type": "Point"
   },
   "geometry": {
    "type": "Point",
    "coordinates": [
     5.7140237,
     50.381559
    ]
   },
   "_lon": 5.7140237,
   "_lat": 50.381559
  }
 ]
}