{
 "type": "FeatureCollection",
 "features": [
  {
   "type": "Feature",
   "id": "node/4378038375",
   "properties": {
    "description": "Ehemalige wasserbetriebene Mahlmühle, erbaut 17./18. Jh",
    "historic": "yes",
    "image": "https://commons.wikimedia.org/wiki/Category:Kranentalsm%C3%BChle#/media/File:183_Kranentalsm%C3%BChle,Wohn-_u_Wirtschaftsgeb%C3%A4ude.jpg",
    "man_made": "watermill",
    "name": "Kranentalsmühle",
    "wikidata": "Q1786471",
    "wikipedia": "de:Kranentalsmühle",
    "id": "node/4378038375",
    "_lat": "50.8585097",
    "_lon": "6.1654396",
    "_layer": "watermill",
    "_surface": "0",
    "_surface:ha": "0",
    "_length": "0",
    "_length:km": "0.0",
    "_last_edit:contributor": "Parzelle13",
    "_last_edit:contributor:uid": 3423755,
    "_last_edit:changeset": 64012323,
    "_last_edit:timestamp": "2018-10-30T13:47:00Z",
    "_version_number": 3,
    "_geometry:type": "Point",
    "_country": "de"
   },
   "geometry": {
    "type": "Point",
    "coordinates": [
     6.1654396,
     50.8585097
    ]
   },
   "_lon": 6.1654396,
   "_lat": 50.8585097
  },
  {
   "type": "Feature",
   "id": "node/4378056768",
   "properties": {
    "description": "Ehemalige wasserbetriebene Mahlmühle, erbaut vor 1683",
    "disused:watermill": "yes",
    "historic": "yes",
    "image": "https://commons.wikimedia.org/wiki/Category:Broicher_M%C3%BChle#/media/File:182_Broicher_M%C3%BChle,_Wohnhaus_1.jpg",
    "man_made": "watermill",
    "name": "Broicher Mühle",
    "wikidata": "Q925343",
    "wikipedia": "de:Broicher Mühle",
    "id": "node/4378056768",
    "_lat": "50.8539806",
    "_lon": "6.1705752",
    "_layer": "watermill",
    "_surface": "0",
    "_surface:ha": "0",
    "_length": "0",
    "_length:km": "0.0",
    "_last_edit:contributor": "Parzelle13",
    "_last_edit:contributor:uid": 3423755,
    "_last_edit:changeset": 64012203,
    "_last_edit:timestamp": "2018-10-30T13:44:13Z",
    "_version_number": 3,
    "_geometry:type": "Point",
    "_country": "de"
   },
   "geometry": {
    "type": "Point",
    "coordinates": [
     6.1705752,
     50.8539806
    ]
   },
   "_lon": 6.1705752,
   "_lat": 50.8539806
  },
  {
   "type": "Feature",
   "id": "node/4381314584",
   "properties": {
    "description": "Ehemalige wasserbetriebene Mahlmühle, erbaut vor 1600",
    "historic": "yes",
    "image": "https://commons.wikimedia.org/wiki/Category:Kellersberger_M%C3%BChle#/media/File:184_Kellersberger_M%C3%BChle,_Wirtschaftsgeb%C3%A4ude.jpg",
    "man_made": "watermill",
    "name": "Kellersberger Mühle",
    "wikidata": "Q1366251",
    "wikipedia": "de:Kellersberger Mühle",
    "id": "node/4381314584",
    "_lat": "50.8611162",
    "_lon": "6.1627282",
    "_layer": "watermill",
    "_surface": "0",
    "_surface:ha": "0",
    "_length": "0",
    "_length:km": "0.0",
    "_last_edit:contributor": "Parzelle13",
    "_last_edit:contributor:uid": 3423755,
    "_last_edit:changeset": 64012298,
    "_last_edit:timestamp": "2018-10-30T13:46:26Z",
    "_version_number": 4,
    "_geometry:type": "Point",
    "_country": "de"
   },
   "geometry": {
    "type": "Point",
    "coordinates": [
     6.1627282,
     50.8611162
    ]
   },
   "_lon": 6.1627282,
   "_lat": 50.8611162
  }
 ]
}