{
 "type": "FeatureCollection",
 "features": [
  {
   "type": "Feature",
   "id": "node/5048151231",
   "properties": {
    "information": "board",
    "tourism": "information",
    "id": "node/5048151231",
    "_lat": "51.4838606",
    "_lon": "3.8393946",
    "_layer": "information_board",
    "_length": "0",
    "_length:km": "0.0",
    "_last_edit:contributor": "AdVerburg",
    "_last_edit:contributor:uid": 2831457,
    "_last_edit:changeset": 51303213,
    "_last_edit:timestamp": "2017-08-21T12:14:28Z",
    "_version_number": 1,
    "_geometry:type": "Point",
    "_country": "nl"
   },
   "geometry": {
    "type": "Point",
    "coordinates": [
     3.8393946,
     51.4838606
    ]
   },
   "_lon": 3.8393946,
   "_lat": 51.4838606
  },
  {
   "type": "Feature",
   "id": "node/6414954008",
   "properties": {
    "board_type": "history",
    "information": "board",
    "name": "Kasteelbergen",
    "tourism": "information",
    "id": "node/6414954008",
    "_lat": "51.4898472",
    "_lon": "3.825519",
    "_layer": "information_board",
    "_length": "0",
    "_length:km": "0.0",
    "_last_edit:contributor": "AdVerburg",
    "_last_edit:contributor:uid": 2831457,
    "_last_edit:changeset": 69356236,
    "_last_edit:timestamp": "2019-04-18T18:59:08Z",
    "_version_number": 1,
    "_geometry:type": "Point",
    "_country": "nl"
   },
   "geometry": {
    "type": "Point",
    "coordinates": [
     3.825519,
     51.4898472
    ]
   },
   "_lon": 3.825519,
   "_lat": 51.4898472
  },
  {
   "type": "Feature",
   "id": "node/6414954235",
   "properties": {
    "board_type": "history",
    "information": "board",
    "name": "Station 's-Heer Arendskerke",
    "tourism": "information",
    "id": "node/6414954235",
    "_lat": "51.4996157",
    "_lon": "3.8148282",
    "_layer": "information_board",
    "_length": "0",
    "_length:km": "0.0",
    "_last_edit:contributor": "AdVerburg",
    "_last_edit:contributor:uid": 2831457,
    "_last_edit:changeset": 69356236,
    "_last_edit:timestamp": "2019-04-18T18:59:10Z",
    "_version_number": 1,
    "_geometry:type": "Point",
    "_country": "nl"
   },
   "geometry": {
    "type": "Point",
    "coordinates": [
     3.8148282,
     51.4996157
    ]
   },
   "_lon": 3.8148282,
   "_lat": 51.4996157
  },
  {
   "type": "Feature",
   "id": "node/6414954236",
   "properties": {
    "board_type": "history",
    "information": "board",
    "name": "Nooit Gedacht",
    "tourism": "information",
    "id": "node/6414954236",
    "_lat": "51.4996055",
    "_lon": "3.8147301",
    "_layer": "information_board",
    "_length": "0",
    "_length:km": "0.0",
    "_last_edit:contributor": "AdVerburg",
    "_last_edit:contributor:uid": 2831457,
    "_last_edit:changeset": 69356236,
    "_last_edit:timestamp": "2019-04-18T18:59:10Z",
    "_version_number": 1,
    "_geometry:type": "Point",
    "_country": "nl"
   },
   "geometry": {
    "type": "Point",
    "coordinates": [
     3.8147301,
     51.4996055
    ]
   },
   "_lon": 3.8147301,
   "_lat": 51.4996055
  }
 ]
}