{
 "type": "FeatureCollection",
 "features": [
  {
   "type": "Feature",
   "id": "node/3682128086",
   "properties": {
    "amenity": "drinking_water",
    "bottle": "yes",
    "operator": "WML Limburgs drinkwater",
    "seasonal": "yes",
    "id": "node/3682128086",
    "_lat": "50.8155269",
    "_lon": "5.8949632",
    "_layer": "drinking_water",
    "_length": "0",
    "_length:km": "0.0",
    "_last_edit:contributor": "Infodisiac",
    "_last_edit:contributor:uid": 8367,
    "_last_edit:changeset": 77876588,
    "_last_edit:timestamp": "2019-12-03T12:31:40Z",
    "_version_number": 2,
    "_geometry:type": "Point",
    "_closest_other_drinking_water": "{\"id\":\"way/879577157\",\"distance\":\"112.69470302819883\"}",
    "_closest_other_drinking_water_id": "way/879577157",
    "_closest_other_drinking_water_distance": "112"
   },
   "geometry": {
    "type": "Point",
    "coordinates": [
     5.8949632,
     50.8155269
    ]
   },
   "_lon": 5.8949632,
   "_lat": 50.8155269
  },
  {
   "type": "Feature",
   "id": "node/8010514819",
   "properties": {
    "amenity": "drinking_water",
    "bottle": "yes",
    "fee": "no",
    "operator": "Waterleiding Maatschappij Limburg",
    "seasonal": "yes",
    "website": "https://www.wml.nl/alles-over-water/limburgs-water-drinken/watertaps-in-de-buurt",
    "id": "node/8010514819",
    "_lat": "50.8342834",
    "_lon": "5.9750048",
    "_layer": "drinking_water",
    "_length": "0",
    "_length:km": "0.0",
    "_last_edit:contributor": "Buxtehude",
    "_last_edit:contributor:uid": 1433710,
    "_last_edit:changeset": 92534969,
    "_last_edit:timestamp": "2020-10-15T16:49:59Z",
    "_version_number": 1,
    "_geometry:type": "Point",
    "_closest_other_drinking_water": "{\"id\":\"way/220018829\",\"distance\":\"80.94956445683623\"}",
    "_closest_other_drinking_water_id": "way/220018829",
    "_closest_other_drinking_water_distance": "80"
   },
   "geometry": {
    "type": "Point",
    "coordinates": [
     5.9750048,
     50.8342834
    ]
   },
   "_lon": 5.9750048,
   "_lat": 50.8342834
  }
 ]
}