{
 "type": "FeatureCollection",
 "features": [
  {
   "type": "Feature",
   "id": "node/9546685813",
   "properties": {
    "information": "board",
    "tourism": "information",
    "id": "node/9546685813",
    "_lat": "50.5771924",
    "_lon": "4.2798311",
    "_layer": "information_board",
    "_surface": "0",
    "_surface:ha": "0",
    "_length": "0",
    "_length:km": "0.0",
    "_last_edit:contributor": "Jakka",
    "_last_edit:contributor:uid": 2403313,
    "_last_edit:changeset": 117968158,
    "_last_edit:timestamp": "2022-03-01T07:20:15Z",
    "_version_number": 1,
    "_geometry:type": "Point",
    "_country": "be"
   },
   "geometry": {
    "type": "Point",
    "coordinates": [
     4.2798311,
     50.5771924
    ]
   },
   "_lon": 4.2798311,
   "_lat": 50.5771924
  },
  {
   "type": "Feature",
   "id": "node/9776753123",
   "properties": {
    "board_type": "notice",
    "description": "Tourist information",
    "information": "board",
    "name": "Province de Hainaut",
    "tourism": "information",
    "id": "node/9776753123",
    "_lat": "50.5916424",
    "_lon": "4.2215083",
    "_layer": "information_board",
    "_surface": "0",
    "_surface:ha": "0",
    "_length": "0",
    "_length:km": "0.0",
    "_last_edit:contributor": "Mizuna",
    "_last_edit:contributor:uid": 12496737,
    "_last_edit:changeset": 121615298,
    "_last_edit:timestamp": "2022-05-28T12:41:31Z",
    "_version_number": 1,
    "_geometry:type": "Point",
    "_country": "be"
   },
   "geometry": {
    "type": "Point",
    "coordinates": [
     4.2215083,
     50.5916424
    ]
   },
   "_lon": 4.2215083,
   "_lat": 50.5916424
  }
 ]
}