{
 "type": "FeatureCollection",
 "features": [
  {
   "type": "Feature",
   "id": "node/2994517122",
   "properties": {
    "board_type": "wildlife",
    "information": "board",
    "tourism": "information",
    "id": "node/2994517122",
    "_lat": "51.2897669",
    "_lon": "5.3839952",
    "_layer": "information_board",
    "_surface": "0",
    "_surface:ha": "0",
    "_length": "0",
    "_length:km": "0.0",
    "_last_edit:contributor": "Sander H",
    "_last_edit:contributor:uid": 327477,
    "_last_edit:changeset": 24521587,
    "_last_edit:timestamp": "2014-08-03T18:18:54Z",
    "_version_number": 1,
    "_geometry:type": "Point",
    "_country": "nl"
   },
   "geometry": {
    "type": "Point",
    "coordinates": [
     5.3839952,
     51.2897669
    ]
   },
   "_lon": 5.3839952,
   "_lat": 51.2897669
  },
  {
   "type": "Feature",
   "id": "node/3734944943",
   "properties": {
    "board_type": "nature",
    "information": "board",
    "name": "De Malpie",
    "tourism": "information",
    "id": "node/3734944943",
    "_lat": "51.333579",
    "_lon": "5.4442888",
    "_layer": "information_board",
    "_surface": "0",
    "_surface:ha": "0",
    "_length": "0",
    "_length:km": "0.0",
    "_last_edit:contributor": "Kin Sapalot",
    "_last_edit:contributor:uid": 1780315,
    "_last_edit:changeset": 82458438,
    "_last_edit:timestamp": "2020-03-21T12:35:52Z",
    "_version_number": 3,
    "_geometry:type": "Point",
    "_country": "nl"
   },
   "geometry": {
    "type": "Point",
    "coordinates": [
     5.4442888,
     51.333579
    ]
   },
   "_lon": 5.4442888,
   "_lat": 51.333579
  },
  {
   "type": "Feature",
   "id": "node/6141092032",
   "properties": {
    "bicycle": "yes",
    "highway": "trailhead",
    "hiking": "yes",
    "information": "board",
    "name": "Natuurpoort De Malpie",
    "source": "gpsfietsroutesnederland.nl",
    "survey:date": "2018-11",
    "tourism": "information",
    "url": "https://gpsfietsroutesnederland.nl/toeristische-overstappunten/",
    "website": "https://www.natuurpoorten.nl/",
    "wikipedia": "nl:Toeristisch Overstappunt",
    "id": "node/6141092032",
    "_lat": "51.33757",
    "_lon": "5.445517",
    "_layer": "information_board",
    "_surface": "0",
    "_surface:ha": "0",
    "_length": "0",
    "_length:km": "0.0",
    "_last_edit:contributor": "Peter Elderson",
    "_last_edit:contributor:uid": 7103674,
    "_last_edit:changeset": 65734658,
    "_last_edit:timestamp": "2018-12-24T09:25:42Z",
    "_version_number": 3,
    "_geometry:type": "Point",
    "_country": "nl"
   },
   "geometry": {
    "type": "Point",
    "coordinates": [
     5.445517,
     51.33757
    ]
   },
   "_lon": 5.445517,
   "_lat": 51.33757
  }
 ]
}