{
 "type": "FeatureCollection",
 "features": [
  {
   "type": "Feature",
   "id": "node/4494814384",
   "properties": {
    "amenity": "toilets",
    "description:en": "Free for children less than 1.40 m",
    "description:fr": "Gratuit pour les enfants de moins de 1,40 m",
    "fee": "yes",
    "toilets:wheelchair": "yes",
    "wheelchair": "yes",
    "id": "node/4494814384",
    "_lat": "50.6684775",
    "_lon": "4.378991",
    "_layer": "toilet",
    "_surface": "0",
    "_surface:ha": "0",
    "_length": "0",
    "_length:km": "0.0",
    "_last_edit:contributor": "wheelmap_visitor",
    "_last_edit:contributor:uid": 290680,
    "_last_edit:changeset": 45614655,
    "_last_edit:timestamp": "2017-01-29T09:17:55Z",
    "_version_number": 5,
    "_geometry:type": "Point",
    "_country": "be"
   },
   "geometry": {
    "type": "Point",
    "coordinates": [
     4.378991,
     50.6684775
    ]
   },
   "_lon": 4.378991,
   "_lat": 50.6684775
  },
  {
   "type": "Feature",
   "id": "node/4527030487",
   "properties": {
    "amenity": "toilets",
    "indoor": "yes",
    "id": "node/4527030487",
    "_lat": "50.6790435",
    "_lon": "4.3864656",
    "_layer": "toilet",
    "_surface": "0",
    "_surface:ha": "0",
    "_length": "0",
    "_length:km": "0.0",
    "_last_edit:contributor": "metatech",
    "_last_edit:contributor:uid": 1545711,
    "_last_edit:changeset": 44019356,
    "_last_edit:timestamp": "2016-11-28T21:24:44Z",
    "_version_number": 1,
    "_geometry:type": "Point",
    "_country": "be"
   },
   "geometry": {
    "type": "Point",
    "coordinates": [
     4.3864656,
     50.6790435
    ]
   },
   "_lon": 4.3864656,
   "_lat": 50.6790435
  },
  {
   "type": "Feature",
   "id": "node/9863550417",
   "properties": {
    "amenity": "toilets",
    "name": "Toilette du stade Gaston Reiff",
    "id": "node/9863550417",
    "_lat": "50.6782638",
    "_lon": "4.3863993",
    "_layer": "toilet",
    "_surface": "0",
    "_surface:ha": "0",
    "_length": "0",
    "_length:km": "0.0",
    "_last_edit:contributor": "Karan De Bel",
    "_last_edit:contributor:uid": 12321767,
    "_last_edit:changeset": 123144454,
    "_last_edit:timestamp": "2022-07-03T09:36:20Z",
    "_version_number": 1,
    "_geometry:type": "Point",
    "_country": "be"
   },
   "geometry": {
    "type": "Point",
    "coordinates": [
     4.3863993,
     50.6782638
    ]
   },
   "_lon": 4.3863993,
   "_lat": 50.6782638
  }
 ]
}