{
 "type": "FeatureCollection",
 "features": [
  {
   "type": "Feature",
   "id": "node/639088308",
   "properties": {
    "board_type": "nature",
    "information": "board",
    "name": "Hexenkull Hardter Wald",
    "tourism": "information",
    "id": "node/639088308",
    "_lat": "51.1903624",
    "_lon": "6.3447215",
    "_layer": "information_board",
    "_length": "0",
    "_length:km": "0.0",
    "_last_edit:contributor": "FraHaar",
    "_last_edit:contributor:uid": 213258,
    "_last_edit:changeset": 5616769,
    "_last_edit:timestamp": "2010-08-28T14:50:49Z",
    "_version_number": 2,
    "_geometry:type": "Point",
    "_country": "de"
   },
   "geometry": {
    "type": "Point",
    "coordinates": [
     6.3447215,
     51.1903624
    ]
   },
   "_lon": 6.3447215,
   "_lat": 51.1903624
  },
  {
   "type": "Feature",
   "id": "node/641295416",
   "properties": {
    "board_type": "nature",
    "description": "Alte und abgestorbene Bäume als Lebensraum",
    "information": "board",
    "tourism": "information",
    "id": "node/641295416",
    "_lat": "51.1983396",
    "_lon": "6.3282918",
    "_layer": "information_board",
    "_length": "0",
    "_length:km": "0.0",
    "_last_edit:contributor": "physi",
    "_last_edit:contributor:uid": 80762,
    "_last_edit:changeset": 105350442,
    "_last_edit:timestamp": "2021-05-26T10:42:58Z",
    "_version_number": 2,
    "_geometry:type": "Point",
    "_country": "de"
   },
   "geometry": {
    "type": "Point",
    "coordinates": [
     6.3282918,
     51.1983396
    ]
   },
   "_lon": 6.3282918,
   "_lat": 51.1983396
  },
  {
   "type": "Feature",
   "id": "node/884625215",
   "properties": {
    "board_type": "nature",
    "information": "board",
    "name": "Teufelskull",
    "tourism": "information",
    "id": "node/884625215",
    "_lat": "51.1823842",
    "_lon": "6.3565527",
    "_layer": "information_board",
    "_length": "0",
    "_length:km": "0.0",
    "_last_edit:contributor": "FraHaar",
    "_last_edit:contributor:uid": 213258,
    "_last_edit:changeset": 5616791,
    "_last_edit:timestamp": "2010-08-28T14:52:53Z",
    "_version_number": 1,
    "_geometry:type": "Point",
    "_country": "de"
   },
   "geometry": {
    "type": "Point",
    "coordinates": [
     6.3565527,
     51.1823842
    ]
   },
   "_lon": 6.3565527,
   "_lat": 51.1823842
  },
  {
   "type": "Feature",
   "id": "node/884630693",
   "properties": {
    "board_type": "nature",
    "information": "board",
    "name": "Hardter Wald, Landwehre",
    "tourism": "information",
    "id": "node/884630693",
    "_lat": "51.1824085",
    "_lon": "6.356323",
    "_layer": "information_board",
    "_length": "0",
    "_length:km": "0.0",
    "_last_edit:contributor": "FraHaar",
    "_last_edit:contributor:uid": 213258,
    "_last_edit:changeset": 5616808,
    "_last_edit:timestamp": "2010-08-28T14:55:16Z",
    "_version_number": 1,
    "_geometry:type": "Point",
    "_country": "de"
   },
   "geometry": {
    "type": "Point",
    "coordinates": [
     6.356323,
     51.1824085
    ]
   },
   "_lon": 6.356323,
   "_lat": 51.1824085
  },
  {
   "type": "Feature",
   "id": "node/942373987",
   "properties": {
    "board_type": "sight",
    "information": "board",
    "name": "Museum Abteiberg",
    "tourism": "information",
    "traffic_sign": "DE:386.3",
    "id": "node/942373987",
    "_lat": "51.2212329",
    "_lon": "6.4092099",
    "_layer": "information_board",
    "_length": "0",
    "_length:km": "0.0",
    "_last_edit:contributor": "GB_Germany_Vie",
    "_last_edit:contributor:uid": 46828,
    "_last_edit:changeset": 34429958,
    "_last_edit:timestamp": "2015-10-04T15:22:54Z",
    "_version_number": 4,
    "_geometry:type": "Point",
    "_country": "de"
   },
   "geometry": {
    "type": "Point",
    "coordinates": [
     6.4092099,
     51.2212329
    ]
   },
   "_lon": 6.4092099,
   "_lat": 51.2212329
  },
  {
   "type": "Feature",
   "id": "node/2356111202",
   "properties": {
    "board_type": "notice",
    "information": "board",
    "tourism": "information",
    "id": "node/2356111202",
    "_lat": "51.2045767",
    "_lon": "6.3433165",
    "_layer": "information_board",
    "_length": "0",
    "_length:km": "0.0",
    "_last_edit:contributor": "waldhans",
    "_last_edit:contributor:uid": 1969678,
    "_last_edit:changeset": 65702528,
    "_last_edit:timestamp": "2018-12-22T20:31:09Z",
    "_version_number": 2,
    "_geometry:type": "Point",
    "_country": "de"
   },
   "geometry": {
    "type": "Point",
    "coordinates": [
     6.3433165,
     51.2045767
    ]
   },
   "_lon": 6.3433165,
   "_lat": 51.2045767
  }
 ]
}