{
 "type": "FeatureCollection",
 "features": [
  {
   "type": "Feature",
   "id": "node/6583231467",
   "properties": {
    "board_type": "notice",
    "information": "board",
    "name": "Landbouwleerpad Blankenberge",
    "tourism": "information",
    "id": "node/6583231467",
    "_lat": "51.3046452",
    "_lon": "3.1710403",
    "_layer": "information_board",
    "_surface": "0",
    "_surface:ha": "0",
    "_length": "0",
    "_length:km": "0.0",
    "_last_edit:contributor": "Peilscheibe",
    "_last_edit:contributor:uid": 35560,
    "_last_edit:changeset": 71807787,
    "_last_edit:timestamp": "2019-07-02T05:43:29Z",
    "_version_number": 1,
    "_geometry:type": "Point"
   },
   "geometry": {
    "type": "Point",
    "coordinates": [
     3.1710403,
     51.3046452
    ]
   },
   "_lon": 3.1710403,
   "_lat": 51.3046452
  },
  {
   "type": "Feature",
   "id": "node/8306736342",
   "properties": {
    "board_type": "nature",
    "information": "board",
    "tourism": "information",
    "id": "node/8306736342",
    "_lat": "51.3328612",
    "_lon": "3.2304703",
    "_layer": "information_board",
    "_surface": "0",
    "_surface:ha": "0",
    "_length": "0",
    "_length:km": "0.0",
    "_last_edit:contributor": "SustainableMobile",
    "_last_edit:contributor:uid": 291048,
    "_last_edit:changeset": 97224328,
    "_last_edit:timestamp": "2021-01-09T18:27:07Z",
    "_version_number": 1,
    "_geometry:type": "Point"
   },
   "geometry": {
    "type": "Point",
    "coordinates": [
     3.2304703,
     51.3328612
    ]
   },
   "_lon": 3.2304703,
   "_lat": 51.3328612
  },
  {
   "type": "Feature",
   "id": "node/8606862393",
   "properties": {
    "image": "https://i.imgur.com/RjwAPVV.jpg",
    "information": "board",
    "tourism": "information",
    "id": "node/8606862393",
    "_lat": "51.3401637",
    "_lon": "3.2279179",
    "_layer": "information_board",
    "_surface": "0",
    "_surface:ha": "0",
    "_length": "0",
    "_length:km": "0.0",
    "_last_edit:contributor": "Pieter Vander Vennet",
    "_last_edit:contributor:uid": 3818858,
    "_last_edit:changeset": 102567651,
    "_last_edit:timestamp": "2021-04-08T13:43:21Z",
    "_version_number": 2,
    "_geometry:type": "Point"
   },
   "geometry": {
    "type": "Point",
    "coordinates": [
     3.2279179,
     51.3401637
    ]
   },
   "_lon": 3.2279179,
   "_lat": 51.3401637
  },
  {
   "type": "Feature",
   "id": "node/9289666522",
   "properties": {
    "board_type": "map",
    "information": "board",
    "tourism": "information",
    "id": "node/9289666522",
    "_lat": "51.3294124",
    "_lon": "3.1834849",
    "_layer": "information_board",
    "_surface": "0",
    "_surface:ha": "0",
    "_length": "0",
    "_length:km": "0.0",
    "_last_edit:contributor": "smx574",
    "_last_edit:contributor:uid": 14531738,
    "_last_edit:changeset": 114316369,
    "_last_edit:timestamp": "2021-11-28T08:42:46Z",
    "_version_number": 1,
    "_geometry:type": "Point"
   },
   "geometry": {
    "type": "Point",
    "coordinates": [
     3.1834849,
     51.3294124
    ]
   },
   "_lon": 3.1834849,
   "_lat": 51.3294124
  },
  {
   "type": "Feature",
   "id": "node/9289666523",
   "properties": {
    "board_type": "information",
    "information": "board",
    "tourism": "information",
    "id": "node/9289666523",
    "_lat": "51.3294241",
    "_lon": "3.1835084",
    "_layer": "information_board",
    "_surface": "0",
    "_surface:ha": "0",
    "_length": "0",
    "_length:km": "0.0",
    "_last_edit:contributor": "smx574",
    "_last_edit:contributor:uid": 14531738,
    "_last_edit:changeset": 114316369,
    "_last_edit:timestamp": "2021-11-28T08:42:46Z",
    "_version_number": 1,
    "_geometry:type": "Point"
   },
   "geometry": {
    "type": "Point",
    "coordinates": [
     3.1835084,
     51.3294241
    ]
   },
   "_lon": 3.1835084,
   "_lat": 51.3294241
  }
 ]
}