{
 "type": "FeatureCollection",
 "features": [
  {
   "type": "Feature",
   "id": "node/4704958429",
   "properties": {
    "description": "https://photos.app.goo.gl/eQP416W9kWoPx3JN7",
    "image": "https://images.mapillary.com/SIHRjXDVJxVE69qxvIxkBu/thumb-2048.jpg",
    "leisure": "bird_hide",
    "mapillary": "https://www.mapillary.com/map/im/SIHRjXDVJxVE69qxvIxkBu",
    "name": "Kiekoet Oehoe-vallei",
    "tourism": "viewpoint",
    "wikidata": "Q108127486",
    "id": "node/4704958429",
    "_lat": "50.8306453",
    "_lon": "5.6834957",
    "_layer": "birdhide",
    "_length": "0",
    "_length:km": "0.0",
    "_last_edit:contributor": "Romaine2",
    "_last_edit:contributor:uid": 2132827,
    "_last_edit:changeset": 110391427,
    "_last_edit:timestamp": "2021-08-28T18:56:33Z",
    "_version_number": 3
   },
   "geometry": {
    "type": "Point",
    "coordinates": [
     5.6834957,
     50.8306453
    ]
   },
   "_lon": 5.6834957,
   "_lat": 50.8306453
  }
 ]
}