{
 "type": "FeatureCollection",
 "features": [
  {
   "type": "Feature",
   "id": "node/6027914001",
   "properties": {
    "leisure": "bird_hide",
    "name": "Trektelpost Gaverbeekse Meersen",
    "id": "node/6027914001",
    "_lat": "50.8971242",
    "_lon": "3.4310827",
    "_layer": "birdhide",
    "_length": "0",
    "_length:km": "0.0",
    "_last_edit:contributor": "Thibault Rommel",
    "_last_edit:contributor:uid": 5846458,
    "_last_edit:changeset": 72140640,
    "_last_edit:timestamp": "2019-07-11T15:03:28Z",
    "_version_number": 2,
    "_geometry:type": "Point",
    "_country": "be"
   },
   "geometry": {
    "type": "Point",
    "coordinates": [
     3.4310827,
     50.8971242
    ]
   },
   "_lon": 3.4310827,
   "_lat": 50.8971242
  }
 ]
}