{
 "type": "FeatureCollection",
 "features": [
  {
   "type": "Feature",
   "id": "node/9922360482",
   "properties": {
    "amenity": "drinking_water",
    "name": "Drinking water",
    "id": "node/9922360482",
    "_lat": "51.2333415",
    "_lon": "5.4345272",
    "_layer": "drinking_water",
    "_surface": "0",
    "_surface:ha": "0",
    "_length": "0",
    "_length:km": "0.0",
    "_last_edit:contributor": "Eebie",
    "_last_edit:contributor:uid": 715684,
    "_last_edit:changeset": 129493564,
    "_last_edit:timestamp": "2022-11-28T21:46:56Z",
    "_version_number": 2,
    "_geometry:type": "Point",
    "_country": "be",
    "_closest_other_drinking_water": "{\"id\":\"node/10224492232\",\"distance\":\"6.031606877799077\"}",
    "_closest_other_drinking_water_id": "node/10224492232",
    "_closest_other_drinking_water_distance": "6"
   },
   "geometry": {
    "type": "Point",
    "coordinates": [
     5.4345272,
     51.2333415
    ]
   },
   "_lon": 5.4345272,
   "_lat": 51.2333415,
   "_is_patched": true
  }
 ]
}