{
 "type": "FeatureCollection",
 "features": [
  {
   "type": "Feature",
   "id": "node/2476898085",
   "properties": {
    "board_type": "nature",
    "information": "board",
    "name": "Oude Leiarm Gottem",
    "tourism": "information",
    "id": "node/2476898085",
    "_lat": "50.9492806",
    "_lon": "3.4562566",
    "_layer": "information_board",
    "_length": "0",
    "_length:km": "0.0",
    "_last_edit:contributor": "meannder",
    "_last_edit:contributor:uid": 149496,
    "_last_edit:changeset": 18098458,
    "_last_edit:timestamp": "2013-09-29T18:59:03Z",
    "_version_number": 1,
    "_country": "be"
   },
   "geometry": {
    "type": "Point",
    "coordinates": [
     3.4562566,
     50.9492806
    ]
   },
   "_lon": 3.4562566,
   "_lat": 50.9492806
  }
 ]
}