{
 "type": "FeatureCollection",
 "features": [
  {
   "type": "Feature",
   "id": "node/5907865891",
   "properties": {
    "information": "board",
    "name": "Krochten",
    "tourism": "information",
    "id": "node/5907865891",
    "_lat": "51.4456359",
    "_lon": "4.6593663",
    "_layer": "information_board",
    "_length": "0",
    "_length:km": "0.0",
    "_last_edit:contributor": "LudoStes",
    "_last_edit:contributor:uid": 4237934,
    "_last_edit:changeset": 62608397,
    "_last_edit:timestamp": "2018-09-15T10:38:57Z",
    "_version_number": 1,
    "_country": "nl"
   },
   "geometry": {
    "type": "Point",
    "coordinates": [
     4.6593663,
     51.4456359
    ]
   },
   "_lon": 4.6593663,
   "_lat": 51.4456359
  }
 ]
}