{
 "type": "FeatureCollection",
 "features": [
  {
   "type": "Feature",
   "id": "node/9986111759",
   "properties": {
    "information": "board",
    "name": "Via Francigena",
    "tourism": "information",
    "id": "node/9986111759",
    "_lat": "50.3504826",
    "_lon": "2.6926192",
    "_layer": "information_board",
    "_surface": "0",
    "_surface:ha": "0",
    "_length": "0",
    "_length:km": "0.0",
    "_last_edit:contributor": "Kazing",
    "_last_edit:contributor:uid": 4741702,
    "_last_edit:changeset": 125524721,
    "_last_edit:timestamp": "2022-08-29T13:37:48Z",
    "_version_number": 1,
    "_geometry:type": "Point",
    "_country": "fr"
   },
   "geometry": {
    "type": "Point",
    "coordinates": [
     2.6926192,
     50.3504826
    ]
   },
   "_lon": 2.6926192,
   "_lat": 50.3504826
  }
 ]
}