{
  "type": "FeatureCollection",
  "features": [
    {
      "type": "Feature",
      "properties": {
        "address_id": "237056",
        "box_number": "",
        "house_number": "50",
        "municipality_id": "84010",
        "municipality_name_de": "",
        "municipality_name_fr": "Bouillon",
        "municipality_name_nl": "",
        "postcode": "6832",
        "postname_fr": "",
        "postname_nl": "",
        "street_id": "7745238",
        "streetname_de": "",
        "streetname_fr": "Rue des Quatre Moineaux",
        "streetname_nl": "",
        "region_code": "BE-WAL",
        "status": "current"
      },
      "geometry": {
        "type": "Point",
        "coordinates": [
          5.07375,
          49.81003
        ]
      }
    },
    {
      "type": "Feature",
      "properties": {
        "address_id": "1920149",
        "box_number": "",
        "house_number": "55A",
        "municipality_id": "84010",
        "municipality_name_de": "",
        "municipality_name_fr": "Bouillon",
        "municipality_name_nl": "",
        "postcode": "6832",
        "postname_fr": "",
        "postname_nl": "",
        "street_id": "7745167",
        "streetname_de": "",
        "streetname_fr": "Rue de la Bichetour",
        "streetname_nl": "",
        "region_code": "BE-WAL",
        "status": "current"
      },
      "geometry": {
        "type": "Point",
        "coordinates": [
          5.0754,
          49.81363
        ]
      }
    },
    {
      "type": "Feature",
      "properties": {
        "address_id": "238276",
        "box_number": "",
        "house_number": "55",
        "municipality_id": "84010",
        "municipality_name_de": "",
        "municipality_name_fr": "Bouillon",
        "municipality_name_nl": "",
        "postcode": "6832",
        "postname_fr": "",
        "postname_nl": "",
        "street_id": "7745167",
        "streetname_de": "",
        "streetname_fr": "Rue de la Bichetour",
        "streetname_nl": "",
        "region_code": "BE-WAL",
        "status": "current"
      },
      "geometry": {
        "type": "Point",
        "coordinates": [
          5.07564,
          49.81365
        ]
      }
    }
  ]
}