{
  "type": "FeatureCollection",
  "features": [
    {
      "type": "Feature",
      "properties": {
        "address_id": "607510",
        "box_number": "",
        "house_number": "2",
        "municipality_id": "53053",
        "municipality_name_de": "",
        "municipality_name_fr": "Mons",
        "municipality_name_nl": "",
        "postcode": "7034",
        "postname_fr": "",
        "postname_nl": "",
        "street_id": "7713762",
        "streetname_de": "",
        "streetname_fr": "Rue des Fabriques",
        "streetname_nl": "",
        "region_code": "BE-WAL",
        "status": "current"
      },
      "geometry": {
        "type": "Point",
        "coordinates": [
          3.99593,
          50.47197
        ]
      }
    },
    {
      "type": "Feature",
      "properties": {
        "address_id": "1921596",
        "box_number": "",
        "house_number": "31",
        "municipality_id": "53053",
        "municipality_name_de": "",
        "municipality_name_fr": "Mons",
        "municipality_name_nl": "",
        "postcode": "7034",
        "postname_fr": "",
        "postname_nl": "",
        "street_id": "7713697",
        "streetname_de": "",
        "streetname_fr": "Rue d'Empire",
        "streetname_nl": "",
        "region_code": "BE-WAL",
        "status": "current"
      },
      "geometry": {
        "type": "Point",
        "coordinates": [
          3.99865,
          50.4756
        ]
      }
    },
    {
      "type": "Feature",
      "properties": {
        "address_id": "619974",
        "box_number": "",
        "house_number": "2",
        "municipality_id": "53053",
        "municipality_name_de": "",
        "municipality_name_fr": "Mons",
        "municipality_name_nl": "",
        "postcode": "7034",
        "postname_fr": "",
        "postname_nl": "",
        "street_id": "7713697",
        "streetname_de": "",
        "streetname_fr": "Rue d'Empire",
        "streetname_nl": "",
        "region_code": "BE-WAL",
        "status": "current"
      },
      "geometry": {
        "type": "Point",
        "coordinates": [
          3.99561,
          50.47591
        ]
      }
    },
    {
      "type": "Feature",
      "properties": {
        "address_id": "581315",
        "box_number": "",
        "house_number": "3",
        "municipality_id": "53053",
        "municipality_name_de": "",
        "municipality_name_fr": "Mons",
        "municipality_name_nl": "",
        "postcode": "7034",
        "postname_fr": "",
        "postname_nl": "",
        "street_id": "7713222",
        "streetname_de": "",
        "streetname_fr": "Chemin du Pont d'Haine",
        "streetname_nl": "",
        "region_code": "BE-WAL",
        "status": "current"
      },
      "geometry": {
        "type": "Point",
        "coordinates": [
          3.98033,
          50.47809
        ]
      }
    },
    {
      "type": "Feature",
      "properties": {
        "address_id": "581316",
        "box_number": "",
        "house_number": "2",
        "municipality_id": "53053",
        "municipality_name_de": "",
        "municipality_name_fr": "Mons",
        "municipality_name_nl": "",
        "postcode": "7034",
        "postname_fr": "",
        "postname_nl": "",
        "street_id": "7713222",
        "streetname_de": "",
        "streetname_fr": "Chemin du Pont d'Haine",
        "streetname_nl": "",
        "region_code": "BE-WAL",
        "status": "current"
      },
      "geometry": {
        "type": "Point",
        "coordinates": [
          3.98336,
          50.48141
        ]
      }
    },
    {
      "type": "Feature",
      "properties": {
        "address_id": "581317",
        "box_number": "",
        "house_number": "1",
        "municipality_id": "53053",
        "municipality_name_de": "",
        "municipality_name_fr": "Mons",
        "municipality_name_nl": "",
        "postcode": "7034",
        "postname_fr": "",
        "postname_nl": "",
        "street_id": "7713222",
        "streetname_de": "",
        "streetname_fr": "Chemin du Pont d'Haine",
        "streetname_nl": "",
        "region_code": "BE-WAL",
        "status": "current"
      },
      "geometry": {
        "type": "Point",
        "coordinates": [
          3.9805,
          50.47841
        ]
      }
    }
  ]
}