{
  "type": "FeatureCollection",
  "features": [
    {
      "type": "Feature",
      "properties": {
        "address_id": "1416022",
        "box_number": "",
        "house_number": "122",
        "municipality_id": "82032",
        "municipality_name_de": "",
        "municipality_name_fr": "Vielsalm",
        "municipality_name_nl": "",
        "postcode": "6690",
        "postname_fr": "",
        "postname_nl": "",
        "street_id": "7742804",
        "streetname_de": "",
        "streetname_fr": "Neuville-Haut",
        "streetname_nl": "",
        "region_code": "BE-WAL",
        "status": "current"
      },
      "geometry": {
        "type": "Point",
        "coordinates": [
          5.96015,
          50.27481
        ]
      }
    }
  ]
}