{
  "type": "FeatureCollection",
  "features": [
    {
      "type": "Feature",
      "properties": {
        "address_id": "791006",
        "box_number": "",
        "house_number": "3",
        "municipality_id": "56016",
        "municipality_name_de": "",
        "municipality_name_fr": "Chimay",
        "municipality_name_nl": "",
        "postcode": "6461",
        "postname_fr": "",
        "postname_nl": "",
        "street_id": "7720046",
        "streetname_de": "",
        "streetname_fr": "Rue de la Ferrière",
        "streetname_nl": "",
        "region_code": "BE-WAL",
        "status": "current"
      },
      "geometry": {
        "type": "Point",
        "coordinates": [
          4.34835,
          50.08723
        ]
      }
    },
    {
      "type": "Feature",
      "properties": {
        "address_id": "791007",
        "box_number": "",
        "house_number": "2",
        "municipality_id": "56016",
        "municipality_name_de": "",
        "municipality_name_fr": "Chimay",
        "municipality_name_nl": "",
        "postcode": "6461",
        "postname_fr": "",
        "postname_nl": "",
        "street_id": "7720046",
        "streetname_de": "",
        "streetname_fr": "Rue de la Ferrière",
        "streetname_nl": "",
        "region_code": "BE-WAL",
        "status": "current"
      },
      "geometry": {
        "type": "Point",
        "coordinates": [
          4.3424,
          50.08675
        ]
      }
    },
    {
      "type": "Feature",
      "properties": {
        "address_id": "791008",
        "box_number": "",
        "house_number": "1A",
        "municipality_id": "56016",
        "municipality_name_de": "",
        "municipality_name_fr": "Chimay",
        "municipality_name_nl": "",
        "postcode": "6461",
        "postname_fr": "",
        "postname_nl": "",
        "street_id": "7720046",
        "streetname_de": "",
        "streetname_fr": "Rue de la Ferrière",
        "streetname_nl": "",
        "region_code": "BE-WAL",
        "status": "current"
      },
      "geometry": {
        "type": "Point",
        "coordinates": [
          4.34062,
          50.08164
        ]
      }
    },
    {
      "type": "Feature",
      "properties": {
        "address_id": "791009",
        "box_number": "",
        "house_number": "1",
        "municipality_id": "56016",
        "municipality_name_de": "",
        "municipality_name_fr": "Chimay",
        "municipality_name_nl": "",
        "postcode": "6461",
        "postname_fr": "",
        "postname_nl": "",
        "street_id": "7720046",
        "streetname_de": "",
        "streetname_fr": "Rue de la Ferrière",
        "streetname_nl": "",
        "region_code": "BE-WAL",
        "status": "current"
      },
      "geometry": {
        "type": "Point",
        "coordinates": [
          4.33791,
          50.0795
        ]
      }
    },
    {
      "type": "Feature",
      "properties": {
        "address_id": "789077",
        "box_number": "",
        "house_number": "4",
        "municipality_id": "56016",
        "municipality_name_de": "",
        "municipality_name_fr": "Chimay",
        "municipality_name_nl": "",
        "postcode": "6461",
        "postname_fr": "",
        "postname_nl": "",
        "street_id": "7719942",
        "streetname_de": "",
        "streetname_fr": "Bois de Virelles",
        "streetname_nl": "",
        "region_code": "BE-WAL",
        "status": "current"
      },
      "geometry": {
        "type": "Point",
        "coordinates": [
          4.33027,
          50.08872
        ]
      }
    }
  ]
}