{
  "type": "FeatureCollection",
  "features": [
    {
      "type": "Feature",
      "properties": {
        "address_id": "194090",
        "box_number": "",
        "house_number": "1",
        "municipality_id": "83031",
        "municipality_name_de": "",
        "municipality_name_fr": "La Roche-en-Ardenne",
        "municipality_name_nl": "",
        "postcode": "6982",
        "postname_fr": "",
        "postname_nl": "",
        "street_id": "7743745",
        "streetname_de": "",
        "streetname_fr": "Bois Saint Jean",
        "streetname_nl": "",
        "region_code": "BE-WAL",
        "status": "current"
      },
      "geometry": {
        "type": "Point",
        "coordinates": [
          5.69969,
          50.21312
        ]
      }
    }
  ]
}