{
  "type": "FeatureCollection",
  "features": [
    {
      "type": "Feature",
      "properties": {
        "address_id": "430032",
        "box_number": "",
        "house_number": "14",
        "municipality_id": "93014",
        "municipality_name_de": "",
        "municipality_name_fr": "Couvin",
        "municipality_name_nl": "",
        "postcode": "5660",
        "postname_fr": "",
        "postname_nl": "",
        "street_id": "7756816",
        "streetname_de": "",
        "streetname_fr": "Rue de la Platinerie",
        "streetname_nl": "",
        "region_code": "BE-WAL",
        "status": "current"
      },
      "geometry": {
        "type": "Point",
        "coordinates": [
          4.51967,
          50.0358
        ]
      }
    },
    {
      "type": "Feature",
      "properties": {
        "address_id": "430027",
        "box_number": "",
        "house_number": "20",
        "municipality_id": "93014",
        "municipality_name_de": "",
        "municipality_name_fr": "Couvin",
        "municipality_name_nl": "",
        "postcode": "5660",
        "postname_fr": "",
        "postname_nl": "",
        "street_id": "7756816",
        "streetname_de": "",
        "streetname_fr": "Rue de la Platinerie",
        "streetname_nl": "",
        "region_code": "BE-WAL",
        "status": "current"
      },
      "geometry": {
        "type": "Point",
        "coordinates": [
          4.52113,
          50.03571
        ]
      }
    },
    {
      "type": "Feature",
      "properties": {
        "address_id": "430030",
        "box_number": "",
        "house_number": "16",
        "municipality_id": "93014",
        "municipality_name_de": "",
        "municipality_name_fr": "Couvin",
        "municipality_name_nl": "",
        "postcode": "5660",
        "postname_fr": "",
        "postname_nl": "",
        "street_id": "7756816",
        "streetname_de": "",
        "streetname_fr": "Rue de la Platinerie",
        "streetname_nl": "",
        "region_code": "BE-WAL",
        "status": "current"
      },
      "geometry": {
        "type": "Point",
        "coordinates": [
          4.52003,
          50.03593
        ]
      }
    },
    {
      "type": "Feature",
      "properties": {
        "address_id": "430031",
        "box_number": "",
        "house_number": "15",
        "municipality_id": "93014",
        "municipality_name_de": "",
        "municipality_name_fr": "Couvin",
        "municipality_name_nl": "",
        "postcode": "5660",
        "postname_fr": "",
        "postname_nl": "",
        "street_id": "7756816",
        "streetname_de": "",
        "streetname_fr": "Rue de la Platinerie",
        "streetname_nl": "",
        "region_code": "BE-WAL",
        "status": "current"
      },
      "geometry": {
        "type": "Point",
        "coordinates": [
          4.51196,
          50.03582
        ]
      }
    },
    {
      "type": "Feature",
      "properties": {
        "address_id": "430033",
        "box_number": "",
        "house_number": "12",
        "municipality_id": "93014",
        "municipality_name_de": "",
        "municipality_name_fr": "Couvin",
        "municipality_name_nl": "",
        "postcode": "5660",
        "postname_fr": "",
        "postname_nl": "",
        "street_id": "7756816",
        "streetname_de": "",
        "streetname_fr": "Rue de la Platinerie",
        "streetname_nl": "",
        "region_code": "BE-WAL",
        "status": "current"
      },
      "geometry": {
        "type": "Point",
        "coordinates": [
          4.51934,
          50.03567
        ]
      }
    }
  ]
}