{
  "type": "FeatureCollection",
  "features": [
    {
      "type": "Feature",
      "properties": {
        "address_id": "291989",
        "box_number": "",
        "house_number": "31",
        "municipality_id": "91114",
        "municipality_name_de": "",
        "municipality_name_fr": "Rochefort",
        "municipality_name_nl": "",
        "postcode": "5580",
        "postname_fr": "",
        "postname_nl": "",
        "street_id": "7750413",
        "streetname_de": "",
        "streetname_fr": "Rue de l'Espérance",
        "streetname_nl": "",
        "region_code": "BE-WAL",
        "status": "current"
      },
      "geometry": {
        "type": "Point",
        "coordinates": [
          5.1509,
          50.17487
        ]
      }
    },
    {
      "type": "Feature",
      "properties": {
        "address_id": "291991",
        "box_number": "",
        "house_number": "17",
        "municipality_id": "91114",
        "municipality_name_de": "",
        "municipality_name_fr": "Rochefort",
        "municipality_name_nl": "",
        "postcode": "5580",
        "postname_fr": "",
        "postname_nl": "",
        "street_id": "7750413",
        "streetname_de": "",
        "streetname_fr": "Rue de l'Espérance",
        "streetname_nl": "",
        "region_code": "BE-WAL",
        "status": "current"
      },
      "geometry": {
        "type": "Point",
        "coordinates": [
          5.14673,
          50.17649
        ]
      }
    }
  ]
}