{
  "type": "FeatureCollection",
  "features": [
    {
      "type": "Feature",
      "properties": {
        "address_id": "1821764",
        "box_number": "0036",
        "house_number": "104",
        "municipality_id": "63075",
        "municipality_name_de": "",
        "municipality_name_fr": "Stoumont",
        "municipality_name_nl": "",
        "postcode": "4987",
        "postname_fr": "",
        "postname_nl": "",
        "street_id": "7738235",
        "streetname_de": "",
        "streetname_fr": "Borgoumont",
        "streetname_nl": "",
        "region_code": "BE-WAL",
        "status": "current"
      },
      "geometry": {
        "type": "Point",
        "coordinates": [
          5.85715,
          50.43183
        ]
      }
    },
    {
      "type": "Feature",
      "properties": {
        "address_id": "1821762",
        "box_number": "0316",
        "house_number": "104",
        "municipality_id": "63075",
        "municipality_name_de": "",
        "municipality_name_fr": "Stoumont",
        "municipality_name_nl": "",
        "postcode": "4987",
        "postname_fr": "",
        "postname_nl": "",
        "street_id": "7738235",
        "streetname_de": "",
        "streetname_fr": "Borgoumont",
        "streetname_nl": "",
        "region_code": "BE-WAL",
        "status": "current"
      },
      "geometry": {
        "type": "Point",
        "coordinates": [
          5.85715,
          50.43183
        ]
      }
    },
    {
      "type": "Feature",
      "properties": {
        "address_id": "1821763",
        "box_number": "0287",
        "house_number": "104",
        "municipality_id": "63075",
        "municipality_name_de": "",
        "municipality_name_fr": "Stoumont",
        "municipality_name_nl": "",
        "postcode": "4987",
        "postname_fr": "",
        "postname_nl": "",
        "street_id": "7738235",
        "streetname_de": "",
        "streetname_fr": "Borgoumont",
        "streetname_nl": "",
        "region_code": "BE-WAL",
        "status": "current"
      },
      "geometry": {
        "type": "Point",
        "coordinates": [
          5.85715,
          50.43183
        ]
      }
    },
    {
      "type": "Feature",
      "properties": {
        "address_id": "1297155",
        "box_number": "",
        "house_number": "104",
        "municipality_id": "63075",
        "municipality_name_de": "",
        "municipality_name_fr": "Stoumont",
        "municipality_name_nl": "",
        "postcode": "4987",
        "postname_fr": "",
        "postname_nl": "",
        "street_id": "7738235",
        "streetname_de": "",
        "streetname_fr": "Borgoumont",
        "streetname_nl": "",
        "region_code": "BE-WAL",
        "status": "current"
      },
      "geometry": {
        "type": "Point",
        "coordinates": [
          5.85715,
          50.43183
        ]
      }
    }
  ]
}