{
  "type": "FeatureCollection",
  "features": [
    {
      "type": "Feature",
      "properties": {
        "address_id": "1908545",
        "box_number": "",
        "house_number": "20B",
        "municipality_id": "84075",
        "municipality_name_de": "",
        "municipality_name_fr": "Wellin",
        "municipality_name_nl": "",
        "postcode": "6920",
        "postname_fr": "",
        "postname_nl": "",
        "street_id": "7746614",
        "streetname_de": "",
        "streetname_fr": "Rue Haute",
        "streetname_nl": "",
        "region_code": "BE-WAL",
        "status": "current"
      },
      "geometry": {
        "type": "Point",
        "coordinates": [
          5.06377,
          50.0623
        ]
      }
    }
  ]
}