{
  "type": "FeatureCollection",
  "features": [
    {
      "type": "Feature",
      "properties": {
        "address_id": "1300427",
        "box_number": "",
        "house_number": "4",
        "municipality_id": "63004",
        "municipality_name_de": "",
        "municipality_name_fr": "Baelen",
        "municipality_name_nl": "",
        "postcode": "4837",
        "postname_fr": "",
        "postname_nl": "",
        "street_id": "7735211",
        "streetname_de": "",
        "streetname_fr": "Hestreux",
        "streetname_nl": "",
        "region_code": "BE-WAL",
        "status": "current"
      },
      "geometry": {
        "type": "Point",
        "coordinates": [
          6.03568,
          50.57081
        ]
      }
    },
    {
      "type": "Feature",
      "properties": {
        "address_id": "1300428",
        "box_number": "",
        "house_number": "2",
        "municipality_id": "63004",
        "municipality_name_de": "",
        "municipality_name_fr": "Baelen",
        "municipality_name_nl": "",
        "postcode": "4837",
        "postname_fr": "",
        "postname_nl": "",
        "street_id": "7735211",
        "streetname_de": "",
        "streetname_fr": "Hestreux",
        "streetname_nl": "",
        "region_code": "BE-WAL",
        "status": "current"
      },
      "geometry": {
        "type": "Point",
        "coordinates": [
          6.03499,
          50.57179
        ]
      }
    }
  ]
}