{
  "type": "FeatureCollection",
  "features": [
    {
      "type": "Feature",
      "properties": {
        "address_id": "1426541",
        "box_number": "",
        "house_number": "563",
        "municipality_id": "91013",
        "municipality_name_de": "",
        "municipality_name_fr": "Beauraing",
        "municipality_name_nl": "",
        "postcode": "5570",
        "postname_fr": "",
        "postname_nl": "",
        "street_id": "7748506",
        "streetname_de": "",
        "streetname_fr": "Rue des Ardennes",
        "streetname_nl": "",
        "region_code": "BE-WAL",
        "status": "current"
      },
      "geometry": {
        "type": "Point",
        "coordinates": [
          4.88972,
          50.09155
        ]
      }
    },
    {
      "type": "Feature",
      "properties": {
        "address_id": "1856619",
        "box_number": "",
        "house_number": "565",
        "municipality_id": "91013",
        "municipality_name_de": "",
        "municipality_name_fr": "Beauraing",
        "municipality_name_nl": "",
        "postcode": "5570",
        "postname_fr": "",
        "postname_nl": "",
        "street_id": "7748506",
        "streetname_de": "",
        "streetname_fr": "Rue des Ardennes",
        "streetname_nl": "",
        "region_code": "BE-WAL",
        "status": "current"
      },
      "geometry": {
        "type": "Point",
        "coordinates": [
          4.8897,
          50.09144
        ]
      }
    }
  ]
}