{
  "type": "FeatureCollection",
  "features": [
    {
      "type": "Feature",
      "properties": {
        "address_id": "242068",
        "box_number": "",
        "house_number": "289",
        "municipality_id": "85039",
        "municipality_name_de": "",
        "municipality_name_fr": "Tintigny",
        "municipality_name_nl": "",
        "postcode": "6730",
        "postname_fr": "",
        "postname_nl": "",
        "street_id": "7747627",
        "streetname_de": "",
        "streetname_fr": "Rue de la Ferme du Fency",
        "streetname_nl": "",
        "region_code": "BE-WAL",
        "status": "current"
      },
      "geometry": {
        "type": "Point",
        "coordinates": [
          5.49851,
          49.72648
        ]
      }
    }
  ]
}