{
  "type": "FeatureCollection",
  "features": [
    {
      "type": "Feature",
      "properties": {
        "address_id": "211225",
        "box_number": "",
        "house_number": "44",
        "municipality_id": "84033",
        "municipality_name_de": "",
        "municipality_name_fr": "Léglise",
        "municipality_name_nl": "",
        "postcode": "6860",
        "postname_fr": "",
        "postname_nl": "",
        "street_id": "7745599",
        "streetname_de": "",
        "streetname_fr": "Rue Garde-de-Dieu",
        "streetname_nl": "",
        "region_code": "BE-WAL",
        "status": "current"
      },
      "geometry": {
        "type": "Point",
        "coordinates": [
          5.4701,
          49.77643
        ]
      }
    },
    {
      "type": "Feature",
      "properties": {
        "address_id": "211221",
        "box_number": "",
        "house_number": "36",
        "municipality_id": "84033",
        "municipality_name_de": "",
        "municipality_name_fr": "Léglise",
        "municipality_name_nl": "",
        "postcode": "6860",
        "postname_fr": "",
        "postname_nl": "",
        "street_id": "7745599",
        "streetname_de": "",
        "streetname_fr": "Rue Garde-de-Dieu",
        "streetname_nl": "",
        "region_code": "BE-WAL",
        "status": "current"
      },
      "geometry": {
        "type": "Point",
        "coordinates": [
          5.47111,
          49.77695
        ]
      }
    },
    {
      "type": "Feature",
      "properties": {
        "address_id": "211222",
        "box_number": "",
        "house_number": "38",
        "municipality_id": "84033",
        "municipality_name_de": "",
        "municipality_name_fr": "Léglise",
        "municipality_name_nl": "",
        "postcode": "6860",
        "postname_fr": "",
        "postname_nl": "",
        "street_id": "7745599",
        "streetname_de": "",
        "streetname_fr": "Rue Garde-de-Dieu",
        "streetname_nl": "",
        "region_code": "BE-WAL",
        "status": "current"
      },
      "geometry": {
        "type": "Point",
        "coordinates": [
          5.47089,
          49.77685
        ]
      }
    },
    {
      "type": "Feature",
      "properties": {
        "address_id": "211223",
        "box_number": "",
        "house_number": "39",
        "municipality_id": "84033",
        "municipality_name_de": "",
        "municipality_name_fr": "Léglise",
        "municipality_name_nl": "",
        "postcode": "6860",
        "postname_fr": "",
        "postname_nl": "",
        "street_id": "7745599",
        "streetname_de": "",
        "streetname_fr": "Rue Garde-de-Dieu",
        "streetname_nl": "",
        "region_code": "BE-WAL",
        "status": "current"
      },
      "geometry": {
        "type": "Point",
        "coordinates": [
          5.47099,
          49.7765
        ]
      }
    },
    {
      "type": "Feature",
      "properties": {
        "address_id": "211224",
        "box_number": "",
        "house_number": "40",
        "municipality_id": "84033",
        "municipality_name_de": "",
        "municipality_name_fr": "Léglise",
        "municipality_name_nl": "",
        "postcode": "6860",
        "postname_fr": "",
        "postname_nl": "",
        "street_id": "7745599",
        "streetname_de": "",
        "streetname_fr": "Rue Garde-de-Dieu",
        "streetname_nl": "",
        "region_code": "BE-WAL",
        "status": "current"
      },
      "geometry": {
        "type": "Point",
        "coordinates": [
          5.47062,
          49.77674
        ]
      }
    }
  ]
}