{
  "type": "FeatureCollection",
  "features": [
    {
      "type": "Feature",
      "properties": {
        "address_id": "1494898",
        "box_number": "",
        "house_number": "74",
        "municipality_id": "82005",
        "municipality_name_de": "",
        "municipality_name_fr": "Bertogne",
        "municipality_name_nl": "",
        "postcode": "6687",
        "postname_fr": "",
        "postname_nl": "",
        "street_id": "7762947",
        "streetname_de": "",
        "streetname_fr": "Rue de Rastad",
        "streetname_nl": "",
        "region_code": "BE-WAL",
        "status": "current"
      },
      "geometry": {
        "type": "Point",
        "coordinates": [
          5.70882,
          50.09297
        ]
      }
    },
    {
      "type": "Feature",
      "properties": {
        "address_id": "181601",
        "box_number": "",
        "house_number": "65",
        "municipality_id": "82005",
        "municipality_name_de": "",
        "municipality_name_fr": "Bertogne",
        "municipality_name_nl": "",
        "postcode": "6687",
        "postname_fr": "",
        "postname_nl": "",
        "street_id": "7762947",
        "streetname_de": "",
        "streetname_fr": "Rue de Rastad",
        "streetname_nl": "",
        "region_code": "BE-WAL",
        "status": "current"
      },
      "geometry": {
        "type": "Point",
        "coordinates": [
          5.70762,
          50.0924
        ]
      }
    },
    {
      "type": "Feature",
      "properties": {
        "address_id": "1486662",
        "box_number": "",
        "house_number": "11",
        "municipality_id": "82005",
        "municipality_name_de": "",
        "municipality_name_fr": "Bertogne",
        "municipality_name_nl": "",
        "postcode": "6687",
        "postname_fr": "",
        "postname_nl": "",
        "street_id": "7762946",
        "streetname_de": "",
        "streetname_fr": "Rue de Bouchay",
        "streetname_nl": "",
        "region_code": "BE-WAL",
        "status": "current"
      },
      "geometry": {
        "type": "Point",
        "coordinates": [
          5.70939,
          50.09252
        ]
      }
    },
    {
      "type": "Feature",
      "properties": {
        "address_id": "181600",
        "box_number": "",
        "house_number": "15",
        "municipality_id": "82005",
        "municipality_name_de": "",
        "municipality_name_fr": "Bertogne",
        "municipality_name_nl": "",
        "postcode": "6687",
        "postname_fr": "",
        "postname_nl": "",
        "street_id": "7762946",
        "streetname_de": "",
        "streetname_fr": "Rue de Bouchay",
        "streetname_nl": "",
        "region_code": "BE-WAL",
        "status": "current"
      },
      "geometry": {
        "type": "Point",
        "coordinates": [
          5.70984,
          50.0927
        ]
      }
    },
    {
      "type": "Feature",
      "properties": {
        "address_id": "181602",
        "box_number": "",
        "house_number": "70",
        "municipality_id": "82005",
        "municipality_name_de": "",
        "municipality_name_fr": "Bertogne",
        "municipality_name_nl": "",
        "postcode": "6687",
        "postname_fr": "",
        "postname_nl": "",
        "street_id": "7762947",
        "streetname_de": "",
        "streetname_fr": "Rue de Rastad",
        "streetname_nl": "",
        "region_code": "BE-WAL",
        "status": "current"
      },
      "geometry": {
        "type": "Point",
        "coordinates": [
          5.70846,
          50.09269
        ]
      }
    }
  ]
}