{
  "type": "FeatureCollection",
  "features": [
    {
      "type": "Feature",
      "properties": {
        "address_id": "189638",
        "box_number": "",
        "house_number": "1",
        "municipality_id": "83013",
        "municipality_name_de": "",
        "municipality_name_fr": "Erezée",
        "municipality_name_nl": "",
        "postcode": "6997",
        "postname_fr": "",
        "postname_nl": "",
        "street_id": "7743562",
        "streetname_de": "",
        "streetname_fr": "Rue du Bois de Tave",
        "streetname_nl": "",
        "region_code": "BE-WAL",
        "status": "current"
      },
      "geometry": {
        "type": "Point",
        "coordinates": [
          5.56393,
          50.24754
        ]
      }
    },
    {
      "type": "Feature",
      "properties": {
        "address_id": "192889",
        "box_number": "",
        "house_number": "1",
        "municipality_id": "83013",
        "municipality_name_de": "",
        "municipality_name_fr": "Erezée",
        "municipality_name_nl": "",
        "postcode": "6997",
        "postname_fr": "",
        "postname_nl": "",
        "street_id": "7743584",
        "streetname_de": "",
        "streetname_fr": "Rue Fond de Tave",
        "streetname_nl": "",
        "region_code": "BE-WAL",
        "status": "current"
      },
      "geometry": {
        "type": "Point",
        "coordinates": [
          5.56197,
          50.25834
        ]
      }
    }
  ]
}