{
  "type": "FeatureCollection",
  "features": [
    {
      "type": "Feature",
      "properties": {
        "address_id": "431441",
        "box_number": "",
        "house_number": "1",
        "municipality_id": "93014",
        "municipality_name_de": "",
        "municipality_name_fr": "Couvin",
        "municipality_name_nl": "",
        "postcode": "5660",
        "postname_fr": "",
        "postname_nl": "",
        "street_id": "7756708",
        "streetname_de": "",
        "streetname_fr": "Le Moulin des Bois",
        "streetname_nl": "",
        "region_code": "BE-WAL",
        "status": "current"
      },
      "geometry": {
        "type": "Point",
        "coordinates": [
          4.53385,
          50.03223
        ]
      }
    },
    {
      "type": "Feature",
      "properties": {
        "address_id": "438940",
        "box_number": "",
        "house_number": "5",
        "municipality_id": "93014",
        "municipality_name_de": "",
        "municipality_name_fr": "Couvin",
        "municipality_name_nl": "",
        "postcode": "5660",
        "postname_fr": "",
        "postname_nl": "",
        "street_id": "7756649",
        "streetname_de": "",
        "streetname_fr": "Barrage du Ry de Rome",
        "streetname_nl": "",
        "region_code": "BE-WAL",
        "status": "current"
      },
      "geometry": {
        "type": "Point",
        "coordinates": [
          4.53385,
          50.02342
        ]
      }
    },
    {
      "type": "Feature",
      "properties": {
        "address_id": "438941",
        "box_number": "",
        "house_number": "3",
        "municipality_id": "93014",
        "municipality_name_de": "",
        "municipality_name_fr": "Couvin",
        "municipality_name_nl": "",
        "postcode": "5660",
        "postname_fr": "",
        "postname_nl": "",
        "street_id": "7756649",
        "streetname_de": "",
        "streetname_fr": "Barrage du Ry de Rome",
        "streetname_nl": "",
        "region_code": "BE-WAL",
        "status": "current"
      },
      "geometry": {
        "type": "Point",
        "coordinates": [
          4.53388,
          50.02357
        ]
      }
    }
  ]
}