{
  "type": "FeatureCollection",
  "features": [
    {
      "type": "Feature",
      "properties": {
        "address_id": "229933",
        "box_number": "",
        "house_number": "33",
        "municipality_id": "84077",
        "municipality_name_de": "",
        "municipality_name_fr": "Libramont-Chevigny",
        "municipality_name_nl": "",
        "postcode": "6800",
        "postname_fr": "",
        "postname_nl": "",
        "street_id": "7746715",
        "streetname_de": "",
        "streetname_fr": "Le Serpont",
        "streetname_nl": "",
        "region_code": "BE-WAL",
        "status": "current"
      },
      "geometry": {
        "type": "Point",
        "coordinates": [
          5.3505,
          49.93757
        ]
      }
    }
  ]
}