{
  "type": "FeatureCollection",
  "features": [
    {
      "type": "Feature",
      "properties": {
        "address_id": "1492211",
        "box_number": "",
        "house_number": "3",
        "municipality_id": "82037",
        "municipality_name_de": "",
        "municipality_name_fr": "Gouvy",
        "municipality_name_nl": "",
        "postcode": "6672",
        "postname_fr": "",
        "postname_nl": "",
        "street_id": "7762713",
        "streetname_de": "",
        "streetname_fr": "Quartier des Artisans",
        "streetname_nl": "",
        "region_code": "BE-WAL",
        "status": "current"
      },
      "geometry": {
        "type": "Point",
        "coordinates": [
          6.02057,
          50.18322
        ]
      }
    },
    {
      "type": "Feature",
      "properties": {
        "address_id": "1492215",
        "box_number": "",
        "house_number": "1",
        "municipality_id": "82037",
        "municipality_name_de": "",
        "municipality_name_fr": "Gouvy",
        "municipality_name_nl": "",
        "postcode": "6672",
        "postname_fr": "",
        "postname_nl": "",
        "street_id": "7762713",
        "streetname_de": "",
        "streetname_fr": "Quartier des Artisans",
        "streetname_nl": "",
        "region_code": "BE-WAL",
        "status": "current"
      },
      "geometry": {
        "type": "Point",
        "coordinates": [
          6.02128,
          50.18236
        ]
      }
    }
  ]
}