{
  "type": "FeatureCollection",
  "features": [
    {
      "type": "Feature",
      "properties": {
        "address_id": "1496081",
        "box_number": "",
        "house_number": "1",
        "municipality_id": "91054",
        "municipality_name_de": "",
        "municipality_name_fr": "Gedinne",
        "municipality_name_nl": "",
        "postcode": "5575",
        "postname_fr": "",
        "postname_nl": "",
        "street_id": "7749422",
        "streetname_de": "",
        "streetname_fr": "Champ Rond",
        "streetname_nl": "",
        "region_code": "BE-WAL",
        "status": "current"
      },
      "geometry": {
        "type": "Point",
        "coordinates": [
          4.88121,
          50.01641
        ]
      }
    },
    {
      "type": "Feature",
      "properties": {
        "address_id": "1497019",
        "box_number": "",
        "house_number": "99",
        "municipality_id": "91054",
        "municipality_name_de": "",
        "municipality_name_fr": "Gedinne",
        "municipality_name_nl": "",
        "postcode": "5575",
        "postname_fr": "",
        "postname_nl": "",
        "street_id": "7749483",
        "streetname_de": "",
        "streetname_fr": "Rue de Bohée",
        "streetname_nl": "",
        "region_code": "BE-WAL",
        "status": "current"
      },
      "geometry": {
        "type": "Point",
        "coordinates": [
          4.88035,
          50.00965
        ]
      }
    }
  ]
}