{
  "type": "FeatureCollection",
  "features": [
    {
      "type": "Feature",
      "properties": {
        "address_id": "300707",
        "box_number": "",
        "house_number": "1",
        "municipality_id": "91072",
        "municipality_name_de": "",
        "municipality_name_fr": "Houyet",
        "municipality_name_nl": "",
        "postcode": "5560",
        "postname_fr": "",
        "postname_nl": "",
        "street_id": "7750046",
        "streetname_de": "",
        "streetname_fr": "Route du Bois de Chaleux",
        "streetname_nl": "",
        "region_code": "BE-WAL",
        "status": "current"
      },
      "geometry": {
        "type": "Point",
        "coordinates": [
          4.93626,
          50.2107
        ]
      }
    },
    {
      "type": "Feature",
      "properties": {
        "address_id": "288627",
        "box_number": "",
        "house_number": "1",
        "municipality_id": "91034",
        "municipality_name_de": "",
        "municipality_name_fr": "Dinant",
        "municipality_name_nl": "",
        "postcode": "5500",
        "postname_fr": "",
        "postname_nl": "",
        "street_id": "7749346",
        "streetname_de": "",
        "streetname_fr": "Rue du Ry de Vesse",
        "streetname_nl": "",
        "region_code": "BE-WAL",
        "status": "current"
      },
      "geometry": {
        "type": "Point",
        "coordinates": [
          4.9331,
          50.20523
        ]
      }
    },
    {
      "type": "Feature",
      "properties": {
        "address_id": "1500778",
        "box_number": "",
        "house_number": "1",
        "municipality_id": "91072",
        "municipality_name_de": "",
        "municipality_name_fr": "Houyet",
        "municipality_name_nl": "",
        "postcode": "5560",
        "postname_fr": "",
        "postname_nl": "",
        "street_id": "7750025",
        "streetname_de": "",
        "streetname_fr": "Poujoi",
        "streetname_nl": "",
        "region_code": "BE-WAL",
        "status": "current"
      },
      "geometry": {
        "type": "Point",
        "coordinates": [
          4.93318,
          50.21686
        ]
      }
    }
  ]
}