{
  "type": "FeatureCollection",
  "features": [
    {
      "type": "Feature",
      "properties": {
        "address_id": "305293",
        "box_number": "",
        "house_number": "80",
        "municipality_id": "91054",
        "municipality_name_de": "",
        "municipality_name_fr": "Gedinne",
        "municipality_name_nl": "",
        "postcode": "5575",
        "postname_fr": "",
        "postname_nl": "",
        "street_id": "7749496",
        "streetname_de": "",
        "streetname_fr": "Rue de France",
        "streetname_nl": "",
        "region_code": "BE-WAL",
        "status": "current"
      },
      "geometry": {
        "type": "Point",
        "coordinates": [
          4.91754,
          49.95049
        ]
      }
    }
  ]
}