{
  "type": "FeatureCollection",
  "features": [
    {
      "type": "Feature",
      "properties": {
        "address_id": "230900",
        "box_number": "",
        "house_number": "89",
        "municipality_id": "84075",
        "municipality_name_de": "",
        "municipality_name_fr": "Wellin",
        "municipality_name_nl": "",
        "postcode": "6922",
        "postname_fr": "",
        "postname_nl": "",
        "street_id": "7746586",
        "streetname_de": "",
        "streetname_fr": "Rue de Libin",
        "streetname_nl": "",
        "region_code": "BE-WAL",
        "status": "current"
      },
      "geometry": {
        "type": "Point",
        "coordinates": [
          5.13773,
          50.06334
        ]
      }
    },
    {
      "type": "Feature",
      "properties": {
        "address_id": "230902",
        "box_number": "",
        "house_number": "90",
        "municipality_id": "84075",
        "municipality_name_de": "",
        "municipality_name_fr": "Wellin",
        "municipality_name_nl": "",
        "postcode": "6922",
        "postname_fr": "",
        "postname_nl": "",
        "street_id": "7746586",
        "streetname_de": "",
        "streetname_fr": "Rue de Libin",
        "streetname_nl": "",
        "region_code": "BE-WAL",
        "status": "current"
      },
      "geometry": {
        "type": "Point",
        "coordinates": [
          5.13826,
          50.0606
        ]
      }
    },
    {
      "type": "Feature",
      "properties": {
        "address_id": "230903",
        "box_number": "",
        "house_number": "91",
        "municipality_id": "84075",
        "municipality_name_de": "",
        "municipality_name_fr": "Wellin",
        "municipality_name_nl": "",
        "postcode": "6922",
        "postname_fr": "",
        "postname_nl": "",
        "street_id": "7746586",
        "streetname_de": "",
        "streetname_fr": "Rue de Libin",
        "streetname_nl": "",
        "region_code": "BE-WAL",
        "status": "current"
      },
      "geometry": {
        "type": "Point",
        "coordinates": [
          5.14022,
          50.0603
        ]
      }
    },
    {
      "type": "Feature",
      "properties": {
        "address_id": "231323",
        "box_number": "",
        "house_number": "87",
        "municipality_id": "84075",
        "municipality_name_de": "",
        "municipality_name_fr": "Wellin",
        "municipality_name_nl": "",
        "postcode": "6922",
        "postname_fr": "",
        "postname_nl": "",
        "street_id": "7746562",
        "streetname_de": "",
        "streetname_fr": "Route Pierre-Napoléon Bonaparte",
        "streetname_nl": "",
        "region_code": "BE-WAL",
        "status": "current"
      },
      "geometry": {
        "type": "Point",
        "coordinates": [
          5.13701,
          50.0619
        ]
      }
    },
    {
      "type": "Feature",
      "properties": {
        "address_id": "231324",
        "box_number": "",
        "house_number": "88",
        "municipality_id": "84075",
        "municipality_name_de": "",
        "municipality_name_fr": "Wellin",
        "municipality_name_nl": "",
        "postcode": "6922",
        "postname_fr": "",
        "postname_nl": "",
        "street_id": "7746562",
        "streetname_de": "",
        "streetname_fr": "Route Pierre-Napoléon Bonaparte",
        "streetname_nl": "",
        "region_code": "BE-WAL",
        "status": "current"
      },
      "geometry": {
        "type": "Point",
        "coordinates": [
          5.13724,
          50.06086
        ]
      }
    }
  ]
}