{
  "type": "FeatureCollection",
  "features": [
    {
      "type": "Feature",
      "properties": {
        "address_id": "146702",
        "box_number": "",
        "house_number": "1",
        "municipality_id": "81003",
        "municipality_name_de": "",
        "municipality_name_fr": "Attert",
        "municipality_name_nl": "",
        "postcode": "6717",
        "postname_fr": "",
        "postname_nl": "",
        "street_id": "7741799",
        "streetname_de": "",
        "streetname_fr": "Härebësch",
        "streetname_nl": "",
        "region_code": "BE-WAL",
        "status": "current"
      },
      "geometry": {
        "type": "Point",
        "coordinates": [
          5.73553,
          49.76462
        ]
      }
    },
    {
      "type": "Feature",
      "properties": {
        "address_id": "146703",
        "box_number": "",
        "house_number": "110",
        "municipality_id": "81003",
        "municipality_name_de": "",
        "municipality_name_fr": "Attert",
        "municipality_name_nl": "",
        "postcode": "6717",
        "postname_fr": "",
        "postname_nl": "",
        "street_id": "7741799",
        "streetname_de": "",
        "streetname_fr": "Härebësch",
        "streetname_nl": "",
        "region_code": "BE-WAL",
        "status": "current"
      },
      "geometry": {
        "type": "Point",
        "coordinates": [
          5.74276,
          49.75419
        ]
      }
    },
    {
      "type": "Feature",
      "properties": {
        "address_id": "146704",
        "box_number": "",
        "house_number": "1",
        "municipality_id": "81003",
        "municipality_name_de": "",
        "municipality_name_fr": "Attert",
        "municipality_name_nl": "",
        "postcode": "6717",
        "postname_fr": "",
        "postname_nl": "",
        "street_id": "7741800",
        "streetname_de": "",
        "streetname_fr": "Heibësch",
        "streetname_nl": "",
        "region_code": "BE-WAL",
        "status": "current"
      },
      "geometry": {
        "type": "Point",
        "coordinates": [
          5.73865,
          49.75922
        ]
      }
    }
  ]
}