{
  "type": "FeatureCollection",
  "features": [
    {
      "type": "Feature",
      "properties": {
        "address_id": "1876221",
        "box_number": "",
        "house_number": "97",
        "municipality_id": "91143",
        "municipality_name_de": "",
        "municipality_name_fr": "Vresse-sur-Semois",
        "municipality_name_nl": "",
        "postcode": "5550",
        "postname_fr": "",
        "postname_nl": "",
        "street_id": "7751282",
        "streetname_de": "",
        "streetname_fr": "L'Espérance",
        "streetname_nl": "",
        "region_code": "BE-WAL",
        "status": "current"
      },
      "geometry": {
        "type": "Point",
        "coordinates": [
          4.86552,
          49.79355
        ]
      }
    }
  ]
}