{
  "type": "FeatureCollection",
  "features": [
    {
      "type": "Feature",
      "properties": {
        "address_id": "250563",
        "box_number": "",
        "house_number": "8",
        "municipality_id": "85011",
        "municipality_name_de": "",
        "municipality_name_fr": "Florenville",
        "municipality_name_nl": "",
        "postcode": "6820",
        "postname_fr": "",
        "postname_nl": "",
        "street_id": "7747307",
        "streetname_de": "",
        "streetname_fr": "Rue Mé d'Cholet",
        "streetname_nl": "",
        "region_code": "BE-WAL",
        "status": "current"
      },
      "geometry": {
        "type": "Point",
        "coordinates": [
          5.22916,
          49.71599
        ]
      }
    },
    {
      "type": "Feature",
      "properties": {
        "address_id": "1968274",
        "box_number": "",
        "house_number": "14",
        "municipality_id": "85011",
        "municipality_name_de": "",
        "municipality_name_fr": "Florenville",
        "municipality_name_nl": "",
        "postcode": "6820",
        "postname_fr": "",
        "postname_nl": "",
        "street_id": "7747266",
        "streetname_de": "",
        "streetname_fr": "Rue des Quatre Arbres",
        "streetname_nl": "",
        "region_code": "BE-WAL",
        "status": "current"
      },
      "geometry": {
        "type": "Point",
        "coordinates": [
          5.2291,
          49.71254
        ]
      }
    }
  ]
}