{
  "type": "FeatureCollection",
  "features": [
    {
      "type": "Feature",
      "properties": {
        "address_id": "265139",
        "box_number": "",
        "house_number": "151A",
        "municipality_id": "91013",
        "municipality_name_de": "",
        "municipality_name_fr": "Beauraing",
        "municipality_name_nl": "",
        "postcode": "5570",
        "postname_fr": "",
        "postname_nl": "",
        "street_id": "7748447",
        "streetname_de": "",
        "streetname_fr": "Rue de France",
        "streetname_nl": "",
        "region_code": "BE-WAL",
        "status": "current"
      },
      "geometry": {
        "type": "Point",
        "coordinates": [
          4.84987,
          50.10108
        ]
      }
    },
    {
      "type": "Feature",
      "properties": {
        "address_id": "265140",
        "box_number": "",
        "house_number": "151",
        "municipality_id": "91013",
        "municipality_name_de": "",
        "municipality_name_fr": "Beauraing",
        "municipality_name_nl": "",
        "postcode": "5570",
        "postname_fr": "",
        "postname_nl": "",
        "street_id": "7748447",
        "streetname_de": "",
        "streetname_fr": "Rue de France",
        "streetname_nl": "",
        "region_code": "BE-WAL",
        "status": "current"
      },
      "geometry": {
        "type": "Point",
        "coordinates": [
          4.85016,
          50.10103
        ]
      }
    },
    {
      "type": "Feature",
      "properties": {
        "address_id": "1497163",
        "box_number": "",
        "house_number": "142",
        "municipality_id": "91013",
        "municipality_name_de": "",
        "municipality_name_fr": "Beauraing",
        "municipality_name_nl": "",
        "postcode": "5570",
        "postname_fr": "",
        "postname_nl": "",
        "street_id": "7748447",
        "streetname_de": "",
        "streetname_fr": "Rue de France",
        "streetname_nl": "",
        "region_code": "BE-WAL",
        "status": "current"
      },
      "geometry": {
        "type": "Point",
        "coordinates": [
          4.85338,
          50.10073
        ]
      }
    }
  ]
}