{
  "type": "FeatureCollection",
  "features": [
    {
      "type": "Feature",
      "properties": {
        "address_id": "298642",
        "box_number": "",
        "house_number": "1",
        "municipality_id": "91072",
        "municipality_name_de": "",
        "municipality_name_fr": "Houyet",
        "municipality_name_nl": "",
        "postcode": "5561",
        "postname_fr": "",
        "postname_nl": "",
        "street_id": "7749972",
        "streetname_de": "",
        "streetname_fr": "Bry",
        "streetname_nl": "",
        "region_code": "BE-WAL",
        "status": "current"
      },
      "geometry": {
        "type": "Point",
        "coordinates": [
          5.03259,
          50.24439
        ]
      }
    },
    {
      "type": "Feature",
      "properties": {
        "address_id": "298641",
        "box_number": "",
        "house_number": "2",
        "municipality_id": "91072",
        "municipality_name_de": "",
        "municipality_name_fr": "Houyet",
        "municipality_name_nl": "",
        "postcode": "5561",
        "postname_fr": "",
        "postname_nl": "",
        "street_id": "7749972",
        "streetname_de": "",
        "streetname_fr": "Bry",
        "streetname_nl": "",
        "region_code": "BE-WAL",
        "status": "current"
      },
      "geometry": {
        "type": "Point",
        "coordinates": [
          5.03276,
          50.24434
        ]
      }
    }
  ]
}