{
  "type": "FeatureCollection",
  "features": [
    {
      "type": "Feature",
      "properties": {
        "address_id": "460967",
        "box_number": "",
        "house_number": "6",
        "municipality_id": "93056",
        "municipality_name_de": "",
        "municipality_name_fr": "Philippeville",
        "municipality_name_nl": "",
        "postcode": "5600",
        "postname_fr": "",
        "postname_nl": "",
        "street_id": "7757414",
        "streetname_de": "",
        "streetname_fr": "Champ-Bouval",
        "streetname_nl": "",
        "region_code": "BE-WAL",
        "status": "current"
      },
      "geometry": {
        "type": "Point",
        "coordinates": [
          4.62035,
          50.20819
        ]
      }
    },
    {
      "type": "Feature",
      "properties": {
        "address_id": "460968",
        "box_number": "",
        "house_number": "5",
        "municipality_id": "93056",
        "municipality_name_de": "",
        "municipality_name_fr": "Philippeville",
        "municipality_name_nl": "",
        "postcode": "5600",
        "postname_fr": "",
        "postname_nl": "",
        "street_id": "7757414",
        "streetname_de": "",
        "streetname_fr": "Champ-Bouval",
        "streetname_nl": "",
        "region_code": "BE-WAL",
        "status": "current"
      },
      "geometry": {
        "type": "Point",
        "coordinates": [
          4.62012,
          50.2058
        ]
      }
    }
  ]
}