{
  "type": "FeatureCollection",
  "features": [
    {
      "type": "Feature",
      "properties": {
        "address_id": "255785",
        "box_number": "",
        "house_number": "16",
        "municipality_id": "84059",
        "municipality_name_de": "",
        "municipality_name_fr": "Saint-Hubert",
        "municipality_name_nl": "",
        "postcode": "6870",
        "postname_fr": "",
        "postname_nl": "",
        "street_id": "7746372",
        "streetname_de": "",
        "streetname_fr": "Rue du Moulin",
        "streetname_nl": "",
        "region_code": "BE-WAL",
        "status": "current"
      },
      "geometry": {
        "type": "Point",
        "coordinates": [
          5.2513,
          50.05326
        ]
      }
    }
  ]
}