{
  "type": "FeatureCollection",
  "features": [
    {
      "type": "Feature",
      "properties": {
        "address_id": "304016",
        "box_number": "",
        "house_number": "1",
        "municipality_id": "91103",
        "municipality_name_de": "",
        "municipality_name_fr": "Onhaye",
        "municipality_name_nl": "",
        "postcode": "5523",
        "postname_fr": "",
        "postname_nl": "",
        "street_id": "7750177",
        "streetname_de": "",
        "streetname_fr": "Frémiveaux",
        "streetname_nl": "",
        "region_code": "BE-WAL",
        "status": "current"
      },
      "geometry": {
        "type": "Point",
        "coordinates": [
          4.80056,
          50.25329
        ]
      }
    }
  ]
}