{
  "type": "FeatureCollection",
  "features": [
    {
      "type": "Feature",
      "properties": {
        "address_id": "257978",
        "box_number": "",
        "house_number": "100",
        "municipality_id": "91013",
        "municipality_name_de": "",
        "municipality_name_fr": "Beauraing",
        "municipality_name_nl": "",
        "postcode": "5570",
        "postname_fr": "",
        "postname_nl": "",
        "street_id": "7748438",
        "streetname_de": "",
        "streetname_fr": "Rue de Cumont",
        "streetname_nl": "",
        "region_code": "BE-WAL",
        "status": "current"
      },
      "geometry": {
        "type": "Point",
        "coordinates": [
          4.96131,
          50.07676
        ]
      }
    }
  ]
}