{
  "type": "FeatureCollection",
  "features": [
    {
      "type": "Feature",
      "properties": {
        "address_id": "784804",
        "box_number": "",
        "house_number": "84",
        "municipality_id": "58002",
        "municipality_name_de": "",
        "municipality_name_fr": "Binche",
        "municipality_name_nl": "",
        "postcode": "7130",
        "postname_fr": "",
        "postname_nl": "",
        "street_id": "7719706",
        "streetname_de": "",
        "streetname_fr": "Rue Delcampe",
        "streetname_nl": "",
        "region_code": "BE-WAL",
        "status": "current"
      },
      "geometry": {
        "type": "Point",
        "coordinates": [
          4.11113,
          50.4372
        ]
      }
    },
    {
      "type": "Feature",
      "properties": {
        "address_id": "784805",
        "box_number": "",
        "house_number": "82",
        "municipality_id": "58002",
        "municipality_name_de": "",
        "municipality_name_fr": "Binche",
        "municipality_name_nl": "",
        "postcode": "7130",
        "postname_fr": "",
        "postname_nl": "",
        "street_id": "7719706",
        "streetname_de": "",
        "streetname_fr": "Rue Delcampe",
        "streetname_nl": "",
        "region_code": "BE-WAL",
        "status": "current"
      },
      "geometry": {
        "type": "Point",
        "coordinates": [
          4.11088,
          50.43721
        ]
      }
    },
    {
      "type": "Feature",
      "properties": {
        "address_id": "784806",
        "box_number": "",
        "house_number": "80",
        "municipality_id": "58002",
        "municipality_name_de": "",
        "municipality_name_fr": "Binche",
        "municipality_name_nl": "",
        "postcode": "7130",
        "postname_fr": "",
        "postname_nl": "",
        "street_id": "7719706",
        "streetname_de": "",
        "streetname_fr": "Rue Delcampe",
        "streetname_nl": "",
        "region_code": "BE-WAL",
        "status": "current"
      },
      "geometry": {
        "type": "Point",
        "coordinates": [
          4.11084,
          50.43718
        ]
      }
    }
  ]
}