{
  "type": "FeatureCollection",
  "features": [
    {
      "type": "Feature",
      "properties": {
        "address_id": "299824",
        "box_number": "",
        "house_number": "3",
        "municipality_id": "91072",
        "municipality_name_de": "",
        "municipality_name_fr": "Houyet",
        "municipality_name_nl": "",
        "postcode": "5560",
        "postname_fr": "",
        "postname_nl": "",
        "street_id": "7749991",
        "streetname_de": "",
        "streetname_fr": "Courvite",
        "streetname_nl": "",
        "region_code": "BE-WAL",
        "status": "current"
      },
      "geometry": {
        "type": "Point",
        "coordinates": [
          4.87047,
          50.1739
        ]
      }
    },
    {
      "type": "Feature",
      "properties": {
        "address_id": "299825",
        "box_number": "",
        "house_number": "1A",
        "municipality_id": "91072",
        "municipality_name_de": "",
        "municipality_name_fr": "Houyet",
        "municipality_name_nl": "",
        "postcode": "5560",
        "postname_fr": "",
        "postname_nl": "",
        "street_id": "7749991",
        "streetname_de": "",
        "streetname_fr": "Courvite",
        "streetname_nl": "",
        "region_code": "BE-WAL",
        "status": "current"
      },
      "geometry": {
        "type": "Point",
        "coordinates": [
          4.86974,
          50.1744
        ]
      }
    },
    {
      "type": "Feature",
      "properties": {
        "address_id": "299826",
        "box_number": "",
        "house_number": "1",
        "municipality_id": "91072",
        "municipality_name_de": "",
        "municipality_name_fr": "Houyet",
        "municipality_name_nl": "",
        "postcode": "5560",
        "postname_fr": "",
        "postname_nl": "",
        "street_id": "7749991",
        "streetname_de": "",
        "streetname_fr": "Courvite",
        "streetname_nl": "",
        "region_code": "BE-WAL",
        "status": "current"
      },
      "geometry": {
        "type": "Point",
        "coordinates": [
          4.86979,
          50.17438
        ]
      }
    },
    {
      "type": "Feature",
      "properties": {
        "address_id": "301250",
        "box_number": "",
        "house_number": "9",
        "municipality_id": "91072",
        "municipality_name_de": "",
        "municipality_name_fr": "Houyet",
        "municipality_name_nl": "",
        "postcode": "5560",
        "postname_fr": "",
        "postname_nl": "",
        "street_id": "7750051",
        "streetname_de": "",
        "streetname_fr": "Rue de Bennui",
        "streetname_nl": "",
        "region_code": "BE-WAL",
        "status": "current"
      },
      "geometry": {
        "type": "Point",
        "coordinates": [
          4.87666,
          50.16915
        ]
      }
    },
    {
      "type": "Feature",
      "properties": {
        "address_id": "301251",
        "box_number": "",
        "house_number": "7",
        "municipality_id": "91072",
        "municipality_name_de": "",
        "municipality_name_fr": "Houyet",
        "municipality_name_nl": "",
        "postcode": "5560",
        "postname_fr": "",
        "postname_nl": "",
        "street_id": "7750051",
        "streetname_de": "",
        "streetname_fr": "Rue de Bennui",
        "streetname_nl": "",
        "region_code": "BE-WAL",
        "status": "current"
      },
      "geometry": {
        "type": "Point",
        "coordinates": [
          4.8777,
          50.16943
        ]
      }
    },
    {
      "type": "Feature",
      "properties": {
        "address_id": "301254",
        "box_number": "",
        "house_number": "2",
        "municipality_id": "91072",
        "municipality_name_de": "",
        "municipality_name_fr": "Houyet",
        "municipality_name_nl": "",
        "postcode": "5560",
        "postname_fr": "",
        "postname_nl": "",
        "street_id": "7750051",
        "streetname_de": "",
        "streetname_fr": "Rue de Bennui",
        "streetname_nl": "",
        "region_code": "BE-WAL",
        "status": "current"
      },
      "geometry": {
        "type": "Point",
        "coordinates": [
          4.87733,
          50.1699
        ]
      }
    },
    {
      "type": "Feature",
      "properties": {
        "address_id": "301255",
        "box_number": "",
        "house_number": "11",
        "municipality_id": "91072",
        "municipality_name_de": "",
        "municipality_name_fr": "Houyet",
        "municipality_name_nl": "",
        "postcode": "5560",
        "postname_fr": "",
        "postname_nl": "",
        "street_id": "7750051",
        "streetname_de": "",
        "streetname_fr": "Rue de Bennui",
        "streetname_nl": "",
        "region_code": "BE-WAL",
        "status": "current"
      },
      "geometry": {
        "type": "Point",
        "coordinates": [
          4.87594,
          50.16915
        ]
      }
    }
  ]
}