{
  "type": "FeatureCollection",
  "features": [
    {
      "type": "Feature",
      "properties": {
        "address_id": "281985",
        "box_number": "",
        "house_number": "8",
        "municipality_id": "91030",
        "municipality_name_de": "",
        "municipality_name_fr": "Ciney",
        "municipality_name_nl": "",
        "postcode": "5590",
        "postname_fr": "",
        "postname_nl": "",
        "street_id": "7748896",
        "streetname_de": "",
        "streetname_fr": "Rue de Spontin",
        "streetname_nl": "",
        "region_code": "BE-WAL",
        "status": "current"
      },
      "geometry": {
        "type": "Point",
        "coordinates": [
          5.02338,
          50.31701
        ]
      }
    },
    {
      "type": "Feature",
      "properties": {
        "address_id": "281987",
        "box_number": "",
        "house_number": "4",
        "municipality_id": "91030",
        "municipality_name_de": "",
        "municipality_name_fr": "Ciney",
        "municipality_name_nl": "",
        "postcode": "5590",
        "postname_fr": "",
        "postname_nl": "",
        "street_id": "7748896",
        "streetname_de": "",
        "streetname_fr": "Rue de Spontin",
        "streetname_nl": "",
        "region_code": "BE-WAL",
        "status": "current"
      },
      "geometry": {
        "type": "Point",
        "coordinates": [
          5.02304,
          50.3169
        ]
      }
    },
    {
      "type": "Feature",
      "properties": {
        "address_id": "281988",
        "box_number": "",
        "house_number": "2",
        "municipality_id": "91030",
        "municipality_name_de": "",
        "municipality_name_fr": "Ciney",
        "municipality_name_nl": "",
        "postcode": "5590",
        "postname_fr": "",
        "postname_nl": "",
        "street_id": "7748896",
        "streetname_de": "",
        "streetname_fr": "Rue de Spontin",
        "streetname_nl": "",
        "region_code": "BE-WAL",
        "status": "current"
      },
      "geometry": {
        "type": "Point",
        "coordinates": [
          5.02297,
          50.31685
        ]
      }
    },
    {
      "type": "Feature",
      "properties": {
        "address_id": "281991",
        "box_number": "",
        "house_number": "1",
        "municipality_id": "91030",
        "municipality_name_de": "",
        "municipality_name_fr": "Ciney",
        "municipality_name_nl": "",
        "postcode": "5590",
        "postname_fr": "",
        "postname_nl": "",
        "street_id": "7748896",
        "streetname_de": "",
        "streetname_fr": "Rue de Spontin",
        "streetname_nl": "",
        "region_code": "BE-WAL",
        "status": "current"
      },
      "geometry": {
        "type": "Point",
        "coordinates": [
          5.024,
          50.31592
        ]
      }
    },
    {
      "type": "Feature",
      "properties": {
        "address_id": "281986",
        "box_number": "",
        "house_number": "6",
        "municipality_id": "91030",
        "municipality_name_de": "",
        "municipality_name_fr": "Ciney",
        "municipality_name_nl": "",
        "postcode": "5590",
        "postname_fr": "",
        "postname_nl": "",
        "street_id": "7748896",
        "streetname_de": "",
        "streetname_fr": "Rue de Spontin",
        "streetname_nl": "",
        "region_code": "BE-WAL",
        "status": "current"
      },
      "geometry": {
        "type": "Point",
        "coordinates": [
          5.02328,
          50.31692
        ]
      }
    }
  ]
}