{
  "type": "FeatureCollection",
  "features": [
    {
      "type": "Feature",
      "properties": {
        "address_id": "1503691",
        "box_number": "",
        "house_number": "11A",
        "municipality_id": "83013",
        "municipality_name_de": "",
        "municipality_name_fr": "Erezée",
        "municipality_name_nl": "",
        "postcode": "6997",
        "postname_fr": "",
        "postname_nl": "",
        "street_id": "7743578",
        "streetname_de": "",
        "streetname_fr": "Rue du Stockay",
        "streetname_nl": "",
        "region_code": "BE-WAL",
        "status": "current"
      },
      "geometry": {
        "type": "Point",
        "coordinates": [
          5.57418,
          50.31409
        ]
      }
    },
    {
      "type": "Feature",
      "properties": {
        "address_id": "192840",
        "box_number": "",
        "house_number": "12",
        "municipality_id": "83013",
        "municipality_name_de": "",
        "municipality_name_fr": "Erezée",
        "municipality_name_nl": "",
        "postcode": "6997",
        "postname_fr": "",
        "postname_nl": "",
        "street_id": "7743578",
        "streetname_de": "",
        "streetname_fr": "Rue du Stockay",
        "streetname_nl": "",
        "region_code": "BE-WAL",
        "status": "current"
      },
      "geometry": {
        "type": "Point",
        "coordinates": [
          5.57714,
          50.31366
        ]
      }
    },
    {
      "type": "Feature",
      "properties": {
        "address_id": "192841",
        "box_number": "",
        "house_number": "13",
        "municipality_id": "83013",
        "municipality_name_de": "",
        "municipality_name_fr": "Erezée",
        "municipality_name_nl": "",
        "postcode": "6997",
        "postname_fr": "",
        "postname_nl": "",
        "street_id": "7743578",
        "streetname_de": "",
        "streetname_fr": "Rue du Stockay",
        "streetname_nl": "",
        "region_code": "BE-WAL",
        "status": "current"
      },
      "geometry": {
        "type": "Point",
        "coordinates": [
          5.57858,
          50.31176
        ]
      }
    },
    {
      "type": "Feature",
      "properties": {
        "address_id": "196184",
        "box_number": "",
        "house_number": "17",
        "municipality_id": "83013",
        "municipality_name_de": "",
        "municipality_name_fr": "Erezée",
        "municipality_name_nl": "",
        "postcode": "6997",
        "postname_fr": "",
        "postname_nl": "",
        "street_id": "7743597",
        "streetname_de": "",
        "streetname_fr": "Rue Oster",
        "streetname_nl": "",
        "region_code": "BE-WAL",
        "status": "current"
      },
      "geometry": {
        "type": "Point",
        "coordinates": [
          5.55945,
          50.30916
        ]
      }
    }
  ]
}