{
  "type": "FeatureCollection",
  "features": [
    {
      "type": "Feature",
      "properties": {
        "address_id": "1490865",
        "box_number": "",
        "house_number": "10",
        "municipality_id": "82005",
        "municipality_name_de": "",
        "municipality_name_fr": "Bertogne",
        "municipality_name_nl": "",
        "postcode": "6687",
        "postname_fr": "",
        "postname_nl": "",
        "street_id": "7763117",
        "streetname_de": "",
        "streetname_fr": "Route Nationale 4",
        "streetname_nl": "",
        "region_code": "BE-WAL",
        "status": "current"
      },
      "geometry": {
        "type": "Point",
        "coordinates": [
          5.62398,
          50.01944
        ]
      }
    }
  ]
}