{
  "type": "FeatureCollection",
  "features": [
    {
      "type": "Feature",
      "properties": {
        "address_id": "171986",
        "box_number": "",
        "house_number": "690",
        "municipality_id": "82003",
        "municipality_name_de": "",
        "municipality_name_fr": "Bastogne",
        "municipality_name_nl": "",
        "postcode": "6600",
        "postname_fr": "",
        "postname_nl": "",
        "street_id": "7742499",
        "streetname_de": "",
        "streetname_fr": "Wicourt",
        "streetname_nl": "",
        "region_code": "BE-WAL",
        "status": "current"
      },
      "geometry": {
        "type": "Point",
        "coordinates": [
          5.78703,
          50.1068
        ]
      }
    },
    {
      "type": "Feature",
      "properties": {
        "address_id": "180220",
        "box_number": "",
        "house_number": "65",
        "municipality_id": "82014",
        "municipality_name_de": "",
        "municipality_name_fr": "Houffalize",
        "municipality_name_nl": "",
        "postcode": "6660",
        "postname_fr": "",
        "postname_nl": "",
        "street_id": "7742714",
        "streetname_de": "",
        "streetname_fr": "Rue de Bastogne",
        "streetname_nl": "",
        "region_code": "BE-WAL",
        "status": "current"
      },
      "geometry": {
        "type": "Point",
        "coordinates": [
          5.79119,
          50.11539
        ]
      }
    },
    {
      "type": "Feature",
      "properties": {
        "address_id": "180221",
        "box_number": "",
        "house_number": "66",
        "municipality_id": "82014",
        "municipality_name_de": "",
        "municipality_name_fr": "Houffalize",
        "municipality_name_nl": "",
        "postcode": "6660",
        "postname_fr": "",
        "postname_nl": "",
        "street_id": "7742714",
        "streetname_de": "",
        "streetname_fr": "Rue de Bastogne",
        "streetname_nl": "",
        "region_code": "BE-WAL",
        "status": "current"
      },
      "geometry": {
        "type": "Point",
        "coordinates": [
          5.79004,
          50.11502
        ]
      }
    }
  ]
}