{
  "type": "FeatureCollection",
  "features": [
    {
      "type": "Feature",
      "properties": {
        "address_id": "166867",
        "box_number": "",
        "house_number": "10A",
        "municipality_id": "82003",
        "municipality_name_de": "",
        "municipality_name_fr": "Bastogne",
        "municipality_name_nl": "",
        "postcode": "6600",
        "postname_fr": "",
        "postname_nl": "",
        "street_id": "7742369",
        "streetname_de": "",
        "streetname_fr": "Lutremange",
        "streetname_nl": "",
        "region_code": "BE-WAL",
        "status": "current"
      },
      "geometry": {
        "type": "Point",
        "coordinates": [
          5.7568,
          49.94476
        ]
      }
    },
    {
      "type": "Feature",
      "properties": {
        "address_id": "166868",
        "box_number": "",
        "house_number": "10B",
        "municipality_id": "82003",
        "municipality_name_de": "",
        "municipality_name_fr": "Bastogne",
        "municipality_name_nl": "",
        "postcode": "6600",
        "postname_fr": "",
        "postname_nl": "",
        "street_id": "7742369",
        "streetname_de": "",
        "streetname_fr": "Lutremange",
        "streetname_nl": "",
        "region_code": "BE-WAL",
        "status": "current"
      },
      "geometry": {
        "type": "Point",
        "coordinates": [
          5.7566,
          49.94495
        ]
      }
    },
    {
      "type": "Feature",
      "properties": {
        "address_id": "187754",
        "box_number": "",
        "house_number": "2",
        "municipality_id": "82003",
        "municipality_name_de": "",
        "municipality_name_fr": "Bastogne",
        "municipality_name_nl": "",
        "postcode": "6600",
        "postname_fr": "",
        "postname_nl": "",
        "street_id": "7742496",
        "streetname_de": "",
        "streetname_fr": "Villers-la-Bonne-Eau",
        "streetname_nl": "",
        "region_code": "BE-WAL",
        "status": "current"
      },
      "geometry": {
        "type": "Point",
        "coordinates": [
          5.74349,
          49.93978
        ]
      }
    }
  ]
}