{
  "type": "FeatureCollection",
  "features": [
    {
      "type": "Feature",
      "properties": {
        "address_id": "1416234",
        "box_number": "",
        "house_number": "33",
        "municipality_id": "91034",
        "municipality_name_de": "",
        "municipality_name_fr": "Dinant",
        "municipality_name_nl": "",
        "postcode": "5500",
        "postname_fr": "",
        "postname_nl": "",
        "street_id": "7749312",
        "streetname_de": "",
        "streetname_fr": "Rue du Bois de Bailleu",
        "streetname_nl": "",
        "region_code": "BE-WAL",
        "status": "current"
      },
      "geometry": {
        "type": "Point",
        "coordinates": [
          4.90049,
          50.20689
        ]
      }
    },
    {
      "type": "Feature",
      "properties": {
        "address_id": "288801",
        "box_number": "",
        "house_number": "1",
        "municipality_id": "91034",
        "municipality_name_de": "",
        "municipality_name_fr": "Dinant",
        "municipality_name_nl": "",
        "postcode": "5500",
        "postname_fr": "",
        "postname_nl": "",
        "street_id": "7749310",
        "streetname_de": "",
        "streetname_fr": "Rue du Barrage",
        "streetname_nl": "",
        "region_code": "BE-WAL",
        "status": "current"
      },
      "geometry": {
        "type": "Point",
        "coordinates": [
          4.92131,
          50.21904
        ]
      }
    }
  ]
}