{
  "type": "FeatureCollection",
  "features": [
    {
      "type": "Feature",
      "properties": {
        "address_id": "805972",
        "box_number": "",
        "house_number": "10",
        "municipality_id": "56022",
        "municipality_name_de": "",
        "municipality_name_fr": "Erquelinnes",
        "municipality_name_nl": "",
        "postcode": "6560",
        "postname_fr": "",
        "postname_nl": "",
        "street_id": "7720365",
        "streetname_de": "",
        "streetname_fr": "Rue Trieu Colinot",
        "streetname_nl": "",
        "region_code": "BE-WAL",
        "status": "current"
      },
      "geometry": {
        "type": "Point",
        "coordinates": [
          4.14136,
          50.28562
        ]
      }
    },
    {
      "type": "Feature",
      "properties": {
        "address_id": "806980",
        "box_number": "",
        "house_number": "25",
        "municipality_id": "56022",
        "municipality_name_de": "",
        "municipality_name_fr": "Erquelinnes",
        "municipality_name_nl": "",
        "postcode": "6560",
        "postname_fr": "",
        "postname_nl": "",
        "street_id": "7720365",
        "streetname_de": "",
        "streetname_fr": "Rue Trieu Colinot",
        "streetname_nl": "",
        "region_code": "BE-WAL",
        "status": "current"
      },
      "geometry": {
        "type": "Point",
        "coordinates": [
          4.13386,
          50.28128
        ]
      }
    },
    {
      "type": "Feature",
      "properties": {
        "address_id": "806988",
        "box_number": "",
        "house_number": "12",
        "municipality_id": "56022",
        "municipality_name_de": "",
        "municipality_name_fr": "Erquelinnes",
        "municipality_name_nl": "",
        "postcode": "6560",
        "postname_fr": "",
        "postname_nl": "",
        "street_id": "7720365",
        "streetname_de": "",
        "streetname_fr": "Rue Trieu Colinot",
        "streetname_nl": "",
        "region_code": "BE-WAL",
        "status": "current"
      },
      "geometry": {
        "type": "Point",
        "coordinates": [
          4.14147,
          50.28508
        ]
      }
    },
    {
      "type": "Feature",
      "properties": {
        "address_id": "803870",
        "box_number": "",
        "house_number": "8",
        "municipality_id": "56022",
        "municipality_name_de": "",
        "municipality_name_fr": "Erquelinnes",
        "municipality_name_nl": "",
        "postcode": "6560",
        "postname_fr": "",
        "postname_nl": "",
        "street_id": "7720365",
        "streetname_de": "",
        "streetname_fr": "Rue Trieu Colinot",
        "streetname_nl": "",
        "region_code": "BE-WAL",
        "status": "current"
      },
      "geometry": {
        "type": "Point",
        "coordinates": [
          4.14136,
          50.2857
        ]
      }
    }
  ]
}