{
  "type": "FeatureCollection",
  "features": [
    {
      "type": "Feature",
      "properties": {
        "address_id": "1521305",
        "box_number": "",
        "house_number": "2",
        "municipality_id": "81003",
        "municipality_name_de": "",
        "municipality_name_fr": "Attert",
        "municipality_name_nl": "",
        "postcode": "6717",
        "postname_fr": "",
        "postname_nl": "",
        "street_id": "7741830",
        "streetname_de": "",
        "streetname_fr": "Route de Habay",
        "streetname_nl": "",
        "region_code": "BE-WAL",
        "status": "current"
      },
      "geometry": {
        "type": "Point",
        "coordinates": [
          5.74266,
          49.77795
        ]
      }
    },
    {
      "type": "Feature",
      "properties": {
        "address_id": "1521306",
        "box_number": "",
        "house_number": "4",
        "municipality_id": "81003",
        "municipality_name_de": "",
        "municipality_name_fr": "Attert",
        "municipality_name_nl": "",
        "postcode": "6717",
        "postname_fr": "",
        "postname_nl": "",
        "street_id": "7741830",
        "streetname_de": "",
        "streetname_fr": "Route de Habay",
        "streetname_nl": "",
        "region_code": "BE-WAL",
        "status": "current"
      },
      "geometry": {
        "type": "Point",
        "coordinates": [
          5.73551,
          49.77003
        ]
      }
    }
  ]
}