{
  "type": "FeatureCollection",
  "features": [
    {
      "type": "Feature",
      "properties": {
        "address_id": "1462099",
        "box_number": "",
        "house_number": "62",
        "municipality_id": "64056",
        "municipality_name_de": "",
        "municipality_name_fr": "Oreye",
        "municipality_name_nl": "",
        "postcode": "4360",
        "postname_fr": "",
        "postname_nl": "",
        "street_id": "7740764",
        "streetname_de": "",
        "streetname_fr": "Rue de Horpmael",
        "streetname_nl": "",
        "region_code": "BE-WAL",
        "status": "current"
      },
      "geometry": {
        "type": "Point",
        "coordinates": [
          5.34644,
          50.73739
        ]
      }
    },
    {
      "type": "Feature",
      "properties": {
        "address_id": "1462100",
        "box_number": "",
        "house_number": "60",
        "municipality_id": "64056",
        "municipality_name_de": "",
        "municipality_name_fr": "Oreye",
        "municipality_name_nl": "",
        "postcode": "4360",
        "postname_fr": "",
        "postname_nl": "",
        "street_id": "7740764",
        "streetname_de": "",
        "streetname_fr": "Rue de Horpmael",
        "streetname_nl": "",
        "region_code": "BE-WAL",
        "status": "current"
      },
      "geometry": {
        "type": "Point",
        "coordinates": [
          5.3465,
          50.73731
        ]
      }
    },
    {
      "type": "Feature",
      "properties": {
        "address_id": "1952931",
        "box_number": "",
        "house_number": "77",
        "municipality_id": "64056",
        "municipality_name_de": "",
        "municipality_name_fr": "Oreye",
        "municipality_name_nl": "",
        "postcode": "4360",
        "postname_fr": "",
        "postname_nl": "",
        "street_id": "7740764",
        "streetname_de": "",
        "streetname_fr": "Rue de Horpmael",
        "streetname_nl": "",
        "region_code": "BE-WAL",
        "status": "current"
      },
      "geometry": {
        "type": "Point",
        "coordinates": [
          5.34384,
          50.73863
        ]
      }
    }
  ]
}