{
  "type": "FeatureCollection",
  "features": [
    {
      "type": "Feature",
      "properties": {
        "address_id": "1927977",
        "box_number": "",
        "house_number": "100",
        "municipality_id": "83013",
        "municipality_name_de": "",
        "municipality_name_fr": "Erezée",
        "municipality_name_nl": "",
        "postcode": "6997",
        "postname_fr": "",
        "postname_nl": "",
        "street_id": "7743549",
        "streetname_de": "",
        "streetname_fr": "Rue des Longues Royes",
        "streetname_nl": "",
        "region_code": "BE-WAL",
        "status": "current"
      },
      "geometry": {
        "type": "Point",
        "coordinates": [
          5.59921,
          50.30469
        ]
      }
    }
  ]
}