{
  "type": "FeatureCollection",
  "features": [
    {
      "type": "Feature",
      "properties": {
        "address_id": "760728",
        "box_number": "",
        "house_number": "2",
        "municipality_id": "53084",
        "municipality_name_de": "",
        "municipality_name_fr": "Quévy",
        "municipality_name_nl": "",
        "postcode": "7040",
        "postname_fr": "",
        "postname_nl": "",
        "street_id": "7715400",
        "streetname_de": "",
        "streetname_fr": "Rue de Névergies",
        "streetname_nl": "",
        "region_code": "BE-WAL",
        "status": "current"
      },
      "geometry": {
        "type": "Point",
        "coordinates": [
          3.93267,
          50.3479
        ]
      }
    },
    {
      "type": "Feature",
      "properties": {
        "address_id": "760729",
        "box_number": "",
        "house_number": "1",
        "municipality_id": "53084",
        "municipality_name_de": "",
        "municipality_name_fr": "Quévy",
        "municipality_name_nl": "",
        "postcode": "7040",
        "postname_fr": "",
        "postname_nl": "",
        "street_id": "7715400",
        "streetname_de": "",
        "streetname_fr": "Rue de Névergies",
        "streetname_nl": "",
        "region_code": "BE-WAL",
        "status": "current"
      },
      "geometry": {
        "type": "Point",
        "coordinates": [
          3.92566,
          50.34887
        ]
      }
    },
    {
      "type": "Feature",
      "properties": {
        "address_id": "1656608",
        "box_number": "2",
        "house_number": "13",
        "municipality_id": "53084",
        "municipality_name_de": "",
        "municipality_name_fr": "Quévy",
        "municipality_name_nl": "",
        "postcode": "7040",
        "postname_fr": "",
        "postname_nl": "",
        "street_id": "7715438",
        "streetname_de": "",
        "streetname_fr": "Rue du Cerisier",
        "streetname_nl": "",
        "region_code": "BE-WAL",
        "status": "current"
      },
      "geometry": {
        "type": "Point",
        "coordinates": [
          3.91388,
          50.3594
        ]
      }
    },
    {
      "type": "Feature",
      "properties": {
        "address_id": "1656609",
        "box_number": "1",
        "house_number": "13",
        "municipality_id": "53084",
        "municipality_name_de": "",
        "municipality_name_fr": "Quévy",
        "municipality_name_nl": "",
        "postcode": "7040",
        "postname_fr": "",
        "postname_nl": "",
        "street_id": "7715438",
        "streetname_de": "",
        "streetname_fr": "Rue du Cerisier",
        "streetname_nl": "",
        "region_code": "BE-WAL",
        "status": "current"
      },
      "geometry": {
        "type": "Point",
        "coordinates": [
          3.91388,
          50.3594
        ]
      }
    },
    {
      "type": "Feature",
      "properties": {
        "address_id": "778769",
        "box_number": "",
        "house_number": "13",
        "municipality_id": "53084",
        "municipality_name_de": "",
        "municipality_name_fr": "Quévy",
        "municipality_name_nl": "",
        "postcode": "7040",
        "postname_fr": "",
        "postname_nl": "",
        "street_id": "7715438",
        "streetname_de": "",
        "streetname_fr": "Rue du Cerisier",
        "streetname_nl": "",
        "region_code": "BE-WAL",
        "status": "current"
      },
      "geometry": {
        "type": "Point",
        "coordinates": [
          3.91388,
          50.3594
        ]
      }
    }
  ]
}