{
  "type": "FeatureCollection",
  "features": [
    {
      "type": "Feature",
      "properties": {
        "address_id": "358361",
        "box_number": "",
        "house_number": "1",
        "municipality_id": "92054",
        "municipality_name_de": "",
        "municipality_name_fr": "Gesves",
        "municipality_name_nl": "",
        "postcode": "5340",
        "postname_fr": "",
        "postname_nl": "",
        "street_id": "7752772",
        "streetname_de": "",
        "streetname_fr": "Rue Monty",
        "streetname_nl": "",
        "region_code": "BE-WAL",
        "status": "current"
      },
      "geometry": {
        "type": "Point",
        "coordinates": [
          5.12346,
          50.40868
        ]
      }
    },
    {
      "type": "Feature",
      "properties": {
        "address_id": "383563",
        "box_number": "",
        "house_number": "4",
        "municipality_id": "92097",
        "municipality_name_de": "",
        "municipality_name_fr": "Ohey",
        "municipality_name_nl": "",
        "postcode": "5350",
        "postname_fr": "",
        "postname_nl": "",
        "street_id": "7754774",
        "streetname_de": "",
        "streetname_fr": "Rue de Ciney",
        "streetname_nl": "",
        "region_code": "BE-WAL",
        "status": "current"
      },
      "geometry": {
        "type": "Point",
        "coordinates": [
          5.1227,
          50.41114
        ]
      }
    },
    {
      "type": "Feature",
      "properties": {
        "address_id": "382992",
        "box_number": "",
        "house_number": "2",
        "municipality_id": "92097",
        "municipality_name_de": "",
        "municipality_name_fr": "Ohey",
        "municipality_name_nl": "",
        "postcode": "5350",
        "postname_fr": "",
        "postname_nl": "",
        "street_id": "7754774",
        "streetname_de": "",
        "streetname_fr": "Rue de Ciney",
        "streetname_nl": "",
        "region_code": "BE-WAL",
        "status": "current"
      },
      "geometry": {
        "type": "Point",
        "coordinates": [
          5.12281,
          50.4105
        ]
      }
    },
    {
      "type": "Feature",
      "properties": {
        "address_id": "381919",
        "box_number": "",
        "house_number": "1",
        "municipality_id": "92097",
        "municipality_name_de": "",
        "municipality_name_fr": "Ohey",
        "municipality_name_nl": "",
        "postcode": "5350",
        "postname_fr": "",
        "postname_nl": "",
        "street_id": "7754774",
        "streetname_de": "",
        "streetname_fr": "Rue de Ciney",
        "streetname_nl": "",
        "region_code": "BE-WAL",
        "status": "current"
      },
      "geometry": {
        "type": "Point",
        "coordinates": [
          5.12237,
          50.4126
        ]
      }
    }
  ]
}