{
  "type": "FeatureCollection",
  "features": [
    {
      "type": "Feature",
      "properties": {
        "address_id": "239748",
        "box_number": "",
        "house_number": "16",
        "municipality_id": "84033",
        "municipality_name_de": "",
        "municipality_name_fr": "Léglise",
        "municipality_name_nl": "",
        "postcode": "6860",
        "postname_fr": "",
        "postname_nl": "",
        "street_id": "7745519",
        "streetname_de": "",
        "streetname_fr": "Rue de Saint-Hubert",
        "streetname_nl": "",
        "region_code": "BE-WAL",
        "status": "current"
      },
      "geometry": {
        "type": "Point",
        "coordinates": [
          5.6253,
          49.87959
        ]
      }
    }
  ]
}