{
  "type": "FeatureCollection",
  "features": [
    {
      "type": "Feature",
      "properties": {
        "address_id": "438023",
        "box_number": "",
        "house_number": "19",
        "municipality_id": "93014",
        "municipality_name_de": "",
        "municipality_name_fr": "Couvin",
        "municipality_name_nl": "",
        "postcode": "5660",
        "postname_fr": "",
        "postname_nl": "",
        "street_id": "7756882",
        "streetname_de": "",
        "streetname_fr": "Rue du Bois de Gonrieux",
        "streetname_nl": "",
        "region_code": "BE-WAL",
        "status": "current"
      },
      "geometry": {
        "type": "Point",
        "coordinates": [
          4.4255,
          49.98817
        ]
      }
    },
    {
      "type": "Feature",
      "properties": {
        "address_id": "438024",
        "box_number": "",
        "house_number": "18",
        "municipality_id": "93014",
        "municipality_name_de": "",
        "municipality_name_fr": "Couvin",
        "municipality_name_nl": "",
        "postcode": "5660",
        "postname_fr": "",
        "postname_nl": "",
        "street_id": "7756882",
        "streetname_de": "",
        "streetname_fr": "Rue du Bois de Gonrieux",
        "streetname_nl": "",
        "region_code": "BE-WAL",
        "status": "current"
      },
      "geometry": {
        "type": "Point",
        "coordinates": [
          4.42888,
          49.98749
        ]
      }
    },
    {
      "type": "Feature",
      "properties": {
        "address_id": "438025",
        "box_number": "",
        "house_number": "16",
        "municipality_id": "93014",
        "municipality_name_de": "",
        "municipality_name_fr": "Couvin",
        "municipality_name_nl": "",
        "postcode": "5660",
        "postname_fr": "",
        "postname_nl": "",
        "street_id": "7756882",
        "streetname_de": "",
        "streetname_fr": "Rue du Bois de Gonrieux",
        "streetname_nl": "",
        "region_code": "BE-WAL",
        "status": "current"
      },
      "geometry": {
        "type": "Point",
        "coordinates": [
          4.43063,
          49.98527
        ]
      }
    },
    {
      "type": "Feature",
      "properties": {
        "address_id": "438027",
        "box_number": "",
        "house_number": "14",
        "municipality_id": "93014",
        "municipality_name_de": "",
        "municipality_name_fr": "Couvin",
        "municipality_name_nl": "",
        "postcode": "5660",
        "postname_fr": "",
        "postname_nl": "",
        "street_id": "7756882",
        "streetname_de": "",
        "streetname_fr": "Rue du Bois de Gonrieux",
        "streetname_nl": "",
        "region_code": "BE-WAL",
        "status": "current"
      },
      "geometry": {
        "type": "Point",
        "coordinates": [
          4.43426,
          49.9841
        ]
      }
    },
    {
      "type": "Feature",
      "properties": {
        "address_id": "438028",
        "box_number": "",
        "house_number": "13",
        "municipality_id": "93014",
        "municipality_name_de": "",
        "municipality_name_fr": "Couvin",
        "municipality_name_nl": "",
        "postcode": "5660",
        "postname_fr": "",
        "postname_nl": "",
        "street_id": "7756882",
        "streetname_de": "",
        "streetname_fr": "Rue du Bois de Gonrieux",
        "streetname_nl": "",
        "region_code": "BE-WAL",
        "status": "current"
      },
      "geometry": {
        "type": "Point",
        "coordinates": [
          4.43682,
          49.98323
        ]
      }
    }
  ]
}