{
  "type": "FeatureCollection",
  "features": [
    {
      "type": "Feature",
      "properties": {
        "address_id": "125651",
        "box_number": "",
        "house_number": "21",
        "municipality_id": "25122",
        "municipality_name_de": "",
        "municipality_name_fr": "Ramillies",
        "municipality_name_nl": "",
        "postcode": "1367",
        "postname_fr": "",
        "postname_nl": "",
        "street_id": "7706821",
        "streetname_de": "",
        "streetname_fr": "Rue du Wayaux",
        "streetname_nl": "",
        "region_code": "BE-WAL",
        "status": "current"
      },
      "geometry": {
        "type": "Point",
        "coordinates": [
          4.92918,
          50.6449
        ]
      }
    },
    {
      "type": "Feature",
      "properties": {
        "address_id": "125652",
        "box_number": "",
        "house_number": "23",
        "municipality_id": "25122",
        "municipality_name_de": "",
        "municipality_name_fr": "Ramillies",
        "municipality_name_nl": "",
        "postcode": "1367",
        "postname_fr": "",
        "postname_nl": "",
        "street_id": "7706821",
        "streetname_de": "",
        "streetname_fr": "Rue du Wayaux",
        "streetname_nl": "",
        "region_code": "BE-WAL",
        "status": "current"
      },
      "geometry": {
        "type": "Point",
        "coordinates": [
          4.93108,
          50.64526
        ]
      }
    },
    {
      "type": "Feature",
      "properties": {
        "address_id": "125654",
        "box_number": "",
        "house_number": "24",
        "municipality_id": "25122",
        "municipality_name_de": "",
        "municipality_name_fr": "Ramillies",
        "municipality_name_nl": "",
        "postcode": "1367",
        "postname_fr": "",
        "postname_nl": "",
        "street_id": "7706821",
        "streetname_de": "",
        "streetname_fr": "Rue du Wayaux",
        "streetname_nl": "",
        "region_code": "BE-WAL",
        "status": "current"
      },
      "geometry": {
        "type": "Point",
        "coordinates": [
          4.93093,
          50.64414
        ]
      }
    }
  ]
}