{
  "type": "FeatureCollection",
  "features": [
    {
      "type": "Feature",
      "properties": {
        "address_id": "246364",
        "box_number": "",
        "house_number": "3",
        "municipality_id": "85024",
        "municipality_name_de": "",
        "municipality_name_fr": "Meix-devant-Virton",
        "municipality_name_nl": "",
        "postcode": "6769",
        "postname_fr": "",
        "postname_nl": "",
        "street_id": "7747374",
        "streetname_de": "",
        "streetname_fr": "Rue de la Platinerie",
        "streetname_nl": "",
        "region_code": "BE-WAL",
        "status": "current"
      },
      "geometry": {
        "type": "Point",
        "coordinates": [
          5.42836,
          49.62495
        ]
      }
    }
  ]
}