{
  "type": "FeatureCollection",
  "features": [
    {
      "type": "Feature",
      "properties": {
        "address_id": "1656664",
        "box_number": "000C",
        "house_number": "9",
        "municipality_id": "53083",
        "municipality_name_de": "",
        "municipality_name_fr": "Honnelles",
        "municipality_name_nl": "",
        "postcode": "7387",
        "postname_fr": "",
        "postname_nl": "",
        "street_id": "7715268",
        "streetname_de": "",
        "streetname_fr": "Rue du Piémont",
        "streetname_nl": "",
        "region_code": "BE-WAL",
        "status": "current"
      },
      "geometry": {
        "type": "Point",
        "coordinates": [
          3.73674,
          50.33576
        ]
      }
    },
    {
      "type": "Feature",
      "properties": {
        "address_id": "773307",
        "box_number": "",
        "house_number": "9",
        "municipality_id": "53083",
        "municipality_name_de": "",
        "municipality_name_fr": "Honnelles",
        "municipality_name_nl": "",
        "postcode": "7387",
        "postname_fr": "",
        "postname_nl": "",
        "street_id": "7715268",
        "streetname_de": "",
        "streetname_fr": "Rue du Piémont",
        "streetname_nl": "",
        "region_code": "BE-WAL",
        "status": "current"
      },
      "geometry": {
        "type": "Point",
        "coordinates": [
          3.73674,
          50.33576
        ]
      }
    },
    {
      "type": "Feature",
      "properties": {
        "address_id": "773309",
        "box_number": "",
        "house_number": "7",
        "municipality_id": "53083",
        "municipality_name_de": "",
        "municipality_name_fr": "Honnelles",
        "municipality_name_nl": "",
        "postcode": "7387",
        "postname_fr": "",
        "postname_nl": "",
        "street_id": "7715268",
        "streetname_de": "",
        "streetname_fr": "Rue du Piémont",
        "streetname_nl": "",
        "region_code": "BE-WAL",
        "status": "current"
      },
      "geometry": {
        "type": "Point",
        "coordinates": [
          3.73603,
          50.33517
        ]
      }
    }
  ]
}