{
  "type": "FeatureCollection",
  "features": [
    {
      "type": "Feature",
      "properties": {
        "address_id": "308595",
        "box_number": "",
        "house_number": "23",
        "municipality_id": "91064",
        "municipality_name_de": "",
        "municipality_name_fr": "Havelange",
        "municipality_name_nl": "",
        "postcode": "5376",
        "postname_fr": "",
        "postname_nl": "",
        "street_id": "7749847",
        "streetname_de": "",
        "streetname_fr": "La Fagne",
        "streetname_nl": "",
        "region_code": "BE-WAL",
        "status": "current"
      },
      "geometry": {
        "type": "Point",
        "coordinates": [
          5.22947,
          50.36488
        ]
      }
    },
    {
      "type": "Feature",
      "properties": {
        "address_id": "308593",
        "box_number": "",
        "house_number": "27",
        "municipality_id": "91064",
        "municipality_name_de": "",
        "municipality_name_fr": "Havelange",
        "municipality_name_nl": "",
        "postcode": "5376",
        "postname_fr": "",
        "postname_nl": "",
        "street_id": "7749847",
        "streetname_de": "",
        "streetname_fr": "La Fagne",
        "streetname_nl": "",
        "region_code": "BE-WAL",
        "status": "current"
      },
      "geometry": {
        "type": "Point",
        "coordinates": [
          5.22904,
          50.36456
        ]
      }
    }
  ]
}