{
  "type": "FeatureCollection",
  "features": [
    {
      "type": "Feature",
      "properties": {
        "address_id": "1289042",
        "box_number": "",
        "house_number": "38",
        "municipality_id": "63075",
        "municipality_name_de": "",
        "municipality_name_fr": "Stoumont",
        "municipality_name_nl": "",
        "postcode": "4987",
        "postname_fr": "",
        "postname_nl": "",
        "street_id": "7738251",
        "streetname_de": "",
        "streetname_fr": "Hasoumont",
        "streetname_nl": "",
        "region_code": "BE-WAL",
        "status": "current"
      },
      "geometry": {
        "type": "Point",
        "coordinates": [
          5.84297,
          50.41563
        ]
      }
    },
    {
      "type": "Feature",
      "properties": {
        "address_id": "1289046",
        "box_number": "",
        "house_number": "32",
        "municipality_id": "63075",
        "municipality_name_de": "",
        "municipality_name_fr": "Stoumont",
        "municipality_name_nl": "",
        "postcode": "4987",
        "postname_fr": "",
        "postname_nl": "",
        "street_id": "7738251",
        "streetname_de": "",
        "streetname_fr": "Hasoumont",
        "streetname_nl": "",
        "region_code": "BE-WAL",
        "status": "current"
      },
      "geometry": {
        "type": "Point",
        "coordinates": [
          5.84449,
          50.41698
        ]
      }
    },
    {
      "type": "Feature",
      "properties": {
        "address_id": "1289047",
        "box_number": "",
        "house_number": "31",
        "municipality_id": "63075",
        "municipality_name_de": "",
        "municipality_name_fr": "Stoumont",
        "municipality_name_nl": "",
        "postcode": "4987",
        "postname_fr": "",
        "postname_nl": "",
        "street_id": "7738251",
        "streetname_de": "",
        "streetname_fr": "Hasoumont",
        "streetname_nl": "",
        "region_code": "BE-WAL",
        "status": "current"
      },
      "geometry": {
        "type": "Point",
        "coordinates": [
          5.84416,
          50.4171
        ]
      }
    },
    {
      "type": "Feature",
      "properties": {
        "address_id": "1508877",
        "box_number": "",
        "house_number": "32/1",
        "municipality_id": "63075",
        "municipality_name_de": "",
        "municipality_name_fr": "Stoumont",
        "municipality_name_nl": "",
        "postcode": "4987",
        "postname_fr": "",
        "postname_nl": "",
        "street_id": "7738251",
        "streetname_de": "",
        "streetname_fr": "Hasoumont",
        "streetname_nl": "",
        "region_code": "BE-WAL",
        "status": "current"
      },
      "geometry": {
        "type": "Point",
        "coordinates": [
          5.84436,
          50.41732
        ]
      }
    }
  ]
}