{
  "type": "FeatureCollection",
  "features": [
    {
      "type": "Feature",
      "properties": {
        "address_id": "201964",
        "box_number": "",
        "house_number": "1",
        "municipality_id": "82036",
        "municipality_name_de": "",
        "municipality_name_fr": "Vaux-sur-Sûre",
        "municipality_name_nl": "",
        "postcode": "6640",
        "postname_fr": "",
        "postname_nl": "",
        "street_id": "7742891",
        "streetname_de": "",
        "streetname_fr": "Bois de Waffe",
        "streetname_nl": "",
        "region_code": "BE-WAL",
        "status": "current"
      },
      "geometry": {
        "type": "Point",
        "coordinates": [
          5.5338,
          49.93313
        ]
      }
    }
  ]
}