{
  "type": "FeatureCollection",
  "features": [
    {
      "type": "Feature",
      "properties": {
        "address_id": "1501430",
        "box_number": "",
        "house_number": "62",
        "municipality_id": "63087",
        "municipality_name_de": "Burg-Reuland",
        "municipality_name_fr": "Burg-Reuland",
        "municipality_name_nl": "",
        "postcode": "4790",
        "postname_fr": "",
        "postname_nl": "",
        "street_id": "7763565",
        "streetname_de": "Zur Burgstatt",
        "streetname_fr": "",
        "streetname_nl": "",
        "region_code": "BE-WAL",
        "status": "current"
      },
      "geometry": {
        "type": "Point",
        "coordinates": [
          6.01546,
          50.21899
        ]
      }
    },
    {
      "type": "Feature",
      "properties": {
        "address_id": "1519836",
        "box_number": "",
        "house_number": "22",
        "municipality_id": "63087",
        "municipality_name_de": "Burg-Reuland",
        "municipality_name_fr": "Burg-Reuland",
        "municipality_name_nl": "",
        "postcode": "4790",
        "postname_fr": "",
        "postname_nl": "",
        "street_id": "7763561",
        "streetname_de": "Zum Lie",
        "streetname_fr": "",
        "streetname_nl": "",
        "region_code": "BE-WAL",
        "status": "current"
      },
      "geometry": {
        "type": "Point",
        "coordinates": [
          6.01903,
          50.21857
        ]
      }
    },
    {
      "type": "Feature",
      "properties": {
        "address_id": "1501434",
        "box_number": "",
        "house_number": "68",
        "municipality_id": "63087",
        "municipality_name_de": "Burg-Reuland",
        "municipality_name_fr": "Burg-Reuland",
        "municipality_name_nl": "",
        "postcode": "4790",
        "postname_fr": "",
        "postname_nl": "",
        "street_id": "7763565",
        "streetname_de": "Zur Burgstatt",
        "streetname_fr": "",
        "streetname_nl": "",
        "region_code": "BE-WAL",
        "status": "current"
      },
      "geometry": {
        "type": "Point",
        "coordinates": [
          6.01401,
          50.21816
        ]
      }
    }
  ]
}