{
  "type": "FeatureCollection",
  "features": [
    {
      "type": "Feature",
      "properties": {
        "address_id": "1404649",
        "box_number": "",
        "house_number": "15",
        "municipality_id": "64025",
        "municipality_name_de": "",
        "municipality_name_fr": "Fexhe-le-Haut-Clocher",
        "municipality_name_nl": "",
        "postcode": "4347",
        "postname_fr": "",
        "postname_nl": "",
        "street_id": "7740272",
        "streetname_de": "",
        "streetname_fr": "Rue du Mahay",
        "streetname_nl": "",
        "region_code": "BE-WAL",
        "status": "current"
      },
      "geometry": {
        "type": "Point",
        "coordinates": [
          5.40765,
          50.68018
        ]
      }
    },
    {
      "type": "Feature",
      "properties": {
        "address_id": "1387409",
        "box_number": "",
        "house_number": "5",
        "municipality_id": "64025",
        "municipality_name_de": "",
        "municipality_name_fr": "Fexhe-le-Haut-Clocher",
        "municipality_name_nl": "",
        "postcode": "4347",
        "postname_fr": "",
        "postname_nl": "",
        "street_id": "7740281",
        "streetname_de": "",
        "streetname_fr": "Rue du Village",
        "streetname_nl": "",
        "region_code": "BE-WAL",
        "status": "current"
      },
      "geometry": {
        "type": "Point",
        "coordinates": [
          5.40579,
          50.67986
        ]
      }
    },
    {
      "type": "Feature",
      "properties": {
        "address_id": "1387406",
        "box_number": "",
        "house_number": "7",
        "municipality_id": "64025",
        "municipality_name_de": "",
        "municipality_name_fr": "Fexhe-le-Haut-Clocher",
        "municipality_name_nl": "",
        "postcode": "4347",
        "postname_fr": "",
        "postname_nl": "",
        "street_id": "7740281",
        "streetname_de": "",
        "streetname_fr": "Rue du Village",
        "streetname_nl": "",
        "region_code": "BE-WAL",
        "status": "current"
      },
      "geometry": {
        "type": "Point",
        "coordinates": [
          5.40642,
          50.67999
        ]
      }
    }
  ]
}