{
  "type": "FeatureCollection",
  "features": [
    {
      "type": "Feature",
      "properties": {
        "address_id": "1359104",
        "box_number": "",
        "house_number": "49",
        "municipality_id": "63001",
        "municipality_name_de": "Amel",
        "municipality_name_fr": "Amblève",
        "municipality_name_nl": "",
        "postcode": "4770",
        "postname_fr": "",
        "postname_nl": "",
        "street_id": "7735073",
        "streetname_de": "Zur Morsheck",
        "streetname_fr": "",
        "streetname_nl": "",
        "region_code": "BE-WAL",
        "status": "current"
      },
      "geometry": {
        "type": "Point",
        "coordinates": [
          6.20801,
          50.38936
        ]
      }
    }
  ]
}