{
  "type": "FeatureCollection",
  "features": [
    {
      "type": "Feature",
      "properties": {
        "address_id": "790535",
        "box_number": "",
        "house_number": "13",
        "municipality_id": "56029",
        "municipality_name_de": "",
        "municipality_name_fr": "Froidchapelle",
        "municipality_name_nl": "",
        "postcode": "6440",
        "postname_fr": "",
        "postname_nl": "",
        "street_id": "7720473",
        "streetname_de": "",
        "streetname_fr": "Rue Praye",
        "streetname_nl": "",
        "region_code": "BE-WAL",
        "status": "current"
      },
      "geometry": {
        "type": "Point",
        "coordinates": [
          4.29912,
          50.19094
        ]
      }
    },
    {
      "type": "Feature",
      "properties": {
        "address_id": "860303",
        "box_number": "",
        "house_number": "8",
        "municipality_id": "56005",
        "municipality_name_de": "",
        "municipality_name_fr": "Beaumont",
        "municipality_name_nl": "",
        "postcode": "6500",
        "postname_fr": "",
        "postname_nl": "",
        "street_id": "7719261",
        "streetname_de": "",
        "streetname_fr": "Forge du Haut Marteau",
        "streetname_nl": "",
        "region_code": "BE-WAL",
        "status": "current"
      },
      "geometry": {
        "type": "Point",
        "coordinates": [
          4.28517,
          50.18692
        ]
      }
    },
    {
      "type": "Feature",
      "properties": {
        "address_id": "860306",
        "box_number": "",
        "house_number": "12",
        "municipality_id": "56005",
        "municipality_name_de": "",
        "municipality_name_fr": "Beaumont",
        "municipality_name_nl": "",
        "postcode": "6500",
        "postname_fr": "",
        "postname_nl": "",
        "street_id": "7719261",
        "streetname_de": "",
        "streetname_fr": "Forge du Haut Marteau",
        "streetname_nl": "",
        "region_code": "BE-WAL",
        "status": "current"
      },
      "geometry": {
        "type": "Point",
        "coordinates": [
          4.28933,
          50.17798
        ]
      }
    }
  ]
}