{
  "type": "FeatureCollection",
  "features": [
    {
      "type": "Feature",
      "properties": {
        "address_id": "235988",
        "box_number": "",
        "house_number": "36",
        "municipality_id": "84033",
        "municipality_name_de": "",
        "municipality_name_fr": "Léglise",
        "municipality_name_nl": "",
        "postcode": "6860",
        "postname_fr": "",
        "postname_nl": "",
        "street_id": "7745529",
        "streetname_de": "",
        "streetname_fr": "Rue des Eaux Bonnes",
        "streetname_nl": "",
        "region_code": "BE-WAL",
        "status": "current"
      },
      "geometry": {
        "type": "Point",
        "coordinates": [
          5.62997,
          49.79618
        ]
      }
    },
    {
      "type": "Feature",
      "properties": {
        "address_id": "206976",
        "box_number": "",
        "house_number": "10",
        "municipality_id": "84033",
        "municipality_name_de": "",
        "municipality_name_fr": "Léglise",
        "municipality_name_nl": "",
        "postcode": "6860",
        "postname_fr": "",
        "postname_nl": "",
        "street_id": "7745569",
        "streetname_de": "",
        "streetname_fr": "Rue du Cherbuchi",
        "streetname_nl": "",
        "region_code": "BE-WAL",
        "status": "current"
      },
      "geometry": {
        "type": "Point",
        "coordinates": [
          5.64599,
          49.79708
        ]
      }
    },
    {
      "type": "Feature",
      "properties": {
        "address_id": "207385",
        "box_number": "",
        "house_number": "11",
        "municipality_id": "84033",
        "municipality_name_de": "",
        "municipality_name_fr": "Léglise",
        "municipality_name_nl": "",
        "postcode": "6860",
        "postname_fr": "",
        "postname_nl": "",
        "street_id": "7745569",
        "streetname_de": "",
        "streetname_fr": "Rue du Cherbuchi",
        "streetname_nl": "",
        "region_code": "BE-WAL",
        "status": "current"
      },
      "geometry": {
        "type": "Point",
        "coordinates": [
          5.64597,
          49.7969
        ]
      }
    },
    {
      "type": "Feature",
      "properties": {
        "address_id": "207386",
        "box_number": "",
        "house_number": "13",
        "municipality_id": "84033",
        "municipality_name_de": "",
        "municipality_name_fr": "Léglise",
        "municipality_name_nl": "",
        "postcode": "6860",
        "postname_fr": "",
        "postname_nl": "",
        "street_id": "7745569",
        "streetname_de": "",
        "streetname_fr": "Rue du Cherbuchi",
        "streetname_nl": "",
        "region_code": "BE-WAL",
        "status": "current"
      },
      "geometry": {
        "type": "Point",
        "coordinates": [
          5.6452,
          49.79712
        ]
      }
    }
  ]
}