{
  "type": "FeatureCollection",
  "features": [
    {
      "type": "Feature",
      "properties": {
        "address_id": "175161",
        "box_number": "",
        "house_number": "13",
        "municipality_id": "82037",
        "municipality_name_de": "",
        "municipality_name_fr": "Gouvy",
        "municipality_name_nl": "",
        "postcode": "6670",
        "postname_fr": "",
        "postname_nl": "",
        "street_id": "7742998",
        "streetname_de": "",
        "streetname_fr": "Rue de Bellain",
        "streetname_nl": "",
        "region_code": "BE-WAL",
        "status": "current"
      },
      "geometry": {
        "type": "Point",
        "coordinates": [
          5.96047,
          50.15389
        ]
      }
    },
    {
      "type": "Feature",
      "properties": {
        "address_id": "175162",
        "box_number": "",
        "house_number": "14",
        "municipality_id": "82037",
        "municipality_name_de": "",
        "municipality_name_fr": "Gouvy",
        "municipality_name_nl": "",
        "postcode": "6670",
        "postname_fr": "",
        "postname_nl": "",
        "street_id": "7742998",
        "streetname_de": "",
        "streetname_fr": "Rue de Bellain",
        "streetname_nl": "",
        "region_code": "BE-WAL",
        "status": "current"
      },
      "geometry": {
        "type": "Point",
        "coordinates": [
          5.96144,
          50.15359
        ]
      }
    }
  ]
}