{
  "type": "FeatureCollection",
  "features": [
    {
      "type": "Feature",
      "properties": {
        "address_id": "199289",
        "box_number": "",
        "house_number": "8",
        "municipality_id": "82037",
        "municipality_name_de": "",
        "municipality_name_fr": "Gouvy",
        "municipality_name_nl": "",
        "postcode": "6674",
        "postname_fr": "",
        "postname_nl": "",
        "street_id": "7742982",
        "streetname_de": "",
        "streetname_fr": "Hallonru",
        "streetname_nl": "",
        "region_code": "BE-WAL",
        "status": "current"
      },
      "geometry": {
        "type": "Point",
        "coordinates": [
          5.83151,
          50.1754
        ]
      }
    },
    {
      "type": "Feature",
      "properties": {
        "address_id": "198032",
        "box_number": "",
        "house_number": "12",
        "municipality_id": "82037",
        "municipality_name_de": "",
        "municipality_name_fr": "Gouvy",
        "municipality_name_nl": "",
        "postcode": "6673",
        "postname_fr": "",
        "postname_nl": "",
        "street_id": "7743033",
        "streetname_de": "",
        "streetname_fr": "Vaux",
        "streetname_nl": "",
        "region_code": "BE-WAL",
        "status": "current"
      },
      "geometry": {
        "type": "Point",
        "coordinates": [
          5.83418,
          50.17355
        ]
      }
    },
    {
      "type": "Feature",
      "properties": {
        "address_id": "154981",
        "box_number": "",
        "house_number": "56",
        "municipality_id": "82014",
        "municipality_name_de": "",
        "municipality_name_fr": "Houffalize",
        "municipality_name_nl": "",
        "postcode": "6661",
        "postname_fr": "",
        "postname_nl": "",
        "street_id": "7742751",
        "streetname_de": "",
        "streetname_fr": "Sommerain",
        "streetname_nl": "",
        "region_code": "BE-WAL",
        "status": "current"
      },
      "geometry": {
        "type": "Point",
        "coordinates": [
          5.82311,
          50.16386
        ]
      }
    }
  ]
}