{
  "type": "FeatureCollection",
  "features": [
    {
      "type": "Feature",
      "properties": {
        "address_id": "1390925",
        "box_number": "",
        "house_number": "86",
        "municipality_id": "63049",
        "municipality_name_de": "Malmedy",
        "municipality_name_fr": "Malmedy",
        "municipality_name_nl": "",
        "postcode": "4960",
        "postname_fr": "",
        "postname_nl": "",
        "street_id": "7736900",
        "streetname_de": "",
        "streetname_fr": "Grand Rue",
        "streetname_nl": "",
        "region_code": "BE-WAL",
        "status": "current"
      },
      "geometry": {
        "type": "Point",
        "coordinates": [
          6.05885,
          50.35586
        ]
      }
    }
  ]
}