{
  "type": "FeatureCollection",
  "features": [
    {
      "type": "Feature",
      "properties": {
        "address_id": "804930",
        "box_number": "",
        "house_number": "9",
        "municipality_id": "56029",
        "municipality_name_de": "",
        "municipality_name_fr": "Froidchapelle",
        "municipality_name_nl": "",
        "postcode": "6440",
        "postname_fr": "",
        "postname_nl": "",
        "street_id": "7720445",
        "streetname_de": "",
        "streetname_fr": "Rue du Bois le Comte",
        "streetname_nl": "",
        "region_code": "BE-WAL",
        "status": "current"
      },
      "geometry": {
        "type": "Point",
        "coordinates": [
          4.36553,
          50.08753
        ]
      }
    },
    {
      "type": "Feature",
      "properties": {
        "address_id": "804932",
        "box_number": "",
        "house_number": "7",
        "municipality_id": "56029",
        "municipality_name_de": "",
        "municipality_name_fr": "Froidchapelle",
        "municipality_name_nl": "",
        "postcode": "6440",
        "postname_fr": "",
        "postname_nl": "",
        "street_id": "7720445",
        "streetname_de": "",
        "streetname_fr": "Rue du Bois le Comte",
        "streetname_nl": "",
        "region_code": "BE-WAL",
        "status": "current"
      },
      "geometry": {
        "type": "Point",
        "coordinates": [
          4.35298,
          50.08944
        ]
      }
    },
    {
      "type": "Feature",
      "properties": {
        "address_id": "804934",
        "box_number": "",
        "house_number": "5",
        "municipality_id": "56029",
        "municipality_name_de": "",
        "municipality_name_fr": "Froidchapelle",
        "municipality_name_nl": "",
        "postcode": "6440",
        "postname_fr": "",
        "postname_nl": "",
        "street_id": "7720445",
        "streetname_de": "",
        "streetname_fr": "Rue du Bois le Comte",
        "streetname_nl": "",
        "region_code": "BE-WAL",
        "status": "current"
      },
      "geometry": {
        "type": "Point",
        "coordinates": [
          4.35283,
          50.08979
        ]
      }
    },
    {
      "type": "Feature",
      "properties": {
        "address_id": "803918",
        "box_number": "",
        "house_number": "14",
        "municipality_id": "56029",
        "municipality_name_de": "",
        "municipality_name_fr": "Froidchapelle",
        "municipality_name_nl": "",
        "postcode": "6440",
        "postname_fr": "",
        "postname_nl": "",
        "street_id": "7720445",
        "streetname_de": "",
        "streetname_fr": "Rue du Bois le Comte",
        "streetname_nl": "",
        "region_code": "BE-WAL",
        "status": "current"
      },
      "geometry": {
        "type": "Point",
        "coordinates": [
          4.36791,
          50.09033
        ]
      }
    },
    {
      "type": "Feature",
      "properties": {
        "address_id": "1504608",
        "box_number": "",
        "house_number": "16",
        "municipality_id": "56029",
        "municipality_name_de": "",
        "municipality_name_fr": "Froidchapelle",
        "municipality_name_nl": "",
        "postcode": "6440",
        "postname_fr": "",
        "postname_nl": "",
        "street_id": "7720445",
        "streetname_de": "",
        "streetname_fr": "Rue du Bois le Comte",
        "streetname_nl": "",
        "region_code": "BE-WAL",
        "status": "current"
      },
      "geometry": {
        "type": "Point",
        "coordinates": [
          4.36937,
          50.08774
        ]
      }
    },
    {
      "type": "Feature",
      "properties": {
        "address_id": "1660609",
        "box_number": "1",
        "house_number": "7",
        "municipality_id": "56029",
        "municipality_name_de": "",
        "municipality_name_fr": "Froidchapelle",
        "municipality_name_nl": "",
        "postcode": "6440",
        "postname_fr": "",
        "postname_nl": "",
        "street_id": "7720445",
        "streetname_de": "",
        "streetname_fr": "Rue du Bois le Comte",
        "streetname_nl": "",
        "region_code": "BE-WAL",
        "status": "current"
      },
      "geometry": {
        "type": "Point",
        "coordinates": [
          4.35298,
          50.08944
        ]
      }
    }
  ]
}