{
  "type": "FeatureCollection",
  "features": [
    {
      "type": "Feature",
      "properties": {
        "address_id": "1862896",
        "box_number": "",
        "house_number": "1",
        "municipality_id": "84010",
        "municipality_name_de": "",
        "municipality_name_fr": "Bouillon",
        "municipality_name_nl": "",
        "postcode": "6830",
        "postname_fr": "",
        "postname_nl": "",
        "street_id": "7745106",
        "streetname_de": "",
        "streetname_fr": "Les Amerois",
        "streetname_nl": "",
        "region_code": "BE-WAL",
        "status": "current"
      },
      "geometry": {
        "type": "Point",
        "coordinates": [
          5.15117,
          49.7484
        ]
      }
    },
    {
      "type": "Feature",
      "properties": {
        "address_id": "1862900",
        "box_number": "",
        "house_number": "4",
        "municipality_id": "84010",
        "municipality_name_de": "",
        "municipality_name_fr": "Bouillon",
        "municipality_name_nl": "",
        "postcode": "6830",
        "postname_fr": "",
        "postname_nl": "",
        "street_id": "7745106",
        "streetname_de": "",
        "streetname_fr": "Les Amerois",
        "streetname_nl": "",
        "region_code": "BE-WAL",
        "status": "current"
      },
      "geometry": {
        "type": "Point",
        "coordinates": [
          5.15158,
          49.74953
        ]
      }
    },
    {
      "type": "Feature",
      "properties": {
        "address_id": "1862899",
        "box_number": "",
        "house_number": "3",
        "municipality_id": "84010",
        "municipality_name_de": "",
        "municipality_name_fr": "Bouillon",
        "municipality_name_nl": "",
        "postcode": "6830",
        "postname_fr": "",
        "postname_nl": "",
        "street_id": "7745106",
        "streetname_de": "",
        "streetname_fr": "Les Amerois",
        "streetname_nl": "",
        "region_code": "BE-WAL",
        "status": "current"
      },
      "geometry": {
        "type": "Point",
        "coordinates": [
          5.14757,
          49.74972
        ]
      }
    }
  ]
}