{
  "type": "FeatureCollection",
  "features": [
    {
      "type": "Feature",
      "properties": {
        "address_id": "183579",
        "box_number": "",
        "house_number": "65",
        "municipality_id": "82014",
        "municipality_name_de": "",
        "municipality_name_fr": "Houffalize",
        "municipality_name_nl": "",
        "postcode": "6660",
        "postname_fr": "",
        "postname_nl": "",
        "street_id": "7742724",
        "streetname_de": "",
        "streetname_fr": "Rue de La-Roche",
        "streetname_nl": "",
        "region_code": "BE-WAL",
        "status": "current"
      },
      "geometry": {
        "type": "Point",
        "coordinates": [
          5.75074,
          50.13443
        ]
      }
    }
  ]
}