{
  "type": "FeatureCollection",
  "features": [
    {
      "type": "Feature",
      "properties": {
        "address_id": "460341",
        "box_number": "",
        "house_number": "190",
        "municipality_id": "93022",
        "municipality_name_de": "",
        "municipality_name_fr": "Florennes",
        "municipality_name_nl": "",
        "postcode": "5620",
        "postname_fr": "",
        "postname_nl": "",
        "street_id": "7757160",
        "streetname_de": "",
        "streetname_fr": "Route Charlemagne",
        "streetname_nl": "",
        "region_code": "BE-WAL",
        "status": "current"
      },
      "geometry": {
        "type": "Point",
        "coordinates": [
          4.65542,
          50.2254
        ]
      }
    },
    {
      "type": "Feature",
      "properties": {
        "address_id": "458768",
        "box_number": "",
        "house_number": "189",
        "municipality_id": "93022",
        "municipality_name_de": "",
        "municipality_name_fr": "Florennes",
        "municipality_name_nl": "",
        "postcode": "5620",
        "postname_fr": "",
        "postname_nl": "",
        "street_id": "7757160",
        "streetname_de": "",
        "streetname_fr": "Route Charlemagne",
        "streetname_nl": "",
        "region_code": "BE-WAL",
        "status": "current"
      },
      "geometry": {
        "type": "Point",
        "coordinates": [
          4.65522,
          50.22537
        ]
      }
    }
  ]
}