{
  "type": "FeatureCollection",
  "features": [
    {
      "type": "Feature",
      "properties": {
        "address_id": "784893",
        "box_number": "",
        "house_number": "15",
        "municipality_id": "56016",
        "municipality_name_de": "",
        "municipality_name_fr": "Chimay",
        "municipality_name_nl": "",
        "postcode": "6460",
        "postname_fr": "",
        "postname_nl": "",
        "street_id": "7720132",
        "streetname_de": "",
        "streetname_fr": "Rue du Maronet",
        "streetname_nl": "",
        "region_code": "BE-WAL",
        "status": "current"
      },
      "geometry": {
        "type": "Point",
        "coordinates": [
          4.32705,
          50.11753
        ]
      }
    }
  ]
}