{
  "type": "FeatureCollection",
  "features": [
    {
      "type": "Feature",
      "properties": {
        "address_id": "295605",
        "box_number": "",
        "house_number": "64",
        "municipality_id": "91064",
        "municipality_name_de": "",
        "municipality_name_fr": "Havelange",
        "municipality_name_nl": "",
        "postcode": "5370",
        "postname_fr": "",
        "postname_nl": "",
        "street_id": "7749876",
        "streetname_de": "",
        "streetname_fr": "Rue Albert Billy",
        "streetname_nl": "",
        "region_code": "BE-WAL",
        "status": "current"
      },
      "geometry": {
        "type": "Point",
        "coordinates": [
          5.22808,
          50.33306
        ]
      }
    },
    {
      "type": "Feature",
      "properties": {
        "address_id": "295606",
        "box_number": "",
        "house_number": "62",
        "municipality_id": "91064",
        "municipality_name_de": "",
        "municipality_name_fr": "Havelange",
        "municipality_name_nl": "",
        "postcode": "5370",
        "postname_fr": "",
        "postname_nl": "",
        "street_id": "7749876",
        "streetname_de": "",
        "streetname_fr": "Rue Albert Billy",
        "streetname_nl": "",
        "region_code": "BE-WAL",
        "status": "current"
      },
      "geometry": {
        "type": "Point",
        "coordinates": [
          5.22848,
          50.33331
        ]
      }
    },
    {
      "type": "Feature",
      "properties": {
        "address_id": "295607",
        "box_number": "",
        "house_number": "60",
        "municipality_id": "91064",
        "municipality_name_de": "",
        "municipality_name_fr": "Havelange",
        "municipality_name_nl": "",
        "postcode": "5370",
        "postname_fr": "",
        "postname_nl": "",
        "street_id": "7749876",
        "streetname_de": "",
        "streetname_fr": "Rue Albert Billy",
        "streetname_nl": "",
        "region_code": "BE-WAL",
        "status": "current"
      },
      "geometry": {
        "type": "Point",
        "coordinates": [
          5.22888,
          50.33301
        ]
      }
    },
    {
      "type": "Feature",
      "properties": {
        "address_id": "295622",
        "box_number": "",
        "house_number": "31",
        "municipality_id": "91064",
        "municipality_name_de": "",
        "municipality_name_fr": "Havelange",
        "municipality_name_nl": "",
        "postcode": "5370",
        "postname_fr": "",
        "postname_nl": "",
        "street_id": "7749876",
        "streetname_de": "",
        "streetname_fr": "Rue Albert Billy",
        "streetname_nl": "",
        "region_code": "BE-WAL",
        "status": "current"
      },
      "geometry": {
        "type": "Point",
        "coordinates": [
          5.22868,
          50.33284
        ]
      }
    },
    {
      "type": "Feature",
      "properties": {
        "address_id": "295621",
        "box_number": "",
        "house_number": "31B",
        "municipality_id": "91064",
        "municipality_name_de": "",
        "municipality_name_fr": "Havelange",
        "municipality_name_nl": "",
        "postcode": "5370",
        "postname_fr": "",
        "postname_nl": "",
        "street_id": "7749876",
        "streetname_de": "",
        "streetname_fr": "Rue Albert Billy",
        "streetname_nl": "",
        "region_code": "BE-WAL",
        "status": "current"
      },
      "geometry": {
        "type": "Point",
        "coordinates": [
          5.22825,
          50.33271
        ]
      }
    },
    {
      "type": "Feature",
      "properties": {
        "address_id": "304885",
        "box_number": "",
        "house_number": "1",
        "municipality_id": "91064",
        "municipality_name_de": "",
        "municipality_name_fr": "Havelange",
        "municipality_name_nl": "",
        "postcode": "5370",
        "postname_fr": "",
        "postname_nl": "",
        "street_id": "7749828",
        "streetname_de": "",
        "streetname_fr": "Ferme du Bois de Rémont",
        "streetname_nl": "",
        "region_code": "BE-WAL",
        "status": "current"
      },
      "geometry": {
        "type": "Point",
        "coordinates": [
          5.22089,
          50.33882
        ]
      }
    }
  ]
}