{
  "type": "FeatureCollection",
  "features": [
    {
      "type": "Feature",
      "properties": {
        "address_id": "194178",
        "box_number": "",
        "house_number": "1",
        "municipality_id": "83031",
        "municipality_name_de": "",
        "municipality_name_fr": "La Roche-en-Ardenne",
        "municipality_name_nl": "",
        "postcode": "6983",
        "postname_fr": "",
        "postname_nl": "",
        "street_id": "7743891",
        "streetname_de": "",
        "streetname_fr": "Vieux-Château",
        "streetname_nl": "",
        "region_code": "BE-WAL",
        "status": "current"
      },
      "geometry": {
        "type": "Point",
        "coordinates": [
          5.65778,
          50.10585
        ]
      }
    },
    {
      "type": "Feature",
      "properties": {
        "address_id": "1564651",
        "box_number": "0001",
        "house_number": "1",
        "municipality_id": "83031",
        "municipality_name_de": "",
        "municipality_name_fr": "La Roche-en-Ardenne",
        "municipality_name_nl": "",
        "postcode": "6983",
        "postname_fr": "",
        "postname_nl": "",
        "street_id": "7743891",
        "streetname_de": "",
        "streetname_fr": "Vieux-Château",
        "streetname_nl": "",
        "region_code": "BE-WAL",
        "status": "current"
      },
      "geometry": {
        "type": "Point",
        "coordinates": [
          5.65778,
          50.10585
        ]
      }
    }
  ]
}