{
  "type": "FeatureCollection",
  "features": [
    {
      "type": "Feature",
      "properties": {
        "address_id": "288492",
        "box_number": "",
        "house_number": "30",
        "municipality_id": "91034",
        "municipality_name_de": "",
        "municipality_name_fr": "Dinant",
        "municipality_name_nl": "",
        "postcode": "5501",
        "postname_fr": "",
        "postname_nl": "",
        "street_id": "7749113",
        "streetname_de": "",
        "streetname_fr": "Chemin des Massennes",
        "streetname_nl": "",
        "region_code": "BE-WAL",
        "status": "current"
      },
      "geometry": {
        "type": "Point",
        "coordinates": [
          4.94379,
          50.29395
        ]
      }
    },
    {
      "type": "Feature",
      "properties": {
        "address_id": "288501",
        "box_number": "",
        "house_number": "15",
        "municipality_id": "91034",
        "municipality_name_de": "",
        "municipality_name_fr": "Dinant",
        "municipality_name_nl": "",
        "postcode": "5501",
        "postname_fr": "",
        "postname_nl": "",
        "street_id": "7749113",
        "streetname_de": "",
        "streetname_fr": "Chemin des Massennes",
        "streetname_nl": "",
        "region_code": "BE-WAL",
        "status": "current"
      },
      "geometry": {
        "type": "Point",
        "coordinates": [
          4.94304,
          50.29396
        ]
      }
    }
  ]
}