{
  "type": "FeatureCollection",
  "features": [
    {
      "type": "Feature",
      "properties": {
        "address_id": "233265",
        "box_number": "",
        "house_number": "1",
        "municipality_id": "84010",
        "municipality_name_de": "",
        "municipality_name_fr": "Bouillon",
        "municipality_name_nl": "",
        "postcode": "6838",
        "postname_fr": "",
        "postname_nl": "",
        "street_id": "7745103",
        "streetname_de": "",
        "streetname_fr": "Le Ban d'Alle",
        "streetname_nl": "",
        "region_code": "BE-WAL",
        "status": "current"
      },
      "geometry": {
        "type": "Point",
        "coordinates": [
          4.96968,
          49.80398
        ]
      }
    },
    {
      "type": "Feature",
      "properties": {
        "address_id": "233266",
        "box_number": "",
        "house_number": "2",
        "municipality_id": "84010",
        "municipality_name_de": "",
        "municipality_name_fr": "Bouillon",
        "municipality_name_nl": "",
        "postcode": "6838",
        "postname_fr": "",
        "postname_nl": "",
        "street_id": "7745103",
        "streetname_de": "",
        "streetname_fr": "Le Ban d'Alle",
        "streetname_nl": "",
        "region_code": "BE-WAL",
        "status": "current"
      },
      "geometry": {
        "type": "Point",
        "coordinates": [
          4.97033,
          49.80405
        ]
      }
    }
  ]
}