{
  "type": "FeatureCollection",
  "features": [
    {
      "type": "Feature",
      "properties": {
        "address_id": "167918",
        "box_number": "",
        "house_number": "129",
        "municipality_id": "82003",
        "municipality_name_de": "",
        "municipality_name_fr": "Bastogne",
        "municipality_name_nl": "",
        "postcode": "6600",
        "postname_fr": "",
        "postname_nl": "",
        "street_id": "7742338",
        "streetname_de": "",
        "streetname_fr": "Bourcy",
        "streetname_nl": "",
        "region_code": "BE-WAL",
        "status": "current"
      },
      "geometry": {
        "type": "Point",
        "coordinates": [
          5.80029,
          50.06025
        ]
      }
    },
    {
      "type": "Feature",
      "properties": {
        "address_id": "167920",
        "box_number": "",
        "house_number": "130",
        "municipality_id": "82003",
        "municipality_name_de": "",
        "municipality_name_fr": "Bastogne",
        "municipality_name_nl": "",
        "postcode": "6600",
        "postname_fr": "",
        "postname_nl": "",
        "street_id": "7742338",
        "streetname_de": "",
        "streetname_fr": "Bourcy",
        "streetname_nl": "",
        "region_code": "BE-WAL",
        "status": "current"
      },
      "geometry": {
        "type": "Point",
        "coordinates": [
          5.80018,
          50.06092
        ]
      }
    },
    {
      "type": "Feature",
      "properties": {
        "address_id": "167921",
        "box_number": "",
        "house_number": "132",
        "municipality_id": "82003",
        "municipality_name_de": "",
        "municipality_name_fr": "Bastogne",
        "municipality_name_nl": "",
        "postcode": "6600",
        "postname_fr": "",
        "postname_nl": "",
        "street_id": "7742338",
        "streetname_de": "",
        "streetname_fr": "Bourcy",
        "streetname_nl": "",
        "region_code": "BE-WAL",
        "status": "current"
      },
      "geometry": {
        "type": "Point",
        "coordinates": [
          5.80033,
          50.0608
        ]
      }
    },
    {
      "type": "Feature",
      "properties": {
        "address_id": "167924",
        "box_number": "",
        "house_number": "140",
        "municipality_id": "82003",
        "municipality_name_de": "",
        "municipality_name_fr": "Bastogne",
        "municipality_name_nl": "",
        "postcode": "6600",
        "postname_fr": "",
        "postname_nl": "",
        "street_id": "7742338",
        "streetname_de": "",
        "streetname_fr": "Bourcy",
        "streetname_nl": "",
        "region_code": "BE-WAL",
        "status": "current"
      },
      "geometry": {
        "type": "Point",
        "coordinates": [
          5.79893,
          50.06103
        ]
      }
    },
    {
      "type": "Feature",
      "properties": {
        "address_id": "167927",
        "box_number": "",
        "house_number": "148",
        "municipality_id": "82003",
        "municipality_name_de": "",
        "municipality_name_fr": "Bastogne",
        "municipality_name_nl": "",
        "postcode": "6600",
        "postname_fr": "",
        "postname_nl": "",
        "street_id": "7742338",
        "streetname_de": "",
        "streetname_fr": "Bourcy",
        "streetname_nl": "",
        "region_code": "BE-WAL",
        "status": "current"
      },
      "geometry": {
        "type": "Point",
        "coordinates": [
          5.79742,
          50.0613
        ]
      }
    }
  ]
}