{
  "type": "FeatureCollection",
  "features": [
    {
      "type": "Feature",
      "properties": {
        "address_id": "186357",
        "box_number": "",
        "house_number": "37",
        "municipality_id": "82014",
        "municipality_name_de": "",
        "municipality_name_fr": "Houffalize",
        "municipality_name_nl": "",
        "postcode": "6662",
        "postname_fr": "",
        "postname_nl": "",
        "street_id": "7742671",
        "streetname_de": "",
        "streetname_fr": "Boeur",
        "streetname_nl": "",
        "region_code": "BE-WAL",
        "status": "current"
      },
      "geometry": {
        "type": "Point",
        "coordinates": [
          5.83218,
          50.06937
        ]
      }
    }
  ]
}