{
  "type": "FeatureCollection",
  "features": [
    {
      "type": "Feature",
      "properties": {
        "address_id": "219862",
        "box_number": "",
        "house_number": "41",
        "municipality_id": "84009",
        "municipality_name_de": "",
        "municipality_name_fr": "Bertrix",
        "municipality_name_nl": "",
        "postcode": "6880",
        "postname_fr": "",
        "postname_nl": "",
        "street_id": "7744855",
        "streetname_de": "",
        "streetname_fr": "Chernaudame",
        "streetname_nl": "",
        "region_code": "BE-WAL",
        "status": "current"
      },
      "geometry": {
        "type": "Point",
        "coordinates": [
          5.18465,
          49.80941
        ]
      }
    },
    {
      "type": "Feature",
      "properties": {
        "address_id": "219863",
        "box_number": "",
        "house_number": "43",
        "municipality_id": "84009",
        "municipality_name_de": "",
        "municipality_name_fr": "Bertrix",
        "municipality_name_nl": "",
        "postcode": "6880",
        "postname_fr": "",
        "postname_nl": "",
        "street_id": "7744855",
        "streetname_de": "",
        "streetname_fr": "Chernaudame",
        "streetname_nl": "",
        "region_code": "BE-WAL",
        "status": "current"
      },
      "geometry": {
        "type": "Point",
        "coordinates": [
          5.18441,
          49.80904
        ]
      }
    },
    {
      "type": "Feature",
      "properties": {
        "address_id": "219865",
        "box_number": "",
        "house_number": "52",
        "municipality_id": "84009",
        "municipality_name_de": "",
        "municipality_name_fr": "Bertrix",
        "municipality_name_nl": "",
        "postcode": "6880",
        "postname_fr": "",
        "postname_nl": "",
        "street_id": "7744855",
        "streetname_de": "",
        "streetname_fr": "Chernaudame",
        "streetname_nl": "",
        "region_code": "BE-WAL",
        "status": "current"
      },
      "geometry": {
        "type": "Point",
        "coordinates": [
          5.18383,
          49.8085
        ]
      }
    }
  ]
}