{
  "type": "FeatureCollection",
  "features": [
    {
      "type": "Feature",
      "properties": {
        "address_id": "436224",
        "box_number": "",
        "house_number": "151",
        "municipality_id": "93014",
        "municipality_name_de": "",
        "municipality_name_fr": "Couvin",
        "municipality_name_nl": "",
        "postcode": "5660",
        "postname_fr": "",
        "postname_nl": "",
        "street_id": "7756785",
        "streetname_de": "",
        "streetname_fr": "Rue de Cerfontaine",
        "streetname_nl": "",
        "region_code": "BE-WAL",
        "status": "current"
      },
      "geometry": {
        "type": "Point",
        "coordinates": [
          4.41586,
          50.11558
        ]
      }
    }
  ]
}