{
  "type": "FeatureCollection",
  "features": [
    {
      "type": "Feature",
      "properties": {
        "address_id": "163119",
        "box_number": "",
        "house_number": "4",
        "municipality_id": "81013",
        "municipality_name_de": "",
        "municipality_name_fr": "Martelange",
        "municipality_name_nl": "",
        "postcode": "6630",
        "postname_fr": "",
        "postname_nl": "",
        "street_id": "7742153",
        "streetname_de": "",
        "streetname_fr": "La Folie",
        "streetname_nl": "",
        "region_code": "BE-WAL",
        "status": "current"
      },
      "geometry": {
        "type": "Point",
        "coordinates": [
          5.74133,
          49.79491
        ]
      }
    }
  ]
}