{
  "type": "FeatureCollection",
  "features": [
    {
      "type": "Feature",
      "properties": {
        "address_id": "186183",
        "box_number": "",
        "house_number": "38",
        "municipality_id": "82003",
        "municipality_name_de": "",
        "municipality_name_fr": "Bastogne",
        "municipality_name_nl": "",
        "postcode": "6600",
        "postname_fr": "",
        "postname_nl": "",
        "street_id": "7742495",
        "streetname_de": "",
        "streetname_fr": "Vaux",
        "streetname_nl": "",
        "region_code": "BE-WAL",
        "status": "current"
      },
      "geometry": {
        "type": "Point",
        "coordinates": [
          5.75595,
          50.07837
        ]
      }
    },
    {
      "type": "Feature",
      "properties": {
        "address_id": "186210",
        "box_number": "",
        "house_number": "50",
        "municipality_id": "82003",
        "municipality_name_de": "",
        "municipality_name_fr": "Bastogne",
        "municipality_name_nl": "",
        "postcode": "6600",
        "postname_fr": "",
        "postname_nl": "",
        "street_id": "7742495",
        "streetname_de": "",
        "streetname_fr": "Vaux",
        "streetname_nl": "",
        "region_code": "BE-WAL",
        "status": "current"
      },
      "geometry": {
        "type": "Point",
        "coordinates": [
          5.75628,
          50.07875
        ]
      }
    }
  ]
}