{
  "type": "FeatureCollection",
  "features": [
    {
      "type": "Feature",
      "properties": {
        "address_id": "281851",
        "box_number": "",
        "house_number": "7",
        "municipality_id": "91030",
        "municipality_name_de": "",
        "municipality_name_fr": "Ciney",
        "municipality_name_nl": "",
        "postcode": "5590",
        "postname_fr": "",
        "postname_nl": "",
        "street_id": "7748761",
        "streetname_de": "",
        "streetname_fr": "Happe",
        "streetname_nl": "",
        "region_code": "BE-WAL",
        "status": "current"
      },
      "geometry": {
        "type": "Point",
        "coordinates": [
          5.16151,
          50.25517
        ]
      }
    },
    {
      "type": "Feature",
      "properties": {
        "address_id": "281852",
        "box_number": "",
        "house_number": "5",
        "municipality_id": "91030",
        "municipality_name_de": "",
        "municipality_name_fr": "Ciney",
        "municipality_name_nl": "",
        "postcode": "5590",
        "postname_fr": "",
        "postname_nl": "",
        "street_id": "7748761",
        "streetname_de": "",
        "streetname_fr": "Happe",
        "streetname_nl": "",
        "region_code": "BE-WAL",
        "status": "current"
      },
      "geometry": {
        "type": "Point",
        "coordinates": [
          5.16129,
          50.25517
        ]
      }
    },
    {
      "type": "Feature",
      "properties": {
        "address_id": "281853",
        "box_number": "",
        "house_number": "4",
        "municipality_id": "91030",
        "municipality_name_de": "",
        "municipality_name_fr": "Ciney",
        "municipality_name_nl": "",
        "postcode": "5590",
        "postname_fr": "",
        "postname_nl": "",
        "street_id": "7748761",
        "streetname_de": "",
        "streetname_fr": "Happe",
        "streetname_nl": "",
        "region_code": "BE-WAL",
        "status": "current"
      },
      "geometry": {
        "type": "Point",
        "coordinates": [
          5.16126,
          50.25474
        ]
      }
    },
    {
      "type": "Feature",
      "properties": {
        "address_id": "281854",
        "box_number": "",
        "house_number": "3",
        "municipality_id": "91030",
        "municipality_name_de": "",
        "municipality_name_fr": "Ciney",
        "municipality_name_nl": "",
        "postcode": "5590",
        "postname_fr": "",
        "postname_nl": "",
        "street_id": "7748761",
        "streetname_de": "",
        "streetname_fr": "Happe",
        "streetname_nl": "",
        "region_code": "BE-WAL",
        "status": "current"
      },
      "geometry": {
        "type": "Point",
        "coordinates": [
          5.16107,
          50.25517
        ]
      }
    },
    {
      "type": "Feature",
      "properties": {
        "address_id": "281856",
        "box_number": "",
        "house_number": "2A",
        "municipality_id": "91030",
        "municipality_name_de": "",
        "municipality_name_fr": "Ciney",
        "municipality_name_nl": "",
        "postcode": "5590",
        "postname_fr": "",
        "postname_nl": "",
        "street_id": "7748761",
        "streetname_de": "",
        "streetname_fr": "Happe",
        "streetname_nl": "",
        "region_code": "BE-WAL",
        "status": "current"
      },
      "geometry": {
        "type": "Point",
        "coordinates": [
          5.16044,
          50.25507
        ]
      }
    },
    {
      "type": "Feature",
      "properties": {
        "address_id": "282463",
        "box_number": "",
        "house_number": "1",
        "municipality_id": "91030",
        "municipality_name_de": "",
        "municipality_name_fr": "Ciney",
        "municipality_name_nl": "",
        "postcode": "5590",
        "postname_fr": "",
        "postname_nl": "",
        "street_id": "7748894",
        "streetname_de": "",
        "streetname_fr": "Rue de Rochefort",
        "streetname_nl": "",
        "region_code": "BE-WAL",
        "status": "current"
      },
      "geometry": {
        "type": "Point",
        "coordinates": [
          5.15271,
          50.25578
        ]
      }
    }
  ]
}