{
  "type": "FeatureCollection",
  "features": [
    {
      "type": "Feature",
      "properties": {
        "address_id": "203206",
        "box_number": "",
        "house_number": "61",
        "municipality_id": "83034",
        "municipality_name_de": "",
        "municipality_name_fr": "Marche-en-Famenne",
        "municipality_name_nl": "",
        "postcode": "6900",
        "postname_fr": "",
        "postname_nl": "",
        "street_id": "7743991",
        "streetname_de": "",
        "streetname_fr": "Route de Waillet",
        "streetname_nl": "",
        "region_code": "BE-WAL",
        "status": "current"
      },
      "geometry": {
        "type": "Point",
        "coordinates": [
          5.32709,
          50.2492
        ]
      }
    },
    {
      "type": "Feature",
      "properties": {
        "address_id": "203208",
        "box_number": "",
        "house_number": "63",
        "municipality_id": "83034",
        "municipality_name_de": "",
        "municipality_name_fr": "Marche-en-Famenne",
        "municipality_name_nl": "",
        "postcode": "6900",
        "postname_fr": "",
        "postname_nl": "",
        "street_id": "7743991",
        "streetname_de": "",
        "streetname_fr": "Route de Waillet",
        "streetname_nl": "",
        "region_code": "BE-WAL",
        "status": "current"
      },
      "geometry": {
        "type": "Point",
        "coordinates": [
          5.32325,
          50.24843
        ]
      }
    }
  ]
}