{
  "type": "FeatureCollection",
  "features": [
    {
      "type": "Feature",
      "properties": {
        "address_id": "155009",
        "box_number": "",
        "house_number": "74J",
        "municipality_id": "82014",
        "municipality_name_de": "",
        "municipality_name_fr": "Houffalize",
        "municipality_name_nl": "",
        "postcode": "6661",
        "postname_fr": "",
        "postname_nl": "",
        "street_id": "7742751",
        "streetname_de": "",
        "streetname_fr": "Sommerain",
        "streetname_nl": "",
        "region_code": "BE-WAL",
        "status": "current"
      },
      "geometry": {
        "type": "Point",
        "coordinates": [
          5.82366,
          50.15855
        ]
      }
    },
    {
      "type": "Feature",
      "properties": {
        "address_id": "155015",
        "box_number": "",
        "house_number": "76C",
        "municipality_id": "82014",
        "municipality_name_de": "",
        "municipality_name_fr": "Houffalize",
        "municipality_name_nl": "",
        "postcode": "6661",
        "postname_fr": "",
        "postname_nl": "",
        "street_id": "7742751",
        "streetname_de": "",
        "streetname_fr": "Sommerain",
        "streetname_nl": "",
        "region_code": "BE-WAL",
        "status": "current"
      },
      "geometry": {
        "type": "Point",
        "coordinates": [
          5.82454,
          50.15796
        ]
      }
    },
    {
      "type": "Feature",
      "properties": {
        "address_id": "155010",
        "box_number": "",
        "house_number": "74K",
        "municipality_id": "82014",
        "municipality_name_de": "",
        "municipality_name_fr": "Houffalize",
        "municipality_name_nl": "",
        "postcode": "6661",
        "postname_fr": "",
        "postname_nl": "",
        "street_id": "7742751",
        "streetname_de": "",
        "streetname_fr": "Sommerain",
        "streetname_nl": "",
        "region_code": "BE-WAL",
        "status": "current"
      },
      "geometry": {
        "type": "Point",
        "coordinates": [
          5.8242,
          50.15855
        ]
      }
    },
    {
      "type": "Feature",
      "properties": {
        "address_id": "155014",
        "box_number": "",
        "house_number": "76A",
        "municipality_id": "82014",
        "municipality_name_de": "",
        "municipality_name_fr": "Houffalize",
        "municipality_name_nl": "",
        "postcode": "6661",
        "postname_fr": "",
        "postname_nl": "",
        "street_id": "7742751",
        "streetname_de": "",
        "streetname_fr": "Sommerain",
        "streetname_nl": "",
        "region_code": "BE-WAL",
        "status": "current"
      },
      "geometry": {
        "type": "Point",
        "coordinates": [
          5.82297,
          50.1582
        ]
      }
    },
    {
      "type": "Feature",
      "properties": {
        "address_id": "155016",
        "box_number": "",
        "house_number": "76D",
        "municipality_id": "82014",
        "municipality_name_de": "",
        "municipality_name_fr": "Houffalize",
        "municipality_name_nl": "",
        "postcode": "6661",
        "postname_fr": "",
        "postname_nl": "",
        "street_id": "7742751",
        "streetname_de": "",
        "streetname_fr": "Sommerain",
        "streetname_nl": "",
        "region_code": "BE-WAL",
        "status": "current"
      },
      "geometry": {
        "type": "Point",
        "coordinates": [
          5.82496,
          50.1581
        ]
      }
    },
    {
      "type": "Feature",
      "properties": {
        "address_id": "155017",
        "box_number": "",
        "house_number": "77",
        "municipality_id": "82014",
        "municipality_name_de": "",
        "municipality_name_fr": "Houffalize",
        "municipality_name_nl": "",
        "postcode": "6661",
        "postname_fr": "",
        "postname_nl": "",
        "street_id": "7742751",
        "streetname_de": "",
        "streetname_fr": "Sommerain",
        "streetname_nl": "",
        "region_code": "BE-WAL",
        "status": "current"
      },
      "geometry": {
        "type": "Point",
        "coordinates": [
          5.82752,
          50.15905
        ]
      }
    }
  ]
}