{
  "type": "FeatureCollection",
  "features": [
    {
      "type": "Feature",
      "properties": {
        "address_id": "793825",
        "box_number": "",
        "house_number": "99",
        "municipality_id": "56016",
        "municipality_name_de": "",
        "municipality_name_fr": "Chimay",
        "municipality_name_nl": "",
        "postcode": "6464",
        "postname_fr": "",
        "postname_nl": "",
        "street_id": "7720164",
        "streetname_de": "",
        "streetname_fr": "Rue Hauts Marais",
        "streetname_nl": "",
        "region_code": "BE-WAL",
        "status": "current"
      },
      "geometry": {
        "type": "Point",
        "coordinates": [
          4.38921,
          49.97168
        ]
      }
    },
    {
      "type": "Feature",
      "properties": {
        "address_id": "793834",
        "box_number": "",
        "house_number": "101",
        "municipality_id": "56016",
        "municipality_name_de": "",
        "municipality_name_fr": "Chimay",
        "municipality_name_nl": "",
        "postcode": "6464",
        "postname_fr": "",
        "postname_nl": "",
        "street_id": "7720164",
        "streetname_de": "",
        "streetname_fr": "Rue Hauts Marais",
        "streetname_nl": "",
        "region_code": "BE-WAL",
        "status": "current"
      },
      "geometry": {
        "type": "Point",
        "coordinates": [
          4.39416,
          49.97338
        ]
      }
    },
    {
      "type": "Feature",
      "properties": {
        "address_id": "792000",
        "box_number": "",
        "house_number": "28",
        "municipality_id": "56016",
        "municipality_name_de": "",
        "municipality_name_fr": "Chimay",
        "municipality_name_nl": "",
        "postcode": "6464",
        "postname_fr": "",
        "postname_nl": "",
        "street_id": "7719988",
        "streetname_de": "",
        "streetname_fr": "Petit Canton",
        "streetname_nl": "",
        "region_code": "BE-WAL",
        "status": "current"
      },
      "geometry": {
        "type": "Point",
        "coordinates": [
          4.38005,
          49.97674
        ]
      }
    },
    {
      "type": "Feature",
      "properties": {
        "address_id": "794188",
        "box_number": "",
        "house_number": "6",
        "municipality_id": "56016",
        "municipality_name_de": "",
        "municipality_name_fr": "Chimay",
        "municipality_name_nl": "",
        "postcode": "6464",
        "postname_fr": "",
        "postname_nl": "",
        "street_id": "7719972",
        "streetname_de": "",
        "streetname_fr": "Forge Jean Petit",
        "streetname_nl": "",
        "region_code": "BE-WAL",
        "status": "current"
      },
      "geometry": {
        "type": "Point",
        "coordinates": [
          4.38367,
          49.97691
        ]
      }
    }
  ]
}