{
  "type": "FeatureCollection",
  "features": [
    {
      "type": "Feature",
      "properties": {
        "address_id": "1491856",
        "box_number": "",
        "house_number": "89",
        "municipality_id": "63087",
        "municipality_name_de": "Burg-Reuland",
        "municipality_name_fr": "Burg-Reuland",
        "municipality_name_nl": "",
        "postcode": "4790",
        "postname_fr": "",
        "postname_nl": "",
        "street_id": "7763263",
        "streetname_de": "Eichenbuschstraße",
        "streetname_fr": "",
        "streetname_nl": "",
        "region_code": "BE-WAL",
        "status": "current"
      },
      "geometry": {
        "type": "Point",
        "coordinates": [
          6.18652,
          50.18268
        ]
      }
    }
  ]
}