{
  "type": "FeatureCollection",
  "features": [
    {
      "type": "Feature",
      "properties": {
        "address_id": "1409525",
        "box_number": "",
        "house_number": "33",
        "municipality_id": "63086",
        "municipality_name_de": "",
        "municipality_name_fr": "Trois-Ponts",
        "municipality_name_nl": "",
        "postcode": "4980",
        "postname_fr": "",
        "postname_nl": "",
        "street_id": "7739476",
        "streetname_de": "",
        "streetname_fr": "Belle Femme",
        "streetname_nl": "",
        "region_code": "BE-WAL",
        "status": "current"
      },
      "geometry": {
        "type": "Point",
        "coordinates": [
          5.95712,
          50.37114
        ]
      }
    }
  ]
}