{
  "type": "FeatureCollection",
  "features": [
    {
      "type": "Feature",
      "properties": {
        "address_id": "1118252",
        "box_number": "",
        "house_number": "1",
        "municipality_id": "62027",
        "municipality_name_de": "",
        "municipality_name_fr": "Dalhem",
        "municipality_name_nl": "",
        "postcode": "4608",
        "postname_fr": "",
        "postname_nl": "",
        "street_id": "7728391",
        "streetname_de": "",
        "streetname_fr": "Als",
        "streetname_nl": "",
        "region_code": "BE-WAL",
        "status": "current"
      },
      "geometry": {
        "type": "Point",
        "coordinates": [
          5.80693,
          50.72269
        ]
      }
    }
  ]
}