{
  "type": "FeatureCollection",
  "features": [
    {
      "type": "Feature",
      "properties": {
        "address_id": "784000",
        "box_number": "",
        "house_number": "3",
        "municipality_id": "56022",
        "municipality_name_de": "",
        "municipality_name_fr": "Erquelinnes",
        "municipality_name_nl": "",
        "postcode": "6560",
        "postname_fr": "",
        "postname_nl": "",
        "street_id": "7720331",
        "streetname_de": "",
        "streetname_fr": "Rue du Petit Binche",
        "streetname_nl": "",
        "region_code": "BE-WAL",
        "status": "current"
      },
      "geometry": {
        "type": "Point",
        "coordinates": [
          4.05351,
          50.33538
        ]
      }
    },
    {
      "type": "Feature",
      "properties": {
        "address_id": "784001",
        "box_number": "",
        "house_number": "1",
        "municipality_id": "56022",
        "municipality_name_de": "",
        "municipality_name_fr": "Erquelinnes",
        "municipality_name_nl": "",
        "postcode": "6560",
        "postname_fr": "",
        "postname_nl": "",
        "street_id": "7720331",
        "streetname_de": "",
        "streetname_fr": "Rue du Petit Binche",
        "streetname_nl": "",
        "region_code": "BE-WAL",
        "status": "current"
      },
      "geometry": {
        "type": "Point",
        "coordinates": [
          4.05357,
          50.33555
        ]
      }
    }
  ]
}