{
  "type": "FeatureCollection",
  "features": [
    {
      "type": "Feature",
      "properties": {
        "address_id": "1838807",
        "box_number": "",
        "house_number": "2",
        "municipality_id": "91054",
        "municipality_name_de": "",
        "municipality_name_fr": "Gedinne",
        "municipality_name_nl": "",
        "postcode": "5575",
        "postname_fr": "",
        "postname_nl": "",
        "street_id": "7749576",
        "streetname_de": "",
        "streetname_fr": "Rue du Bochetay",
        "streetname_nl": "",
        "region_code": "BE-WAL",
        "status": "current"
      },
      "geometry": {
        "type": "Point",
        "coordinates": [
          4.95493,
          49.93658
        ]
      }
    },
    {
      "type": "Feature",
      "properties": {
        "address_id": "1517525",
        "box_number": "",
        "house_number": "55",
        "municipality_id": "91054",
        "municipality_name_de": "",
        "municipality_name_fr": "Gedinne",
        "municipality_name_nl": "",
        "postcode": "5575",
        "postname_fr": "",
        "postname_nl": "",
        "street_id": "7749426",
        "streetname_de": "",
        "streetname_fr": "Chemin de Merreau",
        "streetname_nl": "",
        "region_code": "BE-WAL",
        "status": "current"
      },
      "geometry": {
        "type": "Point",
        "coordinates": [
          4.94615,
          49.93138
        ]
      }
    },
    {
      "type": "Feature",
      "properties": {
        "address_id": "1517518",
        "box_number": "",
        "house_number": "5",
        "municipality_id": "91054",
        "municipality_name_de": "",
        "municipality_name_fr": "Gedinne",
        "municipality_name_nl": "",
        "postcode": "5575",
        "postname_fr": "",
        "postname_nl": "",
        "street_id": "7749426",
        "streetname_de": "",
        "streetname_fr": "Chemin de Merreau",
        "streetname_nl": "",
        "region_code": "BE-WAL",
        "status": "current"
      },
      "geometry": {
        "type": "Point",
        "coordinates": [
          4.94464,
          49.93421
        ]
      }
    }
  ]
}