{
  "type": "FeatureCollection",
  "features": [
    {
      "type": "Feature",
      "properties": {
        "address_id": "238819",
        "box_number": "",
        "house_number": "2",
        "municipality_id": "84033",
        "municipality_name_de": "",
        "municipality_name_fr": "Léglise",
        "municipality_name_nl": "",
        "postcode": "6860",
        "postname_fr": "",
        "postname_nl": "",
        "street_id": "7745475",
        "streetname_de": "",
        "streetname_fr": "Les Forges",
        "streetname_nl": "",
        "region_code": "BE-WAL",
        "status": "current"
      },
      "geometry": {
        "type": "Point",
        "coordinates": [
          5.52298,
          49.75215
        ]
      }
    },
    {
      "type": "Feature",
      "properties": {
        "address_id": "238820",
        "box_number": "",
        "house_number": "4",
        "municipality_id": "84033",
        "municipality_name_de": "",
        "municipality_name_fr": "Léglise",
        "municipality_name_nl": "",
        "postcode": "6860",
        "postname_fr": "",
        "postname_nl": "",
        "street_id": "7745475",
        "streetname_de": "",
        "streetname_fr": "Les Forges",
        "streetname_nl": "",
        "region_code": "BE-WAL",
        "status": "current"
      },
      "geometry": {
        "type": "Point",
        "coordinates": [
          5.52744,
          49.74489
        ]
      }
    }
  ]
}