{
  "type": "FeatureCollection",
  "features": [
    {
      "type": "Feature",
      "properties": {
        "address_id": "227490",
        "box_number": "",
        "house_number": "90",
        "municipality_id": "84077",
        "municipality_name_de": "",
        "municipality_name_fr": "Libramont-Chevigny",
        "municipality_name_nl": "",
        "postcode": "6800",
        "postname_fr": "",
        "postname_nl": "",
        "street_id": "7746818",
        "streetname_de": "",
        "streetname_fr": "Rue du Patronage",
        "streetname_nl": "",
        "region_code": "BE-WAL",
        "status": "current"
      },
      "geometry": {
        "type": "Point",
        "coordinates": [
          5.40114,
          49.96531
        ]
      }
    },
    {
      "type": "Feature",
      "properties": {
        "address_id": "227492",
        "box_number": "",
        "house_number": "94",
        "municipality_id": "84077",
        "municipality_name_de": "",
        "municipality_name_fr": "Libramont-Chevigny",
        "municipality_name_nl": "",
        "postcode": "6800",
        "postname_fr": "",
        "postname_nl": "",
        "street_id": "7746818",
        "streetname_de": "",
        "streetname_fr": "Rue du Patronage",
        "streetname_nl": "",
        "region_code": "BE-WAL",
        "status": "current"
      },
      "geometry": {
        "type": "Point",
        "coordinates": [
          5.40112,
          49.96521
        ]
      }
    },
    {
      "type": "Feature",
      "properties": {
        "address_id": "227493",
        "box_number": "",
        "house_number": "98",
        "municipality_id": "84077",
        "municipality_name_de": "",
        "municipality_name_fr": "Libramont-Chevigny",
        "municipality_name_nl": "",
        "postcode": "6800",
        "postname_fr": "",
        "postname_nl": "",
        "street_id": "7746818",
        "streetname_de": "",
        "streetname_fr": "Rue du Patronage",
        "streetname_nl": "",
        "region_code": "BE-WAL",
        "status": "current"
      },
      "geometry": {
        "type": "Point",
        "coordinates": [
          5.40113,
          49.96481
        ]
      }
    }
  ]
}