{
  "type": "FeatureCollection",
  "features": [
    {
      "type": "Feature",
      "properties": {
        "address_id": "1326281",
        "box_number": "",
        "house_number": "241",
        "municipality_id": "63023",
        "municipality_name_de": "Eupen",
        "municipality_name_fr": "Eupen",
        "municipality_name_nl": "",
        "postcode": "4700",
        "postname_fr": "",
        "postname_nl": "",
        "street_id": "7735896",
        "streetname_de": "Schönefelderweg",
        "streetname_fr": "",
        "streetname_nl": "",
        "region_code": "BE-WAL",
        "status": "current"
      },
      "geometry": {
        "type": "Point",
        "coordinates": [
          6.10734,
          50.63032
        ]
      }
    }
  ]
}