{
  "type": "FeatureCollection",
  "features": [
    {
      "type": "Feature",
      "properties": {
        "address_id": "800436",
        "box_number": "",
        "house_number": "33",
        "municipality_id": "56029",
        "municipality_name_de": "",
        "municipality_name_fr": "Froidchapelle",
        "municipality_name_nl": "",
        "postcode": "6440",
        "postname_fr": "",
        "postname_nl": "",
        "street_id": "7720425",
        "streetname_de": "",
        "streetname_fr": "Rue de Mariembourg",
        "streetname_nl": "",
        "region_code": "BE-WAL",
        "status": "current"
      },
      "geometry": {
        "type": "Point",
        "coordinates": [
          4.34891,
          50.12034
        ]
      }
    },
    {
      "type": "Feature",
      "properties": {
        "address_id": "789078",
        "box_number": "",
        "house_number": "12C",
        "municipality_id": "56016",
        "municipality_name_de": "",
        "municipality_name_fr": "Chimay",
        "municipality_name_nl": "",
        "postcode": "6461",
        "postname_fr": "",
        "postname_nl": "",
        "street_id": "7719942",
        "streetname_de": "",
        "streetname_fr": "Bois de Virelles",
        "streetname_nl": "",
        "region_code": "BE-WAL",
        "status": "current"
      },
      "geometry": {
        "type": "Point",
        "coordinates": [
          4.3332,
          50.11844
        ]
      }
    },
    {
      "type": "Feature",
      "properties": {
        "address_id": "789079",
        "box_number": "",
        "house_number": "12B",
        "municipality_id": "56016",
        "municipality_name_de": "",
        "municipality_name_fr": "Chimay",
        "municipality_name_nl": "",
        "postcode": "6461",
        "postname_fr": "",
        "postname_nl": "",
        "street_id": "7719942",
        "streetname_de": "",
        "streetname_fr": "Bois de Virelles",
        "streetname_nl": "",
        "region_code": "BE-WAL",
        "status": "current"
      },
      "geometry": {
        "type": "Point",
        "coordinates": [
          4.33292,
          50.11829
        ]
      }
    },
    {
      "type": "Feature",
      "properties": {
        "address_id": "789080",
        "box_number": "",
        "house_number": "12A",
        "municipality_id": "56016",
        "municipality_name_de": "",
        "municipality_name_fr": "Chimay",
        "municipality_name_nl": "",
        "postcode": "6461",
        "postname_fr": "",
        "postname_nl": "",
        "street_id": "7719942",
        "streetname_de": "",
        "streetname_fr": "Bois de Virelles",
        "streetname_nl": "",
        "region_code": "BE-WAL",
        "status": "current"
      },
      "geometry": {
        "type": "Point",
        "coordinates": [
          4.33292,
          50.11829
        ]
      }
    },
    {
      "type": "Feature",
      "properties": {
        "address_id": "789081",
        "box_number": "",
        "house_number": "12",
        "municipality_id": "56016",
        "municipality_name_de": "",
        "municipality_name_fr": "Chimay",
        "municipality_name_nl": "",
        "postcode": "6461",
        "postname_fr": "",
        "postname_nl": "",
        "street_id": "7719942",
        "streetname_de": "",
        "streetname_fr": "Bois de Virelles",
        "streetname_nl": "",
        "region_code": "BE-WAL",
        "status": "current"
      },
      "geometry": {
        "type": "Point",
        "coordinates": [
          4.33292,
          50.11868
        ]
      }
    }
  ]
}