{
  "type": "FeatureCollection",
  "features": [
    {
      "type": "Feature",
      "properties": {
        "address_id": "226532",
        "box_number": "",
        "house_number": "2",
        "municipality_id": "84077",
        "municipality_name_de": "",
        "municipality_name_fr": "Libramont-Chevigny",
        "municipality_name_nl": "",
        "postcode": "6800",
        "postname_fr": "",
        "postname_nl": "",
        "street_id": "7746675",
        "streetname_de": "",
        "streetname_fr": "Ferme de la Cannetière",
        "streetname_nl": "",
        "region_code": "BE-WAL",
        "status": "current"
      },
      "geometry": {
        "type": "Point",
        "coordinates": [
          5.43859,
          49.98182
        ]
      }
    },
    {
      "type": "Feature",
      "properties": {
        "address_id": "226579",
        "box_number": "",
        "house_number": "27",
        "municipality_id": "84077",
        "municipality_name_de": "",
        "municipality_name_fr": "Libramont-Chevigny",
        "municipality_name_nl": "",
        "postcode": "6800",
        "postname_fr": "",
        "postname_nl": "",
        "street_id": "7746765",
        "streetname_de": "",
        "streetname_fr": "Rue de la Fange du Loup",
        "streetname_nl": "",
        "region_code": "BE-WAL",
        "status": "current"
      },
      "geometry": {
        "type": "Point",
        "coordinates": [
          5.44463,
          49.98775
        ]
      }
    }
  ]
}