{
  "type": "FeatureCollection",
  "features": [
    {
      "type": "Feature",
      "properties": {
        "address_id": "219965",
        "box_number": "",
        "house_number": "36",
        "municipality_id": "83040",
        "municipality_name_de": "",
        "municipality_name_fr": "Nassogne",
        "municipality_name_nl": "",
        "postcode": "6952",
        "postname_fr": "",
        "postname_nl": "",
        "street_id": "7744281",
        "streetname_de": "",
        "streetname_fr": "Chemin du Bois de Grune",
        "streetname_nl": "",
        "region_code": "BE-WAL",
        "status": "current"
      },
      "geometry": {
        "type": "Point",
        "coordinates": [
          5.40186,
          50.13199
        ]
      }
    },
    {
      "type": "Feature",
      "properties": {
        "address_id": "219966",
        "box_number": "",
        "house_number": "38",
        "municipality_id": "83040",
        "municipality_name_de": "",
        "municipality_name_fr": "Nassogne",
        "municipality_name_nl": "",
        "postcode": "6952",
        "postname_fr": "",
        "postname_nl": "",
        "street_id": "7744281",
        "streetname_de": "",
        "streetname_fr": "Chemin du Bois de Grune",
        "streetname_nl": "",
        "region_code": "BE-WAL",
        "status": "current"
      },
      "geometry": {
        "type": "Point",
        "coordinates": [
          5.40106,
          50.13164
        ]
      }
    }
  ]
}