{
  "type": "FeatureCollection",
  "features": [
    {
      "type": "Feature",
      "properties": {
        "address_id": "602075",
        "box_number": "",
        "house_number": "1",
        "municipality_id": "53046",
        "municipality_name_de": "",
        "municipality_name_fr": "Lens",
        "municipality_name_nl": "",
        "postcode": "7870",
        "postname_fr": "",
        "postname_nl": "",
        "street_id": "7712899",
        "streetname_de": "",
        "streetname_fr": "Chemin Saint-Donat",
        "streetname_nl": "",
        "region_code": "BE-WAL",
        "status": "current"
      },
      "geometry": {
        "type": "Point",
        "coordinates": [
          3.9399,
          50.5534
        ]
      }
    },
    {
      "type": "Feature",
      "properties": {
        "address_id": "586836",
        "box_number": "",
        "house_number": "10",
        "municipality_id": "53044",
        "municipality_name_de": "",
        "municipality_name_fr": "Jurbise",
        "municipality_name_nl": "",
        "postcode": "7050",
        "postname_fr": "",
        "postname_nl": "",
        "street_id": "7712808",
        "streetname_de": "",
        "streetname_fr": "Rue des Hauts Arbres",
        "streetname_nl": "",
        "region_code": "BE-WAL",
        "status": "current"
      },
      "geometry": {
        "type": "Point",
        "coordinates": [
          3.93365,
          50.54265
        ]
      }
    },
    {
      "type": "Feature",
      "properties": {
        "address_id": "600138",
        "box_number": "",
        "house_number": "11",
        "municipality_id": "53046",
        "municipality_name_de": "",
        "municipality_name_fr": "Lens",
        "municipality_name_nl": "",
        "postcode": "7870",
        "postname_fr": "",
        "postname_nl": "",
        "street_id": "7712999",
        "streetname_de": "",
        "streetname_fr": "Rue Val de la Marquette",
        "streetname_nl": "",
        "region_code": "BE-WAL",
        "status": "current"
      },
      "geometry": {
        "type": "Point",
        "coordinates": [
          3.94888,
          50.55469
        ]
      }
    },
    {
      "type": "Feature",
      "properties": {
        "address_id": "599519",
        "box_number": "",
        "house_number": "3",
        "municipality_id": "53046",
        "municipality_name_de": "",
        "municipality_name_fr": "Lens",
        "municipality_name_nl": "",
        "postcode": "7870",
        "postname_fr": "",
        "postname_nl": "",
        "street_id": "7712907",
        "streetname_de": "",
        "streetname_fr": "Pavé de Saint-Pierre",
        "streetname_nl": "",
        "region_code": "BE-WAL",
        "status": "current"
      },
      "geometry": {
        "type": "Point",
        "coordinates": [
          3.95063,
          50.55406
        ]
      }
    }
  ]
}