{
  "type": "FeatureCollection",
  "features": [
    {
      "type": "Feature",
      "properties": {
        "address_id": "461704",
        "box_number": "",
        "house_number": "105",
        "municipality_id": "93056",
        "municipality_name_de": "",
        "municipality_name_fr": "Philippeville",
        "municipality_name_nl": "",
        "postcode": "5600",
        "postname_fr": "",
        "postname_nl": "",
        "street_id": "7757613",
        "streetname_de": "",
        "streetname_fr": "Rue du Fraity",
        "streetname_nl": "",
        "region_code": "BE-WAL",
        "status": "current"
      },
      "geometry": {
        "type": "Point",
        "coordinates": [
          4.51265,
          50.12702
        ]
      }
    }
  ]
}