{
  "type": "FeatureCollection",
  "features": [
    {
      "type": "Feature",
      "properties": {
        "address_id": "273266",
        "box_number": "",
        "house_number": "1",
        "municipality_id": "85045",
        "municipality_name_de": "",
        "municipality_name_fr": "Virton",
        "municipality_name_nl": "",
        "postcode": "6760",
        "postname_fr": "",
        "postname_nl": "",
        "street_id": "7747801",
        "streetname_de": "",
        "streetname_fr": "Rue de Bar",
        "streetname_nl": "",
        "region_code": "BE-WAL",
        "status": "current"
      },
      "geometry": {
        "type": "Point",
        "coordinates": [
          5.58475,
          49.61498
        ]
      }
    },
    {
      "type": "Feature",
      "properties": {
        "address_id": "273271",
        "box_number": "",
        "house_number": "6",
        "municipality_id": "85045",
        "municipality_name_de": "",
        "municipality_name_fr": "Virton",
        "municipality_name_nl": "",
        "postcode": "6760",
        "postname_fr": "",
        "postname_nl": "",
        "street_id": "7747801",
        "streetname_de": "",
        "streetname_fr": "Rue de Bar",
        "streetname_nl": "",
        "region_code": "BE-WAL",
        "status": "current"
      },
      "geometry": {
        "type": "Point",
        "coordinates": [
          5.58367,
          49.61976
        ]
      }
    },
    {
      "type": "Feature",
      "properties": {
        "address_id": "273272",
        "box_number": "",
        "house_number": "7",
        "municipality_id": "85045",
        "municipality_name_de": "",
        "municipality_name_fr": "Virton",
        "municipality_name_nl": "",
        "postcode": "6760",
        "postname_fr": "",
        "postname_nl": "",
        "street_id": "7747801",
        "streetname_de": "",
        "streetname_fr": "Rue de Bar",
        "streetname_nl": "",
        "region_code": "BE-WAL",
        "status": "current"
      },
      "geometry": {
        "type": "Point",
        "coordinates": [
          5.58955,
          49.62445
        ]
      }
    },
    {
      "type": "Feature",
      "properties": {
        "address_id": "273269",
        "box_number": "",
        "house_number": "4",
        "municipality_id": "85045",
        "municipality_name_de": "",
        "municipality_name_fr": "Virton",
        "municipality_name_nl": "",
        "postcode": "6760",
        "postname_fr": "",
        "postname_nl": "",
        "street_id": "7747801",
        "streetname_de": "",
        "streetname_fr": "Rue de Bar",
        "streetname_nl": "",
        "region_code": "BE-WAL",
        "status": "current"
      },
      "geometry": {
        "type": "Point",
        "coordinates": [
          5.58444,
          49.6151
        ]
      }
    },
    {
      "type": "Feature",
      "properties": {
        "address_id": "273268",
        "box_number": "",
        "house_number": "2",
        "municipality_id": "85045",
        "municipality_name_de": "",
        "municipality_name_fr": "Virton",
        "municipality_name_nl": "",
        "postcode": "6760",
        "postname_fr": "",
        "postname_nl": "",
        "street_id": "7747801",
        "streetname_de": "",
        "streetname_fr": "Rue de Bar",
        "streetname_nl": "",
        "region_code": "BE-WAL",
        "status": "current"
      },
      "geometry": {
        "type": "Point",
        "coordinates": [
          5.58471,
          49.61547
        ]
      }
    }
  ]
}