{
  "type": "FeatureCollection",
  "features": [
    {
      "type": "Feature",
      "properties": {
        "check_user": null,
        "reasons": [
          {
            "id": 40,
            "name": "New mapper"
          }
        ],
        "tags": [],
        "features": [],
        "user": "Botschfter",
        "uid": "12456299",
        "editor": "MapComplete 0.8.1",
        "comment": "Adding data with #MapComplete for theme #hailhydrant",
        "comments_count": 0,
        "source": "Not reported",
        "imagery_used": "Not reported",
        "date": "2021-06-26T06:37:56Z",
        "reviewed_features": [],
        "create": 0,
        "modify": 4,
        "delete": 0,
        "area": 0,
        "is_suspect": true,
        "harmful": null,
        "checked": false,
        "check_date": null,
        "metadata": {
          "host": "pietervdvn.github.io",
          "path": "mc/develop/",
          "theme": "hailhydrant",
          "imagery": "HDM_HOT",
          "language": "en",
          "theme-creator": "Erwin Olario"
        }
      },
      "geometry": {
        "type": "Point",
        "coordinates": [
          8.0934908,
          50.4049327
        ]
      }
    }
  ]
}