{
  "type": "FeatureCollection",
  "features": [
    {
      "type": "Feature",
      "properties": {
        "check_user": null,
        "reasons": [],
        "tags": [],
        "features": [],
        "user": "chimel38",
        "uid": "148831",
        "editor": "MapComplete 0.10.6",
        "comment": "Adding data with #MapComplete for theme #hailhydrant",
        "comments_count": 0,
        "source": "Not reported",
        "imagery_used": "Not reported",
        "date": "2021-10-18T06:57:06Z",
        "reviewed_features": [],
        "create": 0,
        "modify": 1,
        "delete": 0,
        "area": 0,
        "is_suspect": false,
        "harmful": null,
        "checked": false,
        "check_date": null,
        "id": 112637945,
        "host": "mapcomplete.osm.be",
        "theme": "hailhydrant",
        "imagery": "HDM_HOT",
        "language": "en",
        "theme-creator": "Erwin Olario"
      },
      "geometry": {
        "type": "Point",
        "coordinates": [
          5.616621,
          44.827888
        ]
      }
    },
    {
      "type": "Feature",
      "properties": {
        "check_user": null,
        "reasons": [
          {
            "id": 40,
            "name": "New mapper"
          }
        ],
        "tags": [],
        "features": [],
        "user": "emilinfrance",
        "uid": "14568184",
        "editor": "MapComplete 0.12.13",
        "comment": "Adding data with #MapComplete for theme #shops",
        "comments_count": 0,
        "source": "Not reported",
        "imagery_used": "Not reported",
        "date": "2021-12-29T19:51:11Z",
        "reviewed_features": [],
        "create": 0,
        "modify": 8,
        "delete": 0,
        "area": 0.00000752628239999239,
        "is_suspect": true,
        "harmful": null,
        "checked": false,
        "check_date": null,
        "id": 115535515,
        "host": "mapcomplete.osm.be",
        "theme": "shops",
        "answer": 9,
        "imagery": "osm",
        "language": "en"
      },
      "geometry": {
        "type": "Point",
        "coordinates": [
          5.3802349,
          44.485122700000005
        ]
      }
    },
    {
      "type": "Feature",
      "properties": {
        "check_user": null,
        "reasons": [],
        "tags": [],
        "features": [],
        "user": "joost schouppe",
        "uid": "67832",
        "editor": "MapComplete 0.5.12",
        "comment": "Adding data with #MapComplete for theme #campersite",
        "comments_count": 0,
        "source": "survey",
        "imagery_used": "Not reported",
        "date": "2021-03-15T18:31:26Z",
        "reviewed_features": [],
        "create": 0,
        "modify": 4,
        "delete": 0,
        "area": 8.10745300004477e-7,
        "is_suspect": false,
        "harmful": null,
        "checked": false,
        "check_date": null,
        "id": 101069649,
        "host": "mapcomplete.osm.be",
        "theme": "campersite",
        "imagery": "osm",
        "language": "en",
        "theme-creator": "joost schouppe"
      },
      "geometry": {
        "type": "Point",
        "coordinates": [
          4.55219895,
          44.3052706
        ]
      }
    },
    {
      "type": "Feature",
      "properties": {
        "check_user": null,
        "reasons": [
          {
            "id": 40,
            "name": "New mapper"
          }
        ],
        "tags": [],
        "features": [],
        "user": "coalins",
        "uid": "13318098",
        "editor": "MapComplete 0.7.2",
        "comment": "Adding data with #MapComplete for theme #aed",
        "comments_count": 0,
        "source": "Not reported",
        "imagery_used": "Not reported",
        "date": "2021-05-13T10:12:54Z",
        "reviewed_features": [],
        "create": 2,
        "modify": 5,
        "delete": 0,
        "area": 2.60725704031522,
        "is_suspect": true,
        "harmful": null,
        "checked": false,
        "check_date": null,
        "id": 104627844,
        "host": "pietervdvn.github.io",
        "theme": "aed",
        "imagery": "osm",
        "language": "fr",
        "theme-creator": "MapComplete"
      },
      "geometry": {
        "type": "Point",
        "coordinates": [
          4.6307239000000004,
          44.17029475
        ]
      }
    }
  ]
}