{
  "type": "FeatureCollection",
  "features": [
    {
      "type": "Feature",
      "properties": {
        "check_user": null,
        "reasons": [
          {
            "id": 40,
            "name": "New mapper"
          }
        ],
        "tags": [],
        "features": [],
        "user": "stebnu",
        "uid": "20452786",
        "editor": "MapComplete 0.33.7",
        "comment": "Adding data with #MapComplete for theme #maxspeed",
        "comments_count": 0,
        "source": "Not reported",
        "imagery_used": "Not reported",
        "date": "2023-10-11T19:12:51Z",
        "reviewed_features": [],
        "tag_changes": {
          "highway": [
            "unclassified"
          ],
          "maxspeed": [
            "45mph"
          ]
        },
        "create": 0,
        "modify": 1,
        "delete": 0,
        "area": 0.00041776490799995,
        "is_suspect": true,
        "harmful": null,
        "checked": false,
        "check_date": null,
        "host": "https://mapcomplete.org/maxspeed.html",
        "theme": "maxspeed",
        "answer": 1,
        "locale": "en",
        "id": 142449697
      },
      "geometry": {
        "type": "Point",
        "coordinates": [
          35.409709,
          -85.24888849999999
        ]
      },
      "id": 142449697
    }
  ]
}