{
  "type": "FeatureCollection",
  "features": [
    {
      "type": "Feature",
      "properties": {
        "check_user": null,
        "reasons": [],
        "tags": [],
        "features": [],
        "user": "NaanAvanIllai",
        "uid": "14062769",
        "editor": "MapComplete 0.27.1",
        "comment": "Adding data with #MapComplete for theme #etymology",
        "comments_count": 0,
        "source": "Not reported",
        "imagery_used": "Not reported",
        "date": "2023-05-01T04:09:02Z",
        "reviewed_features": [],
        "tag_changes": {
          "leisure": [
            "park"
          ],
          "name:etymology:wikidata": [
            "Q684845",
            "Q156347"
          ]
        },
        "create": 0,
        "modify": 31,
        "delete": 0,
        "area": 403.519964872274,
        "is_suspect": false,
        "harmful": null,
        "checked": false,
        "check_date": null,
        "host": "https://mapcomplete.osm.be/etymology.html",
        "theme": "etymology",
        "answer": 33,
        "locale": "en",
        "imagery": "osm",
        "id": 135558724
      },
      "geometry": {
        "type": "Point",
        "coordinates": [
          82.28423395,
          23.613047350000002
        ]
      },
      "id": 135558724
    }
  ]
}