{
  "type": "FeatureCollection",
  "features": [
    {
      "type": "Feature",
      "properties": {
        "check_user": null,
        "reasons": [],
        "tags": [],
        "features": [],
        "user": "NaanAvanIllai",
        "uid": "14062769",
        "editor": "MapComplete 0.36.9",
        "comment": "Adding data with #MapComplete for theme #etymology",
        "comments_count": 0,
        "source": "Not reported",
        "imagery_used": "Not reported",
        "date": "2024-01-05T17:45:45Z",
        "reviewed_features": [],
        "tag_changes": {
          "amenity": [
            "college"
          ],
          "highway": [
            "tertiary",
            "residential"
          ],
          "name:etymology:wikidata": [
            "Q134160",
            "Q2375435",
            "Q5619976",
            "Q124151136",
            "Q65217843",
            "Q8018468",
            "Q47478",
            "Q231690"
          ]
        },
        "create": 0,
        "modify": 32,
        "delete": 0,
        "area": 295.563676880027,
        "is_suspect": false,
        "harmful": null,
        "checked": false,
        "check_date": null,
        "host": "https://mapcomplete.org/etymology",
        "theme": "etymology",
        "answer": 32,
        "locale": "en",
        "id": 145931781
      },
      "geometry": {
        "type": "Point",
        "coordinates": [
          81.1216046,
          19.78644685
        ]
      },
      "id": 145931781
    },
    {
      "type": "Feature",
      "properties": {
        "check_user": null,
        "reasons": [
          {
            "id": 531,
            "name": "Mapbox: Overlapping features"
          }
        ],
        "tags": [],
        "features": [
          {
            "url": "way-211659217",
            "note": "Overlapping features reported in [\"name\",\"name:etymology:wikidata\"] tags in the feature",
            "osm_id": 211659217,
            "reasons": [
              531
            ],
            "version": 4
          }
        ],
        "user": "NaanAvanIllai",
        "uid": "14062769",
        "editor": "MapComplete 0.36.9",
        "comment": "Adding data with #MapComplete for theme #etymology",
        "comments_count": 0,
        "source": "Not reported",
        "imagery_used": "Not reported",
        "date": "2024-01-06T05:35:01Z",
        "reviewed_features": [],
        "tag_changes": {
          "power": [
            "line"
          ],
          "amenity": [
            "school"
          ],
          "highway": [
            "residential",
            "unclassified",
            "tertiary",
            "secondary",
            "trunk",
            "living_street"
          ],
          "leisure": [
            "park"
          ],
          "boundary": [
            "administrative"
          ],
          "building": [
            "yes",
            "commercial"
          ],
          "waterway": [
            "stream",
            "canal"
          ],
          "name:etymology:wikidata": [
            "Q984634",
            "Q138765",
            "Q522048",
            "Q127868",
            "Q734509",
            "Q2353373",
            "Q7117382",
            "Q492527",
            "Q3351697",
            "Q9513",
            "Q1149"
          ]
        },
        "create": 0,
        "modify": 154,
        "delete": 0,
        "area": 337.662128147009,
        "is_suspect": true,
        "harmful": null,
        "checked": false,
        "check_date": null,
        "host": "https://mapcomplete.org/etymology",
        "theme": "etymology",
        "answer": 156,
        "locale": "en",
        "id": 145945011
      },
      "geometry": {
        "type": "Point",
        "coordinates": [
          81.0091023,
          20.68816745
        ]
      },
      "id": 145945011
    }
  ]
}