{
  "type": "FeatureCollection",
  "features": [
    {
      "type": "Feature",
      "properties": {
        "check_user": null,
        "reasons": [
          {
            "id": 40,
            "name": "New mapper"
          }
        ],
        "tags": [],
        "features": [],
        "user": "SAEMS09",
        "uid": "15140872",
        "editor": "MapComplete 0.16.3",
        "comment": "Adding data with #MapComplete for theme #hailhydrant",
        "comments_count": 0,
        "source": "Not reported",
        "imagery_used": "Not reported",
        "date": "2022-02-24T22:20:58Z",
        "reviewed_features": [],
        "tag_changes": {},
        "create": 4,
        "modify": 6,
        "delete": 0,
        "area": 0.0929881394560803,
        "is_suspect": true,
        "harmful": null,
        "checked": false,
        "check_date": null,
        "host": "mapcomplete.osm.be",
        "theme": "hailhydrant",
        "answer": 10,
        "locale": "en",
        "imagery": "Mapbox",
        "id": 117829610
      },
      "geometry": {
        "type": "Point",
        "coordinates": [
          39.9161975,
          -78.4818488
        ]
      },
      "id": 117829610
    },
    {
      "type": "Feature",
      "properties": {
        "check_user": null,
        "reasons": [],
        "tags": [],
        "features": [],
        "user": "rpjjpr",
        "uid": "7507995",
        "editor": "MapComplete 0.31.2",
        "comment": "Adding data with #MapComplete for theme #nature",
        "comments_count": 0,
        "source": "Not reported",
        "imagery_used": "Not reported",
        "date": "2023-08-17T19:01:34Z",
        "reviewed_features": [],
        "tag_changes": {
          "dog": [
            "leashed"
          ],
          "access": [
            "yes"
          ],
          "leisure": [
            "nature_reserve"
          ],
          "boundary": [
            "protected_area"
          ]
        },
        "create": 0,
        "modify": 2,
        "delete": 0,
        "area": 0.0106254192810608,
        "is_suspect": false,
        "harmful": null,
        "checked": false,
        "check_date": null,
        "host": "https://mapcomplete.osm.be/nature.html",
        "theme": "nature",
        "answer": 3,
        "locale": "en-US",
        "id": 140027498
      },
      "geometry": {
        "type": "Point",
        "coordinates": [
          41.13803905,
          -78.5875433
        ]
      },
      "id": 140027498
    }
  ]
}