{
  "type": "FeatureCollection",
  "features": [
    {
      "type": "Feature",
      "properties": {
        "check_user": null,
        "reasons": [
          {
            "id": 4,
            "name": "mass modification"
          }
        ],
        "tags": [],
        "features": [],
        "user": "NaanAvanIllai",
        "uid": "14062769",
        "editor": "MapComplete 0.22.1",
        "comment": "Adding data with #MapComplete for theme #etymology",
        "comments_count": 0,
        "source": "Not reported",
        "imagery_used": "Not reported",
        "date": "2022-07-04T17:28:22Z",
        "reviewed_features": [],
        "tag_changes": {},
        "create": 0,
        "modify": 252,
        "delete": 0,
        "area": 392.244674736266,
        "is_suspect": true,
        "harmful": null,
        "checked": false,
        "check_date": null,
        "host": "https://mapcomplete.osm.be/etymology.html",
        "theme": "etymology",
        "answer": 327,
        "locale": "en",
        "imagery": "osm",
        "id": 123201433
      },
      "geometry": {
        "type": "Point",
        "coordinates": [
          19.44209135,
          79.4121288
        ]
      },
      "id": 123201433
    },
    {
      "type": "Feature",
      "properties": {
        "check_user": null,
        "reasons": [],
        "tags": [],
        "features": [],
        "user": "NaanAvanIllai",
        "uid": "14062769",
        "editor": "MapComplete 0.26.1",
        "comment": "Adding data with #MapComplete for theme #etymology",
        "comments_count": 0,
        "source": "Not reported",
        "imagery_used": "Not reported",
        "date": "2023-02-18T19:28:50Z",
        "reviewed_features": [],
        "tag_changes": {
          "leisure": [
            "stadium",
            "park"
          ],
          "name:etymology:wikidata": [
            "Q1001",
            "Q116820610"
          ]
        },
        "create": 0,
        "modify": 24,
        "delete": 0,
        "area": 231.926127206375,
        "is_suspect": false,
        "harmful": null,
        "checked": false,
        "check_date": null,
        "host": "https://mapcomplete.osm.be/etymology.html",
        "theme": "etymology",
        "answer": 24,
        "locale": "en",
        "imagery": "osm",
        "id": 132726679
      },
      "geometry": {
        "type": "Point",
        "coordinates": [
          18.9913305,
          79.42088925
        ]
      },
      "id": 132726679
    }
  ]
}