{
  "type": "FeatureCollection",
  "features": [
    {
      "type": "Feature",
      "properties": {
        "check_user": null,
        "reasons": [
          {
            "id": 531,
            "name": "Mapbox: Overlapping features"
          }
        ],
        "tags": [],
        "features": [
          {
            "url": "way-265900949",
            "note": "Overlapping features reported in [\"name:etymology:wikidata\"] tags in the feature",
            "osm_id": 265900949,
            "reasons": [
              531
            ],
            "version": 2
          }
        ],
        "user": "NaanAvanIllai",
        "uid": "14062769",
        "editor": "MapComplete 0.22.2",
        "comment": "Adding data with #MapComplete for theme #etymology",
        "comments_count": 0,
        "source": "Not reported",
        "imagery_used": "Not reported",
        "date": "2022-07-11T12:43:45Z",
        "reviewed_features": [],
        "tag_changes": {
          "amenity": [
            "college"
          ],
          "highway": [
            "residential"
          ],
          "leisure": [
            "stadium"
          ],
          "name:etymology:wikidata": [
            "Q3633008"
          ]
        },
        "create": 0,
        "modify": 48,
        "delete": 0,
        "area": 348.733992946395,
        "is_suspect": true,
        "harmful": null,
        "checked": false,
        "check_date": null,
        "host": "https://mapcomplete.osm.be/etymology.html",
        "theme": "etymology",
        "answer": 68,
        "locale": "en",
        "imagery": "osm",
        "id": 123474099
      },
      "geometry": {
        "type": "Point",
        "coordinates": [
          84.48960055,
          22.2138646
        ]
      },
      "id": 123474099
    },
    {
      "type": "Feature",
      "properties": {
        "check_user": null,
        "reasons": [],
        "tags": [],
        "features": [],
        "user": "NaanAvanIllai",
        "uid": "14062769",
        "editor": "MapComplete 0.31.0",
        "comment": "Adding data with #MapComplete for theme #etymology",
        "comments_count": 0,
        "source": "Not reported",
        "imagery_used": "Not reported",
        "date": "2023-07-21T11:37:06Z",
        "reviewed_features": [],
        "tag_changes": {
          "highway": [
            "tertiary",
            "secondary",
            "unclassified"
          ],
          "name:etymology:wikidata": [
            "Q65453597",
            "Q2713385"
          ]
        },
        "create": 0,
        "modify": 13,
        "delete": 0,
        "area": 10.5667823334445,
        "is_suspect": false,
        "harmful": null,
        "checked": false,
        "check_date": null,
        "host": "https://mapcomplete.osm.be/etymology.html",
        "theme": "etymology",
        "answer": 13,
        "locale": "en",
        "id": 138808814
      },
      "geometry": {
        "type": "Point",
        "coordinates": [
          84.5413922,
          24.48451085
        ]
      },
      "id": 138808814
    }
  ]
}