{
  "type": "FeatureCollection",
  "features": [
    {
      "type": "Feature",
      "properties": {
        "check_user": null,
        "reasons": [
          {
            "id": 40,
            "name": "New mapper"
          }
        ],
        "tags": [],
        "features": [],
        "user": "Theo Van Cutsem",
        "uid": "11832752",
        "editor": "MapComplete 0.0.8f",
        "comment": "Adding data with #MapComplete for theme #buurtnatuur",
        "comments_count": 0,
        "source": "Not reported",
        "imagery_used": "Not reported",
        "date": "2020-10-06T06:09:39Z",
        "reviewed_features": [],
        "create": 0,
        "modify": 7,
        "delete": 0,
        "area": 0.000846339807830166,
        "is_suspect": true,
        "harmful": null,
        "checked": false,
        "check_date": null,
        "metadata": {
          "theme": "buurtnatuur",
          "theme-creator": "Pieter Vander Vennet"
        }
      },
      "geometry": {
        "type": "Point",
        "coordinates": [
          4.62886185,
          50.88363855
        ]
      }
    },
    {
      "type": "Feature",
      "properties": {
        "check_user": null,
        "reasons": [],
        "tags": [],
        "features": [],
        "user": "beardhatcode",
        "uid": "5439560",
        "editor": "MapComplete 0.8.4",
        "comment": "Adding data with #MapComplete for theme #sport_pitches",
        "comments_count": 0,
        "source": "Not reported",
        "imagery_used": "Not reported",
        "date": "2021-07-25T08:49:23Z",
        "reviewed_features": [],
        "create": 0,
        "modify": 1,
        "delete": 0,
        "area": 0.00000108979809000292,
        "is_suspect": false,
        "harmful": null,
        "checked": false,
        "check_date": null,
        "metadata": {
          "host": "mapcomplete.osm.be",
          "theme": "sport_pitches",
          "imagery": "osm",
          "language": "en"
        }
      },
      "geometry": {
        "type": "Point",
        "coordinates": [
          4.62736645,
          50.86434745
        ]
      }
    }
  ]
}