{
  "type": "FeatureCollection",
  "features": [
    {
      "type": "Feature",
      "properties": {
        "check_user": null,
        "reasons": [
          {
            "id": 40,
            "name": "New mapper"
          }
        ],
        "tags": [],
        "features": [],
        "user": "ClarissaWAM",
        "uid": "13745921",
        "editor": "MapComplete 0.9.12",
        "comment": "Adding data with #MapComplete for theme #bookcases",
        "comments_count": 0,
        "source": "Not reported",
        "imagery_used": "Not reported",
        "date": "2021-09-17T11:34:55Z",
        "reviewed_features": [],
        "create": 1,
        "modify": 3,
        "delete": 0,
        "area": 0,
        "is_suspect": true,
        "harmful": null,
        "checked": false,
        "check_date": null,
        "metadata": {
          "host": "mapcomplete.osm.be",
          "theme": "bookcases",
          "imagery": "osm",
          "language": "en",
          "theme-creator": "MapComplete"
        }
      },
      "geometry": {
        "type": "Point",
        "coordinates": [
          6.2451053,
          49.6538075
        ]
      }
    }
  ]
}