{
  "type": "FeatureCollection",
  "features": [
    {
      "type": "Feature",
      "properties": {
        "check_user": null,
        "reasons": [
          {
            "id": 40,
            "name": "New mapper"
          }
        ],
        "tags": [],
        "features": [],
        "user": "Will-Ink",
        "uid": "13186657",
        "editor": "MapComplete 0.7.0a",
        "comment": "Adding data with #MapComplete for theme #bookcases",
        "comments_count": 0,
        "source": "Not reported",
        "imagery_used": "Not reported",
        "date": "2021-04-27T07:30:51Z",
        "reviewed_features": [],
        "create": 1,
        "modify": 2,
        "delete": 0,
        "area": 0,
        "is_suspect": true,
        "harmful": null,
        "checked": false,
        "check_date": null,
        "metadata": {
          "host": "mapcomplete.osm.be",
          "theme": "bookcases",
          "imagery": "fr.ign.bdortho",
          "language": "en",
          "theme-creator": "MapComplete"
        }
      },
      "geometry": {
        "type": "Point",
        "coordinates": [
          2.8990066,
          42.7019566
        ]
      }
    }
  ]
}