{
  "type": "FeatureCollection",
  "features": [
    {
      "type": "Feature",
      "properties": {
        "check_user": null,
        "reasons": [],
        "tags": [],
        "features": [],
        "user": "colorful-corvid",
        "uid": "10620526",
        "editor": "MapComplete 0.40.5",
        "comment": "Adding data with #MapComplete for theme #ghostbikes",
        "comments_count": 0,
        "source": "Not reported",
        "imagery_used": "Not reported",
        "date": "2024-03-16T22:35:08Z",
        "reviewed_features": [],
        "tag_changes": {},
        "create": 1,
        "modify": 1,
        "delete": 0,
        "area": 9.256160001320859e-9,
        "is_suspect": false,
        "harmful": null,
        "checked": false,
        "check_date": null,
        "host": "https://mapcomplete.org/ghostbikes.html",
        "move": 1,
        "theme": "ghostbikes",
        "answer": 1,
        "locale": "en",
        "move:node/11737735063": "improve_accuracy",
        "id": 148752621
      },
      "geometry": {
        "type": "Point",
        "coordinates": [
          -75.1595706,
          39.9463898
        ]
      },
      "id": 148752621
    },
    {
      "type": "Feature",
      "properties": {
        "check_user": null,
        "reasons": [
          {
            "id": 4,
            "name": "mass modification"
          }
        ],
        "tags": [],
        "features": [],
        "user": "SpeedMcCool",
        "uid": "2260722",
        "editor": "MapComplete 0.41.4",
        "comment": "Adding data with #MapComplete for theme #etymology",
        "comments_count": 0,
        "source": "Not reported",
        "imagery_used": "Not reported",
        "date": "2024-04-07T19:14:12Z",
        "reviewed_features": [],
        "tag_changes": {},
        "create": 0,
        "modify": 842,
        "delete": 0,
        "area": 20.244175649419915,
        "is_suspect": true,
        "harmful": null,
        "checked": false,
        "check_date": null,
        "host": "https://mapcomplete.org/etymology",
        "theme": "etymology",
        "answer": 908,
        "locale": "en",
        "change_over_5000m": 8,
        "id": 149706698
      },
      "geometry": {
        "type": "Point",
        "coordinates": [
          -74.62697245,
          40.56849485
        ]
      },
      "id": 149706698
    },
    {
      "type": "Feature",
      "properties": {
        "check_user": null,
        "reasons": [
          {
            "id": 40,
            "name": "New mapper"
          }
        ],
        "tags": [],
        "features": [],
        "user": "rsromano",
        "uid": "9203312",
        "editor": "MapComplete 0.41.4",
        "comment": "Adding data with #MapComplete for theme #street_lighting",
        "comments_count": 0,
        "source": "Not reported",
        "imagery_used": "Not reported",
        "date": "2024-04-12T16:11:52Z",
        "reviewed_features": [],
        "tag_changes": {},
        "create": 2,
        "modify": 1,
        "delete": 0,
        "area": 9.244731999753682e-8,
        "is_suspect": true,
        "harmful": null,
        "checked": false,
        "check_date": null,
        "host": "https://mapcomplete.org/street_lighting.html",
        "theme": "street_lighting",
        "answer": 10,
        "locale": "en",
        "id": 149918413
      },
      "geometry": {
        "type": "Point",
        "coordinates": [
          -75.55280355,
          40.1314191
        ]
      },
      "id": 149918413
    },
    {
      "type": "Feature",
      "properties": {
        "check_user": null,
        "reasons": [],
        "tags": [],
        "features": [],
        "user": "pkoby",
        "uid": "999995",
        "editor": "MapComplete 0.44.3",
        "comment": "Adding data with #MapComplete for theme #shops",
        "comments_count": 0,
        "source": "Not reported",
        "imagery_used": "Not reported",
        "date": "2024-07-09T01:42:59Z",
        "reviewed_features": [],
        "tag_changes": {
          "shop": [
            "pastry"
          ],
          "not:brand": [
            "yes"
          ]
        },
        "create": 0,
        "modify": 1,
        "delete": 0,
        "area": 0,
        "is_suspect": false,
        "harmful": null,
        "checked": false,
        "check_date": null,
        "host": "https://mapcomplete.org/shops",
        "theme": "shops",
        "answer": 1,
        "locale": "en",
        "id": 153725491
      },
      "geometry": {
        "type": "Point",
        "coordinates": [
          -75.2134866,
          40.03211
        ]
      },
      "id": 153725491
    }
  ]
}