{
  "type": "FeatureCollection",
  "features": [
    {
      "type": "Feature",
      "properties": {
        "check_user": null,
        "reasons": [
          {
            "id": 40,
            "name": "New mapper"
          }
        ],
        "tags": [],
        "features": [],
        "user": "funmog",
        "uid": "175580",
        "editor": "MapComplete 0.33.7",
        "comment": "Adding data with #MapComplete for theme #shops",
        "comments_count": 0,
        "source": "Not reported",
        "imagery_used": "Not reported",
        "date": "2023-10-07T15:27:53Z",
        "reviewed_features": [],
        "tag_changes": {
          "shop": [
            "mobile_phone"
          ],
          "payment:cash": [
            "yes"
          ],
          "payment:cards": [
            "no"
          ],
          "internet_access": [
            "no",
            "service"
          ],
          "payment:qr_code": [
            "no"
          ]
        },
        "create": 0,
        "modify": 2,
        "delete": 0,
        "area": 0,
        "is_suspect": true,
        "harmful": null,
        "checked": false,
        "check_date": null,
        "host": "https://mapcomplete.org/shops.html",
        "theme": "shops",
        "answer": 2,
        "locale": "de-DE",
        "id": 142274070
      },
      "geometry": {
        "type": "Point",
        "coordinates": [
          103.9654407,
          16.3210938
        ]
      },
      "id": 142274070
    },
    {
      "type": "Feature",
      "properties": {
        "check_user": null,
        "reasons": [
          {
            "id": 40,
            "name": "New mapper"
          }
        ],
        "tags": [],
        "features": [],
        "user": "funmog",
        "uid": "175580",
        "editor": "MapComplete 0.33.9",
        "comment": "Adding data with #MapComplete for theme #shops",
        "comments_count": 0,
        "source": "Not reported",
        "imagery_used": "Not reported",
        "date": "2023-10-19T14:58:40Z",
        "reviewed_features": [],
        "tag_changes": {
          "shop": [
            "mobile_phone"
          ],
          "second_hand": [
            "yes"
          ]
        },
        "create": 0,
        "modify": 1,
        "delete": 0,
        "area": 0,
        "is_suspect": true,
        "harmful": null,
        "checked": false,
        "check_date": null,
        "host": "https://mapcomplete.org/shops.html",
        "theme": "shops",
        "answer": 1,
        "locale": "de",
        "id": 142820628
      },
      "geometry": {
        "type": "Point",
        "coordinates": [
          103.9654407,
          16.3210938
        ]
      },
      "id": 142820628
    }
  ]
}