{
  "type": "FeatureCollection",
  "features": [
    {
      "type": "Feature",
      "properties": {
        "check_user": null,
        "reasons": [],
        "tags": [],
        "features": [],
        "user": "NaanAvanIllai",
        "uid": "14062769",
        "editor": "MapComplete 0.21.0",
        "comment": "Adding data with #MapComplete for theme #etymology",
        "comments_count": 0,
        "source": "Not reported",
        "imagery_used": "Not reported",
        "date": "2022-06-24T14:44:17Z",
        "reviewed_features": [],
        "tag_changes": {
          "amenity": [
            "hospital"
          ],
          "leisure": [
            "park"
          ],
          "name:etymology:wikidata": [
            "Q237879"
          ]
        },
        "create": 0,
        "modify": 90,
        "delete": 0,
        "area": 309.72463741324,
        "is_suspect": false,
        "harmful": null,
        "checked": false,
        "check_date": null,
        "host": "https://mapcomplete.osm.be/etymology.html",
        "theme": "etymology",
        "answer": 126,
        "locale": "en",
        "imagery": "osm",
        "id": 122806720
      },
      "geometry": {
        "type": "Point",
        "coordinates": [
          19.63871655,
          80.6698308
        ]
      },
      "id": 122806720
    },
    {
      "type": "Feature",
      "properties": {
        "check_user": null,
        "reasons": [
          {
            "id": 489,
            "name": "Mapbox: Spam text"
          }
        ],
        "tags": [],
        "features": [
          {
            "url": "way-959702161",
            "note": "Spam text reported in [\"name\",\"name:etymology:wikidata\"] tags in the feature",
            "osm_id": 959702161,
            "reasons": [
              489
            ],
            "version": 2
          },
          {
            "url": "way-769787741",
            "note": "Spam text reported in [\"name\",\"name:etymology:wikidata\"] tags in the feature",
            "osm_id": 769787741,
            "reasons": [
              489
            ],
            "version": 3
          },
          {
            "url": "way-363904548",
            "note": "Spam text reported in [\"name\",\"name:etymology:wikidata\"] tags in the feature",
            "osm_id": 363904548,
            "reasons": [
              489
            ],
            "version": 3
          },
          {
            "url": "way-769789056",
            "note": "Spam text reported in [\"name\",\"name:etymology:wikidata\"] tags in the feature",
            "osm_id": 769789056,
            "reasons": [
              489
            ],
            "version": 2
          }
        ],
        "user": "NaanAvanIllai",
        "uid": "14062769",
        "editor": "MapComplete 0.23.2",
        "comment": "Adding data with #MapComplete for theme #etymology",
        "comments_count": 0,
        "source": "Not reported",
        "imagery_used": "Not reported",
        "date": "2022-09-05T05:58:28Z",
        "reviewed_features": [],
        "tag_changes": {
          "route": [
            "road"
          ],
          "amenity": [
            "school",
            "college",
            "university"
          ],
          "barrier": [
            "wall"
          ],
          "highway": [
            "unclassified",
            "tertiary",
            "residential",
            "track",
            "service",
            "trunk"
          ],
          "leisure": [
            "park"
          ],
          "name:etymology:wikidata": [
            "Q467662",
            "Q3631426",
            "Q3633365",
            "Q951444",
            "Q732414"
          ]
        },
        "create": 0,
        "modify": 141,
        "delete": 0,
        "area": 449.840924305474,
        "is_suspect": true,
        "harmful": null,
        "checked": false,
        "check_date": null,
        "host": "https://mapcomplete.osm.be/etymology.html",
        "theme": "etymology",
        "answer": 171,
        "locale": "en",
        "imagery": "osm",
        "id": 125796969
      },
      "geometry": {
        "type": "Point",
        "coordinates": [
          20.27678005,
          80.6848827
        ]
      },
      "id": 125796969
    }
  ]
}