{
  "type": "FeatureCollection",
  "features": [
    {
      "type": "Feature",
      "properties": {
        "check_user": null,
        "reasons": [
          {
            "id": 40,
            "name": "New mapper"
          }
        ],
        "tags": [],
        "features": [],
        "user": "jipaul",
        "uid": "1860281",
        "editor": "MapComplete 0.45.3",
        "comment": "Adding data with #MapComplete for theme #food",
        "comments_count": 0,
        "source": "Not reported",
        "imagery_used": "Not reported",
        "date": "2024-08-19T22:41:33Z",
        "reviewed_features": [],
        "tag_changes": {
          "name": [
            "18 Marmites",
            "17 Marmites"
          ],
          "fixme": [
            "Freeform tag `cuisine` used, to be doublechecked"
          ],
          "amenity": [
            "fast_food",
            "restaurant"
          ]
        },
        "create": 0,
        "modify": 3,
        "delete": 0,
        "area": 0,
        "is_suspect": true,
        "harmful": null,
        "checked": false,
        "check_date": null,
        "host": "https://mapcomplete.org/food.html",
        "theme": "food",
        "answer": 3,
        "locale": "fr",
        "id": 155484578
      },
      "geometry": {
        "type": "Point",
        "coordinates": [
          2.5876226,
          9.3384753
        ]
      },
      "id": 155484578
    }
  ]
}