{
  "type": "FeatureCollection",
  "features": [
    {
      "type": "Feature",
      "properties": {
        "check_user": null,
        "reasons": [
          {
            "id": 40,
            "name": "New mapper"
          }
        ],
        "tags": [],
        "features": [],
        "user": "Goni1031",
        "uid": "17133073",
        "editor": "MapComplete 0.23.2",
        "comment": "Adding data with #MapComplete for theme #kerbs_and_crossings",
        "comments_count": 0,
        "source": "Not reported",
        "imagery_used": "Not reported",
        "date": "2022-11-10T07:54:50Z",
        "reviewed_features": [],
        "tag_changes": {
          "lit": [
            "yes"
          ],
          "bicycle": [
            "no"
          ],
          "highway": [
            "track",
            "unclassified",
            "service",
            "crossing",
            "residential",
            "cycleway"
          ],
          "railway": [
            "abandoned"
          ],
          "surface": [
            "asphalt"
          ],
          "crossing": [
            "unmarked"
          ],
          "cycleway": [
            "no"
          ],
          "maxspeed": [
            "50"
          ],
          "waterway": [
            "river"
          ],
          "smoothness": [
            "intermediate",
            "excellent"
          ],
          "tactile_paving": [
            "no"
          ],
          "button_operated": [
            "yes"
          ],
          "crossing:island": [
            "yes",
            "no"
          ]
        },
        "create": 0,
        "modify": 12,
        "delete": 0,
        "area": 18.6122456611222,
        "is_suspect": true,
        "harmful": null,
        "checked": false,
        "check_date": null,
        "host": "https://mapcomplete.osm.be/kerbs_and_crossings.html",
        "theme": "kerbs_and_crossings",
        "answer": 33,
        "locale": "en",
        "imagery": "osm",
        "id": 128719281
      },
      "geometry": {
        "type": "Point",
        "coordinates": [
          117.73156755,
          23.74508785
        ]
      },
      "id": 128719281
    }
  ]
}