{
  "type": "FeatureCollection",
  "features": [
    {
      "type": "Feature",
      "properties": {
        "check_user": null,
        "reasons": [
          {
            "id": 40,
            "name": "New mapper"
          }
        ],
        "tags": [],
        "features": [],
        "user": "rmartinic",
        "uid": "399114",
        "editor": "MapComplete 0.23.2",
        "comment": "Adding data with #MapComplete for theme #artwork",
        "comments_count": 0,
        "source": "survey",
        "imagery_used": "Not reported",
        "date": "2022-09-24T20:23:01Z",
        "reviewed_features": [],
        "tag_changes": {
          "tourism": [
            "artwork"
          ]
        },
        "create": 2,
        "modify": 0,
        "delete": 0,
        "area": 0,
        "is_suspect": true,
        "harmful": null,
        "checked": false,
        "check_date": null,
        "host": "https://mapcomplete.osm.be/artwork.html",
        "theme": "artwork",
        "locale": "en",
        "imagery": "osm",
        "change_over_5000m": 2,
        "id": 126596309
      },
      "geometry": {
        "type": "Point",
        "coordinates": [
          -40.2139788,
          -72.2678961
        ]
      },
      "id": 126596309
    }
  ]
}