{
  "type": "FeatureCollection",
  "features": [
    {
      "type": "Feature",
      "properties": {
        "check_user": null,
        "reasons": [
          {
            "id": 40,
            "name": "New mapper"
          }
        ],
        "tags": [],
        "features": [],
        "user": "paytv",
        "uid": "13422838",
        "editor": "MapComplete 0.7.2l",
        "comment": "Adding data with #MapComplete for theme #waldbrand",
        "comments_count": 0,
        "source": "Not reported",
        "imagery_used": "Not reported",
        "date": "2021-05-27T09:07:53Z",
        "reviewed_features": [],
        "create": 6,
        "modify": 9,
        "delete": 0,
        "area": 0.000126185690399969,
        "is_suspect": true,
        "harmful": null,
        "checked": false,
        "check_date": null,
        "metadata": {
          "host": "waldbrand-app.de",
          "theme": "waldbrand",
          "imagery": "osm",
          "language": "de",
          "theme-creator": "Sebastian Kürten"
        }
      },
      "geometry": {
        "type": "Point",
        "coordinates": [
          13.7139912,
          52.2423022
        ]
      }
    }
  ]
}