{
  "type": "FeatureCollection",
  "features": [
    {
      "type": "Feature",
      "properties": {
        "check_user": null,
        "reasons": [],
        "tags": [],
        "features": [],
        "user": "bponkishore",
        "uid": "14062769",
        "editor": "MapComplete 0.12.13",
        "comment": "Adding data with #MapComplete for theme #etymology",
        "comments_count": 0,
        "source": "Not reported",
        "imagery_used": "Not reported",
        "date": "2021-12-20T16:19:03Z",
        "reviewed_features": [],
        "create": 0,
        "modify": 10,
        "delete": 0,
        "area": 0.00183103467912001,
        "is_suspect": false,
        "harmful": null,
        "checked": false,
        "check_date": null,
        "id": 115173185,
        "host": "mapcomplete.osm.be",
        "theme": "etymology",
        "answer": 12,
        "imagery": "osm",
        "language": "en"
      },
      "geometry": {
        "type": "Point",
        "coordinates": [
          78.07914,
          9.8945045
        ]
      }
    },
    {
      "type": "Feature",
      "properties": {
        "check_user": null,
        "reasons": [
          {
            "id": 40,
            "name": "New mapper"
          }
        ],
        "tags": [],
        "features": [],
        "user": "divyaboomi",
        "uid": "14872477",
        "editor": "MapComplete 0.13.1",
        "comment": "Adding data with #MapComplete for theme #aed",
        "comments_count": 0,
        "source": "survey",
        "imagery_used": "Not reported",
        "date": "2022-01-17T09:48:47Z",
        "reviewed_features": [],
        "create": 1,
        "modify": 0,
        "delete": 0,
        "area": 0,
        "is_suspect": true,
        "harmful": null,
        "checked": false,
        "check_date": null,
        "id": 116245840,
        "host": "mapcomplete.osm.be",
        "theme": "aed",
        "imagery": "osm",
        "language": "en",
        "change_over_5000m": 1
      },
      "geometry": {
        "type": "Point",
        "coordinates": [
          78.1197721,
          9.9251855
        ]
      }
    },
    {
      "type": "Feature",
      "properties": {
        "check_user": null,
        "reasons": [],
        "tags": [],
        "features": [],
        "user": "bponkishore",
        "uid": "14062769",
        "editor": "MapComplete 0.16.1",
        "comment": "Adding data with #MapComplete for theme #etymology",
        "comments_count": 0,
        "source": "Not reported",
        "imagery_used": "Not reported",
        "date": "2022-02-20T06:35:34Z",
        "reviewed_features": [],
        "create": 0,
        "modify": 35,
        "delete": 0,
        "area": 21.3692873444107,
        "is_suspect": false,
        "harmful": null,
        "checked": false,
        "check_date": null,
        "id": 117626715,
        "host": "mapcomplete.osm.be",
        "theme": "etymology",
        "answer": 41,
        "locale": "en",
        "imagery": "osm"
      },
      "geometry": {
        "type": "Point",
        "coordinates": [
          77.8249553,
          10.92797195
        ]
      }
    },
    {
      "type": "Feature",
      "properties": {
        "check_user": null,
        "reasons": [],
        "tags": [],
        "features": [],
        "user": "NaanAvanIllai",
        "uid": "14062769",
        "editor": "MapComplete 0.18.0",
        "comment": "Adding data with #MapComplete for theme #etymology",
        "comments_count": 0,
        "source": "Not reported",
        "imagery_used": "Not reported",
        "date": "2022-04-11T07:13:42Z",
        "reviewed_features": [],
        "tag_changes": {},
        "create": 0,
        "modify": 25,
        "delete": 0,
        "area": 15.6717397646643,
        "is_suspect": false,
        "harmful": null,
        "checked": false,
        "check_date": null,
        "id": 119563361,
        "host": "mapcomplete.osm.be",
        "theme": "etymology",
        "answer": 25,
        "locale": "en",
        "imagery": "osm"
      },
      "geometry": {
        "type": "Point",
        "coordinates": [
          78.64066945,
          10.60095375
        ]
      }
    }
  ]
}