{
  "type": "FeatureCollection",
  "features": [
    {
      "type": "Feature",
      "properties": {
        "check_user": null,
        "reasons": [
          {
            "id": 40,
            "name": "New mapper"
          }
        ],
        "tags": [],
        "features": [],
        "user": "Der Kalle",
        "uid": "13998301",
        "editor": "MapComplete 0.7.2l",
        "comment": "Adding data with #MapComplete for theme #hailhydrant",
        "comments_count": 0,
        "source": "Not reported",
        "imagery_used": "Not reported",
        "date": "2021-08-26T10:30:53Z",
        "reviewed_features": [],
        "create": 1,
        "modify": 0,
        "delete": 0,
        "area": 0,
        "is_suspect": true,
        "harmful": null,
        "checked": false,
        "check_date": null,
        "metadata": {
          "host": "waldbrand-app.de",
          "theme": "hailhydrant",
          "imagery": "HDM_HOT",
          "language": "en",
          "theme-creator": "Erwin Olario"
        }
      },
      "geometry": {
        "type": "Point",
        "coordinates": [
          14.71425,
          51.9491832
        ]
      }
    }
  ]
}