{
  "type": "FeatureCollection",
  "features": [
    {
      "type": "Feature",
      "properties": {
        "check_user": null,
        "reasons": [],
        "tags": [],
        "features": [],
        "user": "benjamintchik",
        "uid": "6290466",
        "editor": "MapComplete 0.37.1",
        "comment": "Adding data with #MapComplete for theme #etymology",
        "comments_count": 0,
        "source": "Not reported",
        "imagery_used": "Not reported",
        "date": "2024-02-09T20:34:01Z",
        "reviewed_features": [],
        "tag_changes": {
          "highway": [
            "residential",
            "service",
            "path",
            "pedestrian"
          ],
          "name:etymology:wikidata": [
            "Q232453",
            "Q2657745",
            "Q3109901",
            "Q190928",
            "Q15973976"
          ]
        },
        "create": 0,
        "modify": 31,
        "delete": 0,
        "area": 403.463235413902,
        "is_suspect": false,
        "harmful": null,
        "checked": false,
        "check_date": null,
        "host": "https://mapcomplete.org/etymology.html",
        "theme": "etymology",
        "answer": 31,
        "locale": "fr",
        "id": 147271789
      },
      "geometry": {
        "type": "Point",
        "coordinates": [
          -36.508301550000006,
          44.32578075
        ]
      },
      "id": 147271789
    }
  ]
}