{
  "type": "FeatureCollection",
  "features": [
    {
      "type": "Feature",
      "properties": {
        "check_user": null,
        "reasons": [
          {
            "id": 43,
            "name": "Invalid key value combination"
          }
        ],
        "tags": [],
        "features": [
          {
            "url": "node-9487156863",
            "osm_id": 9487156863,
            "reasons": [
              43
            ],
            "version": 1,
            "primary_tags": {
              "tourism": "map"
            }
          }
        ],
        "user": "mike140",
        "uid": "2471547",
        "editor": "MapComplete 0.15.4",
        "comment": "Adding data with #MapComplete for theme #maps",
        "comments_count": 0,
        "source": "Not reported",
        "imagery_used": "Not reported",
        "date": "2022-02-07T15:48:01Z",
        "reviewed_features": [],
        "create": 1,
        "modify": 0,
        "delete": 0,
        "area": 0,
        "is_suspect": false,
        "harmful": null,
        "checked": false,
        "check_date": null,
        "id": 117125249,
        "host": "mapcomplete.osm.be",
        "theme": "maps",
        "locale": "ru",
        "imagery": "osm"
      },
      "geometry": {
        "type": "Point",
        "coordinates": [
          34.7990064,
          50.8962661
        ]
      }
    },
    {
      "type": "Feature",
      "properties": {
        "check_user": null,
        "reasons": [],
        "tags": [],
        "features": [],
        "user": "mike140",
        "uid": "2471547",
        "editor": "MapComplete 0.18.2",
        "comment": "Adding data with #MapComplete for theme #etymology",
        "comments_count": 0,
        "source": "Not reported",
        "imagery_used": "Not reported",
        "date": "2022-04-26T18:30:33Z",
        "reviewed_features": [],
        "create": 0,
        "modify": 2,
        "delete": 0,
        "area": 0.0000139655131199935,
        "is_suspect": false,
        "harmful": null,
        "checked": false,
        "check_date": null,
        "id": 120225439,
        "host": "mapcomplete.osm.be",
        "theme": "etymology",
        "answer": 2,
        "locale": "ru",
        "imagery": "osm"
      },
      "geometry": {
        "type": "Point",
        "coordinates": [
          34.797018800000004,
          50.905050700000004
        ]
      }
    }
  ]
}