{
  "type": "FeatureCollection",
  "features": [
    {
      "type": "Feature",
      "properties": {
        "check_user": null,
        "reasons": [],
        "tags": [],
        "features": [],
        "user": "Mastrocom",
        "uid": "13802623",
        "editor": "MapComplete 0.45.3",
        "comment": "Adding data with #MapComplete for theme #etymology",
        "comments_count": 0,
        "source": "Not reported",
        "imagery_used": "Not reported",
        "date": "2024-08-18T14:13:50Z",
        "reviewed_features": [],
        "tag_changes": {
          "highway": [
            "unclassified",
            "residential",
            "tertiary",
            "primary",
            "living_street",
            "footway",
            "path"
          ],
          "leisure": [
            "park"
          ],
          "name:etymology:wikidata": [
            "Q1403",
            "Q146183",
            "Q676555",
            "Q46",
            "Q310158",
            "Q153688",
            "Q271814",
            "Q3725896",
            "Q83038",
            "Q311802",
            "Q6602",
            "Q193018",
            "Q43922",
            "Q1458",
            "Q534409",
            "Q345",
            "Q1447",
            "Q1064",
            "Q982512",
            "Q45581",
            "Q982573",
            "Q239",
            "Q202303",
            "Q166092",
            "Q78782",
            "Q9696",
            "Q51176",
            "Q170516",
            "Q168691",
            "Q188692",
            "Q183240"
          ]
        },
        "create": 0,
        "modify": 91,
        "delete": 0,
        "area": 0.00025260886349996546,
        "is_suspect": false,
        "harmful": null,
        "checked": false,
        "check_date": null,
        "host": "https://mapcomplete.org/etymology.html",
        "theme": "etymology",
        "answer": 91,
        "locale": "it",
        "change_over_5000m": 55,
        "id": 155417432
      },
      "geometry": {
        "type": "Point",
        "coordinates": [
          16.9340762,
          40.62635845
        ]
      },
      "id": 155417432
    }
  ]
}