{
  "type": "FeatureCollection",
  "features": [
    {
      "type": "Feature",
      "properties": {
        "check_user": null,
        "reasons": [
          {
            "id": 40,
            "name": "New mapper"
          }
        ],
        "tags": [],
        "features": [],
        "user": "OSM_paurafi",
        "uid": "10180559",
        "editor": "MapComplete 0.9.0-rc0",
        "comment": "Adding data with #MapComplete for theme #cycle_infra",
        "comments_count": 0,
        "source": "Not reported",
        "imagery_used": "Not reported",
        "date": "2021-08-03T09:34:36Z",
        "reviewed_features": [],
        "create": 0,
        "modify": 2,
        "delete": 0,
        "area": 0.00000163784574999551,
        "is_suspect": true,
        "harmful": null,
        "checked": false,
        "check_date": null,
        "metadata": {
          "host": "pietervdvn.github.io",
          "path": "mc/project/cycle-infra/",
          "theme": "cycle_infra",
          "imagery": "AGIV10cm",
          "language": "nl"
        }
      },
      "geometry": {
        "type": "Point",
        "coordinates": [
          4.56855905,
          51.301993749999994
        ]
      }
    }
  ]
}