{
  "type": "FeatureCollection",
  "features": [
    {
      "type": "Feature",
      "properties": {
        "check_user": null,
        "reasons": [],
        "tags": [],
        "features": [],
        "user": "benjamintchik",
        "uid": "6290466",
        "editor": "MapComplete 0.27.3",
        "comment": "Adding data with #MapComplete for theme #etymology",
        "comments_count": 0,
        "source": "Not reported",
        "imagery_used": "Not reported",
        "date": "2023-05-14T14:23:54Z",
        "reviewed_features": [],
        "tag_changes": {
          "highway": [
            "living_street",
            "tertiary",
            "residential"
          ],
          "name:etymology:wikidata": [
            "Q18409819",
            "Q12556141",
            "Q811122",
            "Q77590"
          ]
        },
        "create": 0,
        "modify": 23,
        "delete": 0,
        "area": 19.0783829915885,
        "is_suspect": false,
        "harmful": null,
        "checked": false,
        "check_date": null,
        "host": "https://mapcomplete.osm.be/etymology.html",
        "theme": "etymology",
        "answer": 30,
        "locale": "fr",
        "imagery": "osm",
        "id": 136087499
      },
      "geometry": {
        "type": "Point",
        "coordinates": [
          27.314517000000002,
          58.43365295
        ]
      },
      "id": 136087499
    },
    {
      "type": "Feature",
      "properties": {
        "check_user": null,
        "reasons": [],
        "tags": [],
        "features": [],
        "user": "benjamintchik",
        "uid": "6290466",
        "editor": "MapComplete 0.27.4",
        "comment": "Adding data with #MapComplete for theme #etymology",
        "comments_count": 0,
        "source": "Not reported",
        "imagery_used": "Not reported",
        "date": "2023-06-03T16:52:47Z",
        "reviewed_features": [],
        "tag_changes": {
          "highway": [
            "primary",
            "residential"
          ],
          "name:etymology:wikidata": [
            "Q1773",
            "Q193198"
          ]
        },
        "create": 0,
        "modify": 25,
        "delete": 0,
        "area": 0.000329150016899868,
        "is_suspect": false,
        "harmful": null,
        "checked": false,
        "check_date": null,
        "host": "https://mapcomplete.osm.be/etymology.html",
        "theme": "etymology",
        "answer": 33,
        "locale": "fr",
        "imagery": "osm",
        "id": 136909249
      },
      "geometry": {
        "type": "Point",
        "coordinates": [
          28.31325125,
          57.8187375
        ]
      },
      "id": 136909249
    }
  ]
}