{
  "type": "FeatureCollection",
  "features": [
    {
      "type": "Feature",
      "properties": {
        "check_user": null,
        "reasons": [],
        "tags": [],
        "features": [],
        "user": "Morten Lange",
        "uid": "337846",
        "editor": "MapComplete 0.0.0",
        "comment": "Beantwoorden van vragen met #MapComplete voor vragenset #cyclofix",
        "comments_count": null,
        "source": "Not reported",
        "imagery_used": "Not reported",
        "date": "2020-08-07T17:09:44Z",
        "reviewed_features": [],
        "tag_changes": {},
        "create": 1,
        "modify": 0,
        "delete": 0,
        "area": 0,
        "is_suspect": false,
        "harmful": null,
        "checked": false,
        "check_date": null,
        "id": 89102934
      },
      "geometry": {
        "type": "Point",
        "coordinates": [
          70.3703315,
          31.1099339
        ]
      },
      "id": 89102934
    },
    {
      "type": "Feature",
      "properties": {
        "check_user": null,
        "reasons": [],
        "tags": [],
        "features": [],
        "user": "korobkov",
        "uid": "389895",
        "editor": "MapComplete 0.23.2",
        "comment": "Adding data with #MapComplete for theme #etymology",
        "comments_count": 0,
        "source": "Not reported",
        "imagery_used": "Not reported",
        "date": "2022-09-17T12:08:16Z",
        "reviewed_features": [],
        "tag_changes": {
          "highway": [
            "tertiary",
            "residential",
            "primary",
            "service"
          ],
          "boundary": [
            "administrative"
          ],
          "name:etymology:wikidata": [
            "Q1799415",
            "Q8148",
            "Q15980591",
            "Q163931"
          ]
        },
        "create": 0,
        "modify": 23,
        "delete": 0,
        "area": 0.00247785747365935,
        "is_suspect": false,
        "harmful": null,
        "checked": false,
        "check_date": null,
        "host": "https://mapcomplete.osm.be/etymology.html",
        "theme": "etymology",
        "answer": 35,
        "locale": "ru",
        "imagery": "osm",
        "id": 126296155
      },
      "geometry": {
        "type": "Point",
        "coordinates": [
          68.98888099999999,
          33.105233549999994
        ]
      },
      "id": 126296155
    }
  ]
}