{
  "type": "FeatureCollection",
  "features": [
    {
      "type": "Feature",
      "properties": {
        "check_user": null,
        "reasons": [
          {
            "id": 40,
            "name": "New mapper"
          }
        ],
        "tags": [],
        "features": [],
        "user": "Lukas233",
        "uid": "13740435",
        "editor": "MapComplete 0.8.3e",
        "comment": "Adding data with #MapComplete for theme #hailhydrant",
        "comments_count": 0,
        "source": "Not reported",
        "imagery_used": "Not reported",
        "date": "2021-07-11T19:32:27Z",
        "reviewed_features": [],
        "create": 1,
        "modify": 4,
        "delete": 0,
        "area": 0,
        "is_suspect": true,
        "harmful": null,
        "checked": false,
        "check_date": null,
        "metadata": {
          "host": "mapcomplete.osm.be",
          "theme": "hailhydrant",
          "imagery": "HDM_HOT",
          "language": "en",
          "theme-creator": "Erwin Olario"
        }
      },
      "geometry": {
        "type": "Point",
        "coordinates": [
          10.8882263,
          50.1890977
        ]
      }
    }
  ]
}