{
  "type": "FeatureCollection",
  "features": [
    {
      "type": "Feature",
      "properties": {
        "check_user": null,
        "reasons": [
          {
            "id": 40,
            "name": "New mapper"
          }
        ],
        "tags": [],
        "features": [],
        "user": "leoberniga",
        "uid": "11702212",
        "editor": "MapComplete 0.31.2",
        "comment": "Adding data with #MapComplete for theme #surveillance",
        "comments_count": 0,
        "source": "Not reported",
        "imagery_used": "Not reported",
        "date": "2023-08-29T20:20:47Z",
        "reviewed_features": [],
        "tag_changes": {
          "building": [
            "commercial"
          ],
          "man_made": [
            "surveillance"
          ]
        },
        "create": 2,
        "modify": 1,
        "delete": 0,
        "area": 2.32541500004807e-8,
        "is_suspect": true,
        "harmful": null,
        "checked": false,
        "check_date": null,
        "host": "https://mapcomplete.org/surveillance.html",
        "theme": "surveillance",
        "locale": "es",
        "id": 140558642
      },
      "geometry": {
        "type": "Point",
        "coordinates": [
          -25.281595449999998,
          -57.639829649999996
        ]
      },
      "id": 140558642
    },
    {
      "type": "Feature",
      "properties": {
        "check_user": null,
        "reasons": [],
        "tags": [],
        "features": [],
        "user": "Lu Pa",
        "uid": "277734",
        "editor": "MapComplete 0.31.2",
        "comment": "Adding data with #MapComplete for theme #surveillance",
        "comments_count": 0,
        "source": "Not reported",
        "imagery_used": "Not reported",
        "date": "2023-09-12T20:49:31Z",
        "reviewed_features": [],
        "tag_changes": {
          "man_made": [
            "surveillance"
          ]
        },
        "create": 1,
        "modify": 3,
        "delete": 0,
        "area": 0,
        "is_suspect": false,
        "harmful": null,
        "checked": false,
        "check_date": null,
        "host": "https://mapcomplete.org/surveillance.html",
        "theme": "surveillance",
        "answer": 8,
        "locale": "es",
        "id": 141181253
      },
      "geometry": {
        "type": "Point",
        "coordinates": [
          -25.2814679,
          -57.6381498
        ]
      },
      "id": 141181253
    }
  ]
}