{
  "type": "FeatureCollection",
  "features": [
    {
      "type": "Feature",
      "properties": {
        "check_user": null,
        "reasons": [
          {
            "id": 40,
            "name": "New mapper"
          }
        ],
        "tags": [],
        "features": [],
        "user": "WardBeyens",
        "uid": "10343215",
        "editor": "MapComplete 0.8.1",
        "comment": "Adding data with #MapComplete for theme #trees",
        "comments_count": 0,
        "source": "survey",
        "imagery_used": "Not reported",
        "date": "2021-07-05T11:16:42Z",
        "reviewed_features": [],
        "create": 1,
        "modify": 0,
        "delete": 0,
        "area": 0,
        "is_suspect": true,
        "harmful": null,
        "checked": false,
        "check_date": null,
        "metadata": {
          "host": "mapcomplete.osm.be",
          "theme": "trees",
          "imagery": "AGIV",
          "language": "en",
          "theme-creator": "Midgard"
        }
      },
      "geometry": {
        "type": "Point",
        "coordinates": [
          5.0179933,
          51.388831
        ]
      }
    },
    {
      "type": "Feature",
      "properties": {
        "check_user": null,
        "reasons": [
          {
            "id": 40,
            "name": "New mapper"
          }
        ],
        "tags": [],
        "features": [],
        "user": "WardBeyens",
        "uid": "10343215",
        "editor": "MapComplete 0.8.1",
        "comment": "Adding data with #MapComplete for theme #benches",
        "comments_count": 0,
        "source": "survey",
        "imagery_used": "Not reported",
        "date": "2021-07-05T11:15:18Z",
        "reviewed_features": [],
        "create": 1,
        "modify": 0,
        "delete": 0,
        "area": 0,
        "is_suspect": true,
        "harmful": null,
        "checked": false,
        "check_date": null,
        "metadata": {
          "host": "mapcomplete.osm.be",
          "theme": "benches",
          "imagery": "osm",
          "language": "en",
          "theme-creator": "Florian Edelmann"
        }
      },
      "geometry": {
        "type": "Point",
        "coordinates": [
          5.0157416,
          51.3917567
        ]
      }
    },
    {
      "type": "Feature",
      "properties": {
        "check_user": null,
        "reasons": [
          {
            "id": 40,
            "name": "New mapper"
          }
        ],
        "tags": [],
        "features": [],
        "user": "WardBeyens",
        "uid": "10343215",
        "editor": "MapComplete 0.0.8f",
        "comment": "Adding data with #MapComplete for theme #buurtnatuur",
        "comments_count": 0,
        "source": "Not reported",
        "imagery_used": "Not reported",
        "date": "2021-07-03T10:40:24Z",
        "reviewed_features": [],
        "create": 0,
        "modify": 1,
        "delete": 0,
        "area": 0.0087058638197998,
        "is_suspect": true,
        "harmful": null,
        "checked": false,
        "check_date": null,
        "metadata": {
          "theme": "buurtnatuur",
          "theme-creator": "Pieter Vander Vennet"
        }
      },
      "geometry": {
        "type": "Point",
        "coordinates": [
          5.062176,
          51.37753885
        ]
      }
    }
  ]
}