{
  "type": "FeatureCollection",
  "features": [
    {
      "type": "Feature",
      "properties": {
        "check_user": null,
        "reasons": [
          {
            "id": 40,
            "name": "New mapper"
          }
        ],
        "tags": [],
        "features": [],
        "user": "RadagastWiz",
        "uid": "1292503",
        "editor": "MapComplete 0.30.7",
        "comment": "Adding data with #MapComplete for theme #clock",
        "comments_count": 0,
        "source": "Not reported",
        "imagery_used": "Not reported",
        "date": "2023-06-25T21:25:19Z",
        "reviewed_features": [],
        "tag_changes": {
          "date": [
            "no"
          ],
          "faces": [
            "4"
          ],
          "amenity": [
            "clock"
          ],
          "display": [
            "analog"
          ],
          "support": [
            "wall_mounted"
          ],
          "building": [
            "yes"
          ],
          "man_made": [
            "tower"
          ],
          "barometer": [
            "no"
          ],
          "hygrometer": [
            "no"
          ],
          "visibility": [
            "area"
          ],
          "thermometer": [
            "no"
          ]
        },
        "create": 0,
        "modify": 7,
        "delete": 0,
        "area": 9.46250444002137,
        "is_suspect": true,
        "harmful": null,
        "checked": false,
        "check_date": null,
        "host": "https://mapcomplete.osm.be/clock.html",
        "theme": "clock",
        "answer": 21,
        "locale": "en",
        "id": 137767484
      },
      "geometry": {
        "type": "Point",
        "coordinates": [
          -78.11274184999999,
          44.444587150000004
        ]
      },
      "id": 137767484
    }
  ]
}