{
  "type": "FeatureCollection",
  "features": [
    {
      "type": "Feature",
      "properties": {
        "check_user": null,
        "reasons": [],
        "tags": [],
        "features": [],
        "user": "Carto'Cité",
        "uid": "5426135",
        "editor": "MapComplete 0.26.0",
        "comment": "Adding data with #MapComplete for theme #cycle_infra",
        "comments_count": 0,
        "source": "Not reported",
        "imagery_used": "Not reported",
        "date": "2023-02-02T14:25:34Z",
        "reviewed_features": [],
        "tag_changes": {
          "highway": [
            "primary"
          ],
          "cycleway": [
            "separate",
            "no"
          ]
        },
        "create": 0,
        "modify": 1,
        "delete": 0,
        "area": 1.70463399983435e-8,
        "is_suspect": false,
        "harmful": null,
        "checked": false,
        "check_date": null,
        "host": "https://mapcomplete.osm.be/cycle_infra.html",
        "theme": "cycle_infra",
        "answer": 1,
        "locale": "en",
        "imagery": "CartoDB.Voyager",
        "id": 132005641
      },
      "geometry": {
        "type": "Point",
        "coordinates": [
          -1.93424745,
          46.7013963
        ]
      },
      "id": 132005641
    },
    {
      "type": "Feature",
      "properties": {
        "check_user": null,
        "reasons": [],
        "tags": [],
        "features": [],
        "user": "Kalepom",
        "uid": "392288",
        "editor": "MapComplete 0.27.1",
        "comment": "Adding data with #MapComplete for theme #etymology",
        "comments_count": 0,
        "source": "Not reported",
        "imagery_used": "Not reported",
        "date": "2023-03-24T15:37:01Z",
        "reviewed_features": [],
        "tag_changes": {
          "amenity": [
            "school"
          ],
          "highway": [
            "residential"
          ],
          "name:etymology:wikidata": [
            "Q42292",
            "Q81666",
            "Q131113",
            "Q132557",
            "Q3189140",
            "Q3060012",
            "Q27215",
            "Q25273",
            "Q637533",
            "Q171360"
          ]
        },
        "create": 0,
        "modify": 12,
        "delete": 0,
        "area": 0.0000407041775999931,
        "is_suspect": false,
        "harmful": null,
        "checked": false,
        "check_date": null,
        "host": "https://mapcomplete.osm.be/etymology.html",
        "theme": "etymology",
        "answer": 13,
        "locale": "fr",
        "imagery": "osm",
        "id": 134073928
      },
      "geometry": {
        "type": "Point",
        "coordinates": [
          -1.631696,
          47.0328247
        ]
      },
      "id": 134073928
    }
  ]
}