{
  "type": "FeatureCollection",
  "features": [
    {
      "type": "Feature",
      "properties": {
        "check_user": null,
        "reasons": [],
        "tags": [],
        "features": [],
        "user": "NaanAvanIllai",
        "uid": "14062769",
        "editor": "MapComplete 0.47.4",
        "comment": "Adding data with #MapComplete for theme #etymology",
        "comments_count": 0,
        "source": "Not reported",
        "imagery_used": "Not reported",
        "date": "2024-10-08T11:37:09Z",
        "reviewed_features": [],
        "tag_changes": {
          "leisure": [
            "park"
          ],
          "name:etymology:wikidata": [
            "Q1047"
          ]
        },
        "create": 0,
        "modify": 1,
        "delete": 0,
        "area": 6.834225700041356e-7,
        "is_suspect": false,
        "harmful": null,
        "checked": false,
        "check_date": null,
        "host": "https://mapcomplete.org/etymology.html",
        "theme": "etymology",
        "answer": 1,
        "locale": "en",
        "id": 157622260
      },
      "geometry": {
        "type": "Point",
        "coordinates": [
          79.43242555,
          28.38288025
        ]
      },
      "id": 157622260
    },
    {
      "type": "Feature",
      "properties": {
        "check_user": null,
        "reasons": [],
        "tags": [],
        "features": [],
        "user": "NaanAvanIllai",
        "uid": "14062769",
        "editor": "MapComplete 0.41.7",
        "comment": "Adding data with #MapComplete for theme #etymology",
        "comments_count": 0,
        "source": "Not reported",
        "imagery_used": "Not reported",
        "date": "2024-04-26T07:54:26Z",
        "reviewed_features": [],
        "tag_changes": {},
        "create": 0,
        "modify": 18,
        "delete": 0,
        "area": 184.75869832640134,
        "is_suspect": false,
        "harmful": null,
        "checked": false,
        "check_date": null,
        "host": "https://mapcomplete.org/etymology.html",
        "theme": "etymology",
        "answer": 18,
        "locale": "en",
        "id": 150525365
      },
      "geometry": {
        "type": "Point",
        "coordinates": [
          81.5571952,
          27.20574225
        ]
      },
      "id": 150525365
    }
  ]
}