{
  "type": "FeatureCollection",
  "features": [
    {
      "type": "Feature",
      "properties": {
        "check_user": null,
        "reasons": [
          {
            "id": 40,
            "name": "New mapper"
          }
        ],
        "tags": [],
        "features": [],
        "user": "cregox",
        "uid": "9515343",
        "editor": "MapComplete 0.8.1",
        "comment": "Adding data with #MapComplete for theme #drinking_water",
        "comments_count": 0,
        "source": "survey",
        "imagery_used": "Not reported",
        "date": "2021-07-04T05:40:19Z",
        "reviewed_features": [],
        "create": 5,
        "modify": 8,
        "delete": 0,
        "area": 0.00561702952145831,
        "is_suspect": true,
        "harmful": null,
        "checked": false,
        "check_date": null,
        "metadata": {
          "host": "mapcomplete.osm.be",
          "theme": "drinking_water",
          "imagery": "CartoDB.Voyager",
          "language": "en",
          "theme-creator": "MapComplete"
        }
      },
      "geometry": {
        "type": "Point",
        "coordinates": [
          -7.7915753,
          41.27653235
        ]
      }
    }
  ]
}