{
  "type": "FeatureCollection",
  "features": [
    {
      "type": "Feature",
      "properties": {
        "check_user": null,
        "reasons": [],
        "tags": [],
        "features": [],
        "user": "art-smith",
        "uid": "13106766",
        "editor": "MapComplete 0.6.8",
        "comment": "Adding data with #MapComplete for theme #trees",
        "comments_count": 0,
        "source": "Not reported",
        "imagery_used": "Not reported",
        "date": "2021-04-18T12:56:16Z",
        "reviewed_features": [],
        "tag_changes": {},
        "create": 0,
        "modify": 1,
        "delete": 0,
        "area": 0,
        "is_suspect": false,
        "harmful": null,
        "checked": false,
        "check_date": null,
        "host": "mapcomplete.osm.be",
        "theme": "trees",
        "imagery": "osm",
        "language": "en",
        "theme-creator": "Midgard",
        "id": 103136285
      },
      "geometry": {
        "type": "Point",
        "coordinates": [
          39.410636,
          -81.4503622
        ]
      },
      "id": 103136285
    },
    {
      "type": "Feature",
      "properties": {
        "check_user": null,
        "reasons": [],
        "tags": [],
        "features": [],
        "user": "wolfgang8741",
        "uid": "307520",
        "editor": "MapComplete 0.8.0a",
        "comment": "Adding data with #MapComplete for theme #cyclofix",
        "comments_count": 0,
        "source": "Not reported",
        "imagery_used": "Not reported",
        "date": "2021-06-21T18:16:12Z",
        "reviewed_features": [],
        "tag_changes": {},
        "create": 0,
        "modify": 1,
        "delete": 0,
        "area": 0,
        "is_suspect": false,
        "harmful": null,
        "checked": false,
        "check_date": null,
        "host": "mapcomplete.osm.be",
        "theme": "cyclofix",
        "imagery": "CartoDB.Voyager",
        "language": "en",
        "theme-creator": "MapComplete",
        "id": 106731786
      },
      "geometry": {
        "type": "Point",
        "coordinates": [
          39.4148476,
          -81.4565247
        ]
      },
      "id": 106731786
    },
    {
      "type": "Feature",
      "properties": {
        "check_user": null,
        "reasons": [
          {
            "id": 40,
            "name": "New mapper"
          }
        ],
        "tags": [],
        "features": [],
        "user": "JohnWesty",
        "uid": "14854340",
        "editor": "MapComplete 0.13.1",
        "comment": "Adding data with #MapComplete for theme #toilets",
        "comments_count": 0,
        "source": "Not reported",
        "imagery_used": "Not reported",
        "date": "2022-01-14T18:43:44Z",
        "reviewed_features": [],
        "tag_changes": {},
        "create": 1,
        "modify": 2,
        "delete": 0,
        "area": 0,
        "is_suspect": true,
        "harmful": null,
        "checked": false,
        "check_date": null,
        "host": "mapcomplete.osm.be",
        "theme": "toilets",
        "answer": 8,
        "imagery": "USDA-NAIP",
        "language": "en",
        "id": 116159385
      },
      "geometry": {
        "type": "Point",
        "coordinates": [
          41.5201538,
          -81.4058161
        ]
      },
      "id": 116159385
    }
  ]
}