{
  "type": "FeatureCollection",
  "features": [
    {
      "type": "Feature",
      "properties": {
        "check_user": null,
        "reasons": [],
        "tags": [],
        "features": [],
        "user": "SpeedMcCool",
        "uid": "2260722",
        "editor": "MapComplete 0.31.2",
        "comment": "Adding data with #MapComplete for theme #etymology",
        "comments_count": 0,
        "source": "Not reported",
        "imagery_used": "Not reported",
        "date": "2023-08-26T21:00:05Z",
        "reviewed_features": [],
        "tag_changes": {
          "highway": [
            "tertiary",
            "secondary"
          ],
          "name:etymology:wikidata": [
            "Q5050044",
            "Q22073672",
            "Q1618",
            "Q513404",
            "Q6531937"
          ]
        },
        "create": 0,
        "modify": 21,
        "delete": 0,
        "area": 4.31037332593561,
        "is_suspect": false,
        "harmful": null,
        "checked": false,
        "check_date": null,
        "host": "https://mapcomplete.org/etymology",
        "theme": "etymology",
        "answer": 23,
        "locale": "en",
        "id": 140429057
      },
      "geometry": {
        "type": "Point",
        "coordinates": [
          -92.8410936,
          46.655437750000004
        ]
      },
      "id": 140429057
    },
    {
      "type": "Feature",
      "properties": {
        "check_user": null,
        "reasons": [],
        "tags": [],
        "features": [],
        "user": "SpeedMcCool",
        "uid": "2260722",
        "editor": "MapComplete 0.31.2",
        "comment": "Adding data with #MapComplete for theme #etymology",
        "comments_count": 0,
        "source": "Not reported",
        "imagery_used": "Not reported",
        "date": "2023-08-28T02:46:28Z",
        "reviewed_features": [],
        "tag_changes": {
          "highway": [
            "residential",
            "secondary",
            "tertiary"
          ],
          "name:etymology:wikidata": [
            "Q9434",
            "Q211848",
            "Q620656",
            "Q1996502",
            "Q188828",
            "Q466602",
            "Q504678",
            "Q623382",
            "Q584443",
            "Q142788",
            "Q45989",
            "Q729006",
            "Q124230",
            "Q8001558",
            "Q549761",
            "Q775299",
            "Q156901",
            "Q25350",
            "Q130918",
            "Q39121",
            "Q157806",
            "Q1000115",
            "Q26325",
            "Q25243",
            "Q214823",
            "Q855330",
            "Q23154",
            "Q59779164",
            "Q1507416",
            "Q22073672",
            "Q105994608",
            "Q757833",
            "Q1027725",
            "Q184138",
            "Q844058",
            "Q1820330",
            "Q1179217",
            "Q214720",
            "Q34836"
          ]
        },
        "create": 0,
        "modify": 95,
        "delete": 0,
        "area": 5.03222180049331,
        "is_suspect": false,
        "harmful": null,
        "checked": false,
        "check_date": null,
        "host": "https://mapcomplete.osm.be/etymology.html",
        "theme": "etymology",
        "answer": 99,
        "locale": "en",
        "change_over_5000m": 1,
        "id": 140473469
      },
      "geometry": {
        "type": "Point",
        "coordinates": [
          -92.2415509,
          46.1274302
        ]
      },
      "id": 140473469
    }
  ]
}