{
  "type": "FeatureCollection",
  "features": [
    {
      "type": "Feature",
      "properties": {
        "check_user": null,
        "reasons": [],
        "tags": [],
        "features": [],
        "user": "NaanAvanIllai",
        "uid": "14062769",
        "editor": "MapComplete 0.23.0",
        "comment": "Adding data with #MapComplete for theme #etymology",
        "comments_count": 0,
        "source": "Not reported",
        "imagery_used": "Not reported",
        "date": "2022-07-27T07:58:30Z",
        "reviewed_features": [],
        "tag_changes": {
          "highway": [
            "residential",
            "secondary",
            "service",
            "unclassified",
            "tertiary",
            "primary",
            "tertiary_link"
          ],
          "landuse": [
            "residential"
          ],
          "leisure": [
            "park"
          ],
          "boundary": [
            "administrative",
            "political",
            "marker"
          ],
          "building": [
            "yes"
          ],
          "name:etymology:wikidata": [
            "Q1154693",
            "Q7240159",
            "Q90756270",
            "Q684198",
            "Q7399623",
            "Q3630453",
            "Q2628981",
            "Q3634691",
            "Q312966"
          ]
        },
        "create": 0,
        "modify": 80,
        "delete": 0,
        "area": 411.251053723883,
        "is_suspect": false,
        "harmful": null,
        "checked": false,
        "check_date": null,
        "host": "https://mapcomplete.osm.be/etymology.html",
        "theme": "etymology",
        "answer": 132,
        "locale": "en",
        "imagery": "osm",
        "id": 124126540
      },
      "geometry": {
        "type": "Point",
        "coordinates": [
          19.40855345,
          83.1537404
        ]
      },
      "id": 124126540
    },
    {
      "type": "Feature",
      "properties": {
        "check_user": null,
        "reasons": [],
        "tags": [],
        "features": [],
        "user": "NaanAvanIllai",
        "uid": "14062769",
        "editor": "MapComplete 0.23.1",
        "comment": "Adding data with #MapComplete for theme #etymology",
        "comments_count": 0,
        "source": "Not reported",
        "imagery_used": "Not reported",
        "date": "2022-08-29T15:16:50Z",
        "reviewed_features": [],
        "tag_changes": {
          "amenity": [
            "school",
            "hospital"
          ],
          "highway": [
            "unclassified",
            "residential",
            "tertiary"
          ],
          "leisure": [
            "stadium",
            "sports_centre"
          ],
          "name:etymology:wikidata": [
            "Q522048",
            "Q2724411",
            "Q2153",
            "Q4593"
          ]
        },
        "create": 0,
        "modify": 45,
        "delete": 0,
        "area": 391.001562954955,
        "is_suspect": false,
        "harmful": null,
        "checked": false,
        "check_date": null,
        "host": "https://mapcomplete.osm.be/etymology.html",
        "theme": "etymology",
        "answer": 56,
        "locale": "en",
        "imagery": "osm",
        "id": 125529145
      },
      "geometry": {
        "type": "Point",
        "coordinates": [
          17.9401814,
          83.1673316
        ]
      },
      "id": 125529145
    },
    {
      "type": "Feature",
      "properties": {
        "check_user": null,
        "reasons": [],
        "tags": [],
        "features": [],
        "user": "NaanAvanIllai",
        "uid": "14062769",
        "editor": "MapComplete 0.25.6",
        "comment": "Adding data with #MapComplete for theme #etymology",
        "comments_count": 0,
        "source": "Not reported",
        "imagery_used": "Not reported",
        "date": "2023-01-31T10:53:59Z",
        "reviewed_features": [],
        "tag_changes": {
          "amenity": [
            "school",
            "library",
            "college",
            "hospital"
          ],
          "building": [
            "yes"
          ],
          "name:etymology:wikidata": [
            "Q1001",
            "Q4593",
            "Q730045"
          ]
        },
        "create": 0,
        "modify": 20,
        "delete": 0,
        "area": 285.671667861965,
        "is_suspect": false,
        "harmful": null,
        "checked": false,
        "check_date": null,
        "host": "https://mapcomplete.osm.be/etymology.html",
        "theme": "etymology",
        "answer": 21,
        "locale": "en",
        "imagery": "osm",
        "id": 131916092
      },
      "geometry": {
        "type": "Point",
        "coordinates": [
          17.64462475,
          83.17758795
        ]
      },
      "id": 131916092
    }
  ]
}