{
  "type": "FeatureCollection",
  "features": [
    {
      "type": "Feature",
      "properties": {
        "check_user": null,
        "reasons": [
          {
            "id": 40,
            "name": "New mapper"
          }
        ],
        "tags": [],
        "features": [],
        "user": "Triko_CCTV",
        "uid": "20121116",
        "editor": "MapComplete 0.31.3",
        "comment": "Adding data with #MapComplete for theme #surveillance",
        "comments_count": 0,
        "source": "Not reported",
        "imagery_used": "Not reported",
        "date": "2023-08-27T13:10:37Z",
        "reviewed_features": [],
        "tag_changes": {
          "man_made": [
            "surveillance"
          ],
          "operator": [
            "Napier City Council Cameras"
          ],
          "camera:type": [
            "panning"
          ],
          "camera:mount": [
            "pole"
          ]
        },
        "create": 0,
        "modify": 2,
        "delete": 0,
        "area": 0,
        "is_suspect": true,
        "harmful": null,
        "checked": false,
        "check_date": null,
        "host": "https://pietervdvn.github.io/mc/develop/surveillance.html",
        "theme": "surveillance",
        "answer": 3,
        "locale": "en-US",
        "id": 140451048
      },
      "geometry": {
        "type": "Point",
        "coordinates": [
          176.876677,
          -39.511299
        ]
      },
      "id": 140451048
    }
  ]
}