{
  "type": "FeatureCollection",
  "features": [
    {
      "type": "Feature",
      "properties": {
        "check_user": null,
        "reasons": [
          {
            "id": 40,
            "name": "New mapper"
          }
        ],
        "tags": [],
        "features": [],
        "user": "Filipvdl",
        "uid": "1930844",
        "editor": "MapComplete 0.4.9",
        "comment": "Adding data with #MapComplete for theme #benches",
        "comments_count": 0,
        "source": "Not reported",
        "imagery_used": "Not reported",
        "date": "2021-02-02T09:36:41Z",
        "reviewed_features": [],
        "create": 1,
        "modify": 4,
        "delete": 0,
        "area": 0,
        "is_suspect": true,
        "harmful": null,
        "checked": false,
        "check_date": null,
        "metadata": {
          "host": "mapcomplete.osm.be",
          "theme": "benches",
          "imagery": "osm",
          "language": "en",
          "theme-creator": "Florian Edelmann"
        }
      },
      "geometry": {
        "type": "Point",
        "coordinates": [
          4.6952149,
          51.0429887
        ]
      }
    },
    {
      "type": "Feature",
      "properties": {
        "check_user": null,
        "reasons": [],
        "tags": [],
        "features": [],
        "user": "Thierry1030",
        "uid": "286563",
        "editor": "MapComplete 0.7.5",
        "comment": "Adding data with #MapComplete for theme #benches",
        "comments_count": 0,
        "source": "Not reported",
        "imagery_used": "Not reported",
        "date": "2021-06-05T22:22:59Z",
        "reviewed_features": [],
        "create": 0,
        "modify": 3,
        "delete": 0,
        "area": 0.245886507470602,
        "is_suspect": false,
        "harmful": null,
        "checked": false,
        "check_date": null,
        "metadata": {
          "host": "pietervdvn.github.io",
          "theme": "benches",
          "imagery": "osm",
          "language": "en",
          "theme-creator": "Florian Edelmann"
        }
      },
      "geometry": {
        "type": "Point",
        "coordinates": [
          4.69861065,
          51.0226315
        ]
      }
    }
  ]
}