{
  "type": "FeatureCollection",
  "features": [
    {
      "type": "Feature",
      "properties": {
        "check_user": null,
        "reasons": [
          {
            "id": 40,
            "name": "New mapper"
          }
        ],
        "tags": [],
        "features": [],
        "user": "Nos_Fi",
        "uid": "526289",
        "editor": "MapComplete 0.8.3f",
        "comment": "Adding data with #MapComplete for theme #playgrounds",
        "comments_count": 0,
        "source": "Not reported",
        "imagery_used": "Not reported",
        "date": "2021-07-19T10:13:02Z",
        "reviewed_features": [],
        "tag_changes": {},
        "create": 1,
        "modify": 2,
        "delete": 0,
        "area": 0,
        "is_suspect": true,
        "harmful": null,
        "checked": false,
        "check_date": null,
        "host": "mapcomplete.osm.be",
        "theme": "playgrounds",
        "imagery": "osm",
        "language": "en",
        "id": 108241385
      },
      "geometry": {
        "type": "Point",
        "coordinates": [
          13.9470255,
          56.9688806
        ]
      },
      "id": 108241385
    },
    {
      "type": "Feature",
      "properties": {
        "check_user": null,
        "reasons": [],
        "tags": [],
        "features": [],
        "user": "AE35",
        "uid": "21323",
        "editor": "MapComplete 0.34.9",
        "comment": "Adding data with #MapComplete for theme #etymology",
        "comments_count": 0,
        "source": "Not reported",
        "imagery_used": "Not reported",
        "date": "2023-11-28T16:40:44Z",
        "reviewed_features": [],
        "tag_changes": {
          "highway": [
            "secondary",
            "unclassified",
            "residential",
            "tertiary",
            "service",
            "track"
          ],
          "name:etymology:wikidata": [
            "Q2690945",
            "Q503379",
            "Q8148",
            "Q101538",
            "Q5194627",
            "Q156901",
            "Q156099",
            "Q25439"
          ]
        },
        "create": 0,
        "modify": 96,
        "delete": 0,
        "area": 35.085003496835,
        "is_suspect": false,
        "harmful": null,
        "checked": false,
        "check_date": null,
        "host": "https://mapcomplete.org/etymology",
        "theme": "etymology",
        "answer": 106,
        "locale": "da",
        "id": 144556622
      },
      "geometry": {
        "type": "Point",
        "coordinates": [
          13.51321025,
          57.9491884
        ]
      },
      "id": 144556622
    }
  ]
}