{
  "type": "FeatureCollection",
  "features": [
    {
      "type": "Feature",
      "properties": {
        "check_user": null,
        "reasons": [
          {
            "id": 42,
            "name": "Invalid tag modification"
          }
        ],
        "tags": [],
        "features": [
          {
            "url": "relation-5583904",
            "osm_id": 5583904,
            "reasons": [
              42
            ],
            "version": 6,
            "primary_tags": {}
          }
        ],
        "user": "Peter Elderson",
        "uid": "7103674",
        "editor": "MapComplete 0.7.5",
        "comment": "Adding data with #MapComplete for theme #wandelknooppunten",
        "comments_count": 0,
        "source": "survey",
        "imagery_used": "Not reported",
        "date": "2021-06-08T07:02:13Z",
        "reviewed_features": [],
        "create": 3,
        "modify": 37,
        "delete": 0,
        "area": 0.00160111532728003,
        "is_suspect": false,
        "harmful": null,
        "checked": false,
        "check_date": null,
        "metadata": {
          "host": "mapcomplete.osm.be",
          "theme": "wandelknooppunten",
          "imagery": "osm",
          "language": "en",
          "theme-creator": "Peter Elderson"
        }
      },
      "geometry": {
        "type": "Point",
        "coordinates": [
          5.4203578,
          51.2797844
        ]
      }
    }
  ]
}