{
  "type": "FeatureCollection",
  "features": [
    {
      "type": "Feature",
      "properties": {
        "check_user": null,
        "reasons": [],
        "tags": [],
        "features": [],
        "user": "NaanAvanIllai",
        "uid": "14062769",
        "editor": "MapComplete 0.25.6",
        "comment": "Adding data with #MapComplete for theme #etymology",
        "comments_count": 0,
        "source": "Not reported",
        "imagery_used": "Not reported",
        "date": "2023-01-31T13:26:48Z",
        "reviewed_features": [],
        "tag_changes": {
          "amenity": [
            "university",
            "college",
            "school"
          ],
          "barrier": [
            "wall"
          ],
          "highway": [
            "tertiary"
          ],
          "leisure": [
            "park"
          ],
          "name:etymology:wikidata": [
            "Q741700",
            "Q231690",
            "Q7494391",
            "Q1001"
          ]
        },
        "create": 0,
        "modify": 8,
        "delete": 0,
        "area": 83.1597338058646,
        "is_suspect": false,
        "harmful": null,
        "checked": false,
        "check_date": null,
        "host": "https://mapcomplete.osm.be/etymology.html",
        "theme": "etymology",
        "answer": 8,
        "locale": "en",
        "imagery": "osm",
        "id": 131922152
      },
      "geometry": {
        "type": "Point",
        "coordinates": [
          17.62201635,
          76.45463295
        ]
      },
      "id": 131922152
    }
  ]
}