{
  "type": "FeatureCollection",
  "features": [
    {
      "type": "Feature",
      "properties": {
        "check_user": null,
        "reasons": [],
        "tags": [],
        "features": [],
        "user": "NaanAvanIllai",
        "uid": "14062769",
        "editor": "MapComplete 0.47.4",
        "comment": "Adding data with #MapComplete for theme #etymology",
        "comments_count": 0,
        "source": "Not reported",
        "imagery_used": "Not reported",
        "date": "2024-10-04T08:42:37Z",
        "reviewed_features": [],
        "tag_changes": {
          "highway": [
            "secondary"
          ],
          "name:etymology:wikidata": [
            "Q3534483"
          ]
        },
        "create": 0,
        "modify": 1,
        "delete": 0,
        "area": 0.000008400416040011086,
        "is_suspect": false,
        "harmful": null,
        "checked": false,
        "check_date": null,
        "host": "https://mapcomplete.org/etymology.html",
        "theme": "etymology",
        "answer": 1,
        "locale": "en",
        "id": 157450066
      },
      "geometry": {
        "type": "Point",
        "coordinates": [
          78.67856885,
          10.8129678
        ]
      },
      "id": 157450066
    },
    {
      "type": "Feature",
      "properties": {
        "check_user": null,
        "reasons": [],
        "tags": [],
        "features": [],
        "user": "NaanAvanIllai",
        "uid": "14062769",
        "editor": "MapComplete 0.43.1",
        "comment": "Adding data with #MapComplete for theme #etymology",
        "comments_count": 0,
        "source": "Not reported",
        "imagery_used": "Not reported",
        "date": "2024-06-09T04:35:21Z",
        "reviewed_features": [],
        "tag_changes": {
          "highway": [
            "secondary",
            "primary"
          ],
          "name:etymology:wikidata": [
            "Q4784234",
            "Q465018",
            "Q115687325",
            "Q1936913"
          ]
        },
        "create": 0,
        "modify": 73,
        "delete": 0,
        "area": 0.006336179494099692,
        "is_suspect": false,
        "harmful": null,
        "checked": false,
        "check_date": null,
        "host": "https://dev.mapcomplete.org/etymology.html",
        "theme": "etymology",
        "answer": 73,
        "locale": "en",
        "id": 152438508
      },
      "geometry": {
        "type": "Point",
        "coordinates": [
          78.0703758,
          9.909374549999999
        ]
      },
      "id": 152438508
    }
  ]
}