{
  "type": "FeatureCollection",
  "features": [
    {
      "type": "Feature",
      "properties": {
        "check_user": null,
        "reasons": [
          {
            "id": 40,
            "name": "New mapper"
          }
        ],
        "tags": [],
        "features": [],
        "user": "GeertenSabrina",
        "uid": "11834564",
        "editor": "MapComplete 0.0.0",
        "comment": "Beantwoorden van vragen met #MapComplete voor vragenset #buurtnatuur",
        "comments_count": null,
        "source": "Not reported",
        "imagery_used": "Not reported",
        "date": "2020-09-17T18:34:07Z",
        "reviewed_features": [],
        "create": 0,
        "modify": 1,
        "delete": 0,
        "area": 0.000127756486780008,
        "is_suspect": true,
        "harmful": null,
        "checked": false,
        "check_date": null,
        "metadata": {
          "theme": "buurtnatuur"
        }
      },
      "geometry": {
        "type": "Point",
        "coordinates": [
          5.3758485,
          50.88240625
        ]
      }
    },
    {
      "type": "Feature",
      "properties": {
        "check_user": null,
        "reasons": [
          {
            "id": 40,
            "name": "New mapper"
          }
        ],
        "tags": [],
        "features": [],
        "user": "GeertenSabrina",
        "uid": "11834564",
        "editor": "MapComplete 0.0.0",
        "comment": "Beantwoorden van vragen met #MapComplete voor vragenset #buurtnatuur",
        "comments_count": null,
        "source": "Not reported",
        "imagery_used": "Not reported",
        "date": "2020-09-17T18:33:57Z",
        "reviewed_features": [],
        "create": 0,
        "modify": 1,
        "delete": 0,
        "area": 0.000127756486780008,
        "is_suspect": true,
        "harmful": null,
        "checked": false,
        "check_date": null,
        "metadata": {
          "theme": "buurtnatuur"
        }
      },
      "geometry": {
        "type": "Point",
        "coordinates": [
          5.3758485,
          50.88240625
        ]
      }
    },
    {
      "type": "Feature",
      "properties": {
        "check_user": null,
        "reasons": [
          {
            "id": 40,
            "name": "New mapper"
          }
        ],
        "tags": [],
        "features": [],
        "user": "GeertenSabrina",
        "uid": "11834564",
        "editor": "MapComplete 0.0.0",
        "comment": "Beantwoorden van vragen met #MapComplete voor vragenset #buurtnatuur",
        "comments_count": null,
        "source": "Not reported",
        "imagery_used": "Not reported",
        "date": "2020-09-17T18:30:03Z",
        "reviewed_features": [],
        "create": 0,
        "modify": 1,
        "delete": 0,
        "area": 0.00000455201768000445,
        "is_suspect": true,
        "harmful": null,
        "checked": false,
        "check_date": null,
        "metadata": {
          "theme": "buurtnatuur"
        }
      },
      "geometry": {
        "type": "Point",
        "coordinates": [
          5.3710229,
          50.8769488
        ]
      }
    }
  ]
}