{
  "type": "FeatureCollection",
  "features": [
    {
      "type": "Feature",
      "properties": {
        "check_user": null,
        "reasons": [
          {
            "id": 83,
            "name": "User has multiple blocks"
          }
        ],
        "tags": [],
        "features": [],
        "user": "ڕاستی",
        "uid": "4800812",
        "editor": "MapComplete 0.23.2",
        "comment": "Adding data with #MapComplete for theme #hotels",
        "comments_count": 0,
        "source": "Not reported",
        "imagery_used": "Not reported",
        "date": "2022-09-30T19:11:42Z",
        "reviewed_features": [],
        "tag_changes": {
          "name": [
            "میوانخانەی سەرای ئاڵتون",
            "فندق التنسراى",
            "میوانخانەی بەسوود پلازا",
            "هۆتێل بەسوود پلازا",
            "میوانخانەی ئاڵتون مەلەک",
            "Altun Malak Hotel",
            "میوانخانەی سکای",
            "سكاي"
          ],
          "tourism": [
            "hotel"
          ]
        },
        "create": 0,
        "modify": 4,
        "delete": 0,
        "area": 0.0000419263296800477,
        "is_suspect": true,
        "harmful": null,
        "checked": false,
        "check_date": null,
        "host": "https://pietervdvn.github.io/mc/develop/hotels.html",
        "theme": "hotels",
        "answer": 4,
        "locale": "en",
        "imagery": "EsriWorldImagery",
        "id": 126836998
      },
      "geometry": {
        "type": "Point",
        "coordinates": [
          44.0158679,
          36.173928700000005
        ]
      },
      "id": 126836998
    },
    {
      "type": "Feature",
      "properties": {
        "check_user": null,
        "reasons": [
          {
            "id": 83,
            "name": "User has multiple blocks"
          }
        ],
        "tags": [],
        "features": [],
        "user": "LockOnGuy",
        "uid": "15559282",
        "editor": "MapComplete 0.27.1",
        "comment": "Adding data with #MapComplete for theme #charging_stations",
        "comments_count": 0,
        "source": "Not reported",
        "imagery_used": "Not reported",
        "date": "2023-03-18T16:51:47Z",
        "reviewed_features": [],
        "tag_changes": {
          "amenity": [
            "charging_station"
          ]
        },
        "create": 0,
        "modify": 0,
        "delete": 8,
        "area": 0.0609051817249692,
        "is_suspect": true,
        "harmful": null,
        "checked": false,
        "check_date": null,
        "host": "https://mapcomplete.osm.be/charging_stations.html",
        "theme": "charging_stations",
        "locale": "en",
        "imagery": "CartoDB.Voyager",
        "deletion": 8,
        "deletion:node/7911966385": "not found",
        "deletion:node/8035754085": "not found",
        "deletion:node/8037742094": "not found",
        "deletion:node/8150563017": "not found",
        "deletion:node/8412505417": "not found",
        "deletion:node/8679635917": "not found",
        "deletion:node/8978990120": "not found",
        "deletion:node/9611953317": "not found",
        "id": 133830642
      },
      "geometry": {
        "type": "Point",
        "coordinates": [
          44.58822525,
          33.31773145
        ]
      },
      "id": 133830642
    }
  ]
}