{
  "type": "FeatureCollection",
  "features": [
    {
      "type": "Feature",
      "properties": {
        "check_user": null,
        "reasons": [],
        "tags": [],
        "features": [],
        "user": "FennecusZerda",
        "uid": "665677",
        "editor": "MapComplete 0.40.0",
        "comment": "Adding data with #MapComplete for theme #food",
        "comments_count": 0,
        "source": "Not reported",
        "imagery_used": "Not reported",
        "date": "2024-02-28T15:19:22Z",
        "reviewed_features": [],
        "tag_changes": {
          "amenity": [
            "restaurant"
          ]
        },
        "create": 1,
        "modify": 0,
        "delete": 0,
        "area": 0,
        "is_suspect": false,
        "harmful": null,
        "checked": false,
        "check_date": null,
        "host": "https://mapcomplete.org/food.html",
        "theme": "food",
        "locale": "en",
        "change_over_5000m": 1,
        "id": 148017612
      },
      "geometry": {
        "type": "Point",
        "coordinates": [
          10.20439,
          59.7446586
        ]
      },
      "id": 148017612
    },
    {
      "type": "Feature",
      "properties": {
        "check_user": null,
        "reasons": [],
        "tags": [],
        "features": [],
        "user": "Polardfront",
        "uid": "12630812",
        "editor": "MapComplete 0.25.6",
        "comment": "Adding data with #MapComplete for theme #benches",
        "comments_count": 0,
        "source": "survey",
        "imagery_used": "Not reported",
        "date": "2024-04-14T12:10:28Z",
        "reviewed_features": [],
        "tag_changes": {},
        "create": 4,
        "modify": 6,
        "delete": 0,
        "area": 4.568599999863199e-9,
        "is_suspect": false,
        "harmful": null,
        "checked": false,
        "check_date": null,
        "host": "https://mapcomplete.osm.be/benches.html",
        "theme": "benches",
        "answer": 11,
        "locale": "en",
        "imagery": "geovekst-nib",
        "change_over_5000m": 4,
        "change_within_25m": 10,
        "change_within_50m": 1,
        "id": 149989926
      },
      "geometry": {
        "type": "Point",
        "coordinates": [
          10.798832,
          59.835651
        ]
      },
      "id": 149989926
    },
    {
      "type": "Feature",
      "properties": {
        "check_user": null,
        "reasons": [
          {
            "id": 40,
            "name": "New mapper"
          }
        ],
        "tags": [],
        "features": [],
        "user": "Bemjamin8373728",
        "uid": "21586216",
        "editor": "MapComplete 0.42.7",
        "comment": "Adding data with #MapComplete for theme #drinking_water",
        "comments_count": 0,
        "source": "Not reported",
        "imagery_used": "Not reported",
        "date": "2024-05-25T22:01:51Z",
        "reviewed_features": [],
        "tag_changes": {
          "fee": [
            "no"
          ],
          "bottle": [
            "no"
          ],
          "man_made": [
            "water_tap"
          ],
          "seasonal": [
            "spring;summer;autumn"
          ],
          "opening_hours": [
            "Mo 04:30-00:00; Sa 03:30-08:00"
          ]
        },
        "create": 0,
        "modify": 1,
        "delete": 0,
        "area": 0,
        "is_suspect": true,
        "harmful": null,
        "checked": false,
        "check_date": null,
        "host": "https://mapcomplete.org/drinking_water.html",
        "theme": "drinking_water",
        "answer": 4,
        "locale": "nb-NO",
        "id": 151829793
      },
      "geometry": {
        "type": "Point",
        "coordinates": [
          10.6441674,
          59.9119083
        ]
      },
      "id": 151829793
    }
  ]
}