{
  "type": "FeatureCollection",
  "features": [
    {
      "type": "Feature",
      "properties": {
        "check_user": null,
        "reasons": [
          {
            "id": 40,
            "name": "New mapper"
          }
        ],
        "tags": [],
        "features": [],
        "user": "Aaron Brock ☂️",
        "uid": "21787070",
        "editor": "MapComplete 0.44.11",
        "comment": "Adding data with #MapComplete for theme #food",
        "comments_count": 0,
        "source": "Not reported",
        "imagery_used": "Not reported",
        "date": "2024-07-26T20:59:06Z",
        "reviewed_features": [],
        "tag_changes": {
          "amenity": [
            "restaurant"
          ],
          "building": [
            "yes"
          ],
          "opening_hours": [
            "Mo-Sa 12:30-15:30, 18:30-23:00; Su 13:00-16:00",
            "Mo-Sa 12:30-15:30, 19:00-23:00; Su 13:00-16:00"
          ]
        },
        "create": 0,
        "modify": 1,
        "delete": 0,
        "area": 9.6152000001279e-9,
        "is_suspect": true,
        "harmful": null,
        "checked": false,
        "check_date": null,
        "host": "https://mapcomplete.org/food.html",
        "theme": "food",
        "answer": 1,
        "locale": "en",
        "id": 154461249
      },
      "geometry": {
        "type": "Point",
        "coordinates": [
          -77.0345975,
          -12.0936725
        ]
      },
      "id": 154461249
    }
  ]
}