{
  "type": "FeatureCollection",
  "features": [
    {
      "type": "Feature",
      "properties": {
        "check_user": null,
        "reasons": [
          {
            "id": 40,
            "name": "New mapper"
          }
        ],
        "tags": [],
        "features": [],
        "user": "Yaz2345c",
        "uid": "20615224",
        "editor": "MapComplete 0.35.1",
        "comment": "Adding data with #MapComplete for theme #shops",
        "comments_count": 0,
        "source": "Not reported",
        "imagery_used": "Not reported",
        "date": "2023-11-28T12:38:50Z",
        "reviewed_features": [],
        "tag_changes": {
          "shop": [
            "yes"
          ]
        },
        "create": 1,
        "modify": 0,
        "delete": 0,
        "area": 0,
        "is_suspect": true,
        "harmful": null,
        "checked": false,
        "check_date": null,
        "host": "https://mapcomplete.org/shops",
        "theme": "shops",
        "locale": "fa-IR",
        "change_over_5000m": 1,
        "id": 144547522
      },
      "geometry": {
        "type": "Point",
        "coordinates": [
          32.6930347,
          51.6710776
        ]
      },
      "id": 144547522
    },
    {
      "type": "Feature",
      "properties": {
        "check_user": null,
        "reasons": [
          {
            "id": 40,
            "name": "New mapper"
          }
        ],
        "tags": [],
        "features": [],
        "user": "Yaz2345c",
        "uid": "20615224",
        "editor": "MapComplete 0.35.1",
        "comment": "Adding data with #MapComplete for theme #toilets",
        "comments_count": 0,
        "source": "Not reported",
        "imagery_used": "Not reported",
        "date": "2023-11-28T11:58:15Z",
        "reviewed_features": [],
        "tag_changes": {
          "amenity": [
            "toilets"
          ]
        },
        "create": 0,
        "modify": 2,
        "delete": 0,
        "area": 0.0000401046504001966,
        "is_suspect": true,
        "harmful": null,
        "checked": false,
        "check_date": null,
        "host": "https://mapcomplete.org/toilets.html",
        "move": 2,
        "theme": "toilets",
        "locale": "fa-IR",
        "change_within_500m": 1,
        "change_within_5000m": 1,
        "move:node/4730323781": "improve_accuracy",
        "move:node/5026434604": "improve_accuracy",
        "id": 144546021
      },
      "geometry": {
        "type": "Point",
        "coordinates": [
          32.68834185,
          51.6926693
        ]
      },
      "id": 144546021
    },
    {
      "type": "Feature",
      "properties": {
        "check_user": null,
        "reasons": [],
        "tags": [],
        "features": [],
        "user": "mike140",
        "uid": "2471547",
        "editor": "MapComplete 0.41.7",
        "comment": "Adding data with #MapComplete for theme #etymology",
        "comments_count": 0,
        "source": "Not reported",
        "imagery_used": "Not reported",
        "date": "2024-04-22T22:35:07Z",
        "reviewed_features": [],
        "tag_changes": {
          "highway": [
            "residential"
          ],
          "name:etymology:wikidata": [
            "Q4523373"
          ]
        },
        "create": 0,
        "modify": 1,
        "delete": 0,
        "area": 0.000009425735000004372,
        "is_suspect": false,
        "harmful": null,
        "checked": false,
        "check_date": null,
        "host": "https://mapcomplete.org/etymology",
        "theme": "etymology",
        "answer": 1,
        "locale": "ru",
        "id": 150368732
      },
      "geometry": {
        "type": "Point",
        "coordinates": [
          34.81025135,
          50.901355499999994
        ]
      },
      "id": 150368732
    }
  ]
}