{
  "type": "FeatureCollection",
  "features": [
    {
      "type": "Feature",
      "properties": {
        "check_user": null,
        "reasons": [],
        "tags": [],
        "features": [],
        "user": "andrewpmk",
        "uid": "1679",
        "editor": "MapComplete 0.36.7",
        "comment": "Adding data with #MapComplete for theme #waste_basket",
        "comments_count": 0,
        "source": "Not reported",
        "imagery_used": "Not reported",
        "date": "2023-12-26T18:05:53Z",
        "reviewed_features": [],
        "tag_changes": {
          "waste": [
            "trash"
          ],
          "amenity": [
            "waste_basket"
          ]
        },
        "create": 0,
        "modify": 2,
        "delete": 0,
        "area": 0.00000162375151998583,
        "is_suspect": false,
        "harmful": null,
        "checked": false,
        "check_date": null,
        "host": "https://mapcomplete.org/waste_basket.html",
        "theme": "waste_basket",
        "answer": 2,
        "locale": "en",
        "id": 145544700
      },
      "geometry": {
        "type": "Point",
        "coordinates": [
          44.22760045,
          -76.4984832
        ]
      },
      "id": 145544700
    },
    {
      "type": "Feature",
      "properties": {
        "check_user": null,
        "reasons": [],
        "tags": [],
        "features": [],
        "user": "andrewpmk",
        "uid": "1679",
        "editor": "MapComplete 0.36.7",
        "comment": "Adding data with #MapComplete for theme #parkings",
        "comments_count": 0,
        "source": "Not reported",
        "imagery_used": "Not reported",
        "date": "2023-12-26T15:42:58Z",
        "reviewed_features": [],
        "tag_changes": {
          "amenity": [
            "parking"
          ],
          "capacity:disabled": [
            "0",
            "12"
          ]
        },
        "create": 0,
        "modify": 5,
        "delete": 0,
        "area": 0.000551636511999987,
        "is_suspect": false,
        "harmful": null,
        "checked": false,
        "check_date": null,
        "host": "https://mapcomplete.org/parkings.html",
        "theme": "parkings",
        "answer": 5,
        "locale": "en",
        "id": 145539924
      },
      "geometry": {
        "type": "Point",
        "coordinates": [
          44.2349536,
          -76.5023844
        ]
      },
      "id": 145539924
    }
  ]
}