{
  "type": "FeatureCollection",
  "features": [
    {
      "type": "Feature",
      "properties": {
        "check_user": null,
        "reasons": [],
        "tags": [],
        "features": [],
        "user": "rsteenwyk",
        "uid": "8748059",
        "editor": "MapComplete 0.41.4",
        "comment": "Adding data with #MapComplete for theme #trees",
        "comments_count": 0,
        "source": "Not reported",
        "imagery_used": "Not reported",
        "date": "2024-04-12T14:52:52Z",
        "reviewed_features": [],
        "tag_changes": {},
        "create": 1,
        "modify": 0,
        "delete": 0,
        "area": 0,
        "is_suspect": false,
        "harmful": null,
        "checked": false,
        "check_date": null,
        "host": "https://mapcomplete.org/trees.html",
        "theme": "trees",
        "locale": "en",
        "change_over_5000m": 1,
        "id": 149915080
      },
      "geometry": {
        "type": "Point",
        "coordinates": [
          -85.5294656,
          42.9482571
        ]
      },
      "id": 149915080
    },
    {
      "type": "Feature",
      "properties": {
        "check_user": null,
        "reasons": [
          {
            "id": 40,
            "name": "New mapper"
          }
        ],
        "tags": [],
        "features": [],
        "user": "AmyHoss",
        "uid": "21767078",
        "editor": "MapComplete 0.44.9",
        "comment": "Adding data with #MapComplete for theme #glutenfree",
        "comments_count": 0,
        "source": "Not reported",
        "imagery_used": "Not reported",
        "date": "2024-07-18T20:44:29Z",
        "reviewed_features": [],
        "tag_changes": {},
        "create": 0,
        "modify": 1,
        "delete": 0,
        "area": 0,
        "is_suspect": true,
        "harmful": null,
        "checked": false,
        "check_date": null,
        "host": "https://mapcomplete.org/glutenfree.html",
        "theme": "glutenfree",
        "answer": 3,
        "locale": "en",
        "id": 154118464
      },
      "geometry": {
        "type": "Point",
        "coordinates": [
          -85.660175,
          42.994854
        ]
      },
      "id": 154118464
    },
    {
      "type": "Feature",
      "properties": {
        "check_user": null,
        "reasons": [
          {
            "id": 40,
            "name": "New mapper"
          }
        ],
        "tags": [],
        "features": [],
        "user": "J E Hoss",
        "uid": "20459872",
        "editor": "MapComplete 0.44.9",
        "comment": "Adding data with #MapComplete for theme #glutenfree",
        "comments_count": 0,
        "source": "Not reported",
        "imagery_used": "Not reported",
        "date": "2024-07-18T20:25:45Z",
        "reviewed_features": [],
        "tag_changes": {
          "amenity": [
            "restaurant"
          ],
          "diet:gluten_free": [
            "only",
            "yes"
          ]
        },
        "create": 0,
        "modify": 1,
        "delete": 0,
        "area": 0,
        "is_suspect": true,
        "harmful": null,
        "checked": false,
        "check_date": null,
        "host": "https://mapcomplete.org/glutenfree.html",
        "theme": "glutenfree",
        "answer": 3,
        "locale": "en",
        "id": 154117908
      },
      "geometry": {
        "type": "Point",
        "coordinates": [
          -85.6116374,
          42.9121235
        ]
      },
      "id": 154117908
    },
    {
      "type": "Feature",
      "properties": {
        "check_user": null,
        "reasons": [
          {
            "id": 40,
            "name": "New mapper"
          }
        ],
        "tags": [],
        "features": [],
        "user": "Shifty McCool",
        "uid": "21543596",
        "editor": "MapComplete 0.46.9",
        "comment": "Adding data with #MapComplete for theme #food",
        "comments_count": 0,
        "source": "Not reported",
        "imagery_used": "Not reported",
        "date": "2024-09-19T10:20:54Z",
        "reviewed_features": [],
        "tag_changes": {
          "amenity": [
            "restaurant"
          ]
        },
        "create": 1,
        "modify": 6,
        "delete": 1,
        "area": 2.2049999935554023e-11,
        "is_suspect": true,
        "harmful": null,
        "checked": false,
        "check_date": null,
        "host": "https://mapcomplete.org/food.html",
        "theme": "food",
        "answer": 12,
        "locale": "en",
        "deletion": 1,
        "change_over_5000m": 1,
        "change_within_5000m": 1,
        "deletion:node/11489000113": "shop_closed",
        "id": 156812405
      },
      "geometry": {
        "type": "Point",
        "coordinates": [
          -83.53859915,
          42.55214505
        ]
      },
      "id": 156812405
    }
  ]
}