{
  "type": "FeatureCollection",
  "features": [
    {
      "type": "Feature",
      "properties": {
        "check_user": null,
        "reasons": [],
        "tags": [],
        "features": [],
        "user": "mikko_tamura",
        "uid": "2258022",
        "editor": "MapComplete 0.20.1",
        "comment": "Adding data with #MapComplete for theme #https://raw.githubusercontent.com/mapbeks/mapcomplete_lgbt/main/version 4",
        "comments_count": 0,
        "source": "Not reported",
        "imagery_used": "Not reported",
        "date": "2022-06-11T02:47:12Z",
        "reviewed_features": [],
        "tag_changes": {
          "name": [
            "Pink Tiffanys"
          ],
          "amenity": [
            "pub"
          ]
        },
        "create": 0,
        "modify": 1,
        "delete": 0,
        "area": 0,
        "is_suspect": false,
        "harmful": null,
        "checked": false,
        "check_date": null,
        "host": "https://mapcomplete.osm.be/theme.html",
        "theme": "https://raw.githubusercontent.com/mapbeks/mapcomplete_lgbt/main/version 4",
        "answer": 1,
        "locale": "en",
        "imagery": "osm",
        "id": 122233202
      },
      "geometry": {
        "type": "Point",
        "coordinates": [
          85.3100405,
          27.7160656
        ]
      },
      "id": 122233202
    },
    {
      "type": "Feature",
      "properties": {
        "check_user": null,
        "reasons": [
          {
            "id": 40,
            "name": "New mapper"
          }
        ],
        "tags": [],
        "features": [],
        "user": "shahgnp",
        "uid": "16215173",
        "editor": "MapComplete 0.21.0",
        "comment": "Adding data with #MapComplete for theme #toilets",
        "comments_count": 0,
        "source": "survey",
        "imagery_used": "Not reported",
        "date": "2022-06-28T18:32:08Z",
        "reviewed_features": [],
        "tag_changes": {},
        "create": 1,
        "modify": 0,
        "delete": 0,
        "area": 0,
        "is_suspect": true,
        "harmful": null,
        "checked": false,
        "check_date": null,
        "host": "https://mapcomplete.osm.be/toilets.html",
        "theme": "toilets",
        "locale": "en",
        "imagery": "osm",
        "change_over_5000m": 1,
        "id": 122969425
      },
      "geometry": {
        "type": "Point",
        "coordinates": [
          85.3123226,
          27.7134188
        ]
      },
      "id": 122969425
    },
    {
      "type": "Feature",
      "properties": {
        "check_user": null,
        "reasons": [],
        "tags": [],
        "features": [],
        "user": "shashish",
        "uid": "236945",
        "editor": "MapComplete 0.23.1",
        "comment": "Adding data with #MapComplete for theme #trees",
        "comments_count": 0,
        "source": "Not reported",
        "imagery_used": "Not reported",
        "date": "2022-08-25T04:26:58Z",
        "reviewed_features": [],
        "tag_changes": {
          "natural": [
            "tree"
          ]
        },
        "create": 3,
        "modify": 0,
        "delete": 0,
        "area": 0.0000296415471999798,
        "is_suspect": false,
        "harmful": null,
        "checked": false,
        "check_date": null,
        "host": "https://mapcomplete.osm.be/trees.html",
        "theme": "trees",
        "locale": "en",
        "imagery": "EsriWorldImagery",
        "id": 125339323
      },
      "geometry": {
        "type": "Point",
        "coordinates": [
          85.28427065,
          27.6732312
        ]
      },
      "id": 125339323
    }
  ]
}