{
  "type": "FeatureCollection",
  "features": [
    {
      "type": "Feature",
      "properties": {
        "check_user": null,
        "reasons": [],
        "tags": [],
        "features": [],
        "user": "Pieter Vander Vennet",
        "uid": "3818858",
        "editor": "MapComplete 0.13.0-alpha-7",
        "comment": "Adding data with #MapComplete for theme #missing_streets  Mechanical edit: if a single CRAB-address is in the building, has the same housenumber and the same name as a nearby street, then addr:street is added if missing. ",
        "comments_count": 0,
        "source": "Not reported",
        "imagery_used": "Not reported",
        "date": "2021-12-13T18:23:27Z",
        "reviewed_features": [],
        "create": 0,
        "modify": 1,
        "delete": 0,
        "area": 1.70453299993175e-8,
        "is_suspect": false,
        "harmful": null,
        "checked": false,
        "check_date": null,
        "metadata": {
          "host": "127.0.0.1:1234",
          "theme": "missing_streets",
          "answer": 1,
          "language": "nl"
        }
      },
      "geometry": {
        "type": "Point",
        "coordinates": [
          2.9705210500000003,
          51.00569085
        ]
      }
    },
    {
      "type": "Feature",
      "properties": {
        "check_user": null,
        "reasons": [],
        "tags": [],
        "features": [],
        "user": "Pieter Vander Vennet",
        "uid": "3818858",
        "editor": "MapComplete 0.13.0-alpha-7",
        "comment": "Adding data with #MapComplete for theme #missing_streets  Mechanical edit: if a single CRAB-address is in the building, has the same housenumber and the same name as a nearby street, then addr:street is added if missing. ",
        "comments_count": 0,
        "source": "Not reported",
        "imagery_used": "Not reported",
        "date": "2021-12-13T17:32:18Z",
        "reviewed_features": [],
        "create": 0,
        "modify": 1,
        "delete": 0,
        "area": 2.11045999997011e-8,
        "is_suspect": false,
        "harmful": null,
        "checked": false,
        "check_date": null,
        "metadata": {
          "host": "127.0.0.1:1234",
          "theme": "missing_streets",
          "answer": 1,
          "language": "nl"
        }
      },
      "geometry": {
        "type": "Point",
        "coordinates": [
          2.9117993999999996,
          50.9688639
        ]
      }
    }
  ]
}