{
  "type": "FeatureCollection",
  "features": [
    {
      "type": "Feature",
      "properties": {
        "check_user": null,
        "reasons": [
          {
            "id": 40,
            "name": "New mapper"
          }
        ],
        "tags": [],
        "features": [],
        "user": "Ninopiña10",
        "uid": "11138282",
        "editor": "MapComplete 0.9.14",
        "comment": "Adding data with #MapComplete for theme #drinking_water",
        "comments_count": 0,
        "source": "survey",
        "imagery_used": "Not reported",
        "date": "2021-10-04T07:56:18Z",
        "reviewed_features": [],
        "create": 2,
        "modify": 3,
        "delete": 0,
        "area": 0.000751707441310014,
        "is_suspect": true,
        "harmful": null,
        "checked": false,
        "check_date": null,
        "metadata": {
          "host": "mapcomplete.osm.be",
          "theme": "drinking_water",
          "imagery": "osm",
          "language": "nl",
          "theme-creator": "MapComplete"
        }
      },
      "geometry": {
        "type": "Point",
        "coordinates": [
          -3.86484325,
          43.33013425
        ]
      }
    },
    {
      "type": "Feature",
      "properties": {
        "check_user": null,
        "reasons": [
          {
            "id": 40,
            "name": "New mapper"
          }
        ],
        "tags": [],
        "features": [],
        "user": "Ninopiña10",
        "uid": "11138282",
        "editor": "MapComplete 0.12.3",
        "comment": "Adding data with #MapComplete for theme #drinking_water",
        "comments_count": 0,
        "source": "survey",
        "imagery_used": "Not reported",
        "date": "2021-11-08T17:32:37Z",
        "reviewed_features": [],
        "create": 1,
        "modify": 2,
        "delete": 0,
        "area": 0,
        "is_suspect": true,
        "harmful": null,
        "checked": false,
        "check_date": null,
        "metadata": {
          "host": "mapcomplete.osm.be",
          "theme": "drinking_water",
          "answer": 1,
          "create": 1,
          "imagery": "osm",
          "language": "en",
          "add-image": 2
        }
      },
      "geometry": {
        "type": "Point",
        "coordinates": [
          -3.8141441,
          43.3810326
        ]
      }
    }
  ]
}