{
  "type": "FeatureCollection",
  "features": [
    {
      "type": "Feature",
      "properties": {
        "check_user": null,
        "reasons": [],
        "tags": [],
        "features": [],
        "user": "NaanAvanIllai",
        "uid": "14062769",
        "editor": "MapComplete 0.23.0",
        "comment": "Adding data with #MapComplete for theme #etymology",
        "comments_count": 0,
        "source": "Not reported",
        "imagery_used": "Not reported",
        "date": "2022-07-27T07:58:30Z",
        "reviewed_features": [],
        "tag_changes": {
          "highway": [
            "residential",
            "secondary",
            "service",
            "unclassified",
            "tertiary",
            "primary",
            "tertiary_link"
          ],
          "landuse": [
            "residential"
          ],
          "leisure": [
            "park"
          ],
          "boundary": [
            "administrative",
            "political",
            "marker"
          ],
          "building": [
            "yes"
          ],
          "name:etymology:wikidata": [
            "Q1154693",
            "Q7240159",
            "Q90756270",
            "Q684198",
            "Q7399623",
            "Q3630453",
            "Q2628981",
            "Q3634691",
            "Q312966"
          ]
        },
        "create": 0,
        "modify": 80,
        "delete": 0,
        "area": 411.251053723883,
        "is_suspect": false,
        "harmful": null,
        "checked": false,
        "check_date": null,
        "host": "https://mapcomplete.osm.be/etymology.html",
        "theme": "etymology",
        "answer": 132,
        "locale": "en",
        "imagery": "osm",
        "id": 124126540
      },
      "geometry": {
        "type": "Point",
        "coordinates": [
          19.40855345,
          83.1537404
        ]
      },
      "id": 124126540
    },
    {
      "type": "Feature",
      "properties": {
        "check_user": null,
        "reasons": [
          {
            "id": 489,
            "name": "Mapbox: Spam text"
          }
        ],
        "tags": [],
        "features": [
          {
            "url": "way-975944543",
            "note": "Spam text reported in [\"name\",\"name:etymology:wikidata\"] tags in the feature",
            "osm_id": 975944543,
            "reasons": [
              489
            ],
            "version": 2
          }
        ],
        "user": "NaanAvanIllai",
        "uid": "14062769",
        "editor": "MapComplete 0.23.0",
        "comment": "Adding data with #MapComplete for theme #etymology",
        "comments_count": 0,
        "source": "Not reported",
        "imagery_used": "Not reported",
        "date": "2022-08-01T08:43:05Z",
        "reviewed_features": [],
        "tag_changes": {
          "amenity": [
            "university",
            "school"
          ],
          "highway": [
            "secondary",
            "trunk",
            "tertiary",
            "unclassified"
          ],
          "name:etymology:wikidata": [
            "Q7282619",
            "Q3349315",
            "Q692",
            "Q3269584",
            "Q4915440",
            "Q2901773",
            "Q7237582",
            "Q3348980"
          ]
        },
        "create": 0,
        "modify": 151,
        "delete": 0,
        "area": 435.51488957326,
        "is_suspect": true,
        "harmful": null,
        "checked": false,
        "check_date": null,
        "host": "https://mapcomplete.osm.be/etymology.html",
        "theme": "etymology",
        "answer": 181,
        "locale": "en",
        "imagery": "osm",
        "id": 124332910
      },
      "geometry": {
        "type": "Point",
        "coordinates": [
          20.993112500000002,
          82.94314109999999
        ]
      },
      "id": 124332910
    }
  ]
}