{
  "type": "FeatureCollection",
  "features": [
    {
      "type": "Feature",
      "properties": {
        "check_user": null,
        "reasons": [
          {
            "id": 40,
            "name": "New mapper"
          }
        ],
        "tags": [],
        "features": [],
        "user": "emilinfrance",
        "uid": "14568184",
        "editor": "MapComplete 0.12.13",
        "comment": "Adding data with #MapComplete for theme #cycle_infra",
        "comments_count": 0,
        "source": "Not reported",
        "imagery_used": "Not reported",
        "date": "2021-12-29T10:41:35Z",
        "reviewed_features": [],
        "create": 0,
        "modify": 2,
        "delete": 0,
        "area": 0,
        "is_suspect": true,
        "harmful": null,
        "checked": false,
        "check_date": null,
        "metadata": {
          "host": "mapcomplete.osm.be",
          "theme": "cycle_infra",
          "answer": 2,
          "imagery": "CartoDB.Voyager",
          "language": "nl"
        }
      },
      "geometry": {
        "type": "Point",
        "coordinates": [
          5.7179091,
          44.4285732
        ]
      }
    },
    {
      "type": "Feature",
      "properties": {
        "check_user": null,
        "reasons": [
          {
            "id": 40,
            "name": "New mapper"
          }
        ],
        "tags": [],
        "features": [],
        "user": "emilinfrance",
        "uid": "14568184",
        "editor": "MapComplete 0.12.13",
        "comment": "Adding data with #MapComplete for theme #facadegardens",
        "comments_count": 0,
        "source": "Not reported",
        "imagery_used": "Not reported",
        "date": "2021-12-28T10:04:03Z",
        "reviewed_features": [],
        "create": 1,
        "modify": 0,
        "delete": 0,
        "area": 0,
        "is_suspect": true,
        "harmful": null,
        "checked": false,
        "check_date": null,
        "metadata": {
          "host": "mapcomplete.osm.be",
          "theme": "facadegardens",
          "answer": 1,
          "create": 2,
          "imagery": "osm",
          "language": "nl"
        }
      },
      "geometry": {
        "type": "Point",
        "coordinates": [
          5.7158357,
          44.4269075
        ]
      }
    },
    {
      "type": "Feature",
      "properties": {
        "check_user": null,
        "reasons": [
          {
            "id": 40,
            "name": "New mapper"
          }
        ],
        "tags": [],
        "features": [],
        "user": "emilinfrance",
        "uid": "14568184",
        "editor": "MapComplete 0.12.13",
        "comment": "Adding data with #MapComplete for theme #shops",
        "comments_count": 0,
        "source": "Not reported",
        "imagery_used": "Not reported",
        "date": "2021-12-28T09:55:27Z",
        "reviewed_features": [],
        "create": 0,
        "modify": 4,
        "delete": 0,
        "area": 0,
        "is_suspect": true,
        "harmful": null,
        "checked": false,
        "check_date": null,
        "metadata": {
          "host": "mapcomplete.osm.be",
          "theme": "shops",
          "answer": 4,
          "imagery": "osm",
          "language": "en"
        }
      },
      "geometry": {
        "type": "Point",
        "coordinates": [
          5.7157232,
          44.4252561
        ]
      }
    },
    {
      "type": "Feature",
      "properties": {
        "check_user": null,
        "reasons": [
          {
            "id": 40,
            "name": "New mapper"
          }
        ],
        "tags": [],
        "features": [],
        "user": "emilinfrance",
        "uid": "14568184",
        "editor": "MapComplete 0.12.13",
        "comment": "Adding data with #MapComplete for theme #shops",
        "comments_count": 0,
        "source": "Not reported",
        "imagery_used": "Not reported",
        "date": "2021-12-28T08:43:28Z",
        "reviewed_features": [],
        "create": 0,
        "modify": 1,
        "delete": 0,
        "area": 0,
        "is_suspect": true,
        "harmful": null,
        "checked": false,
        "check_date": null,
        "metadata": {
          "host": "mapcomplete.osm.be",
          "theme": "shops",
          "answer": 1,
          "imagery": "osm",
          "language": "en"
        }
      },
      "geometry": {
        "type": "Point",
        "coordinates": [
          5.7170669,
          44.4277081
        ]
      }
    }
  ]
}