{
  "type": "FeatureCollection",
  "features": [
    {
      "type": "Feature",
      "properties": {
        "check_user": null,
        "reasons": [
          {
            "id": 40,
            "name": "New mapper"
          }
        ],
        "tags": [],
        "features": [],
        "user": "Casi1980",
        "uid": "13989376",
        "editor": "MapComplete 0.7.2l",
        "comment": "Adding data with #MapComplete for theme #waldbrand",
        "comments_count": 0,
        "source": "Not reported",
        "imagery_used": "Not reported",
        "date": "2021-08-30T18:04:42Z",
        "reviewed_features": [],
        "create": 0,
        "modify": 1,
        "delete": 0,
        "area": 0,
        "is_suspect": true,
        "harmful": null,
        "checked": false,
        "check_date": null,
        "metadata": {
          "host": "waldbrand-app.de",
          "theme": "waldbrand",
          "imagery": "osm",
          "language": "de",
          "theme-creator": "Sebastian Kürten"
        }
      },
      "geometry": {
        "type": "Point",
        "coordinates": [
          14.1588903,
          52.4506053
        ]
      }
    },
    {
      "type": "Feature",
      "properties": {
        "check_user": null,
        "reasons": [
          {
            "id": 40,
            "name": "New mapper"
          }
        ],
        "tags": [],
        "features": [],
        "user": "Casi1980",
        "uid": "13989376",
        "editor": "MapComplete 0.7.2l",
        "comment": "Adding data with #MapComplete for theme #waldbrand",
        "comments_count": 0,
        "source": "Not reported",
        "imagery_used": "Not reported",
        "date": "2021-08-24T23:49:36Z",
        "reviewed_features": [],
        "create": 14,
        "modify": 1,
        "delete": 0,
        "area": 0.000482367774249923,
        "is_suspect": true,
        "harmful": null,
        "checked": false,
        "check_date": null,
        "metadata": {
          "host": "waldbrand-app.de",
          "theme": "waldbrand",
          "imagery": "osm",
          "language": "de",
          "theme-creator": "Sebastian Kürten"
        }
      },
      "geometry": {
        "type": "Point",
        "coordinates": [
          14.17389845,
          52.446407449999995
        ]
      }
    }
  ]
}