{
  "type": "FeatureCollection",
  "features": [
    {
      "type": "Feature",
      "properties": {
        "check_user": null,
        "reasons": [
          {
            "id": 40,
            "name": "New mapper"
          }
        ],
        "tags": [],
        "features": [],
        "user": "Magnus1234",
        "uid": "14305060",
        "editor": "MapComplete 0.11.2",
        "comment": "Adding data with #MapComplete for theme #cyclofix",
        "comments_count": 0,
        "source": "survey",
        "imagery_used": "Not reported",
        "date": "2021-10-26T06:27:31Z",
        "reviewed_features": [],
        "create": 1,
        "modify": 0,
        "delete": 0,
        "area": 0,
        "is_suspect": true,
        "harmful": null,
        "checked": false,
        "check_date": null,
        "metadata": {
          "host": "mapcomplete.osm.be",
          "theme": "cyclofix",
          "create": 1,
          "imagery": "CartoDB.Voyager",
          "language": "en"
        }
      },
      "geometry": {
        "type": "Point",
        "coordinates": [
          7.7512944,
          49.4243983
        ]
      }
    },
    {
      "type": "Feature",
      "properties": {
        "check_user": null,
        "reasons": [
          {
            "id": 40,
            "name": "New mapper"
          }
        ],
        "tags": [],
        "features": [],
        "user": "Magnus1234",
        "uid": "14305060",
        "editor": "MapComplete 0.11.0",
        "comment": "Adding data with #MapComplete for theme #cyclofix",
        "comments_count": 0,
        "source": "survey",
        "imagery_used": "Not reported",
        "date": "2021-10-24T10:29:26Z",
        "reviewed_features": [],
        "create": 1,
        "modify": 1,
        "delete": 0,
        "area": 0,
        "is_suspect": true,
        "harmful": null,
        "checked": false,
        "check_date": null,
        "metadata": {
          "host": "mapcomplete.osm.be",
          "theme": "cyclofix",
          "answer": 2,
          "create": 1,
          "imagery": "CartoDB.Voyager",
          "language": "en"
        }
      },
      "geometry": {
        "type": "Point",
        "coordinates": [
          7.7575386,
          49.4237877
        ]
      }
    },
    {
      "type": "Feature",
      "properties": {
        "check_user": null,
        "reasons": [
          {
            "id": 40,
            "name": "New mapper"
          }
        ],
        "tags": [],
        "features": [],
        "user": "Magnus1234",
        "uid": "14305060",
        "editor": "MapComplete 0.10.6",
        "comment": "Adding data with #MapComplete for theme #cyclofix",
        "comments_count": 0,
        "source": "survey",
        "imagery_used": "Not reported",
        "date": "2021-10-17T12:02:29Z",
        "reviewed_features": [],
        "create": 1,
        "modify": 5,
        "delete": 0,
        "area": 0.00000164706367999686,
        "is_suspect": true,
        "harmful": null,
        "checked": false,
        "check_date": null,
        "metadata": {
          "host": "mapcomplete.osm.be",
          "theme": "cyclofix",
          "imagery": "CartoDB.Voyager",
          "language": "en",
          "theme-creator": "MapComplete"
        }
      },
      "geometry": {
        "type": "Point",
        "coordinates": [
          7.7511352,
          49.4252185
        ]
      }
    },
    {
      "type": "Feature",
      "properties": {
        "check_user": null,
        "reasons": [
          {
            "id": 40,
            "name": "New mapper"
          }
        ],
        "tags": [],
        "features": [],
        "user": "Magnus1234",
        "uid": "14305060",
        "editor": "MapComplete 0.10.6",
        "comment": "Adding data with #MapComplete for theme #cycle_infra",
        "comments_count": 0,
        "source": "survey",
        "imagery_used": "Not reported",
        "date": "2021-10-17T11:57:35Z",
        "reviewed_features": [],
        "create": 0,
        "modify": 1,
        "delete": 0,
        "area": 0,
        "is_suspect": true,
        "harmful": null,
        "checked": false,
        "check_date": null,
        "metadata": {
          "host": "mapcomplete.osm.be",
          "theme": "cycle_infra",
          "imagery": "CartoDB.Voyager",
          "language": "en",
          "theme-creator": "MapComplete"
        }
      },
      "geometry": {
        "type": "Point",
        "coordinates": [
          7.7597241,
          49.4281582
        ]
      }
    }
  ]
}