{
  "type": "FeatureCollection",
  "features": [
    {
      "type": "Feature",
      "properties": {
        "check_user": null,
        "reasons": [
          {
            "id": 40,
            "name": "New mapper"
          }
        ],
        "tags": [],
        "features": [],
        "user": "Pablo667",
        "uid": "13166651",
        "editor": "MapComplete 0.11.3",
        "comment": "Adding data with #MapComplete for theme #toilets",
        "comments_count": 0,
        "source": "Not reported",
        "imagery_used": "Not reported",
        "date": "2021-11-02T16:02:36Z",
        "reviewed_features": [],
        "create": 1,
        "modify": 2,
        "delete": 0,
        "area": 0,
        "is_suspect": true,
        "harmful": null,
        "checked": false,
        "check_date": null,
        "metadata": {
          "host": "mapcomplete.osm.be",
          "theme": "toilets",
          "answer": 4,
          "create": 1,
          "imagery": "osm",
          "language": "en"
        }
      },
      "geometry": {
        "type": "Point",
        "coordinates": [
          12.1995771,
          44.419088
        ]
      }
    }
  ]
}