{
  "type": "FeatureCollection",
  "features": [
    {
      "type": "Feature",
      "properties": {
        "check_user": null,
        "reasons": [
          {
            "id": 40,
            "name": "New mapper"
          }
        ],
        "tags": [],
        "features": [],
        "user": "Stefank3355",
        "uid": "13987313",
        "editor": "MapComplete 0.7.2l",
        "comment": "Adding data with #MapComplete for theme #waldbrand",
        "comments_count": 0,
        "source": "Not reported",
        "imagery_used": "Not reported",
        "date": "2021-08-24T13:41:37Z",
        "reviewed_features": [],
        "create": 2,
        "modify": 1,
        "delete": 0,
        "area": 8.65218770001849e-7,
        "is_suspect": true,
        "harmful": null,
        "checked": false,
        "check_date": null,
        "metadata": {
          "host": "waldbrand-app.de",
          "theme": "waldbrand",
          "imagery": "osm",
          "language": "de",
          "theme-creator": "Sebastian Kürten"
        }
      },
      "geometry": {
        "type": "Point",
        "coordinates": [
          13.48438245,
          52.15649725
        ]
      }
    }
  ]
}