{
  "type": "FeatureCollection",
  "features": [
    {
      "type": "Feature",
      "properties": {
        "check_user": null,
        "reasons": [],
        "tags": [],
        "features": [],
        "user": "Pieter Vander Vennet",
        "uid": "3818858",
        "editor": "MapComplete 0.13.0-alpha-8",
        "comment": "Adding data with #MapComplete for theme #missing_streets  Mechanical edit: if a single CRAB-address is in the building, has the same housenumber and the same name as a nearby street, then addr:street is added if missing. ",
        "comments_count": 0,
        "source": "Not reported",
        "imagery_used": "Not reported",
        "date": "2021-12-19T18:09:20Z",
        "reviewed_features": [],
        "create": 0,
        "modify": 30,
        "delete": 0,
        "area": 0.00967753889369986,
        "is_suspect": false,
        "harmful": null,
        "checked": false,
        "check_date": null,
        "metadata": {
          "host": "127.0.0.1:1234",
          "theme": "missing_streets",
          "answer": 30,
          "language": "nl",
          "change_over_5000m": 30
        }
      },
      "geometry": {
        "type": "Point",
        "coordinates": [
          4.09245765,
          50.9781713
        ]
      }
    }
  ]
}