{
  "type": "FeatureCollection",
  "features": [
    {
      "type": "Feature",
      "properties": {
        "check_user": null,
        "reasons": [],
        "tags": [],
        "features": [],
        "user": "NaanAvanIllai",
        "uid": "14062769",
        "editor": "MapComplete 0.21.0",
        "comment": "Adding data with #MapComplete for theme #etymology",
        "comments_count": 0,
        "source": "Not reported",
        "imagery_used": "Not reported",
        "date": "2022-06-25T16:34:39Z",
        "reviewed_features": [],
        "tag_changes": {},
        "create": 0,
        "modify": 90,
        "delete": 0,
        "area": 310.420779238413,
        "is_suspect": false,
        "harmful": null,
        "checked": false,
        "check_date": null,
        "host": "https://mapcomplete.osm.be/etymology.html",
        "theme": "etymology",
        "answer": 143,
        "locale": "en",
        "imagery": "osm",
        "id": 122843152
      },
      "geometry": {
        "type": "Point",
        "coordinates": [
          21.4901391,
          79.20505345000001
        ]
      },
      "id": 122843152
    },
    {
      "type": "Feature",
      "properties": {
        "check_user": null,
        "reasons": [],
        "tags": [],
        "features": [],
        "user": "NaanAvanIllai",
        "uid": "14062769",
        "editor": "MapComplete 0.23.1",
        "comment": "Adding data with #MapComplete for theme #etymology",
        "comments_count": 0,
        "source": "Not reported",
        "imagery_used": "Not reported",
        "date": "2022-08-31T10:33:34Z",
        "reviewed_features": [],
        "tag_changes": {
          "amenity": [
            "hospital",
            "college",
            "planetarium"
          ],
          "highway": [
            "primary",
            "secondary",
            "unclassified",
            "primary_link"
          ],
          "leisure": [
            "sports_centre",
            "park",
            "stadium"
          ],
          "tourism": [
            "museum"
          ],
          "building": [
            "yes"
          ],
          "name:etymology:wikidata": [
            "Q3633365",
            "Q983057",
            "Q7528501",
            "Q4740313",
            "Q6192525",
            "Q1047",
            "Q1854649",
            "Q471040",
            "Q5521053"
          ]
        },
        "create": 0,
        "modify": 111,
        "delete": 0,
        "area": 148.001491671467,
        "is_suspect": false,
        "harmful": null,
        "checked": false,
        "check_date": null,
        "host": "https://mapcomplete.osm.be/etymology.html",
        "theme": "etymology",
        "answer": 167,
        "locale": "en",
        "imagery": "osm",
        "id": 125605625
      },
      "geometry": {
        "type": "Point",
        "coordinates": [
          22.395775899999997,
          79.04839055
        ]
      },
      "id": 125605625
    },
    {
      "type": "Feature",
      "properties": {
        "check_user": null,
        "reasons": [],
        "tags": [],
        "features": [],
        "user": "NaanAvanIllai",
        "uid": "14062769",
        "editor": "MapComplete 0.25.6",
        "comment": "Adding data with #MapComplete for theme #etymology",
        "comments_count": 0,
        "source": "Not reported",
        "imagery_used": "Not reported",
        "date": "2023-01-31T06:16:54Z",
        "reviewed_features": [],
        "tag_changes": {
          "amenity": [
            "hospital",
            "university",
            "school"
          ],
          "barrier": [
            "wall"
          ],
          "highway": [
            "turning_circle",
            "primary"
          ],
          "leisure": [
            "park"
          ],
          "tourism": [
            "zoo"
          ],
          "name:etymology:wikidata": [
            "Q1585339",
            "Q2721496",
            "Q1942799",
            "Q7639672",
            "Q7241",
            "Q6123435",
            "Q6787362",
            "Q330521",
            "Q12446063",
            "Q12446066"
          ]
        },
        "create": 0,
        "modify": 58,
        "delete": 0,
        "area": 260.676944502721,
        "is_suspect": false,
        "harmful": null,
        "checked": false,
        "check_date": null,
        "host": "https://mapcomplete.osm.be/etymology.html",
        "theme": "etymology",
        "answer": 78,
        "locale": "en",
        "imagery": "osm",
        "id": 131906372
      },
      "geometry": {
        "type": "Point",
        "coordinates": [
          20.7453581,
          79.38147000000001
        ]
      },
      "id": 131906372
    }
  ]
}