{
  "type": "FeatureCollection",
  "features": [
    {
      "type": "Feature",
      "properties": {
        "check_user": null,
        "reasons": [
          {
            "id": 40,
            "name": "New mapper"
          }
        ],
        "tags": [],
        "features": [],
        "user": "Yester_Ko",
        "uid": "7170749",
        "editor": "MapComplete 0.26.0",
        "comment": "Adding data with #MapComplete for theme #playgrounds",
        "comments_count": 0,
        "source": "Not reported",
        "imagery_used": "Not reported",
        "date": "2023-02-07T18:08:03Z",
        "reviewed_features": [],
        "tag_changes": {
          "fee": [
            "no"
          ],
          "access": [
            "yes"
          ],
          "leisure": [
            "playground"
          ],
          "surface": [
            "sand"
          ],
          "opening_hours": [
            "24/7"
          ]
        },
        "create": 2,
        "modify": 8,
        "delete": 0,
        "area": 0.00027485630652001,
        "is_suspect": true,
        "harmful": null,
        "checked": false,
        "check_date": null,
        "host": "https://mapcomplete.osm.be/playgrounds.html",
        "theme": "playgrounds",
        "answer": 14,
        "locale": "en",
        "imagery": "osm",
        "id": 132218714
      },
      "geometry": {
        "type": "Point",
        "coordinates": [
          24.7116409,
          59.3866334
        ]
      },
      "id": 132218714
    },
    {
      "type": "Feature",
      "properties": {
        "check_user": null,
        "reasons": [
          {
            "id": 40,
            "name": "New mapper"
          }
        ],
        "tags": [],
        "features": [],
        "user": "Yester_Ko",
        "uid": "7170749",
        "editor": "MapComplete 0.26.1",
        "comment": "Adding data with #MapComplete for theme #playgrounds",
        "comments_count": 0,
        "source": "survey",
        "imagery_used": "Not reported",
        "date": "2023-02-13T13:14:33Z",
        "reviewed_features": [],
        "tag_changes": {
          "lit": [
            "no"
          ],
          "leisure": [
            "playground"
          ],
          "surface": [
            "grass",
            "sand"
          ]
        },
        "create": 0,
        "modify": 1,
        "delete": 0,
        "area": 0,
        "is_suspect": true,
        "harmful": null,
        "checked": false,
        "check_date": null,
        "host": "https://mapcomplete.osm.be/playgrounds",
        "theme": "playgrounds",
        "answer": 2,
        "locale": "en",
        "imagery": "osm",
        "change_within_25m": 2,
        "id": 132489980
      },
      "geometry": {
        "type": "Point",
        "coordinates": [
          24.7076887,
          59.3877184
        ]
      },
      "id": 132489980
    }
  ]
}