{
  "type": "FeatureCollection",
  "features": [
    {
      "type": "Feature",
      "properties": {
        "check_user": null,
        "reasons": [],
        "tags": [],
        "features": [],
        "user": "Jason Olshefsky",
        "uid": "107979",
        "editor": "MapComplete 0.7.0c",
        "comment": "Adding data with #MapComplete for theme #hailhydrant",
        "comments_count": 0,
        "source": "Not reported",
        "imagery_used": "Not reported",
        "date": "2021-05-12T13:13:17Z",
        "reviewed_features": [],
        "tag_changes": {},
        "create": 2,
        "modify": 2,
        "delete": 0,
        "area": 2.95637399980937e-8,
        "is_suspect": false,
        "harmful": null,
        "checked": false,
        "check_date": null,
        "host": "mapcomplete.osm.be",
        "theme": "hailhydrant",
        "imagery": "HDM_HOT",
        "language": "en",
        "theme-creator": "Erwin Olario",
        "id": 104576707
      },
      "geometry": {
        "type": "Point",
        "coordinates": [
          -77.6209281,
          43.11637895
        ]
      },
      "id": 104576707
    },
    {
      "type": "Feature",
      "properties": {
        "check_user": null,
        "reasons": [],
        "tags": [],
        "features": [],
        "user": "Nate the Mapper",
        "uid": "6466759",
        "editor": "MapComplete 0.13.1",
        "comment": "Adding data with #MapComplete for theme #charging_stations",
        "comments_count": 0,
        "source": "Not reported",
        "imagery_used": "Not reported",
        "date": "2022-01-12T13:58:12Z",
        "reviewed_features": [],
        "tag_changes": {},
        "create": 2,
        "modify": 6,
        "delete": 0,
        "area": 0.0000180687871999255,
        "is_suspect": false,
        "harmful": null,
        "checked": false,
        "check_date": null,
        "host": "mapcomplete.osm.be",
        "theme": "charging_stations",
        "answer": 13,
        "imagery": "EsriWorldImagery",
        "language": "en",
        "id": 116068291
      },
      "geometry": {
        "type": "Point",
        "coordinates": [
          -76.96611775,
          44.264437900000004
        ]
      },
      "id": 116068291
    },
    {
      "type": "Feature",
      "properties": {
        "check_user": null,
        "reasons": [
          {
            "id": 40,
            "name": "New mapper"
          }
        ],
        "tags": [],
        "features": [],
        "user": "RadagastWiz",
        "uid": "1292503",
        "editor": "MapComplete 0.30.7",
        "comment": "Adding data with #MapComplete for theme #clock",
        "comments_count": 0,
        "source": "Not reported",
        "imagery_used": "Not reported",
        "date": "2023-06-25T21:25:19Z",
        "reviewed_features": [],
        "tag_changes": {
          "date": [
            "no"
          ],
          "faces": [
            "4"
          ],
          "amenity": [
            "clock"
          ],
          "display": [
            "analog"
          ],
          "support": [
            "wall_mounted"
          ],
          "building": [
            "yes"
          ],
          "man_made": [
            "tower"
          ],
          "barometer": [
            "no"
          ],
          "hygrometer": [
            "no"
          ],
          "visibility": [
            "area"
          ],
          "thermometer": [
            "no"
          ]
        },
        "create": 0,
        "modify": 7,
        "delete": 0,
        "area": 9.46250444002137,
        "is_suspect": true,
        "harmful": null,
        "checked": false,
        "check_date": null,
        "host": "https://mapcomplete.osm.be/clock.html",
        "theme": "clock",
        "answer": 21,
        "locale": "en",
        "id": 137767484
      },
      "geometry": {
        "type": "Point",
        "coordinates": [
          -78.11274184999999,
          44.444587150000004
        ]
      },
      "id": 137767484
    }
  ]
}