{
  "type": "FeatureCollection",
  "features": [
    {
      "type": "Feature",
      "properties": {
        "check_user": null,
        "reasons": [
          {
            "id": 40,
            "name": "New mapper"
          }
        ],
        "tags": [],
        "features": [],
        "user": "choengbiy",
        "uid": "16317899",
        "editor": "MapComplete 0.20.3",
        "comment": "Adding data with #MapComplete for theme #surveillance",
        "comments_count": 0,
        "source": "Not reported",
        "imagery_used": "Not reported",
        "date": "2022-06-19T16:48:16Z",
        "reviewed_features": [],
        "tag_changes": {
          "man_made": [
            "surveillance"
          ]
        },
        "create": 1,
        "modify": 4,
        "delete": 0,
        "area": 0,
        "is_suspect": true,
        "harmful": null,
        "checked": false,
        "check_date": null,
        "host": "https://mapcomplete.osm.be/surveillance.html",
        "theme": "surveillance",
        "answer": 2,
        "locale": "en",
        "imagery": "EsriWorldImagery",
        "add-image": 2,
        "id": 122586466
      },
      "geometry": {
        "type": "Point",
        "coordinates": [
          103.0384728,
          13.3538336
        ]
      },
      "id": 122586466
    }
  ]
}