{
  "type": "FeatureCollection",
  "features": [
    {
      "type": "Feature",
      "properties": {
        "check_user": null,
        "reasons": [
          {
            "id": 40,
            "name": "New mapper"
          }
        ],
        "tags": [],
        "features": [],
        "user": "Wouter Vanhove",
        "uid": "11484390",
        "editor": "MapComplete 0.0.0",
        "comment": "Beantwoorden van vragen met #MapComplete voor vragenset #buurtnatuur",
        "comments_count": null,
        "source": "Not reported",
        "imagery_used": "Not reported",
        "date": "2020-07-13T07:32:10Z",
        "reviewed_features": [],
        "create": 0,
        "modify": 1,
        "delete": 0,
        "area": 3.43589999995168e-7,
        "is_suspect": true,
        "harmful": null,
        "checked": false,
        "check_date": null,
        "metadata": {
          "theme": "buurtnatuur"
        }
      },
      "geometry": {
        "type": "Point",
        "coordinates": [
          3.67531695,
          51.0727111
        ]
      }
    },
    {
      "type": "Feature",
      "properties": {
        "check_user": null,
        "reasons": [],
        "tags": [],
        "features": [],
        "user": "frank vanhyfte",
        "uid": "1026732",
        "editor": "MapComplete 0.6.0",
        "comment": "Adding data with #MapComplete for theme #cyclofix",
        "comments_count": 0,
        "source": "Not reported",
        "imagery_used": "Not reported",
        "date": "2021-03-23T11:18:52Z",
        "reviewed_features": [],
        "create": 0,
        "modify": 1,
        "delete": 0,
        "area": 8.91894000048929e-9,
        "is_suspect": false,
        "harmful": null,
        "checked": false,
        "check_date": null,
        "metadata": {
          "host": "mapcomplete.osm.be",
          "theme": "cyclofix",
          "imagery": "CartoDB.Voyager",
          "language": "en",
          "theme-creator": "MapComplete"
        }
      },
      "geometry": {
        "type": "Point",
        "coordinates": [
          3.68050505,
          51.0730919
        ]
      }
    }
  ]
}