{
  "type": "FeatureCollection",
  "features": [
    {
      "type": "Feature",
      "properties": {
        "check_user": null,
        "reasons": [
          {
            "id": 40,
            "name": "New mapper"
          }
        ],
        "tags": [],
        "features": [],
        "user": "Pablo667",
        "uid": "13166651",
        "editor": "MapComplete 0.11.2",
        "comment": "Adding data with #MapComplete for theme #toilets",
        "comments_count": 0,
        "source": "Not reported",
        "imagery_used": "Not reported",
        "date": "2021-10-27T16:06:49Z",
        "reviewed_features": [],
        "create": 1,
        "modify": 3,
        "delete": 0,
        "area": 1.00000000023515e-10,
        "is_suspect": true,
        "harmful": null,
        "checked": false,
        "check_date": null,
        "metadata": {
          "host": "mapcomplete.osm.be",
          "move": 1,
          "theme": "toilets",
          "answer": 4,
          "create": 1,
          "imagery": "osm",
          "language": "en",
          "move:node/9205242210": "improve_accuracy"
        }
      },
      "geometry": {
        "type": "Point",
        "coordinates": [
          11.5990736,
          46.66878385
        ]
      }
    },
    {
      "type": "Feature",
      "properties": {
        "check_user": null,
        "reasons": [
          {
            "id": 40,
            "name": "New mapper"
          }
        ],
        "tags": [],
        "features": [],
        "user": "Pablo667",
        "uid": "13166651",
        "editor": "MapComplete 0.11.2",
        "comment": "Adding data with #MapComplete for theme #toilets",
        "comments_count": 0,
        "source": "survey",
        "imagery_used": "Not reported",
        "date": "2021-10-26T16:04:09Z",
        "reviewed_features": [],
        "create": 1,
        "modify": 1,
        "delete": 0,
        "area": 0,
        "is_suspect": true,
        "harmful": null,
        "checked": false,
        "check_date": null,
        "metadata": {
          "host": "mapcomplete.osm.be",
          "theme": "toilets",
          "answer": 2,
          "create": 1,
          "imagery": "osm",
          "language": "en"
        }
      },
      "geometry": {
        "type": "Point",
        "coordinates": [
          11.5689426,
          46.6417558
        ]
      }
    }
  ]
}