{
  "type": "FeatureCollection",
  "features": [
    {
      "type": "Feature",
      "properties": {
        "check_user": null,
        "reasons": [
          {
            "id": 40,
            "name": "New mapper"
          }
        ],
        "tags": [],
        "features": [],
        "user": "ClarissaWAM",
        "uid": "13745921",
        "editor": "MapComplete 0.8.3e",
        "comment": "Adding data with #MapComplete for theme #bookcases",
        "comments_count": 0,
        "source": "Not reported",
        "imagery_used": "Not reported",
        "date": "2021-07-12T16:50:27Z",
        "reviewed_features": [],
        "create": 1,
        "modify": 6,
        "delete": 0,
        "area": 0.0154956753896392,
        "is_suspect": true,
        "harmful": null,
        "checked": false,
        "check_date": null,
        "metadata": {
          "host": "mapcomplete.osm.be",
          "theme": "bookcases",
          "imagery": "osm",
          "language": "en",
          "theme-creator": "MapComplete"
        }
      },
      "geometry": {
        "type": "Point",
        "coordinates": [
          5.94825415,
          49.9165269
        ]
      }
    },
    {
      "type": "Feature",
      "properties": {
        "check_user": null,
        "reasons": [
          {
            "id": 40,
            "name": "New mapper"
          }
        ],
        "tags": [],
        "features": [],
        "user": "ClarissaWAM",
        "uid": "13745921",
        "editor": "MapComplete 0.9.0",
        "comment": "Adding data with #MapComplete for theme #bookcases",
        "comments_count": 0,
        "source": "Not reported",
        "imagery_used": "Not reported",
        "date": "2021-09-11T13:40:12Z",
        "reviewed_features": [],
        "create": 1,
        "modify": 2,
        "delete": 0,
        "area": 0,
        "is_suspect": true,
        "harmful": null,
        "checked": false,
        "check_date": null,
        "metadata": {
          "host": "mapcomplete.osm.be",
          "theme": "bookcases",
          "imagery": "osm",
          "language": "en",
          "theme-creator": "MapComplete"
        }
      },
      "geometry": {
        "type": "Point",
        "coordinates": [
          5.9359699,
          49.9109289
        ]
      }
    }
  ]
}