{
  "type": "FeatureCollection",
  "features": [
    {
      "type": "Feature",
      "properties": {
        "check_user": null,
        "reasons": [
          {
            "id": 40,
            "name": "New mapper"
          }
        ],
        "tags": [],
        "features": [],
        "user": "Feuerwehr Amt Putlitz-Berge",
        "uid": "13580003",
        "editor": "MapComplete 0.7.2l",
        "comment": "Adding data with #MapComplete for theme #waldbrand",
        "comments_count": 0,
        "source": "survey",
        "imagery_used": "Not reported",
        "date": "2021-06-17T08:56:29Z",
        "reviewed_features": [],
        "create": 1,
        "modify": 1,
        "delete": 0,
        "area": 0,
        "is_suspect": true,
        "harmful": null,
        "checked": false,
        "check_date": null,
        "metadata": {
          "host": "waldbrand-app.de",
          "theme": "waldbrand",
          "imagery": "osm",
          "language": "de",
          "theme-creator": "Sebastian Kürten"
        }
      },
      "geometry": {
        "type": "Point",
        "coordinates": [
          12.0327356,
          53.2451823
        ]
      }
    }
  ]
}