{
  "type": "FeatureCollection",
  "features": [
    {
      "type": "Feature",
      "properties": {
        "check_user": null,
        "reasons": [
          {
            "id": 40,
            "name": "New mapper"
          }
        ],
        "tags": [],
        "features": [],
        "user": "Marvin Geisler",
        "uid": "13424339",
        "editor": "MapComplete 0.7.2l",
        "comment": "Adding data with #MapComplete for theme #waldbrand",
        "comments_count": 0,
        "source": "Not reported",
        "imagery_used": "Not reported",
        "date": "2021-10-05T14:39:27Z",
        "reviewed_features": [],
        "create": 0,
        "modify": 1,
        "delete": 0,
        "area": 0,
        "is_suspect": true,
        "harmful": null,
        "checked": false,
        "check_date": null,
        "metadata": {
          "host": "waldbrand-app.de",
          "theme": "waldbrand",
          "imagery": "osm",
          "language": "de",
          "theme-creator": "Sebastian K端rten"
        }
      },
      "geometry": {
        "type": "Point",
        "coordinates": [
          13.8333693,
          51.8019113
        ]
      }
    },
    {
      "type": "Feature",
      "properties": {
        "check_user": null,
        "reasons": [
          {
            "id": 40,
            "name": "New mapper"
          }
        ],
        "tags": [],
        "features": [],
        "user": "Marvin Geisler",
        "uid": "13424339",
        "editor": "MapComplete 0.7.2l",
        "comment": "Adding data with #MapComplete for theme #waldbrand",
        "comments_count": 0,
        "source": "Not reported",
        "imagery_used": "Not reported",
        "date": "2021-05-27T16:49:44Z",
        "reviewed_features": [],
        "create": 1,
        "modify": 2,
        "delete": 0,
        "area": 0.0000026637356099939,
        "is_suspect": true,
        "harmful": null,
        "checked": false,
        "check_date": null,
        "metadata": {
          "host": "waldbrand-app.de",
          "theme": "waldbrand",
          "imagery": "osm",
          "language": "de",
          "theme-creator": "Sebastian K端rten"
        }
      },
      "geometry": {
        "type": "Point",
        "coordinates": [
          13.819718049999999,
          51.81127015
        ]
      }
    },
    {
      "type": "Feature",
      "properties": {
        "check_user": null,
        "reasons": [
          {
            "id": 40,
            "name": "New mapper"
          }
        ],
        "tags": [],
        "features": [],
        "user": "Marvin Geisler",
        "uid": "13424339",
        "editor": "MapComplete 0.7.2l",
        "comment": "Adding data with #MapComplete for theme #waldbrand",
        "comments_count": 0,
        "source": "Not reported",
        "imagery_used": "Not reported",
        "date": "2021-05-27T13:34:43Z",
        "reviewed_features": [],
        "create": 3,
        "modify": 3,
        "delete": 0,
        "area": 0.000367587024000074,
        "is_suspect": true,
        "harmful": null,
        "checked": false,
        "check_date": null,
        "metadata": {
          "host": "waldbrand-app.de",
          "theme": "waldbrand",
          "imagery": "osm",
          "language": "de",
          "theme-creator": "Sebastian K端rten"
        }
      },
      "geometry": {
        "type": "Point",
        "coordinates": [
          13.806082199999999,
          51.8169858
        ]
      }
    },
    {
      "type": "Feature",
      "properties": {
        "check_user": null,
        "reasons": [
          {
            "id": 40,
            "name": "New mapper"
          }
        ],
        "tags": [],
        "features": [],
        "user": "Anne-Marie Hannuschke",
        "uid": "14134184",
        "editor": "MapComplete 0.7.2l",
        "comment": "Adding data with #MapComplete for theme #waldbrand",
        "comments_count": 0,
        "source": "Not reported",
        "imagery_used": "Not reported",
        "date": "2021-09-18T10:37:49Z",
        "reviewed_features": [],
        "create": 4,
        "modify": 3,
        "delete": 0,
        "area": 0.000576460037500006,
        "is_suspect": true,
        "harmful": null,
        "checked": false,
        "check_date": null,
        "metadata": {
          "host": "www.waldbrand-app.de",
          "theme": "waldbrand",
          "imagery": "osm",
          "language": "de",
          "theme-creator": "Sebastian K端rten"
        }
      },
      "geometry": {
        "type": "Point",
        "coordinates": [
          13.80807595,
          51.8142208
        ]
      }
    }
  ]
}