{
  "type": "FeatureCollection",
  "features": [
    {
      "type": "Feature",
      "properties": {
        "check_user": null,
        "reasons": [],
        "tags": [],
        "features": [],
        "user": "Boyan Alexiev",
        "uid": "5686224",
        "editor": "MapComplete 0.36.7",
        "comment": "Adding data with #MapComplete for theme #etymology",
        "comments_count": 0,
        "source": "Not reported",
        "imagery_used": "Not reported",
        "date": "2023-12-28T11:29:49Z",
        "reviewed_features": [],
        "tag_changes": {
          "highway": [
            "pedestrian",
            "residential",
            "tertiary",
            "secondary",
            "unclassified"
          ],
          "tourism": [
            "attraction"
          ],
          "building": [
            "yes"
          ],
          "name:etymology:wikidata": [
            "Q2023149",
            "Q12276691",
            "Q313833",
            "Q941932",
            "Q219",
            "Q2444346",
            "Q360160",
            "Q98059949",
            "Q649",
            "Q318461",
            "Q914",
            "Q1445532",
            "Q1376884",
            "Q1058720",
            "Q1483759",
            "Q2989196",
            "Q7298468",
            "Q527920",
            "Q3393215",
            "Q12298484",
            "Q347118",
            "Q239925",
            "Q114450",
            "Q2092187",
            "Q313535",
            "Q1417232",
            "Q192264",
            "Q187352",
            "Q2499424",
            "Q310630"
          ]
        },
        "create": 0,
        "modify": 86,
        "delete": 0,
        "area": 0.00037618739489994,
        "is_suspect": false,
        "harmful": null,
        "checked": false,
        "check_date": null,
        "host": "https://mapcomplete.org/etymology",
        "theme": "etymology",
        "answer": 89,
        "locale": "en",
        "change_over_5000m": 28,
        "id": 145614672
      },
      "geometry": {
        "type": "Point",
        "coordinates": [
          26.19798925,
          41.7662055
        ]
      },
      "id": 145614672
    }
  ]
}