{
  "type": "FeatureCollection",
  "features": [
    {
      "type": "Feature",
      "properties": {
        "check_user": null,
        "reasons": [
          {
            "id": 40,
            "name": "New mapper"
          }
        ],
        "tags": [],
        "features": [],
        "user": "Manuel C Arco Martos",
        "uid": "13949545",
        "editor": "MapComplete 0.8.4",
        "comment": "Adding data with #MapComplete for theme #drinking_water",
        "comments_count": 0,
        "source": "Not reported",
        "imagery_used": "Not reported",
        "date": "2021-08-19T18:10:34Z",
        "reviewed_features": [],
        "create": 4,
        "modify": 8,
        "delete": 0,
        "area": 0.0000247188862000038,
        "is_suspect": true,
        "harmful": null,
        "checked": false,
        "check_date": null,
        "metadata": {
          "host": "mapcomplete.osm.be",
          "theme": "drinking_water",
          "imagery": "osm",
          "language": "en",
          "theme-creator": "MapComplete"
        }
      },
      "geometry": {
        "type": "Point",
        "coordinates": [
          -1.37447785,
          39.8139357
        ]
      }
    }
  ]
}