{
  "type": "FeatureCollection",
  "features": [
    {
      "type": "Feature",
      "properties": {
        "check_user": null,
        "reasons": [
          {
            "id": 4,
            "name": "mass modification"
          },
          {
            "id": 83,
            "name": "User has multiple blocks"
          }
        ],
        "tags": [],
        "features": [],
        "user": "Simon M",
        "uid": "517839",
        "editor": "MapComplete 0.12.8",
        "comment": "Adding data with #MapComplete for theme #etymology",
        "comments_count": 0,
        "source": "Not reported",
        "imagery_used": "Not reported",
        "date": "2021-11-15T14:21:23Z",
        "reviewed_features": [],
        "create": 0,
        "modify": 231,
        "delete": 0,
        "area": 0.000742580267359978,
        "is_suspect": true,
        "harmful": null,
        "checked": false,
        "check_date": null,
        "host": "mapcomplete.osm.be",
        "theme": "etymology",
        "answer": 324,
        "imagery": "osm",
        "language": "en"
      },
      "geometry": {
        "type": "Point",
        "coordinates": [
          4.593448,
          48.7254492
        ]
      }
    },
    {
      "type": "Feature",
      "properties": {
        "check_user": null,
        "reasons": [],
        "tags": [],
        "features": [],
        "user": "joost schouppe",
        "uid": "67832",
        "editor": "MapComplete 0.8.4",
        "comment": "Adding data with #MapComplete for theme #toilets",
        "comments_count": 0,
        "source": "survey",
        "imagery_used": "Not reported",
        "date": "2021-07-24T16:12:00Z",
        "reviewed_features": [],
        "create": 0,
        "modify": 1,
        "delete": 0,
        "area": 1.01425399996098e-8,
        "is_suspect": false,
        "harmful": null,
        "checked": false,
        "check_date": null,
        "host": "mapcomplete.osm.be",
        "theme": "toilets",
        "imagery": "osm",
        "language": "en",
        "theme-creator": "MapComplete"
      },
      "geometry": {
        "type": "Point",
        "coordinates": [
          4.95734685,
          48.0559873
        ]
      }
    }
  ]
}