{
  "type": "FeatureCollection",
  "features": [
    {
      "type": "Feature",
      "properties": {
        "check_user": null,
        "reasons": [
          {
            "id": 40,
            "name": "New mapper"
          }
        ],
        "tags": [],
        "features": [],
        "user": "chrisw42",
        "uid": "20471852",
        "editor": "MapComplete 0.42.4",
        "comment": "Adding data with #MapComplete for theme #bicycle_parkings",
        "comments_count": 0,
        "source": "Not reported",
        "imagery_used": "Not reported",
        "date": "2024-05-07T14:05:39Z",
        "reviewed_features": [],
        "tag_changes": {
          "amenity": [
            "bicycle_parking"
          ]
        },
        "create": 1,
        "modify": 7,
        "delete": 0,
        "area": 3.103000002961787e-11,
        "is_suspect": true,
        "harmful": null,
        "checked": false,
        "check_date": null,
        "host": "https://mapcomplete.org/bicycle_parkings.html",
        "move": 2,
        "theme": "bicycle_parkings",
        "answer": 6,
        "locale": "en",
        "move:node/11886725646": "improve_accuracy",
        "id": 151012729
      },
      "geometry": {
        "type": "Point",
        "coordinates": [
          -79.32833925,
          43.82170725
        ]
      },
      "id": 151012729
    }
  ]
}