{
  "type": "FeatureCollection",
  "features": [
    {
      "type": "Feature",
      "properties": {
        "check_user": null,
        "reasons": [
          {
            "id": 40,
            "name": "New mapper"
          }
        ],
        "tags": [],
        "features": [],
        "user": "NickFolzie",
        "uid": "12421409",
        "editor": "MapComplete 0.2.6a",
        "comment": "Adding data with #MapComplete for theme #cyclofix",
        "comments_count": 0,
        "source": "Not reported",
        "imagery_used": "Not reported",
        "date": "2021-01-02T05:21:53Z",
        "reviewed_features": [],
        "tag_changes": {},
        "create": 2,
        "modify": 24,
        "delete": 0,
        "area": 0.0417936814663197,
        "is_suspect": true,
        "harmful": null,
        "checked": false,
        "check_date": null,
        "theme": "cyclofix",
        "language": "en",
        "theme-creator": "MapComplete",
        "id": 96794904
      },
      "geometry": {
        "type": "Point",
        "coordinates": [
          -84.3858937,
          39.1887971
        ]
      },
      "id": 96794904
    }
  ]
}