{
  "type": "FeatureCollection",
  "features": [
    {
      "type": "Feature",
      "properties": {
        "check_user": null,
        "reasons": [
          {
            "id": 4,
            "name": "mass modification"
          }
        ],
        "tags": [],
        "features": [],
        "user": "Kalepom",
        "uid": "392288",
        "editor": "MapComplete 0.27.1",
        "comment": "Adding data with #MapComplete for theme #etymology",
        "comments_count": 0,
        "source": "Not reported",
        "imagery_used": "Not reported",
        "date": "2023-03-29T12:10:11Z",
        "reviewed_features": [],
        "tag_changes": {
          "highway": [
            "primary",
            "secondary",
            "tertiary",
            "residential",
            "unclassified",
            "secondary_link",
            "tertiary_link"
          ],
          "boundary": [
            "administrative"
          ],
          "name:etymology:wikidata": [
            "Q12191",
            "Q6616",
            "Q327",
            "Q97",
            "Q1165206",
            "Q752390",
            "Q780040",
            "Q650520",
            "Q311634",
            "Q1115712",
            "Q687553"
          ]
        },
        "create": 0,
        "modify": 343,
        "delete": 0,
        "area": 4093.60717524646,
        "is_suspect": true,
        "harmful": null,
        "checked": false,
        "check_date": null,
        "host": "https://mapcomplete.osm.be/etymology.html",
        "theme": "etymology",
        "answer": 402,
        "locale": "fr",
        "imagery": "osm",
        "id": 134260525
      },
      "geometry": {
        "type": "Point",
        "coordinates": [
          26.624976500000002,
          14.748329700000001
        ]
      },
      "id": 134260525
    },
    {
      "type": "Feature",
      "properties": {
        "check_user": "mcliquid",
        "reasons": [
          {
            "id": 4,
            "name": "mass modification"
          }
        ],
        "tags": [],
        "features": [],
        "user": "Kalepom",
        "uid": "392288",
        "editor": "MapComplete 0.31.2",
        "comment": "Adding data with #MapComplete for theme #etymology",
        "comments_count": 0,
        "source": "Not reported",
        "imagery_used": "Not reported",
        "date": "2023-08-17T13:37:52Z",
        "reviewed_features": [],
        "tag_changes": {},
        "create": 0,
        "modify": 456,
        "delete": 0,
        "area": 4103.51797484948,
        "is_suspect": true,
        "harmful": true,
        "checked": true,
        "check_date": "2023-08-18T07:47:25.082705Z",
        "host": "https://mapcomplete.osm.be/etymology.html",
        "theme": "etymology",
        "answer": 459,
        "locale": "fr",
        "id": 140013696
      },
      "geometry": {
        "type": "Point",
        "coordinates": [
          26.3667352,
          13.94044045
        ]
      },
      "id": 140013696
    },
    {
      "type": "Feature",
      "properties": {
        "check_user": "mcliquid",
        "reasons": [],
        "tags": [],
        "features": [],
        "user": "Kalepom",
        "uid": "392288",
        "editor": "MapComplete 0.31.2",
        "comment": "Adding data with #MapComplete for theme #etymology",
        "comments_count": 0,
        "source": "Not reported",
        "imagery_used": "Not reported",
        "date": "2023-08-17T12:04:30Z",
        "reviewed_features": [],
        "tag_changes": {},
        "create": 0,
        "modify": 137,
        "delete": 0,
        "area": 3852.88869764728,
        "is_suspect": false,
        "harmful": true,
        "checked": true,
        "check_date": "2023-08-17T13:58:21.301918Z",
        "host": "https://mapcomplete.osm.be/etymology.html",
        "theme": "etymology",
        "answer": 137,
        "locale": "fr",
        "id": 140009680
      },
      "geometry": {
        "type": "Point",
        "coordinates": [
          27.325489649999998,
          13.4565006
        ]
      },
      "id": 140009680
    }
  ]
}