{
  "type": "FeatureCollection",
  "features": [
    {
      "type": "Feature",
      "properties": {
        "check_user": null,
        "reasons": [
          {
            "id": 40,
            "name": "New mapper"
          }
        ],
        "tags": [],
        "features": [],
        "user": "Maaike Lootens",
        "uid": "11566064",
        "editor": "MapComplete 0.0.0",
        "comment": "Beantwoorden van vragen met #MapComplete voor vragenset #buurtnatuur",
        "comments_count": null,
        "source": "Not reported",
        "imagery_used": "Not reported",
        "date": "2020-07-28T19:28:15Z",
        "reviewed_features": [],
        "create": 0,
        "modify": 1,
        "delete": 0,
        "area": 0.0000376377874199748,
        "is_suspect": true,
        "harmful": null,
        "checked": false,
        "check_date": null,
        "metadata": {
          "theme": "buurtnatuur"
        }
      },
      "geometry": {
        "type": "Point",
        "coordinates": [
          3.5203777,
          51.08793405
        ]
      }
    },
    {
      "type": "Feature",
      "properties": {
        "check_user": null,
        "reasons": [],
        "tags": [],
        "features": [],
        "user": "Pieter Nuytinck",
        "uid": "3719237",
        "editor": "MapComplete 0.4.9",
        "comment": "Adding data with #MapComplete for theme #bookcases",
        "comments_count": 0,
        "source": "Not reported",
        "imagery_used": "Not reported",
        "date": "2021-02-01T18:45:43Z",
        "reviewed_features": [],
        "create": 4,
        "modify": 24,
        "delete": 0,
        "area": 0.0417926529722997,
        "is_suspect": false,
        "harmful": null,
        "checked": false,
        "check_date": null,
        "metadata": {
          "host": "pietervdvn.github.io",
          "theme": "bookcases",
          "imagery": "osm",
          "language": "en",
          "theme-creator": "MapComplete"
        }
      },
      "geometry": {
        "type": "Point",
        "coordinates": [
          3.5935324499999997,
          51.0801166
        ]
      }
    },
    {
      "type": "Feature",
      "properties": {
        "check_user": null,
        "reasons": [],
        "tags": [],
        "features": [],
        "user": "joost schouppe",
        "uid": "67832",
        "editor": "MapComplete 0.7.5a",
        "comment": "Adding data with #MapComplete for theme #fietsstraten",
        "comments_count": 0,
        "source": "survey",
        "imagery_used": "Not reported",
        "date": "2021-06-10T13:48:05Z",
        "reviewed_features": [],
        "create": 0,
        "modify": 6,
        "delete": 0,
        "area": 0.0799440740714425,
        "is_suspect": false,
        "harmful": null,
        "checked": false,
        "check_date": null,
        "metadata": {
          "host": "mapcomplete.osm.be",
          "theme": "fietsstraten",
          "imagery": "osm",
          "language": "nl",
          "theme-creator": "MapComplete, joost schouppe"
        }
      },
      "geometry": {
        "type": "Point",
        "coordinates": [
          3.5288760999999997,
          51.1046504
        ]
      }
    }
  ]
}