{
  "type": "FeatureCollection",
  "features": [
    {
      "type": "Feature",
      "properties": {
        "check_user": null,
        "reasons": [],
        "tags": [],
        "features": [],
        "user": "Tim Couwelier",
        "uid": "7246683",
        "editor": "MapComplete 0.12.13",
        "comment": "Adding data with #MapComplete for theme #grb",
        "comments_count": 0,
        "source": "Not reported",
        "imagery_used": "Not reported",
        "date": "2021-12-21T10:40:41Z",
        "reviewed_features": [],
        "create": 404,
        "modify": 641,
        "delete": 0,
        "area": 0.0775934234689485,
        "is_suspect": false,
        "harmful": null,
        "checked": false,
        "check_date": null,
        "metadata": {
          "host": "mapcomplete.osm.be",
          "move": 522,
          "theme": "grb",
          "import": 40,
          "imagery": "osm",
          "language": "nl",
          "conflation": 226
        }
      },
      "geometry": {
        "type": "Point",
        "coordinates": [
          3.39684605,
          50.90379795
        ]
      }
    },
    {
      "type": "Feature",
      "properties": {
        "check_user": null,
        "reasons": [],
        "tags": [],
        "features": [],
        "user": "Pieter Vander Vennet",
        "uid": "3818858",
        "editor": "MapComplete 0.13.0-alpha-8",
        "comment": "Adding data with #MapComplete for theme #missing_streets  Mechanical edit: if a single CRAB-address is in the building, has the same housenumber and the same name as a nearby street, then addr:street is added if missing. ",
        "comments_count": 0,
        "source": "Not reported",
        "imagery_used": "Not reported",
        "date": "2021-12-19T00:15:06Z",
        "reviewed_features": [],
        "create": 0,
        "modify": 13,
        "delete": 0,
        "area": 0.00271505351831998,
        "is_suspect": false,
        "harmful": null,
        "checked": false,
        "check_date": null,
        "metadata": {
          "host": "127.0.0.1:1234",
          "theme": "missing_streets",
          "answer": 14,
          "language": "nl"
        }
      },
      "geometry": {
        "type": "Point",
        "coordinates": [
          3.39704555,
          50.9063546
        ]
      }
    },
    {
      "type": "Feature",
      "properties": {
        "check_user": null,
        "reasons": [],
        "tags": [],
        "features": [],
        "user": "Pieter Vander Vennet",
        "uid": "3818858",
        "editor": "MapComplete 0.13.0-alpha-8",
        "comment": "Adding data with #MapComplete for theme #missing_streets  Mechanical edit: if a single CRAB-address is in the building, has the same housenumber and the same name as a nearby street, then addr:street is added if missing. ",
        "comments_count": 0,
        "source": "Not reported",
        "imagery_used": "Not reported",
        "date": "2021-12-19T00:13:42Z",
        "reviewed_features": [],
        "create": 0,
        "modify": 19,
        "delete": 0,
        "area": 0.00019623101589009,
        "is_suspect": false,
        "harmful": null,
        "checked": false,
        "check_date": null,
        "metadata": {
          "host": "127.0.0.1:1234",
          "theme": "missing_streets",
          "answer": 21,
          "language": "nl"
        }
      },
      "geometry": {
        "type": "Point",
        "coordinates": [
          3.37193725,
          50.909577049999996
        ]
      }
    }
  ]
}