{
  "type": "FeatureCollection",
  "features": [
    {
      "type": "Feature",
      "properties": {
        "check_user": null,
        "reasons": [
          {
            "id": 40,
            "name": "New mapper"
          }
        ],
        "tags": [],
        "features": [],
        "user": "Lippmann Richard",
        "uid": "14059700",
        "editor": "MapComplete 0.9.0",
        "comment": "Adding data with #MapComplete for theme #hailhydrant",
        "comments_count": 0,
        "source": "survey",
        "imagery_used": "Not reported",
        "date": "2021-09-05T20:35:17Z",
        "reviewed_features": [],
        "create": 1,
        "modify": 1,
        "delete": 0,
        "area": 0,
        "is_suspect": true,
        "harmful": null,
        "checked": false,
        "check_date": null,
        "metadata": {
          "host": "mapcomplete.osm.be",
          "theme": "hailhydrant",
          "imagery": "HDM_HOT",
          "language": "en",
          "theme-creator": "Erwin Olario"
        }
      },
      "geometry": {
        "type": "Point",
        "coordinates": [
          10.9615713,
          49.4172352
        ]
      }
    }
  ]
}