{
  "type": "FeatureCollection",
  "features": [
    {
      "type": "Feature",
      "properties": {
        "check_user": null,
        "reasons": [
          {
            "id": 40,
            "name": "New mapper"
          }
        ],
        "tags": [],
        "features": [],
        "user": "Mohit Jairath",
        "uid": "15920679",
        "editor": "MapComplete 0.19.2",
        "comment": "Adding data with #MapComplete for theme #toerisme_vlaanderen",
        "comments_count": 0,
        "source": "Not reported",
        "imagery_used": "Not reported",
        "date": "2022-05-15T07:10:39Z",
        "reviewed_features": [],
        "tag_changes": {},
        "create": 1,
        "modify": 0,
        "delete": 0,
        "area": 0,
        "is_suspect": true,
        "harmful": null,
        "checked": false,
        "check_date": null,
        "host": "https://mapcomplete.osm.be/toerisme_vlaanderen",
        "theme": "toerisme_vlaanderen",
        "locale": "nl",
        "imagery": "osm",
        "id": 121001868
      },
      "geometry": {
        "type": "Point",
        "coordinates": [
          75.7769537,
          31.2197083
        ]
      },
      "id": 121001868
    }
  ]
}