{
  "type": "FeatureCollection",
  "features": [
    {
      "type": "Feature",
      "properties": {
        "check_user": null,
        "reasons": [
          {
            "id": 40,
            "name": "New mapper"
          }
        ],
        "tags": [],
        "features": [],
        "user": "numist",
        "uid": "7970679",
        "editor": "MapComplete 0.9.14",
        "comment": "Adding data with #MapComplete for theme #ghostbikes",
        "comments_count": 0,
        "source": "Not reported",
        "imagery_used": "Not reported",
        "date": "2021-09-27T02:08:12Z",
        "reviewed_features": [],
        "create": 1,
        "modify": 0,
        "delete": 0,
        "area": 0,
        "is_suspect": true,
        "harmful": null,
        "checked": false,
        "check_date": null,
        "id": 111745072,
        "host": "mapcomplete.osm.be",
        "theme": "ghostbikes",
        "imagery": "CartoDB.Positron",
        "language": "en",
        "theme-creator": "MapComplete"
      },
      "geometry": {
        "type": "Point",
        "coordinates": [
          -122.2583896,
          37.8367212
        ]
      }
    }
  ]
}