{
  "type": "FeatureCollection",
  "features": [
    {
      "type": "Feature",
      "properties": {
        "check_user": null,
        "reasons": [
          {
            "id": 40,
            "name": "New mapper"
          }
        ],
        "tags": [],
        "features": [],
        "user": "ehburrus",
        "uid": "16958349",
        "editor": "MapComplete 0.23.1",
        "comment": "Adding data with #MapComplete for theme #ghostbikes",
        "comments_count": 0,
        "source": "Not reported",
        "imagery_used": "Not reported",
        "date": "2022-08-28T01:57:09Z",
        "reviewed_features": [],
        "tag_changes": {
          "historic": [
            "memorial"
          ]
        },
        "create": 1,
        "modify": 1,
        "delete": 0,
        "area": 0,
        "is_suspect": true,
        "harmful": null,
        "checked": false,
        "check_date": null,
        "host": "https://mapcomplete.osm.be/ghostbikes.html",
        "theme": "ghostbikes",
        "answer": 1,
        "locale": "en",
        "imagery": "CartoDB.Positron",
        "id": 125461599
      },
      "geometry": {
        "type": "Point",
        "coordinates": [
          -78.8728884,
          42.8732943
        ]
      },
      "id": 125461599
    }
  ]
}