{
  "type": "FeatureCollection",
  "features": [
    {
      "type": "Feature",
      "properties": {
        "check_user": null,
        "reasons": [],
        "tags": [],
        "features": [],
        "user": "Danysan95",
        "uid": "4425563",
        "editor": "MapComplete 0.23.2",
        "comment": "Adding data with #MapComplete for theme #etymology",
        "comments_count": 0,
        "source": "Not reported",
        "imagery_used": "Not reported",
        "date": "2022-09-10T19:52:47Z",
        "reviewed_features": [],
        "tag_changes": {
          "route": [
            "bus"
          ],
          "highway": [
            "residential"
          ],
          "name:etymology:wikidata": [
            "Q749678",
            "Q213462",
            "Q802461",
            "Q2738834"
          ]
        },
        "create": 0,
        "modify": 6,
        "delete": 0,
        "area": 11.1889118802752,
        "is_suspect": false,
        "harmful": null,
        "checked": false,
        "check_date": null,
        "host": "https://mapcomplete.osm.be/etymology.html",
        "theme": "etymology",
        "answer": 7,
        "locale": "en",
        "imagery": "osm",
        "id": 126028377
      },
      "geometry": {
        "type": "Point",
        "coordinates": [
          13.239229550000001,
          42.5181252
        ]
      },
      "id": 126028377
    },
    {
      "type": "Feature",
      "properties": {
        "check_user": null,
        "reasons": [],
        "tags": [],
        "features": [],
        "user": "Daniele Scasciafratte",
        "uid": "6141014",
        "editor": "MapComplete 0.23.2",
        "comment": "Adding data with #MapComplete for theme #cyclofix",
        "comments_count": 0,
        "source": "Not reported",
        "imagery_used": "Not reported",
        "date": "2022-09-26T17:35:30Z",
        "reviewed_features": [],
        "tag_changes": {
          "bottle": [
            "yes"
          ],
          "amenity": [
            "drinking_water"
          ]
        },
        "create": 0,
        "modify": 3,
        "delete": 0,
        "area": 0.000015587004750033,
        "is_suspect": false,
        "harmful": null,
        "checked": false,
        "check_date": null,
        "host": "https://mapcomplete.osm.be/cyclofix.html",
        "theme": "cyclofix",
        "answer": 3,
        "locale": "en",
        "imagery": "CartoDB.Voyager",
        "id": 126665865
      },
      "geometry": {
        "type": "Point",
        "coordinates": [
          12.85653345,
          42.40339815
        ]
      },
      "id": 126665865
    },
    {
      "type": "Feature",
      "properties": {
        "check_user": "Danysan95",
        "reasons": [],
        "tags": [],
        "features": [],
        "user": "ivanbranco",
        "uid": "11220113",
        "editor": "MapComplete 0.23.2",
        "comment": "Adding data with #MapComplete for theme #etymology",
        "comments_count": 0,
        "source": "Not reported",
        "imagery_used": "Not reported",
        "date": "2022-09-28T17:58:27Z",
        "reviewed_features": [],
        "tag_changes": {
          "highway": [
            "motorway_junction",
            "unclassified",
            "motorway",
            "services",
            "residential",
            "service",
            "secondary"
          ],
          "name:etymology:wikidata": [
            "Q1248298",
            "Q113248387",
            "Q44377",
            "Q34",
            "Q29",
            "Q851323"
          ]
        },
        "create": 0,
        "modify": 79,
        "delete": 0,
        "area": 43.5792868687082,
        "is_suspect": false,
        "harmful": false,
        "checked": true,
        "check_date": "2022-10-04T09:31:24.690367Z",
        "host": "https://mapcomplete.osm.be/etymology",
        "theme": "etymology",
        "answer": 110,
        "locale": "it",
        "imagery": "osm",
        "id": 126750902
      },
      "geometry": {
        "type": "Point",
        "coordinates": [
          12.82329355,
          42.88323395
        ]
      },
      "id": 126750902
    }
  ]
}