{
  "type": "FeatureCollection",
  "features": [
    {
      "type": "Feature",
      "properties": {
        "check_user": null,
        "reasons": [],
        "tags": [],
        "features": [],
        "user": "Erin76",
        "uid": "8982454",
        "editor": "MapComplete 0.1.0c",
        "comment": "Adding data with #MapComplete for theme #fietsstraten",
        "comments_count": 0,
        "source": "Not reported",
        "imagery_used": "Not reported",
        "date": "2020-10-14T06:07:16Z",
        "reviewed_features": [],
        "create": 0,
        "modify": 15,
        "delete": 0,
        "area": 0.0784781618812804,
        "is_suspect": false,
        "harmful": null,
        "checked": false,
        "check_date": null,
        "metadata": {
          "theme": "fietsstraten",
          "language": "nl",
          "theme-creator": "MapComlete"
        }
      },
      "geometry": {
        "type": "Point",
        "coordinates": [
          3.5623467,
          50.94651075
        ]
      }
    },
    {
      "type": "Feature",
      "properties": {
        "check_user": null,
        "reasons": [
          {
            "id": 40,
            "name": "New mapper"
          }
        ],
        "tags": [],
        "features": [],
        "user": "JonasWieleman",
        "uid": "11486241",
        "editor": "MapComplete 0.0.0",
        "comment": "Beantwoorden van vragen met #MapComplete voor vragenset #buurtnatuur",
        "comments_count": null,
        "source": "Not reported",
        "imagery_used": "Not reported",
        "date": "2020-07-13T14:40:32Z",
        "reviewed_features": [],
        "create": 0,
        "modify": 1,
        "delete": 0,
        "area": 0.000152841860699988,
        "is_suspect": true,
        "harmful": null,
        "checked": false,
        "check_date": null,
        "metadata": {
          "theme": "buurtnatuur"
        }
      },
      "geometry": {
        "type": "Point",
        "coordinates": [
          3.5602858,
          50.92557795
        ]
      }
    }
  ]
}