{
  "type": "FeatureCollection",
  "features": [
    {
      "type": "Feature",
      "properties": {
        "check_user": null,
        "reasons": [
          {
            "id": 40,
            "name": "New mapper"
          }
        ],
        "tags": [],
        "features": [],
        "user": "Eeule",
        "uid": "12479179",
        "editor": "MapComplete 0.9.0",
        "comment": "Adding data with #MapComplete for theme #cyclofix",
        "comments_count": 0,
        "source": "Not reported",
        "imagery_used": "Not reported",
        "date": "2021-08-29T14:55:40Z",
        "reviewed_features": [],
        "create": 0,
        "modify": 5,
        "delete": 0,
        "area": 0,
        "is_suspect": true,
        "harmful": null,
        "checked": false,
        "check_date": null,
        "metadata": {
          "host": "mapcomplete.osm.be",
          "theme": "cyclofix",
          "imagery": "CartoDB.Voyager",
          "language": "de",
          "theme-creator": "MapComplete"
        }
      },
      "geometry": {
        "type": "Point",
        "coordinates": [
          8.3338032,
          47.8180013
        ]
      }
    }
  ]
}