{
  "type": "FeatureCollection",
  "features": [
    {
      "type": "Feature",
      "properties": {
        "check_user": null,
        "reasons": [
          {
            "id": 40,
            "name": "New mapper"
          }
        ],
        "tags": [],
        "features": [],
        "user": "sonjagerhard",
        "uid": "6332059",
        "editor": "MapComplete 0.8.4",
        "comment": "Adding data with #MapComplete for theme #charging_stations",
        "comments_count": 0,
        "source": "Not reported",
        "imagery_used": "Not reported",
        "date": "2021-08-16T09:15:13Z",
        "reviewed_features": [],
        "create": 3,
        "modify": 16,
        "delete": 0,
        "area": 0.0181698755550997,
        "is_suspect": true,
        "harmful": null,
        "checked": false,
        "check_date": null,
        "id": 109737824,
        "host": "mapcomplete.osm.be",
        "theme": "charging_stations",
        "imagery": "osm",
        "language": "en"
      },
      "geometry": {
        "type": "Point",
        "coordinates": [
          11.40384975,
          49.2066477
        ]
      }
    },
    {
      "type": "Feature",
      "properties": {
        "check_user": null,
        "reasons": [],
        "tags": [],
        "features": [],
        "user": "maggot27",
        "uid": "118021",
        "editor": "MapComplete 0.8.4",
        "comment": "Adding data with #MapComplete for theme #benches",
        "comments_count": 0,
        "source": "Not reported",
        "imagery_used": "Not reported",
        "date": "2021-08-02T17:51:33Z",
        "reviewed_features": [],
        "create": 1,
        "modify": 0,
        "delete": 0,
        "area": 0,
        "is_suspect": false,
        "harmful": null,
        "checked": false,
        "check_date": null,
        "id": 109046140,
        "host": "mapcomplete.osm.be",
        "theme": "benches",
        "imagery": "osm",
        "language": "de",
        "theme-creator": "Florian Edelmann"
      },
      "geometry": {
        "type": "Point",
        "coordinates": [
          12.1027225,
          49.6495494
        ]
      }
    }
  ]
}