{
  "type": "FeatureCollection",
  "features": [
    {
      "type": "Feature",
      "properties": {
        "check_user": null,
        "reasons": [
          {
            "id": 40,
            "name": "New mapper"
          }
        ],
        "tags": [],
        "features": [],
        "user": "Yanxg",
        "uid": "14436337",
        "editor": "MapComplete 0.12.6",
        "comment": "Adding data with #MapComplete for theme #campersite",
        "comments_count": 0,
        "source": "Not reported",
        "imagery_used": "Not reported",
        "date": "2021-11-11T16:17:13Z",
        "reviewed_features": [],
        "create": 1,
        "modify": 0,
        "delete": 0,
        "area": 0,
        "is_suspect": true,
        "harmful": null,
        "checked": false,
        "check_date": null,
        "metadata": {
          "host": "mapcomplete.osm.be",
          "theme": "campersite",
          "create": 2,
          "imagery": "osm",
          "language": "en"
        }
      },
      "geometry": {
        "type": "Point",
        "coordinates": [
          9.1788948,
          49.7538018
        ]
      }
    }
  ]
}