{
  "type": "FeatureCollection",
  "features": [
    {
      "type": "Feature",
      "properties": {
        "check_user": null,
        "reasons": [],
        "tags": [],
        "features": [],
        "user": "NaanAvanIllai",
        "uid": "14062769",
        "editor": "MapComplete 0.25.6",
        "comment": "Adding data with #MapComplete for theme #etymology",
        "comments_count": 0,
        "source": "Not reported",
        "imagery_used": "Not reported",
        "date": "2023-01-25T12:56:25Z",
        "reviewed_features": [],
        "tag_changes": {
          "amenity": [
            "school",
            "hospital",
            "college"
          ],
          "barrier": [
            "wall"
          ],
          "highway": [
            "tertiary",
            "primary",
            "secondary",
            "residential",
            "unclassified"
          ],
          "landuse": [
            "residential"
          ],
          "leisure": [
            "park",
            "stadium"
          ],
          "boundary": [
            "administrative"
          ],
          "name:etymology:wikidata": [
            "Q7526817",
            "Q717798",
            "Q2392864",
            "Q3595817",
            "Q16007413",
            "Q150465",
            "Q3634394",
            "Q279417",
            "Q191114",
            "Q319824",
            "Q890529",
            "Q185790",
            "Q2002511",
            "Q844424",
            "Q983067",
            "Q2044641",
            "Q1978476",
            "Q192207",
            "Q61078183"
          ]
        },
        "create": 0,
        "modify": 64,
        "delete": 0,
        "area": 2.68617515111763,
        "is_suspect": false,
        "harmful": null,
        "checked": false,
        "check_date": null,
        "host": "https://mapcomplete.osm.be/etymology.html",
        "theme": "etymology",
        "answer": 88,
        "locale": "en",
        "imagery": "osm",
        "id": 131694450
      },
      "geometry": {
        "type": "Point",
        "coordinates": [
          27.7452867,
          76.4623473
        ]
      },
      "id": 131694450
    }
  ]
}