{
  "type": "FeatureCollection",
  "features": [
    {
      "type": "Feature",
      "properties": {
        "check_user": null,
        "reasons": [],
        "tags": [],
        "features": [],
        "user": "Colbertson",
        "uid": "10833953",
        "editor": "MapComplete 0.25.3",
        "comment": "Adding data with #MapComplete for theme #etymology",
        "comments_count": 0,
        "source": "Not reported",
        "imagery_used": "Not reported",
        "date": "2023-01-04T09:52:59Z",
        "reviewed_features": [],
        "tag_changes": {
          "highway": [
            "secondary",
            "residential",
            "service",
            "track",
            "tertiary"
          ],
          "name:etymology:wikidata": [
            "Q1773",
            "Q909654",
            "Q525",
            "Q16351536",
            "Q503166",
            "Q454",
            "Q42302",
            "Q12004",
            "Q7777019",
            "Q1626641",
            "Q14921440",
            "Q34679",
            "Q45417383",
            "Q962653",
            "Q744099",
            "Q6565319",
            "Q168473",
            "Q51536533",
            "Q348001",
            "Q14458220",
            "Q196",
            "Q104036"
          ]
        },
        "create": 0,
        "modify": 54,
        "delete": 0,
        "area": 0.00128886655247984,
        "is_suspect": false,
        "harmful": null,
        "checked": false,
        "check_date": null,
        "host": "https://mapcomplete.osm.be/etymology.html",
        "theme": "etymology",
        "answer": 79,
        "locale": "en",
        "imagery": "osm",
        "id": 130858891
      },
      "geometry": {
        "type": "Point",
        "coordinates": [
          22.571590399999998,
          57.2388011
        ]
      },
      "id": 130858891
    }
  ]
}