{
  "type": "FeatureCollection",
  "features": [
    {
      "type": "Feature",
      "properties": {
        "check_user": null,
        "reasons": [],
        "tags": [],
        "features": [],
        "user": "NaanAvanIllai",
        "uid": "14062769",
        "editor": "MapComplete 0.25.6",
        "comment": "Adding data with #MapComplete for theme #etymology",
        "comments_count": 0,
        "source": "Not reported",
        "imagery_used": "Not reported",
        "date": "2023-02-02T06:55:33Z",
        "reviewed_features": [],
        "tag_changes": {
          "highway": [
            "residential"
          ],
          "leisure": [
            "park"
          ],
          "name:etymology:wikidata": [
            "Q2721919",
            "Q4805748",
            "Q2722486"
          ]
        },
        "create": 0,
        "modify": 56,
        "delete": 0,
        "area": 203.090986243392,
        "is_suspect": false,
        "harmful": null,
        "checked": false,
        "check_date": null,
        "host": "https://mapcomplete.osm.be/etymology.html",
        "theme": "etymology",
        "answer": 62,
        "locale": "en",
        "imagery": "osm",
        "id": 131989181
      },
      "geometry": {
        "type": "Point",
        "coordinates": [
          18.3868069,
          78.82032155
        ]
      },
      "id": 131989181
    },
    {
      "type": "Feature",
      "properties": {
        "check_user": null,
        "reasons": [],
        "tags": [],
        "features": [],
        "user": "NaanAvanIllai",
        "uid": "14062769",
        "editor": "MapComplete 0.27.1",
        "comment": "Adding data with #MapComplete for theme #etymology",
        "comments_count": 0,
        "source": "Not reported",
        "imagery_used": "Not reported",
        "date": "2023-04-20T18:50:45Z",
        "reviewed_features": [],
        "tag_changes": {
          "highway": [
            "service",
            "steps"
          ],
          "name:etymology:wikidata": [
            "Q55744",
            "Q2628981",
            "Q256286",
            "Q312551",
            "Q189725"
          ]
        },
        "create": 0,
        "modify": 5,
        "delete": 0,
        "area": 0.0000613193026499878,
        "is_suspect": false,
        "harmful": null,
        "checked": false,
        "check_date": null,
        "host": "https://mapcomplete.osm.be/etymology.html",
        "theme": "etymology",
        "answer": 5,
        "locale": "en",
        "imagery": "osm",
        "id": 135164002
      },
      "geometry": {
        "type": "Point",
        "coordinates": [
          20.76473735,
          78.58998475
        ]
      },
      "id": 135164002
    }
  ]
}