{
  "type": "FeatureCollection",
  "features": [
    {
      "type": "Feature",
      "properties": {
        "check_user": null,
        "reasons": [],
        "tags": [],
        "features": [],
        "user": "benjamintchik",
        "uid": "6290466",
        "editor": "MapComplete 0.26.0",
        "comment": "Adding data with #MapComplete for theme #etymology",
        "comments_count": 0,
        "source": "Not reported",
        "imagery_used": "Not reported",
        "date": "2023-03-05T10:34:18Z",
        "reviewed_features": [],
        "tag_changes": {
          "place": [
            "square"
          ],
          "highway": [
            "primary",
            "tertiary",
            "primary_link",
            "residential",
            "secondary",
            "tertiary_link",
            "unclassified",
            "pedestrian"
          ],
          "name:etymology": [
            "купець Савелій Павлов, який започаткував цукерково-пряникове виробництво в Харкові, побудував на площі кам'яний магазин"
          ],
          "name:etymology:wikidata": [
            "Q111014380",
            "Q7755",
            "Q3918",
            "Q2977"
          ]
        },
        "create": 0,
        "modify": 141,
        "delete": 0,
        "area": 0.0122320707975292,
        "is_suspect": false,
        "harmful": null,
        "checked": false,
        "check_date": null,
        "host": "https://mapcomplete.osm.be/etymology.html",
        "theme": "etymology",
        "answer": 234,
        "locale": "fr",
        "imagery": "osm",
        "id": 133319441
      },
      "geometry": {
        "type": "Point",
        "coordinates": [
          49.96392055,
          36.33033185
        ]
      },
      "id": 133319441
    }
  ]
}