{
  "type": "FeatureCollection",
  "features": [
    {
      "type": "Feature",
      "properties": {
        "check_user": null,
        "reasons": [
          {
            "id": 40,
            "name": "New mapper"
          }
        ],
        "tags": [],
        "features": [],
        "user": "Ritxarcontx",
        "uid": "12997299",
        "editor": "MapComplete 0.9.0",
        "comment": "Adding data with #MapComplete for theme #hailhydrant",
        "comments_count": 0,
        "source": "survey",
        "imagery_used": "Not reported",
        "date": "2021-08-22T15:41:15Z",
        "reviewed_features": [],
        "create": 1,
        "modify": 0,
        "delete": 0,
        "area": 0,
        "is_suspect": true,
        "harmful": null,
        "checked": false,
        "check_date": null,
        "metadata": {
          "host": "mapcomplete.osm.be",
          "theme": "hailhydrant",
          "imagery": "osm",
          "language": "en",
          "theme-creator": "Erwin Olario"
        }
      },
      "geometry": {
        "type": "Point",
        "coordinates": [
          -1.5646386,
          42.5236249
        ]
      }
    },
    {
      "type": "Feature",
      "properties": {
        "check_user": null,
        "reasons": [
          {
            "id": 40,
            "name": "New mapper"
          }
        ],
        "tags": [],
        "features": [],
        "user": "Ritxarcontx",
        "uid": "12997299",
        "editor": "MapComplete 0.9.0",
        "comment": "Adding data with #MapComplete for theme #hailhydrant",
        "comments_count": 0,
        "source": "Not reported",
        "imagery_used": "Not reported",
        "date": "2021-08-22T08:13:06Z",
        "reviewed_features": [],
        "create": 4,
        "modify": 3,
        "delete": 0,
        "area": 0.0000339842224000166,
        "is_suspect": true,
        "harmful": null,
        "checked": false,
        "check_date": null,
        "metadata": {
          "host": "mapcomplete.osm.be",
          "theme": "hailhydrant",
          "imagery": "osm",
          "language": "en",
          "theme-creator": "Erwin Olario"
        }
      },
      "geometry": {
        "type": "Point",
        "coordinates": [
          -1.5620355,
          42.5230351
        ]
      }
    }
  ]
}