{
  "type": "FeatureCollection",
  "features": [
    {
      "type": "Feature",
      "properties": {
        "check_user": null,
        "reasons": [],
        "tags": [],
        "features": [],
        "user": "NaanAvanIllai",
        "uid": "14062769",
        "editor": "MapComplete 0.23.0",
        "comment": "Adding data with #MapComplete for theme #etymology",
        "comments_count": 0,
        "source": "Not reported",
        "imagery_used": "Not reported",
        "date": "2022-08-09T15:08:29Z",
        "reviewed_features": [],
        "tag_changes": {
          "highway": [
            "mini_roundabout"
          ],
          "name:etymology:wikidata": [
            "Q7881063"
          ]
        },
        "create": 0,
        "modify": 1,
        "delete": 0,
        "area": 0,
        "is_suspect": false,
        "harmful": null,
        "checked": false,
        "check_date": null,
        "host": "https://mapcomplete.osm.be/etymology.html",
        "theme": "etymology",
        "answer": 1,
        "locale": "en",
        "imagery": "osm",
        "id": 124690668
      },
      "geometry": {
        "type": "Point",
        "coordinates": [
          17.9899748,
          74.4327511
        ]
      },
      "id": 124690668
    },
    {
      "type": "Feature",
      "properties": {
        "check_user": null,
        "reasons": [],
        "tags": [],
        "features": [],
        "user": "NaanAvanIllai",
        "uid": "14062769",
        "editor": "MapComplete 0.26.1",
        "comment": "Adding data with #MapComplete for theme #etymology",
        "comments_count": 0,
        "source": "Not reported",
        "imagery_used": "Not reported",
        "date": "2023-03-04T06:49:00Z",
        "reviewed_features": [],
        "tag_changes": {
          "amenity": [
            "library",
            "university",
            "college",
            "hospital"
          ],
          "highway": [
            "trunk",
            "unclassified",
            "tertiary",
            "residential",
            "secondary"
          ],
          "leisure": [
            "stadium",
            "park"
          ],
          "name:etymology:wikidata": [
            "Q65048188",
            "Q239505",
            "Q6962286",
            "Q3072027",
            "Q4901476",
            "Q13119634",
            "Q7285778",
            "Q104239664",
            "Q116973666",
            "Q100741785",
            "Q231690",
            "Q6192525",
            "Q83322"
          ]
        },
        "create": 0,
        "modify": 41,
        "delete": 0,
        "area": 9.65877299869294,
        "is_suspect": false,
        "harmful": null,
        "checked": false,
        "check_date": null,
        "host": "https://mapcomplete.osm.be/etymology.html",
        "theme": "etymology",
        "answer": 55,
        "locale": "en",
        "imagery": "osm",
        "id": 133278339
      },
      "geometry": {
        "type": "Point",
        "coordinates": [
          17.96335395,
          74.71080745
        ]
      },
      "id": 133278339
    }
  ]
}