{
  "type": "FeatureCollection",
  "features": [
    {
      "type": "Feature",
      "properties": {
        "check_user": null,
        "reasons": [
          {
            "id": 40,
            "name": "New mapper"
          }
        ],
        "tags": [],
        "features": [],
        "user": "karmickoala",
        "uid": "12749531",
        "editor": "MapComplete 0.4.9",
        "comment": "Adding data with #MapComplete for theme #trees",
        "comments_count": 0,
        "source": "Not reported",
        "imagery_used": "Not reported",
        "date": "2021-02-26T18:55:31Z",
        "reviewed_features": [],
        "tag_changes": {},
        "create": 2,
        "modify": 4,
        "delete": 0,
        "area": 0.0000158577922800136,
        "is_suspect": true,
        "harmful": null,
        "checked": false,
        "check_date": null,
        "host": "pietervdvn.github.io",
        "theme": "trees",
        "imagery": "osm",
        "language": "en",
        "theme-creator": "Midgard",
        "id": 100070322
      },
      "geometry": {
        "type": "Point",
        "coordinates": [
          -43.95752195,
          -19.8671501
        ]
      },
      "id": 100070322
    },
    {
      "type": "Feature",
      "properties": {
        "check_user": null,
        "reasons": [
          {
            "id": 40,
            "name": "New mapper"
          }
        ],
        "tags": [],
        "features": [],
        "user": "karmickoala",
        "uid": "12749531",
        "editor": "MapComplete 0.4.9",
        "comment": "Adding data with #MapComplete for theme #trees",
        "comments_count": 0,
        "source": "Not reported",
        "imagery_used": "Not reported",
        "date": "2021-03-03T14:21:18Z",
        "reviewed_features": [],
        "tag_changes": {},
        "create": 0,
        "modify": 1,
        "delete": 0,
        "area": 0,
        "is_suspect": true,
        "harmful": null,
        "checked": false,
        "check_date": null,
        "host": "pietervdvn.github.io",
        "theme": "trees",
        "imagery": "osm",
        "language": "en",
        "theme-creator": "Midgard",
        "id": 100357539
      },
      "geometry": {
        "type": "Point",
        "coordinates": [
          -43.9619181,
          -19.8680519
        ]
      },
      "id": 100357539
    },
    {
      "type": "Feature",
      "properties": {
        "check_user": null,
        "reasons": [
          {
            "id": 40,
            "name": "New mapper"
          }
        ],
        "tags": [],
        "features": [],
        "user": "c_cesar",
        "uid": "12078598",
        "editor": "MapComplete 0.14.1",
        "comment": "Adding data with #MapComplete for theme #street_lighting",
        "comments_count": 0,
        "source": "Not reported",
        "imagery_used": "Not reported",
        "date": "2022-01-19T02:56:44Z",
        "reviewed_features": [],
        "tag_changes": {},
        "create": 0,
        "modify": 2,
        "delete": 0,
        "area": 0.000101179301879975,
        "is_suspect": true,
        "harmful": null,
        "checked": false,
        "check_date": null,
        "host": "mapcomplete.osm.be",
        "theme": "street_lighting",
        "answer": 2,
        "imagery": "osm",
        "language": "en",
        "id": 116322023
      },
      "geometry": {
        "type": "Point",
        "coordinates": [
          -44.90216035,
          -20.1514238
        ]
      },
      "id": 116322023
    },
    {
      "type": "Feature",
      "properties": {
        "check_user": null,
        "reasons": [],
        "tags": [],
        "features": [],
        "user": "BladeTC",
        "uid": "549284",
        "editor": "MapComplete 0.33.13",
        "comment": "Adding data with #MapComplete for theme #artwork",
        "comments_count": 0,
        "source": "Not reported",
        "imagery_used": "Not reported",
        "date": "2023-11-05T14:48:22Z",
        "reviewed_features": [],
        "tag_changes": {
          "fixme": [
            "Freeform field used for artwork type - doublecheck the value"
          ],
          "tourism": [
            "artwork"
          ]
        },
        "create": 0,
        "modify": 1,
        "delete": 0,
        "area": 0,
        "is_suspect": false,
        "harmful": null,
        "checked": false,
        "check_date": null,
        "host": "https://mapcomplete.org/artwork",
        "theme": "artwork",
        "answer": 1,
        "locale": "pt-BR",
        "id": 143653376
      },
      "geometry": {
        "type": "Point",
        "coordinates": [
          -45.2561022,
          -21.6975853
        ]
      },
      "id": 143653376
    }
  ]
}