{
  "type": "FeatureCollection",
  "features": [
    {
      "type": "Feature",
      "properties": {
        "check_user": null,
        "reasons": [
          {
            "id": 40,
            "name": "New mapper"
          }
        ],
        "tags": [],
        "features": [],
        "user": "NoiramK",
        "uid": "4149326",
        "editor": "MapComplete 0.7.5",
        "comment": "Adding data with #MapComplete for theme #bookcases",
        "comments_count": 0,
        "source": "Not reported",
        "imagery_used": "Not reported",
        "date": "2021-06-07T23:46:56Z",
        "reviewed_features": [],
        "create": 0,
        "modify": 2,
        "delete": 0,
        "area": 3.57419999826466e-10,
        "is_suspect": true,
        "harmful": null,
        "checked": false,
        "check_date": null,
        "host": "pietervdvn.github.io",
        "theme": "bookcases",
        "imagery": "osm",
        "language": "en",
        "theme-creator": "MapComplete"
      },
      "geometry": {
        "type": "Point",
        "coordinates": [
          18.9856387,
          69.64829945
        ]
      }
    }
  ]
}