{
  "type": "FeatureCollection",
  "features": [
    {
      "type": "Feature",
      "properties": {
        "check_user": null,
        "reasons": [
          {
            "id": 40,
            "name": "New mapper"
          }
        ],
        "tags": [],
        "features": [],
        "user": "Niekto7",
        "uid": "17452167",
        "editor": "MapComplete 0.23.2",
        "comment": "Adding data with #MapComplete for theme #shops",
        "comments_count": 0,
        "source": "Not reported",
        "imagery_used": "Not reported",
        "date": "2022-10-21T20:39:20Z",
        "reviewed_features": [],
        "tag_changes": {
          "shop": [
            "supermarket"
          ],
          "image": [
            "https://i.imgur.com/CweNe3r.jpg"
          ],
          "building": [
            "yes"
          ]
        },
        "create": 0,
        "modify": 1,
        "delete": 0,
        "area": 7.49662289992293e-7,
        "is_suspect": true,
        "harmful": null,
        "checked": false,
        "check_date": null,
        "host": "https://mapcomplete.osm.be/shops.html",
        "theme": "shops",
        "locale": "en",
        "imagery": "osm",
        "add-image": 1,
        "id": 127902085
      },
      "geometry": {
        "type": "Point",
        "coordinates": [
          18.93580925,
          49.08865175
        ]
      },
      "id": 127902085
    }
  ]
}