{
  "type": "FeatureCollection",
  "features": [
    {
      "type": "Feature",
      "properties": {
        "check_user": null,
        "reasons": [],
        "tags": [],
        "features": [],
        "user": "MihaiBenta94",
        "uid": "13683531",
        "editor": "MapComplete 0.24.0",
        "comment": "Adding data with #MapComplete for theme #toilets",
        "comments_count": 0,
        "source": "Not reported",
        "imagery_used": "Not reported",
        "date": "2022-12-07T07:40:10Z",
        "reviewed_features": [],
        "tag_changes": {},
        "create": 1,
        "modify": 1,
        "delete": 0,
        "area": 3.32880000001825e-10,
        "is_suspect": false,
        "harmful": null,
        "checked": false,
        "check_date": null,
        "host": "https://mapcomplete.osm.be/toilets.html",
        "move": 1,
        "theme": "toilets",
        "answer": 1,
        "locale": "en",
        "imagery": "osm",
        "move:node/10243984807": "improve_accuracy",
        "id": 129809705
      },
      "geometry": {
        "type": "Point",
        "coordinates": [
          24.411971800000003,
          47.2846332
        ]
      },
      "id": 129809705
    },
    {
      "type": "Feature",
      "properties": {
        "check_user": null,
        "reasons": [
          {
            "id": 40,
            "name": "New mapper"
          }
        ],
        "tags": [],
        "features": [],
        "user": "Ben Der",
        "uid": "8558360",
        "editor": "MapComplete 0.23.2",
        "comment": "Adding data with #MapComplete for theme #hailhydrant",
        "comments_count": 0,
        "source": "Not reported",
        "imagery_used": "Not reported",
        "date": "2022-09-29T16:02:40Z",
        "reviewed_features": [],
        "tag_changes": {},
        "create": 1,
        "modify": 1,
        "delete": 0,
        "area": 0,
        "is_suspect": true,
        "harmful": null,
        "checked": false,
        "check_date": null,
        "host": "https://mapcomplete.osm.be/hailhydrant.html",
        "theme": "hailhydrant",
        "answer": 5,
        "locale": "en",
        "imagery": "Mapbox",
        "id": 126787383
      },
      "geometry": {
        "type": "Point",
        "coordinates": [
          24.5193862,
          46.3959861
        ]
      },
      "id": 126787383
    }
  ]
}