{
  "type": "FeatureCollection",
  "features": [
    {
      "type": "Feature",
      "properties": {
        "check_user": null,
        "reasons": [],
        "tags": [],
        "features": [],
        "user": "Robot8A",
        "uid": "393359",
        "editor": "MapComplete 0.45.7",
        "comment": "Adding data with #MapComplete for theme #etymology",
        "comments_count": 0,
        "source": "Not reported",
        "imagery_used": "Not reported",
        "date": "2024-08-30T08:32:22Z",
        "reviewed_features": [],
        "tag_changes": {
          "highway": [
            "primary"
          ],
          "name:etymology:wikidata": [
            "Q365201"
          ]
        },
        "create": 0,
        "modify": 8,
        "delete": 0,
        "area": 0.00010390021311001815,
        "is_suspect": false,
        "harmful": null,
        "checked": false,
        "check_date": null,
        "host": "https://mapcomplete.org/etymology.html",
        "theme": "etymology",
        "answer": 8,
        "locale": "es",
        "id": 155961789
      },
      "geometry": {
        "type": "Point",
        "coordinates": [
          26.69130295,
          37.79655045
        ]
      },
      "id": 155961789
    }
  ]
}