{
  "type": "FeatureCollection",
  "features": [
    {
      "type": "Feature",
      "properties": {
        "STRAATNM": "Lotelingstraat",
        "HUISNR": "5BIS",
        "HNRLABEL": "5BIS"
      },
      "geometry": {
        "type": "Point",
        "coordinates": [
          4.506262765629062,
          51.00506863543246
        ]
      }
    }
  ]
}