{
  "type": "FeatureCollection",
  "features": [
    {
      "type": "Feature",
      "properties": {
        "STRAATNM": "Kleinbaan",
        "HUISNR": "7",
        "HNRLABEL": "7"
      },
      "geometry": {
        "type": "Point",
        "coordinates": [
          5.081040151113887,
          50.99961794200912
        ]
      }
    },
    {
      "type": "Feature",
      "properties": {
        "STRAATNM": "Kleinbaan",
        "HUISNR": "6",
        "HNRLABEL": "6"
      },
      "geometry": {
        "type": "Point",
        "coordinates": [
          5.081170828036658,
          50.999348992919245
        ]
      }
    },
    {
      "type": "Feature",
      "properties": {
        "STRAATNM": "Kleinbaan",
        "HUISNR": "14",
        "HNRLABEL": "14"
      },
      "geometry": {
        "type": "Point",
        "coordinates": [
          5.080450943264549,
          50.999235141224766
        ]
      }
    },
    {
      "type": "Feature",
      "properties": {
        "STRAATNM": "Kleinbaan",
        "HUISNR": "5",
        "HNRLABEL": "5"
      },
      "geometry": {
        "type": "Point",
        "coordinates": [
          5.08117462209063,
          50.99965443365487
        ]
      }
    },
    {
      "type": "Feature",
      "properties": {
        "STRAATNM": "Kleinbaan",
        "HUISNR": "13B",
        "HNRLABEL": "13B"
      },
      "geometry": {
        "type": "Point",
        "coordinates": [
          5.079899982069358,
          50.99938122898293
        ]
      }
    },
    {
      "type": "Feature",
      "properties": {
        "STRAATNM": "Kleinbaan",
        "HUISNR": "13A",
        "HNRLABEL": "13A"
      },
      "geometry": {
        "type": "Point",
        "coordinates": [
          5.07982784295867,
          50.99936836087644
        ]
      }
    },
    {
      "type": "Feature",
      "properties": {
        "STRAATNM": "Kleinbaan",
        "HUISNR": "9",
        "HNRLABEL": "9"
      },
      "geometry": {
        "type": "Point",
        "coordinates": [
          5.080529664649478,
          50.999521609927726
        ]
      }
    },
    {
      "type": "Feature",
      "properties": {
        "STRAATNM": "Kleinbaan",
        "HUISNR": "11",
        "HNRLABEL": "11"
      },
      "geometry": {
        "type": "Point",
        "coordinates": [
          5.080345697502038,
          50.999481012304734
        ]
      }
    },
    {
      "type": "Feature",
      "properties": {
        "STRAATNM": "Sint-Hubertusplein",
        "HUISNR": "60BIS",
        "HNRLABEL": "60BIS"
      },
      "geometry": {
        "type": "Point",
        "coordinates": [
          5.08078578415251,
          50.99988494330248
        ]
      }
    },
    {
      "type": "Feature",
      "properties": {
        "STRAATNM": "Kleinbaan",
        "HUISNR": "7",
        "HNRLABEL": "7",
        "BUSNR": "0001"
      },
      "geometry": {
        "type": "Point",
        "coordinates": [
          5.081040151113887,
          50.99961794200912
        ]
      }
    },
    {
      "type": "Feature",
      "properties": {
        "STRAATNM": "Kleinbaan",
        "HUISNR": "5",
        "HNRLABEL": "5",
        "BUSNR": "0001"
      },
      "geometry": {
        "type": "Point",
        "coordinates": [
          5.08117462209063,
          50.99965443365487
        ]
      }
    }
  ]
}