{
  "type": "FeatureCollection",
  "features": [
    {
      "type": "Feature",
      "properties": {
        "STRAATNM": "Molenstraat",
        "HUISNR": "173",
        "HNRLABEL": "173"
      },
      "geometry": {
        "type": "Point",
        "coordinates": [
          4.364094562471386,
          50.994035202350496
        ]
      }
    },
    {
      "type": "Feature",
      "properties": {
        "STRAATNM": "Molenstraat",
        "HUISNR": "154",
        "HNRLABEL": "154"
      },
      "geometry": {
        "type": "Point",
        "coordinates": [
          4.364012642328049,
          50.99423349946436
        ]
      }
    },
    {
      "type": "Feature",
      "properties": {
        "STRAATNM": "Molenstraat",
        "HUISNR": "152",
        "HNRLABEL": "152"
      },
      "geometry": {
        "type": "Point",
        "coordinates": [
          4.363798990437253,
          50.99413757799801
        ]
      }
    },
    {
      "type": "Feature",
      "properties": {
        "STRAATNM": "Molenstraat",
        "HUISNR": "150",
        "HNRLABEL": "150-150BIS"
      },
      "geometry": {
        "type": "Point",
        "coordinates": [
          4.363585339421164,
          50.994041656140695
        ]
      }
    },
    {
      "type": "Feature",
      "properties": {
        "STRAATNM": "Molenstraat",
        "HUISNR": "150BIS",
        "HNRLABEL": "150-150BIS"
      },
      "geometry": {
        "type": "Point",
        "coordinates": [
          4.363585339421164,
          50.994041656140695
        ]
      }
    }
  ]
}