{
  "type": "FeatureCollection",
  "features": [
    {
      "type": "Feature",
      "properties": {
        "STRAATNM": "Broekstraat",
        "HUISNR": "21BIS",
        "HNRLABEL": "21BIS"
      },
      "geometry": {
        "type": "Point",
        "coordinates": [
          5.014232249162808,
          51.001561095136324
        ]
      }
    },
    {
      "type": "Feature",
      "properties": {
        "STRAATNM": "Broekstraat",
        "HUISNR": "28",
        "HNRLABEL": "28"
      },
      "geometry": {
        "type": "Point",
        "coordinates": [
          5.015239651632098,
          51.0014071435751
        ]
      }
    },
    {
      "type": "Feature",
      "properties": {
        "STRAATNM": "Broekstraat",
        "HUISNR": "26",
        "HNRLABEL": "26"
      },
      "geometry": {
        "type": "Point",
        "coordinates": [
          5.015090069294967,
          51.00157283238156
        ]
      }
    },
    {
      "type": "Feature",
      "properties": {
        "STRAATNM": "Broekstraat",
        "HUISNR": "27",
        "HNRLABEL": "27"
      },
      "geometry": {
        "type": "Point",
        "coordinates": [
          5.014474550470757,
          51.00101113911822
        ]
      }
    },
    {
      "type": "Feature",
      "properties": {
        "STRAATNM": "Broekstraat",
        "HUISNR": "25",
        "HNRLABEL": "25"
      },
      "geometry": {
        "type": "Point",
        "coordinates": [
          5.01447945198432,
          51.00123216244124
        ]
      }
    },
    {
      "type": "Feature",
      "properties": {
        "STRAATNM": "Broekstraat",
        "HUISNR": "23",
        "HNRLABEL": "23"
      },
      "geometry": {
        "type": "Point",
        "coordinates": [
          5.01435115075678,
          51.00141220639592
        ]
      }
    },
    {
      "type": "Feature",
      "properties": {
        "STRAATNM": "Broekstraat",
        "HUISNR": "29",
        "HNRLABEL": "29"
      },
      "geometry": {
        "type": "Point",
        "coordinates": [
          5.014543080296898,
          51.00086684176423
        ]
      }
    }
  ]
}