{
  "type": "FeatureCollection",
  "features": [
    {
      "type": "Feature",
      "properties": {
        "STRAATNM": "Heuvel",
        "HUISNR": "13",
        "HNRLABEL": "13"
      },
      "geometry": {
        "type": "Point",
        "coordinates": [
          3.642139190741333,
          50.88674262126553
        ]
      }
    },
    {
      "type": "Feature",
      "properties": {
        "STRAATNM": "Heuvel",
        "HUISNR": "11",
        "HNRLABEL": "11"
      },
      "geometry": {
        "type": "Point",
        "coordinates": [
          3.642228687541398,
          50.88689231621448
        ]
      }
    },
    {
      "type": "Feature",
      "properties": {
        "STRAATNM": "Heuvel",
        "HUISNR": "10",
        "HNRLABEL": "10"
      },
      "geometry": {
        "type": "Point",
        "coordinates": [
          3.642621061426127,
          50.886857074463904
        ]
      }
    },
    {
      "type": "Feature",
      "properties": {
        "STRAATNM": "Zandstraat",
        "HUISNR": "2",
        "HNRLABEL": "2"
      },
      "geometry": {
        "type": "Point",
        "coordinates": [
          3.64294797778933,
          50.88668900668095
        ]
      }
    },
    {
      "type": "Feature",
      "properties": {
        "STRAATNM": "Heuvel",
        "HUISNR": "4",
        "HNRLABEL": "4"
      },
      "geometry": {
        "type": "Point",
        "coordinates": [
          3.64235156510775,
          50.8874294998342
        ]
      }
    },
    {
      "type": "Feature",
      "properties": {
        "STRAATNM": "Zandstraat",
        "HUISNR": "4",
        "HNRLABEL": "4-6"
      },
      "geometry": {
        "type": "Point",
        "coordinates": [
          3.64314634528318,
          50.88681087563252
        ]
      }
    },
    {
      "type": "Feature",
      "properties": {
        "STRAATNM": "Heuvel",
        "HUISNR": "7",
        "HNRLABEL": "7"
      },
      "geometry": {
        "type": "Point",
        "coordinates": [
          3.642140422987687,
          50.88702149379867
        ]
      }
    },
    {
      "type": "Feature",
      "properties": {
        "STRAATNM": "Heuvel",
        "HUISNR": "6",
        "HNRLABEL": "6"
      },
      "geometry": {
        "type": "Point",
        "coordinates": [
          3.64254249799113,
          50.887075941021465
        ]
      }
    },
    {
      "type": "Feature",
      "properties": {
        "STRAATNM": "Heuvel",
        "HUISNR": "9",
        "HNRLABEL": "9"
      },
      "geometry": {
        "type": "Point",
        "coordinates": [
          3.642146608126136,
          50.886970739442376
        ]
      }
    },
    {
      "type": "Feature",
      "properties": {
        "STRAATNM": "Zandstraat",
        "HUISNR": "6",
        "HNRLABEL": "4-6"
      },
      "geometry": {
        "type": "Point",
        "coordinates": [
          3.64314634528318,
          50.88681087563252
        ]
      }
    },
    {
      "type": "Feature",
      "properties": {
        "STRAATNM": "Heuvel",
        "HUISNR": "5bis",
        "HNRLABEL": "5bis"
      },
      "geometry": {
        "type": "Point",
        "coordinates": [
          3.64202619392607,
          50.88725811912105
        ]
      }
    },
    {
      "type": "Feature",
      "properties": {
        "STRAATNM": "Heuvel",
        "HUISNR": "7B",
        "HNRLABEL": "7B"
      },
      "geometry": {
        "type": "Point",
        "coordinates": [
          3.642061784307482,
          50.88719909620111
        ]
      }
    },
    {
      "type": "Feature",
      "properties": {
        "STRAATNM": "Heuvel",
        "HUISNR": "11bis",
        "HNRLABEL": "11bis"
      },
      "geometry": {
        "type": "Point",
        "coordinates": [
          3.642220609561445,
          50.88682646061562
        ]
      }
    }
  ]
}