{
  "type": "FeatureCollection",
  "features": [
    {
      "type": "Feature",
      "properties": {
        "STRAATNM": "Terkerkenlaan",
        "HUISNR": "2",
        "HNRLABEL": "2"
      },
      "geometry": {
        "type": "Point",
        "coordinates": [
          3.611441650164262,
          50.852549492656216
        ]
      }
    },
    {
      "type": "Feature",
      "properties": {
        "STRAATNM": "Sint-Jozefsplein",
        "HUISNR": "3",
        "HNRLABEL": "3-4"
      },
      "geometry": {
        "type": "Point",
        "coordinates": [
          3.610394682961475,
          50.85269969902345
        ]
      }
    },
    {
      "type": "Feature",
      "properties": {
        "STRAATNM": "Sint-Jozefsplein",
        "HUISNR": "1",
        "HNRLABEL": "1-1A"
      },
      "geometry": {
        "type": "Point",
        "coordinates": [
          3.610672943157216,
          50.852740962140174
        ]
      }
    },
    {
      "type": "Feature",
      "properties": {
        "STRAATNM": "Sint-Jozefsplein",
        "HUISNR": "8",
        "HNRLABEL": "8"
      },
      "geometry": {
        "type": "Point",
        "coordinates": [
          3.61140958067407,
          50.85192151629722
        ]
      }
    },
    {
      "type": "Feature",
      "properties": {
        "STRAATNM": "Sint-Jozefsplein",
        "HUISNR": "4",
        "HNRLABEL": "3-4"
      },
      "geometry": {
        "type": "Point",
        "coordinates": [
          3.610394682961475,
          50.85269969902345
        ]
      }
    },
    {
      "type": "Feature",
      "properties": {
        "STRAATNM": "Terkerkenlaan",
        "HUISNR": "1",
        "HNRLABEL": "1-1A"
      },
      "geometry": {
        "type": "Point",
        "coordinates": [
          3.610672943157216,
          50.852740962140174
        ]
      }
    },
    {
      "type": "Feature",
      "properties": {
        "STRAATNM": "Terkerkenlaan",
        "HUISNR": "1A",
        "HNRLABEL": "1A"
      },
      "geometry": {
        "type": "Point",
        "coordinates": [
          3.610982820581469,
          50.85269738358529
        ]
      }
    },
    {
      "type": "Feature",
      "properties": {
        "STRAATNM": "Sint-Jozefsplein",
        "HUISNR": "2",
        "HNRLABEL": "2"
      },
      "geometry": {
        "type": "Point",
        "coordinates": [
          3.610698088931173,
          50.85263468329227
        ]
      }
    },
    {
      "type": "Feature",
      "properties": {
        "STRAATNM": "Sint-Jozefsplein",
        "HUISNR": "8bis",
        "HNRLABEL": "8bis"
      },
      "geometry": {
        "type": "Point",
        "coordinates": [
          3.611409579226916,
          50.85192160618756
        ]
      }
    }
  ]
}