{
  "type": "FeatureCollection",
  "features": [
    {
      "type": "Feature",
      "properties": {
        "STRAATNM": "Diestersteenweg",
        "HUISNR": "263",
        "HNRLABEL": "263"
      },
      "geometry": {
        "type": "Point",
        "coordinates": [
          5.017406755033005,
          50.97961677476968
        ]
      }
    },
    {
      "type": "Feature",
      "properties": {
        "STRAATNM": "Diestersteenweg",
        "HUISNR": "267",
        "HNRLABEL": "267"
      },
      "geometry": {
        "type": "Point",
        "coordinates": [
          5.017110778535726,
          50.97967369380093
        ]
      }
    },
    {
      "type": "Feature",
      "properties": {
        "STRAATNM": "Diestersteenweg",
        "HUISNR": "261",
        "HNRLABEL": "261"
      },
      "geometry": {
        "type": "Point",
        "coordinates": [
          5.017729185159546,
          50.97956779943102
        ]
      }
    },
    {
      "type": "Feature",
      "properties": {
        "STRAATNM": "Diestersteenweg",
        "HUISNR": "259",
        "HNRLABEL": "259"
      },
      "geometry": {
        "type": "Point",
        "coordinates": [
          5.018000647341851,
          50.97957106417261
        ]
      }
    },
    {
      "type": "Feature",
      "properties": {
        "STRAATNM": "Diestersteenweg",
        "HUISNR": "259BIS",
        "HNRLABEL": "259BIS"
      },
      "geometry": {
        "type": "Point",
        "coordinates": [
          5.017837002116505,
          50.979569181561
        ]
      }
    },
    {
      "type": "Feature",
      "properties": {
        "STRAATNM": "Diestersteenweg",
        "HUISNR": "263",
        "HNRLABEL": "263",
        "APPTNR": "A001"
      },
      "geometry": {
        "type": "Point",
        "coordinates": [
          5.017406755033005,
          50.97961677476968
        ]
      }
    },
    {
      "type": "Feature",
      "properties": {
        "STRAATNM": "Diestersteenweg",
        "HUISNR": "263",
        "HNRLABEL": "263",
        "APPTNR": "B001"
      },
      "geometry": {
        "type": "Point",
        "coordinates": [
          5.017406755033005,
          50.97961677476968
        ]
      }
    }
  ]
}