{
  "type": "FeatureCollection",
  "features": [
    {
      "type": "Feature",
      "properties": {
        "STRAATNM": "Molenbergstraat",
        "HUISNR": "61",
        "HNRLABEL": "61"
      },
      "geometry": {
        "type": "Point",
        "coordinates": [
          5.064772511997241,
          50.972856092430426
        ]
      }
    },
    {
      "type": "Feature",
      "properties": {
        "STRAATNM": "Molenbergstraat",
        "HUISNR": "67",
        "HNRLABEL": "67"
      },
      "geometry": {
        "type": "Point",
        "coordinates": [
          5.065240628755337,
          50.97256655086786
        ]
      }
    },
    {
      "type": "Feature",
      "properties": {
        "STRAATNM": "Molenbergstraat",
        "HUISNR": "54",
        "HNRLABEL": "54"
      },
      "geometry": {
        "type": "Point",
        "coordinates": [
          5.065022406003969,
          50.97312519788854
        ]
      }
    },
    {
      "type": "Feature",
      "properties": {
        "STRAATNM": "Molenbergstraat",
        "HUISNR": "64",
        "HNRLABEL": "64"
      },
      "geometry": {
        "type": "Point",
        "coordinates": [
          5.065520984140111,
          50.97233736237936
        ]
      }
    },
    {
      "type": "Feature",
      "properties": {
        "STRAATNM": "Molenbergstraat",
        "HUISNR": "65",
        "HNRLABEL": "65"
      },
      "geometry": {
        "type": "Point",
        "coordinates": [
          5.065044652605664,
          50.972667856349794
        ]
      }
    },
    {
      "type": "Feature",
      "properties": {
        "STRAATNM": "Molenbergstraat",
        "HUISNR": "69",
        "HNRLABEL": "69"
      },
      "geometry": {
        "type": "Point",
        "coordinates": [
          5.064880953563674,
          50.97240228553273
        ]
      }
    },
    {
      "type": "Feature",
      "properties": {
        "STRAATNM": "Molenbergstraat",
        "HUISNR": "56BIS",
        "HNRLABEL": "56BIS"
      },
      "geometry": {
        "type": "Point",
        "coordinates": [
          5.065286325877597,
          50.9730160283359
        ]
      }
    },
    {
      "type": "Feature",
      "properties": {
        "STRAATNM": "Molenbergstraat",
        "HUISNR": "66",
        "HNRLABEL": "66"
      },
      "geometry": {
        "type": "Point",
        "coordinates": [
          5.065431944699506,
          50.97228602055621
        ]
      }
    },
    {
      "type": "Feature",
      "properties": {
        "STRAATNM": "Molenbergstraat",
        "HUISNR": "63",
        "HNRLABEL": "63"
      },
      "geometry": {
        "type": "Point",
        "coordinates": [
          5.064992505155789,
          50.97274205968862
        ]
      }
    },
    {
      "type": "Feature",
      "properties": {
        "STRAATNM": "Molenbergstraat",
        "HUISNR": "71",
        "HNRLABEL": "71"
      },
      "geometry": {
        "type": "Point",
        "coordinates": [
          5.064797549865613,
          50.97235648337698
        ]
      }
    },
    {
      "type": "Feature",
      "properties": {
        "STRAATNM": "Molenbergstraat",
        "HUISNR": "58BIS",
        "HNRLABEL": "58BIS"
      },
      "geometry": {
        "type": "Point",
        "coordinates": [
          5.065467400642254,
          50.972841366017654
        ]
      }
    },
    {
      "type": "Feature",
      "properties": {
        "STRAATNM": "Molenbergstraat",
        "HUISNR": "56",
        "HNRLABEL": "56"
      },
      "geometry": {
        "type": "Point",
        "coordinates": [
          5.065193763453854,
          50.97306296325759
        ]
      }
    },
    {
      "type": "Feature",
      "properties": {
        "STRAATNM": "Molenbergstraat",
        "HUISNR": "60",
        "HNRLABEL": "60"
      },
      "geometry": {
        "type": "Point",
        "coordinates": [
          5.065653440799509,
          50.97273256753103
        ]
      }
    },
    {
      "type": "Feature",
      "properties": {
        "STRAATNM": "Molenbergstraat",
        "HUISNR": "58",
        "HNRLABEL": "58"
      },
      "geometry": {
        "type": "Point",
        "coordinates": [
          5.065383618201321,
          50.97289463162521
        ]
      }
    },
    {
      "type": "Feature",
      "properties": {
        "STRAATNM": "Molenbergstraat",
        "HUISNR": "69",
        "HNRLABEL": "69",
        "BUSNR": "1"
      },
      "geometry": {
        "type": "Point",
        "coordinates": [
          5.064880953563674,
          50.97240228553273
        ]
      }
    }
  ]
}