{
  "type": "FeatureCollection",
  "features": [
    {
      "type": "Feature",
      "properties": {
        "STRAATNM": "Zemstseweg",
        "HUISNR": "78",
        "HNRLABEL": "78"
      },
      "geometry": {
        "type": "Point",
        "coordinates": [
          4.440367417061137,
          51.005216368673146
        ]
      }
    },
    {
      "type": "Feature",
      "properties": {
        "STRAATNM": "Zemstseweg",
        "HUISNR": "45",
        "HNRLABEL": "45"
      },
      "geometry": {
        "type": "Point",
        "coordinates": [
          4.441188007846074,
          51.005726442020496
        ]
      }
    },
    {
      "type": "Feature",
      "properties": {
        "STRAATNM": "Zemstseweg",
        "HUISNR": "72",
        "HNRLABEL": "72"
      },
      "geometry": {
        "type": "Point",
        "coordinates": [
          4.440134057055961,
          51.00587280507732
        ]
      }
    },
    {
      "type": "Feature",
      "properties": {
        "STRAATNM": "Zemstseweg",
        "HUISNR": "74BIS",
        "HNRLABEL": "74BIS"
      },
      "geometry": {
        "type": "Point",
        "coordinates": [
          4.440285723063833,
          51.00564196225846
        ]
      }
    },
    {
      "type": "Feature",
      "properties": {
        "STRAATNM": "Zemstseweg",
        "HUISNR": "47",
        "HNRLABEL": "47"
      },
      "geometry": {
        "type": "Point",
        "coordinates": [
          4.440944555598621,
          51.005476246896094
        ]
      }
    },
    {
      "type": "Feature",
      "properties": {
        "STRAATNM": "Zemstseweg",
        "HUISNR": "49",
        "HNRLABEL": "49"
      },
      "geometry": {
        "type": "Point",
        "coordinates": [
          4.440954248894116,
          51.00529627934383
        ]
      }
    },
    {
      "type": "Feature",
      "properties": {
        "STRAATNM": "Zemstseweg",
        "HUISNR": "76",
        "HNRLABEL": "76"
      },
      "geometry": {
        "type": "Point",
        "coordinates": [
          4.440303844480444,
          51.005382256387165
        ]
      }
    },
    {
      "type": "Feature",
      "properties": {
        "STRAATNM": "Zemstseweg",
        "HUISNR": "74",
        "HNRLABEL": "74"
      },
      "geometry": {
        "type": "Point",
        "coordinates": [
          4.440169024487443,
          51.00581974805155
        ]
      }
    },
    {
      "type": "Feature",
      "properties": {
        "STRAATNM": "Zemstseweg",
        "HUISNR": "51",
        "HNRLABEL": "51"
      },
      "geometry": {
        "type": "Point",
        "coordinates": [
          4.440954060974638,
          51.00517546610549
        ]
      }
    },
    {
      "type": "Feature",
      "properties": {
        "STRAATNM": "Zemstseweg",
        "HUISNR": "74B",
        "HNRLABEL": "74B"
      },
      "geometry": {
        "type": "Point",
        "coordinates": [
          4.440231566619881,
          51.00563165801998
        ]
      }
    }
  ]
}