{
  "type": "FeatureCollection",
  "features": [
    {
      "type": "Feature",
      "properties": {
        "STRAATNM": "Osylei",
        "HUISNR": "10",
        "HNRLABEL": "10"
      },
      "geometry": {
        "type": "Point",
        "coordinates": [
          4.449112187973737,
          51.18149351958393
        ]
      }
    },
    {
      "type": "Feature",
      "properties": {
        "STRAATNM": "Osylei",
        "HUISNR": "15",
        "HNRLABEL": "15"
      },
      "geometry": {
        "type": "Point",
        "coordinates": [
          4.449419643728952,
          51.1818922192742
        ]
      }
    },
    {
      "type": "Feature",
      "properties": {
        "STRAATNM": "Osylei",
        "HUISNR": "6",
        "HNRLABEL": "6"
      },
      "geometry": {
        "type": "Point",
        "coordinates": [
          4.448764204311293,
          51.181721257453276
        ]
      }
    },
    {
      "type": "Feature",
      "properties": {
        "STRAATNM": "Osylei",
        "HUISNR": "4",
        "HNRLABEL": "4"
      },
      "geometry": {
        "type": "Point",
        "coordinates": [
          4.448630903416563,
          51.18179658240929
        ]
      }
    },
    {
      "type": "Feature",
      "properties": {
        "STRAATNM": "Amedeus Stockmanslei",
        "HUISNR": "3",
        "HNRLABEL": "3"
      },
      "geometry": {
        "type": "Point",
        "coordinates": [
          4.448808460475129,
          51.18126290203515
        ]
      }
    },
    {
      "type": "Feature",
      "properties": {
        "STRAATNM": "Osylei",
        "HUISNR": "2",
        "HNRLABEL": "2"
      },
      "geometry": {
        "type": "Point",
        "coordinates": [
          4.448479096954745,
          51.18192216568658
        ]
      }
    },
    {
      "type": "Feature",
      "properties": {
        "STRAATNM": "Osylei",
        "HUISNR": "8",
        "HNRLABEL": "8"
      },
      "geometry": {
        "type": "Point",
        "coordinates": [
          4.448937206460292,
          51.18161372624076
        ]
      }
    },
    {
      "type": "Feature",
      "properties": {
        "STRAATNM": "Amedeus Stockmanslei",
        "HUISNR": "1",
        "HNRLABEL": "1"
      },
      "geometry": {
        "type": "Point",
        "coordinates": [
          4.44867299348518,
          51.18149094367535
        ]
      }
    },
    {
      "type": "Feature",
      "properties": {
        "STRAATNM": "Amedeus Stockmanslei",
        "HUISNR": "5",
        "HNRLABEL": "5"
      },
      "geometry": {
        "type": "Point",
        "coordinates": [
          4.448941146602268,
          51.18108142271967
        ]
      }
    },
    {
      "type": "Feature",
      "properties": {
        "STRAATNM": "Osylei",
        "HUISNR": "10BIS",
        "HNRLABEL": "10B-10BIS"
      },
      "geometry": {
        "type": "Point",
        "coordinates": [
          4.449343148656206,
          51.18132707311896
        ]
      }
    },
    {
      "type": "Feature",
      "properties": {
        "STRAATNM": "Osylei",
        "HUISNR": "10B",
        "HNRLABEL": "10B-10BIS"
      },
      "geometry": {
        "type": "Point",
        "coordinates": [
          4.449343148656206,
          51.18132707311896
        ]
      }
    }
  ]
}