{
  "type": "FeatureCollection",
  "features": [
    {
      "type": "Feature",
      "properties": {
        "STRAATNM": "Zeedijk-De Haan",
        "HUISNR": "1TER",
        "HNRLABEL": "1TER"
      },
      "geometry": {
        "type": "Point",
        "coordinates": [
          3.026265244425705,
          51.276931071730495
        ]
      }
    }
  ]
}