{
  "type": "FeatureCollection",
  "features": [
    {
      "type": "Feature",
      "properties": {
        "STRAATNM": "Urnestraat",
        "HUISNR": "20",
        "HNRLABEL": "20"
      },
      "geometry": {
        "type": "Point",
        "coordinates": [
          5.511852770878041,
          51.1578728079058
        ]
      }
    },
    {
      "type": "Feature",
      "properties": {
        "STRAATNM": "Bremstraat",
        "HUISNR": "21",
        "HNRLABEL": "21"
      },
      "geometry": {
        "type": "Point",
        "coordinates": [
          5.512202197999545,
          51.15855119894963
        ]
      }
    },
    {
      "type": "Feature",
      "properties": {
        "STRAATNM": "Urnestraat",
        "HUISNR": "15",
        "HNRLABEL": "15"
      },
      "geometry": {
        "type": "Point",
        "coordinates": [
          5.511076064922464,
          51.157994498413665
        ]
      }
    },
    {
      "type": "Feature",
      "properties": {
        "STRAATNM": "Urnestraat",
        "HUISNR": "24",
        "HNRLABEL": "24"
      },
      "geometry": {
        "type": "Point",
        "coordinates": [
          5.512248142742924,
          51.158069266992776
        ]
      }
    },
    {
      "type": "Feature",
      "properties": {
        "STRAATNM": "Urnestraat",
        "HUISNR": "19",
        "HNRLABEL": "19"
      },
      "geometry": {
        "type": "Point",
        "coordinates": [
          5.511442265341179,
          51.15820823304105
        ]
      }
    },
    {
      "type": "Feature",
      "properties": {
        "STRAATNM": "Urnestraat",
        "HUISNR": "17Bis",
        "HNRLABEL": "17Bis"
      },
      "geometry": {
        "type": "Point",
        "coordinates": [
          5.511034797524733,
          51.15828256729862
        ]
      }
    },
    {
      "type": "Feature",
      "properties": {
        "STRAATNM": "Bremstraat",
        "HUISNR": "38",
        "HNRLABEL": "38"
      },
      "geometry": {
        "type": "Point",
        "coordinates": [
          5.511400539395047,
          51.15864095024472
        ]
      }
    },
    {
      "type": "Feature",
      "properties": {
        "STRAATNM": "Urnestraat",
        "HUISNR": "22",
        "HNRLABEL": "22"
      },
      "geometry": {
        "type": "Point",
        "coordinates": [
          5.512038413645431,
          51.15797546934088
        ]
      }
    },
    {
      "type": "Feature",
      "properties": {
        "STRAATNM": "Bremstraat",
        "HUISNR": "42",
        "HNRLABEL": "42"
      },
      "geometry": {
        "type": "Point",
        "coordinates": [
          5.511819050390025,
          51.15829951461776
        ]
      }
    }
  ]
}