{
  "type": "FeatureCollection",
  "features": [
    {
      "type": "Feature",
      "properties": {
        "STRAATNM": "Laurierlaan",
        "HUISNR": "7",
        "HNRLABEL": "7"
      },
      "geometry": {
        "type": "Point",
        "coordinates": [
          4.530099101392167,
          50.999195399769484
        ]
      }
    },
    {
      "type": "Feature",
      "properties": {
        "STRAATNM": "Laurierlaan",
        "HUISNR": "9",
        "HNRLABEL": "9"
      },
      "geometry": {
        "type": "Point",
        "coordinates": [
          4.530424933702201,
          50.99912348716476
        ]
      }
    },
    {
      "type": "Feature",
      "properties": {
        "STRAATNM": "Laurierlaan",
        "HUISNR": "4",
        "HNRLABEL": "4"
      },
      "geometry": {
        "type": "Point",
        "coordinates": [
          4.529248507225953,
          50.999446735121346
        ]
      }
    },
    {
      "type": "Feature",
      "properties": {
        "STRAATNM": "Laurierlaan",
        "HUISNR": "1",
        "HNRLABEL": "1"
      },
      "geometry": {
        "type": "Point",
        "coordinates": [
          4.529598058700986,
          50.999683928247784
        ]
      }
    },
    {
      "type": "Feature",
      "properties": {
        "STRAATNM": "Laurierlaan",
        "HUISNR": "6",
        "HNRLABEL": "6"
      },
      "geometry": {
        "type": "Point",
        "coordinates": [
          4.529375885460649,
          50.9993289828684
        ]
      }
    },
    {
      "type": "Feature",
      "properties": {
        "STRAATNM": "Laurierlaan",
        "HUISNR": "5",
        "HNRLABEL": "5"
      },
      "geometry": {
        "type": "Point",
        "coordinates": [
          4.530001413119605,
          50.999288391874714
        ]
      }
    },
    {
      "type": "Feature",
      "properties": {
        "STRAATNM": "Laurierlaan",
        "HUISNR": "1BIS",
        "HNRLABEL": "1BIS"
      },
      "geometry": {
        "type": "Point",
        "coordinates": [
          4.529772501262187,
          50.99958175203838
        ]
      }
    }
  ]
}