{
  "type": "FeatureCollection",
  "features": [
    {
      "type": "Feature",
      "properties": {
        "STRAATNM": "Smarre",
        "HUISNR": "6bis",
        "HNRLABEL": "6bis"
      },
      "geometry": {
        "type": "Point",
        "coordinates": [
          3.695120780644681,
          50.86232555424977
        ]
      }
    }
  ]
}